Workbook

Sheet Status
C2: W=Working, C=Complete, R=Risk
B3: Target | C3: 45408 | D3: 45408 | E3: 45443 | F3: 45460 | G3: 45460 | H3: 45586
B4: INTERFACE | C4: ANA-50 Functional Spec | D4: TAR-040 Technical Spec | E4: DES-020 Test Env. Ready | F4: TES-070 Test Plan/Script | G4: TES-070 Test Data | H4: Test Signoff | I4: Latest Comment | J4: Next Steps(s)
B5: Concur Invoice | C5: W | D5: W | E5: W | F5: Laying out unit tests | I5: [Jun-7] We have 3 test POs. Need the business to enter and receive the POs. Then Shared Services will enter the vendor invoice to complete the 3-way match to test the XML BOD back to M3. [Jun-13] Sent email to team asking them to complete test
B6: Concur Travel & Expense
B7: Salesforce | C7: C | D7: C | E7: W | F7: W | G7: W | I7: [Jun-14] Next step is to review test plan with Torborjn
B8: SPS Commerce EDI | C8: W | D8: W | E8: W | I8: [Jun-14] Rich Ospry engaged to assist with technical information, has already started providing information needed to SPS Commerce. [June28 Matt] ANA ready for Barnes review/approval. | J8: [Apr-26] - Kick off meeting with SPS Commerce Apr-30 10:30a EDT. Cheska set up weekly meetings.
B9: PNC Bank (AR) | C9: R | D9: W | I9: [Jun-14] Meeting scheduled Mon Jun 17 to see what additional is needed to complete the ANA and begin setup of test enironement | J9: [Apr-26] Meeting scheduled for May-1 8a EDT with Shared Service, JBA ERP, Infor to discuss process detail
B10: Shared Service (AP) Bank of America | C10: R | D10: W | I10: [Jun-14] Meeting scheduled Mon Jun 17 to see what additional is needed to complete the ANA and begin setup of test enironement | J10: [Apr-26] Meeting scheduled for May-1 8a EDT with Shared Service, JBA ERP, Infor to discuss process detail
B11: Cforia | C11: R | D11: W | E11: W | I11: [Jun-14] Kevin has started query to provide open A/R balance. Amy McGuire to run open balance out of M3. We may need to get Kevin/Dean access to run report out of M3 as open balance can change | J11: [Apr-26] Kevin to refine queries for output files. Work with Cforia to send to test environment.
B12: Fedex | C12: C | D12: W | E12: W | I12: [Jun-14] Jack Adoline reviewing in place of Aaron departure. | J12: [Apr-26] Connectivity to test/prod workstations | K12: Export to correct location, FEDEX>IN, UPS>IN. Can we send prod to both current ERP and M3
B13: UPS | C13: C | D13: W | E13: W | I13: [Jun-14] Jack Adoline reviewing in place of Aaron departure. | J13: [Apr-26] Connectivity to test/prod workstations
B14: Credit Card Processing - CenPOS | C14: W | D14: W | E14: W | I14: [May-15] Uploaded demo environment connection information from CenPOS to Infor site and notified team. Next step is to plug into interface and verify works with M3 test environment. Need to meet with Optimziely vendor CONSID to determine steps needed to connect to e-commerce/Optimizely | J14: [Apr-26] Seems we're already an Evalon\US Bank customer. Work with reps to get gateway access. | K14: CenPOS setup screen from Daniel. Test account setup.
B15: Optimizely | C15: C | D15: W | E15: W | I15: [May-15] ANA under review, questions being answered. Test environment for data feeds to be setup early June. ANA for orders was written. ANA [June28 Matt] Optimizely ANA approved by Amy B. | J15: [Apr-26] Dean to put updated specification on Infor sharepoint.

Sheet Sheet1
A3: Count of Interface ID | B3: Column Labels
A4: Row Labels | B4: 3 - Speccing (ANA-050) | C4: 4 - Tech Spec (TAR-040) | D4: 5 - Development | E4: 6 - Development Testing | F4: Business Testing | G4: (blank) | H4: Grand Total
A5: BoA Shared Service (AP) | D5: 2 | H5: 2
A6: CenPos | F6: 2 | H6: 2
A7: Cforia | B7: 5 | H7: 5
A8: Concur | B8: 2 | C8: 3 | E8: 1 | H8: 6
A9: Fedex | C9: 2 | H9: 2
A10: Optimizely | B10: 5 | C10: 1 | H10: 6
A11: Salesforce | F11: 2 | H11: 2
A12: SPS Commerce EDI | B12: 1 | C12: 4 | E12: 1 | G12: 1 | H12: 7
A13: UPS | C13: 2 | H13: 2
A14: (SPS) PNC Bank (AR) | B14: 2 | H14: 2
A15: PNC Bank (AR) (SPS) | B15: 1 | H15: 1
A16: Grand Total | B16: 16 | C16: 12 | D16: 2 | E16: 2 | F16: 4 | G16: 1 | H16: 37
B21: m | C21: t | D21: w | E21: th | F21: f
B22: BoA | C22: SPS | D22: ups | E22: optimizely
B23: Cforia | D23: fedex | E23: CenPos
B24: Concur
B25: (SPS) PNC Bank (AR)
B26: PNC Bank (AR) (SPS)

Sheet List
A1: Partner/System | B1: Interface ID | C1: Interface | D1: 100% Complete | E1: Stream | F1: Accountable | G1: Barnes Functional | H1: Barnes technical | I1: Status | J1: Action | K1: Process Status | L1: SPS Status | M1: SPS Variable | N1: Totals # of days | O1: SPS + Status | P1: Estimated Completion Date | Q1: Infor FC | R1: 3P Development | S1: Functional Spec ANA-050 | T1: Action - Approved | U1: ANA-050 Date Due | V1: Date Complete | W1: Infor Tech Consultant | X1: Interface spec TAR-040 | Y1: Action | Z1: Date Approved | AA1: Date Due | AB1: Date Completed | AC1: Dev Start | AD1: Dev Complate | AE1: TES-070 | AF1: Testing | AG1: Action | AH1: Testing Start | AI1: Testing Completed | AJ1: DES-030 Deployment | AK1: DES-030 Notes | AL1: Comment/Notes | AM1: Next action, who and date
A2: (SPS) PNC Bank (AR) | B2: FIN001 | C2: PNC Lockbox EDI 823 checks | D2: No | E2: Finance | F2: Infor | G2: Kim | H2: Jeff | I2: Pre Development | J2: SPS | K2: Speccing (ANA-050) | N2: =VLOOKUP(K2,'Drop Down'!$I$2:$K$14,3,FALSE) -> 30 | O2: =SUM(M2:N2) -> 30 | P2: =TODAY()+O2 -> 46325 | Q2: Dennis | S2: WIP | T2: Kim | U2: 45562 | W2: TBD | AL2: 09/16 Dennis to completing review of EDI 823 and 820 mappings by EOD 09/20. ANA-050 to follow completion approx 09/25. 08/27 Dennis had a meeting with PNC and Barnes and SPS. PNC Bank discussed the scope with Barnes 08/08 Dennis initiated weekly recurring calls to track progress. Dean to get the JBA and PNC together to discuss the current process and required specs. | AM2: PNC Bank(Wendella) & SPS Commerce (Courney/Zach) +Dennis for ANA-050 | AN2: Testing in progress by Barnes | AQ2: =CONCATENATE(B2, " ", A2, " ",C2, " ", E2) -> FIN001 (SPS) PNC Bank (AR) PNC Lockbox EDI 823 checks Finance | AR2: CON001 Concur SupplierInvoice Finance
A3: (SPS) PNC Bank (AR) | B3: FIN005 | C3: PNC Lockbox EDI820 flat file ACH ad wires | D3: No | E3: Finance | F3: Infor | G3: Kim | H3: Jeff | I3: Pre Development | J3: SPS | K3: Speccing (ANA-050) | N3: =VLOOKUP(K3,'Drop Down'!$I$2:$K$14,3,FALSE) -> 30 | O3: =SUM(M3:N3) -> 30 | P3: =TODAY()+O3 -> 46325 | Q3: Dennis | S3: WIP | U3: 45562 | W3: TBD | AL3: 09/16 Dennis to completing review of EDI 823 and 820 mappings by EOD 09/20. ANA-050 to follow completion approx 09/25. 08/27 Dennis had a meeting with PNC and Barnes and SPS. PNC Bank discussed the scope with Barnes New file that we found out 20230123, sample file in share point, modified for barnes, we should get stdEDI 820 from bank. Via SPS Commerce? | AM3: PNC Bank(Wendella) & SPS Commerce (Courney/Zach) +Dennis for ANA-050 | AQ3: =CONCATENATE(B3, " ", A3, " ",C3, " ", E3) -> FIN005 (SPS) PNC Bank (AR) PNC Lockbox EDI820 flat file ACH ad wires Finance | AR3: CON002 Concur Goods Receipts Finance
A4: BoA Shared Service (AP) | B4: FIN003 | C4: Check Run Header | D4: No | E4: Finance | F4: Infor | G4: Kim | H4: Jeff | I4: Pending Approval | J4: Finance | K4: Development | N4: =VLOOKUP(K4,'Drop Down'!$I$2:$K$14,3,FALSE) -> 15 | O4: =SUM(M4:N4) -> 15 | P4: =TODAY()+O4 -> 46310 | Q4: Carlo | S4: Completed | W4: Isaiah John Tolentino | X4: Completed | AC4: 45548 | AD4: 45576 | AL4: September 25. Dev almost complete. Sent to Carlo for validation. Carlo need to reply ASAP for dev to continue. Sep 13. Dev started. Redy by Oct 11 8/27 - Carlo sent ANA-50 for approval to Finance 20 Aug - Dean needs to approve Ahmed start func spec after PNC | AM4: Carlo Alcazar | AQ4: =CONCATENATE(B4, " ", A4, " ",C4, " ", E4) -> FIN003 BoA Shared Service (AP) Check Run Header Finance | AR4: CON003 Concur PO Header Finance
A5: BoA Shared Service (AP) | B5: FIN004 | C5: Check Run Details | D5: No | E5: Finance | F5: Infor | G5: Kim | H5: Jeff | I5: Pending Approval | J5: Finance | K5: Development | N5: =VLOOKUP(K5,'Drop Down'!$I$2:$K$14,3,FALSE) -> 15 | O5: =SUM(M5:N5) -> 15 | P5: =TODAY()+O5 -> 46310 | Q5: Carlo | S5: Completed | W5: Isaiah John Tolentino | X5: Completed | AC5: 45548 | AD5: 45576 | AL5: September 25. Dev almost complete. Sent to Carlo for validation. Carlo need to reply ASAP for dev to continue. Sep 13. Dev started. Redy by Oct 11 8/27 - Carlo sent ANA-50 for approval to Finance 20 Aug - Dean needs to approve Ahmed start func spec after PNC | AM5: Carlo Alcazar | AQ5: =CONCATENATE(B5, " ", A5, " ",C5, " ", E5) -> FIN004 BoA Shared Service (AP) Check Run Details Finance | AR5: CON004 Concur PO Lines Finance
A6: CenPos | B6: CNP001 | C6: Payment Authorization | D6: Yes | E6: OTC | F6: Infor | G6: Amy B / Louis | H6: Dean | I6: Testing | J6: Finance | K6: Business Testing | N6: =VLOOKUP(K6,'Drop Down'!$I$2:$K$14,3,FALSE) -> 2 | O6: =SUM(M6:N6) -> 2 | P6: =TODAY()+O6 -> 46297 | Q6: Hubert | S6: NA | W6: N/A | X6: NA | AK6: NA | AL6: August - Infor Standard Integration (OOB) Unknown date > existing Infor CenPos code. this team to verify that it works for Barnes. Hubert/Cheska to test CenPos. 7/18. only Dev person is needed if Hubert/Cheska see need for a change. Unknown date > H5 script, manage in UI. Waiting for contact at Barnes and Worldpay | AM6: Infor (Hubert/Daniel) | AQ6: =CONCATENATE(B6, " ", A6, " ",C6, " ", E6) -> CNP001 CenPos Payment Authorization OTC | AR6: CON005 Concur Vendor Infor Finance
A7: CenPos | B7: CNP002 | C7: Payment Capture | D7: Yes | E7: OTC | F7: Infor | G7: Amy B / Louis | H7: Dean | I7: Testing | J7: Finance | K7: Business Testing | N7: =VLOOKUP(K7,'Drop Down'!$I$2:$K$14,3,FALSE) -> 2 | O7: =SUM(M7:N7) -> 2 | P7: =TODAY()+O7 -> 46297 | Q7: Hubert | S7: NA | W7: N/A | X7: NA | AK7: NA | AL7: August - Infor Standard Integration (OOB) Unknown date > existing Infor CenPos code. this team to verify that it works for Barnes. Hubert/Cheska to test CenPos. 7/18. only Dev person is needed if Hubert/Cheska see need for a change. H5 script, manage in UI. Waiting for contact at Barnes and Worldpay | AM7: Infor (Hubert/Daniel) | AN7: Testing in progress by Barnes | AQ7: =CONCATENATE(B7, " ", A7, " ",C7, " ", E7) -> CNP002 CenPos Payment Capture OTC | AR7: SFDC01 Salesforce Item OTC
A8: Salesforce | B8: SFDC02 | C8: Customer | E8: OTC | F8: Barnes | G8: Robert | H8: Torbjörn | I8: Out of Scope | K8: Out of Scope | N8: =VLOOKUP(K8,'Drop Down'!$I$2:$K$14,3,FALSE) -> 60 | O8: =SUM(M8:N8) -> 60 | P8: =TODAY()+O8 -> 46355 | S8: NA | T8: 45349 | W8: Martin | Y8: Martin | AH8: Daniel/Martin | AK8: Martin | AL8: ANA-050 started ready for review Feb 2 20240126: Meeting anc coclusion is no integration between M3 ans SF. All is going between SF _ Azure •3/20 no longer needed | AM8: Martin | AQ8: =CONCATENATE(B8, " ", A8, " ",C8, " ", E8) -> SFDC02 Salesforce Customer OTC | AR8: SFDC02 Salesforce Customer OTC
A9: Salesforce | B9: SFDC03 | C9: ShipToPartyMaster / Addresses | E9: OTC | F9: Barnes | G9: Robert | H9: Torbjörn | I9: Out of Scope | K9: Out of Scope | N9: =VLOOKUP(K9,'Drop Down'!$I$2:$K$14,3,FALSE) -> 60 | O9: =SUM(M9:N9) -> 60 | P9: =TODAY()+O9 -> 46355 | S9: NA | T9: 45349 | W9: Martin | Y9: Martin | AH9: Daniel/Martin | AK9: Martin | AL9: Credti limit was Removed from scope during CRP. Payment terms on Customer is enought, replaced by ShipToPartyMaster / Addresses. Martin start ANA-050 Jan 29 20240126: Meeting and conclusion is this will not be done in M3CE. Barnes handle the int between SF- AZureDB •3/20 no longer needed | AM9: Martin | AQ9: =CONCATENATE(B9, " ", A9, " ",C9, " ", E9) -> SFDC03 Salesforce ShipToPartyMaster / Addresses OTC | AR9: SFDC03 Salesforce Customer Credit OTC
A10: Cforia | B10: CFO001 | C10: Customer Payments & Credits | D10: No | E10: Finance | F10: Barnes | G10: Kim | H10: Dean | I10: Not Started | K10: Speccing (ANA-050) | N10: =VLOOKUP(K10,'Drop Down'!$I$2:$K$14,3,FALSE) -> 30 | O10: =SUM(M10:N10) -> 30 | P10: =TODAY()+O10 -> 46325 | Q10: Rachelle | S10: WIP | U10: 45565 | W10: Martin | Y10: Dean | AK10: Dean | AL10: 09/16 New Infor finance resource Rachelle Malahito onboarded this week to start work on CFORIA ANA-050 Barnes Kevin Alexander starting on this. Barnes Cforia test environment | AN10: Testing in progress by Barnes | AQ10: =CONCATENATE(B10, " ", A10, " ",C10, " ", E10) -> CFO001 Cforia Customer Payments & Credits Finance | AR10: SFDC04 Salesforce Item Pricing OTC
A11: Cforia | B11: CFO002 | C11: Customer Order | D11: No | E11: Finance | F11: Barnes | G11: Kim | H11: Dean | I11: Not Started | K11: Speccing (ANA-050) | N11: =VLOOKUP(K11,'Drop Down'!$I$2:$K$14,3,FALSE) -> 30 | O11: =SUM(M11:N11) -> 30 | P11: =TODAY()+O11 -> 46325 | Q11: Rachelle | S11: WIP | U11: 45565 | W11: Martin | Y11: Dean | AK11: Dean | AL11: 09/16 New Infor finance resource Rachelle Malahito onboarded this week to start work on CFORIA ANA-050 Barnes Kevin Alexander starting on this | AQ11: =CONCATENATE(B11, " ", A11, " ",C11, " ", E11) -> CFO002 Cforia Customer Order Finance | AR11: EDI001 SPS Commerce EDI EDI Sales Order OTC
A12: Cforia | B12: CFO003 | C12: Customer Master | D12: No | E12: Finance | F12: Barnes | G12: Kim | H12: Dean | I12: Not Started | K12: Speccing (ANA-050) | N12: =VLOOKUP(K12,'Drop Down'!$I$2:$K$14,3,FALSE) -> 30 | O12: =SUM(M12:N12) -> 30 | P12: =TODAY()+O12 -> 46325 | Q12: Rachelle | S12: WIP | U12: 45565 | W12: Martin | Y12: Dean | AK12: Dean | AL12: 09/16 New Infor finance resource Rachelle Malahito onboarded this week to start work on CFORIA ANA-050 Barnes Kevin Alexander starting on this | AQ12: =CONCATENATE(B12, " ", A12, " ",C12, " ", E12) -> CFO003 Cforia Customer Master Finance | AR12: EDI002 SPS Commerce EDI EDI Shipment OTC
A13: Cforia | B13: CFO004 | C13: Invoice Payment History | D13: No | E13: Finance | F13: Barnes | G13: Kim | H13: Dean | I13: Not Started | K13: Speccing (ANA-050) | N13: =VLOOKUP(K13,'Drop Down'!$I$2:$K$14,3,FALSE) -> 30 | O13: =SUM(M13:N13) -> 30 | P13: =TODAY()+O13 -> 46325 | Q13: Rachelle | S13: WIP | U13: 45565 | W13: Martin | Y13: Dean | AK13: Dean | AL13: 09/16 New Infor finance resource Rachelle Malahito onboarded this week to start work on CFORIA ANA-050 Barnes Kevin Alexander starting on this | AQ13: =CONCATENATE(B13, " ", A13, " ",C13, " ", E13) -> CFO004 Cforia Invoice Payment History Finance | AR13: EDI003 SPS Commerce EDI EDI Sales Order Ack OTC
A14: Cforia | B14: CFO005 | C14: Invoice Copies IDM (PDF) | D14: No | E14: Finance | F14: Barnes | G14: Kim | H14: Dean | I14: Not Started | K14: Speccing (ANA-050) | N14: =VLOOKUP(K14,'Drop Down'!$I$2:$K$14,3,FALSE) -> 30 | O14: =SUM(M14:N14) -> 30 | P14: =TODAY()+O14 -> 46325 | Q14: Rachelle | S14: WIP | U14: 45565 | W14: Martin | Y14: Karin | AK14: Karin | AL14: 09/16 New Infor finance resource Rachelle Malahito onboarded this week to start work on CFORIA ANA-050 Barnes Kevin Alexander starting on this | AQ14: =CONCATENATE(B14, " ", A14, " ",C14, " ", E14) -> CFO005 Cforia Invoice Copies IDM (PDF) Finance | AR14: EDI004 SPS Commerce EDI EDI Invoice OTC
A15: Concur | B15: CON002 | C15: Goods Receipts | D15: No | E15: Finance | F15: Barnes | G15: Kim | H15: Kevin | I15: Pre Development | K15: Development Testing | N15: =VLOOKUP(K15,'Drop Down'!$I$2:$K$14,3,FALSE) -> 12 | O15: =SUM(M15:N15) -> 12 | P15: =TODAY()+O15 -> 46307 | Q15: Dennis | S15: WIP | U15: 45555 | W15: Martin | Y15: Dean | AF15: Business | AK15: Dean | AL15: 09/16 Dennis to complete re-write of ANA-050 by 09/20. This ANA-050 consolidates CON001 002 003 004 and 005 into one document. 8/27 - Currently being tested by Amy/Kimberly Aug 20 Jimmy asked Dean for a test meeting. Metrics from Kim on current ASR match rate (cases we can improve in M3). Unit test plan - try full cycle. Dean to setup meeting Kim/Kevin 8/23: Meeting scheduled for 8/26 | AM15: Start week feb 5 | AQ15: =CONCATENATE(B15, " ", A15, " ",C15, " ", E15) -> CON002 Concur Goods Receipts Finance | AR15: EDI005 SPS Commerce EDI EDI Shipment Schedule EDI 862 OTC
A16: Concur | B16: CON003 | C16: PO Header | D16: No | E16: Finance | F16: Barnes | G16: Kim | H16: Kevin | I16: Pre Development | K16: Tech Spec (TAR-040) | N16: =VLOOKUP(K16,'Drop Down'!$I$2:$K$14,3,FALSE) -> 25 | O16: =SUM(M16:N16) -> 25 | P16: =TODAY()+O16 -> 46320 | Q16: Dennis | S16: WIP | U16: 45555 | W16: Martin | Y16: Dean | AF16: Business | AK16: Dean | AL16: 09/16 Dennis to complete re-write of ANA-050 by 09/20. This ANA-050 consolidates CON001 002 003 004 and 005 into one document. 8/27 - Currently being tested by Amy/Kimberly Aug 20 Jimmy asked Dean for a test meeting. Metrics from Kim on current ASR match rate (cases we can improve in M3). Unit test plan - try full cycle. Dean to setup meeting Kim/Kevin 8/23: Meeting scheduled for 8/26
A17: Concur | B17: CON004 | C17: PO Lines | D17: No | E17: Finance | F17: Barnes | G17: Kim | H17: Kevin | I17: Pre Development | K17: Tech Spec (TAR-040) | N17: =VLOOKUP(K17,'Drop Down'!$I$2:$K$14,3,FALSE) -> 25 | O17: =SUM(M17:N17) -> 25 | P17: =TODAY()+O17 -> 46320 | Q17: Dennis | S17: WIP | U17: 45555 | W17: Martin | Y17: Dean | AF17: Business | AK17: Dean | AL17: 09/16 Dennis to complete re-write of ANA-050 by 09/20. This ANA-050 consolidates CON001 002 003 004 and 005 into one document. 8/27 - Currently being tested by Amy/Kimberly Aug 20 Jimmy asked Dean for a test meeting. Metrics from Kim on current ASR match rate (cases we can improve in M3). Unit test plan - try full cycle. Dean to setup meeting Kim/Kevin 8/23: Meeting scheduled for 8/26 | AQ17: =CONCATENATE(B17, " ", A17, " ",C17, " ", E17) -> CON004 Concur PO Lines Finance | AR17: EDI006 SPS Commerce EDI Planning Schedule EDI 830 OTC
A18: SPS Commerce EDI | B18: EDI007 | C18: Application Advice EDI 824 | E18: OTC | F18: Infor | G18: Melissa | H18: Jeff | I18: Out of Scope | K18: Out of Scope | N18: =VLOOKUP(K18,'Drop Down'!$I$2:$K$14,3,FALSE) -> 60 | O18: =SUM(M18:N18) -> 60 | P18: =TODAY()+O18 -> 46355 | Q18: Cheska | S18: N/A | T18: N/A | U18: N/A | V18: N/A | W18: Martin | X18: N/A | Z18: N/A | AA18: N/A | AB18: N/A | AI18: N/A | AJ18: N/A | AK18: N/A | AL18: 8/6/24: this is not part of the SPS Contract so no dev on any side. Review 824, 860 and 997 and in SPS Commerce Portal so no DEV on infor side •Barnes working to get contract with SPS | AM18: N/A | AQ18: =CONCATENATE(B18, " ", A18, " ",C18, " ", E18) -> EDI007 SPS Commerce EDI Application Advice EDI 824 OTC | AR18: EDI007 SPS Commerce EDI Application Advice EDI 824 OTC
A19: Concur | B19: CON005 | C19: Vendor Infor | D19: No | E19: Finance | F19: Barnes | G19: Kim | H19: Kevin | I19: Pre Development | K19: Tech Spec (TAR-040) | N19: =VLOOKUP(K19,'Drop Down'!$I$2:$K$14,3,FALSE) -> 25 | O19: =SUM(M19:N19) -> 25 | P19: =TODAY()+O19 -> 46320 | Q19: Dennis | S19: WIP | U19: 45555 | W19: Martin | Y19: Dean | AF19: Business | AK19: Dean | AL19: 09/16 Dennis to complete re-write of ANA-050 by 09/20. This ANA-050 consolidates CON001 002 003 004 and 005 into one document. 8/27 - Currently being tested by Amy/Kimberly Aug 20 Jimmy asked Dean for a test meeting. Metrics from Kim on current ASR match rate (cases we can improve in M3). Unit test plan - try full cycle. Dean to setup meeting Kim/Kevin 8/23: Meeting scheduled for 8/26 | AN19: PNC to provide a PM and Resource. Create Scope of Work, Send Approval to Barnes. | AQ19: =CONCATENATE(B19, " ", A19, " ",C19, " ", E19) -> CON005 Concur Vendor Infor Finance | AR19: FIN001 PNC Bank (AR) PNC Lockbok Finance
A20: Concur | B20: CON001 | C20: SupplierInvoice | D20: Yes | E20: Finance | F20: Infor | G20: Kim | H20: Kevin | I20: Testing | K20: Speccing (ANA-050) | N20: =VLOOKUP(K20,'Drop Down'!$I$2:$K$14,3,FALSE) -> 30 | O20: =SUM(M20:N20) -> 30 | P20: =TODAY()+O20 -> 46325 | Q20: Dennis | S20: WIP | U20: 45555 | W20: Jen | X20: Completed | Z20: Completed | AC20: Completed | AD20: 45415 | AF20: Business | AG20: Amy Kimberly | AL20: 09/16 Dennis to complete re-write of ANA-050 by 09/20. This ANA-050 consolidates CON001 002 003 004 and 005 into one document. 8/27 - Currently being tested by Amy/Kimberly Aug 20 Jimmy asked Dean for a test meeting. Metrics from Kim on current ASR match rate (cases we can improve in M3). Unit test plan - try full cycle. Dean to setup meeting Kim/Kevin 8/23: Meeting scheduled for 8/26 | AM20: Kimberly/Amy +Dennis ANA-050 | AN20: -PNC to provide a PM and Resource. Create Scope of Work, Send Approval to Barnes. -Dennis to finalize field mappings for ANA-50 | AQ20: =CONCATENATE(B20, " ", A20, " ",C20, " ", E20) -> CON001 Concur SupplierInvoice Finance | AR20: FIN002 PNC Bank (AR) PNC Matcher file Finance
A21: Concur | B21: CONO06 | C21: T&E expense posting | D21: No | E21: Finance | F21: Infor | G21: Kim | H21: Kevin | I21: Pre Development | K21: Speccing (ANA-050) | Q21: Rachelle | S21: WIP | U21: 45565 | W21: Martin | AL21: 09/16 New Infor finance resource Rachelle Malahito onboarded this week to start work on CONCUR Expenses ANA-050 | AM21: Rachelle ANA-050 | AN21: PNC to provide a PM and Resource. Create Scope of Work, Send Approval to Barnes. | AQ21: =CONCATENATE(B21, " ", A21, " ",C21, " ", E21) -> CONO06 Concur T&E expense posting Finance
A22: Fedex | B22: FED001 | C22: FedEx Tracking Number Update | D22: No | E22: Supply chain | F22: Infor | G22: Lori | H22: Jeff | I22: Pre Development | K22: Tech Spec (TAR-040) | N22: =VLOOKUP(K22,'Drop Down'!$I$2:$K$14,3,FALSE) -> 25 | O22: =SUM(M22:N22) -> 25 | P22: =TODAY()+O22 -> 46320 | Q22: Cheska | R22: WIP | S22: Completed | T22: 45457 | U22: Completed | V22: 45407 | W22: Martin | X22: Pending Approval | Y22: Dean | AF22: Business | AG22: Dean | AL22: 9/25 - Sample File provided by Dean, Cheska to update ANA-50. Questions: Where is the Custom PO Number in the sample file? it is missing. We begin development once ANA-50 is updated for FedEx and Question answered 9/18 - open questions re database pull from Dean, cheska to reply 8/29 - Daniel has replied that there is only a configuration in both systems to convert the files from CSV to XML, awaiting dean's reply 8/27 - Sent follow up to Dean for the requested connection details. Dean will try to do it next week if not busy. Aug 20 Martin have tested but need test data and test from server 8/6/24: need to have the picking list editted to reflect the barcode scan, will follow up with Peter and Karin for their time | AM22: Barnes (Dean) | AN22: Need to approve ANA-50 | AQ22: =CONCATENATE(B22, " ", A22, " ",C22, " ", E22) -> FED001 Fedex FedEx Tracking Number Update Supply chain | AR22: FIN003 Shared Service (AP) Check Run Header Finance
A23: Fedex | B23: FED002 | C23: FedEx Shipping information | D23: Yes | E23: Supply chain | F23: Barnes | G23: Dan | H23: Jeff | I23: Pre Development | K23: Tech Spec (TAR-040) | N23: =VLOOKUP(K23,'Drop Down'!$I$2:$K$14,3,FALSE) -> 25 | O23: =SUM(M23:N23) -> 25 | P23: =TODAY()+O23 -> 46320 | T23: to Sonja, review 3/26 | Y23: Jeff | AK23: Jeff | AN23: Need to approve ANA-50 | AQ23: =CONCATENATE(B23, " ", A23, " ",C23, " ", E23) -> FED002 Fedex FedEx Shipping information Supply chain | AR23: FIN004 Shared Service (AP) Check Run Details Finance
A24: Optimizely | B24: OPT006 | C24: Order (email) | D24: No | E24: OTC | F24: Infor | G24: Amy B / Beth W | H24: Dean | I24: Pre Development | K24: Tech Spec (TAR-040) | N24: =VLOOKUP(K24,'Drop Down'!$I$2:$K$14,3,FALSE) -> 25 | O24: =SUM(M24:N24) -> 25 | P24: =TODAY()+O24 -> 46320 | Q24: Cheska | R24: WIP | S24: Completed | T24: 45470 | U24: Completed | V24: 45430 | W24: Martin | X24: Completed | AC24: Completed | AF24: Business | AL24: 9/18/ - ready to test, consid to transform file to xml 8/29/24: build from infor side done, ready to test as long as there is an XML file ready to be ingested. 8/20/24: low prioirty on the list, but ready to test as long as consid can map to the XML 8/6/24: no work needed from Infor end, the work is on Consid. Shall we bring Order in Scope or stick to email? possible BODs usage? | AM24: Barnes | AQ24: =CONCATENATE(B24, " ", A24, " ",C24, " ", E24) -> OPT006 Optimizely Order (email) OTC | AR24: CFO001 Cforia Customer Payments & Credits Finance
A25: Optimizely | B25: OPT001 | C25: Customer and Addresses | D25: No | E25: OTC | F25: Barnes | G25: Amy B / Beth W | H25: Jeff | I25: Not Started | K25: Speccing (ANA-050) | N25: =VLOOKUP(K25,'Drop Down'!$I$2:$K$14,3,FALSE) -> 30 | O25: =SUM(M25:N25) -> 30 | P25: =TODAY()+O25 -> 46325 | Q25: Hubert | S25: Completed | Y25: Dean | AK25: Dean | AL25: extract azure data for use in optimizely, working call 3/25 | AQ25: =CONCATENATE(B25, " ", A25, " ",C25, " ", E25) -> OPT001 Optimizely Customer and Addresses OTC | AR25: CFO002 Cforia Customer Order Finance
A26: Optimizely | B26: OPT002 | C26: Items | D26: No | E26: OTC | F26: Barnes | G26: Amy B / Beth W | H26: Jeff | I26: Not Started | K26: Speccing (ANA-050) | N26: =VLOOKUP(K26,'Drop Down'!$I$2:$K$14,3,FALSE) -> 30 | O26: =SUM(M26:N26) -> 30 | P26: =TODAY()+O26 -> 46325 | Q26: Hubert | S26: Completed | Y26: Dean | AK26: Dean | AL26: ANA050 ready Sep 4 working call 3/25 | AQ26: =CONCATENATE(B26, " ", A26, " ",C26, " ", E26) -> OPT002 Optimizely Items OTC | AR26: CFO003 Cforia Customer Master Finance
A27: Optimizely | B27: OPT003 | C27: Std Price, Cust price, Disc | D27: No | E27: OTC | F27: Barnes | G27: Amy B / Beth W | H27: Jeff | I27: Not Started | K27: Speccing (ANA-050) | N27: =VLOOKUP(K27,'Drop Down'!$I$2:$K$14,3,FALSE) -> 30 | O27: =SUM(M27:N27) -> 30 | P27: =TODAY()+O27 -> 46325 | Q27: Hubert | S27: Completed | Y27: Dean | AK27: Dean | AL27: ANA050 ready Sep 4 working call 3/25 | AQ27: =CONCATENATE(B27, " ", A27, " ",C27, " ", E27) -> OPT003 Optimizely Std Price, Cust price, Disc OTC | AR27: CFO004 Cforia Invoice Payment History Finance
A28: Optimizely | B28: OPT004 | C28: Tax exemption | D28: No | E28: OTC | F28: Barnes | G28: Amy B / Beth W | H28: Jeff | I28: Not Started | K28: Speccing (ANA-050) | N28: =VLOOKUP(K28,'Drop Down'!$I$2:$K$14,3,FALSE) -> 30 | O28: =SUM(M28:N28) -> 30 | P28: =TODAY()+O28 -> 46325 | Q28: Hubert | S28: Completed | Y28: Dean | AK28: Dean | AL28: ANA050 ready Sep 4 working call 3/25 | AQ28: =CONCATENATE(B28, " ", A28, " ",C28, " ", E28) -> OPT004 Optimizely Tax exemption OTC | AR28: CFO005 Cforia Invoice Copies IDM (PDF) Finance
A29: Optimizely | B29: OPT005 | C29: Stock | D29: No | E29: OTC | F29: Barnes | G29: Amy B / Beth W | H29: Jeff | I29: Not Started | K29: Speccing (ANA-050) | N29: =VLOOKUP(K29,'Drop Down'!$I$2:$K$14,3,FALSE) -> 30 | O29: =SUM(M29:N29) -> 30 | P29: =TODAY()+O29 -> 46325 | Q29: Hubert | S29: Completed | Y29: Dean | AK29: Dean | AL29: ANA050 ready Sep 4 Sent sample of M3_InventoryCountReport to Dean 240201, working call 3/25 | AM29: Can we use BOD? | AN29: Dean will try provide mappings for FedEx next week. Currently busy this week. Dean to provide connection details for shared folder | AQ29: =CONCATENATE(B29, " ", A29, " ",C29, " ", E29) -> OPT005 Optimizely Stock OTC | AR29: FED001 Fedex FedEx Tracking Number Update Supply chain
A30: PNC Bank (AR) (SPS) | B30: FIN002 | C30: PNC Matcher file | D30: No | E30: Finance | F30: Infor | G30: Kim | H30: Jeff | I30: Pre Development | K30: Speccing (ANA-050) | N30: =VLOOKUP(K30,'Drop Down'!$I$2:$K$14,3,FALSE) -> 30 | O30: =SUM(M30:N30) -> 30 | P30: =TODAY()+O30 -> 46325 | Q30: Dennis | S30: WIP | U30: 45562 | W30: Martin | AL30: 09/16 Dennis to complete ANA-050 draft by 09/25 08/27 Dennis had a meeting with PNC and Barnes and SPS. PNC Bank discussed the scope with Barnes 08/08 Dennis initiated weekly recurring calls to track progress. Dean to get the JBA and PNC together to discuss the current process and required specs. | AM30: PNC Bank & Infor(Dennis) | AQ30: =CONCATENATE(B30, " ", A30, " ",C30, " ", E30) -> FIN002 PNC Bank (AR) (SPS) PNC Matcher file Finance | AR30: FED002 Fedex FedEx Shipping information Supply chain
A31: Salesforce | B31: SFDC01 | C31: Item | D31: No | E31: OTC | F31: Infor | G31: Torbjörn | H31: Torbjörn | I31: Testing | K31: Business Testing | N31: =VLOOKUP(K31,'Drop Down'!$I$2:$K$14,3,FALSE) -> 2 | O31: =SUM(M31:N31) -> 2 | P31: =TODAY()+O31 -> 46297 | Q31: Jen | S31: Completed | T31: 45349 | W31: Jen | X31: Completed | Z31: Completed | AF31: Business | AG31: Torbjorn | AI31: Pending Confirmation | AL31: DES-030 ready. DEVFMC should be ready Sep 27 and PartCopy Oct 04 Sept 13 - setting up a new Salesforce environment for testing. Also changing Dev environment, which is the last step. August 27 - Successful Testing with Torbjorn. Testing session planned for Aug 27 with Torbjorn Aug 8 issue fixed and new test session with Torbjörn this week. April 11 - Torbjorn for validation Apri 10 - doc this week, Jen tested Wednesday | AM31: Torbjorn | AN31: Dean to provide connection details for shared folder | AQ31: =CONCATENATE(B31, " ", A31, " ",C31, " ", E31) -> SFDC01 Salesforce Item OTC | AR31: UPS001 UPS UPS Tracking Number Update Supply chain
A32: Salesforce | B32: SFDC04 | C32: Item Pricing | D32: No | E32: OTC | F32: Infor | G32: Torbjörn | H32: Torbjörn | I32: Testing | K32: Business Testing | N32: =VLOOKUP(K32,'Drop Down'!$I$2:$K$14,3,FALSE) -> 2 | O32: =SUM(M32:N32) -> 2 | P32: =TODAY()+O32 -> 46297 | Q32: Jen | S32: Completed | T32: 45349 | W32: Jen | X32: Completed | Z32: Completed | AF32: Business | AG32: Torbjorn | AI32: Pending Confirmation | AL32: DES-030 Ready. DEVFMC should be ready Sep 27 and PartCopy Oct 04 Sept 13 - setting up a new Salesforce environment for testing. Also changing Dev environment, which is the last step. August 27 - Successful Testing with Torbjorn. Testing session planned for Aug 27 with Torbjorn Aug 8 issue fixed and new test session with Torbjörn this week. July 30 -0 pending further testing by Torbjorn April 28 - TST070. Then Hubert to test afert getting access. April 11 - Torbjorn for validate 4/11 April 10 doc this week, jen test wed 4/10 2 Feb - ANA-050 started ready for review Feb 2 | AM32: Torbjorn | AQ32: =CONCATENATE(B32, " ", A32, " ",C32, " ", E32) -> SFDC04 Salesforce Item Pricing OTC | AR32: UPS002 UPS UPS Shipping Information Supply chain
A33: SPS Commerce EDI | B33: EDI001 | C33: EDI Sales Order 850 | D33: No | E33: OTC | F33: Infor | G33: Melissa | H33: Jeff | I33: Testing | K33: Development Testing | L33: Testing | M33: 10 | N33: =VLOOKUP(K33,'Drop Down'!$I$2:$K$14,3,FALSE) -> 12 | O33: =SUM(M33:N33) -> 22 | P33: =TODAY()+O33 -> 46317 | Q33: Cheska | R33: Complete | S33: Completed | T33: 45460 | U33: Completed | V33: 45430 | W33: Martin | AB33: 45460 | AF33: Technical | AH33: 45461 | AL33: 9/18/24: tested Grainger, SPS to send down MSC and PACCAR 8/29/24: asked SPS commerce to send down one trading partner for testing, cheska to check if there are any issues and process file until invoice. 8/20/24: paased initial test ready to test for SIT 8/16/24: ready to test we need raw files we need more raw files to drop 8/7/24:: infor mec mapping changes done, Infor functional to test 8/6/24: build completed from SPS commerce side, a few mapping needs to be done from infor tech Jeff has a quote from SPS Commerce, need to schedule follow up meeting to review details with Daniel and team •Barnes working to get contract with SPS | AM33: SIT | AN33: Contact Hubert Santos on updates from testing the standard implementation | AQ33: =CONCATENATE(B33, " ", A33, " ",C33, " ", E33) -> EDI001 SPS Commerce EDI EDI Sales Order 850 OTC | AR33: WOR001 Worldpay Payment Authorization OTC
A34: SPS Commerce EDI | B34: EDI002 | C34: EDI Shipment 856 | D34: No | E34: OTC | F34: Infor | G34: Melissa | H34: Jeff | I34: Pre Development | K34: Tech Spec (TAR-040) | M34: 20 | N34: =VLOOKUP(K34,'Drop Down'!$I$2:$K$14,3,FALSE) -> 25 | O34: =SUM(M34:N34) -> 45 | P34: =TODAY()+O34 -> 46340 | Q34: Cheska | R34: Complete | S34: Completed | T34: Complete | U34: Completed | W34: Martin | X34: WIP | AL34: 9/18/24: tested Grainger, SPS to send down MSC and PACCAR 8/29/24: asked SPS commerce to send down one trading partner for testing, cheska to check if there are any issues and process file until invoice 8/20/24: waiting for SPS commerce to give feedback on structure 8/16/24: completed build from SPS, infor sent out a test xml, waiting for SPS to validate if it passed through or not. 8/9/24: ANA050 uploaded to be reviewed by Barnes 8/6/24: currently with SPS commerce development. This EDI 856 would need to make use of dummy standard packaging to work, this has been agreed on with Sonja, Amy and Melissa. May want to add FYX consultant to team •Barnes working to get contract with SPS | AM34: Infor | AN34: Contact Hubert Santos on updates from testing the standard implementation | AQ34: =CONCATENATE(B34, " ", A34, " ",C34, " ", E34) -> EDI002 SPS Commerce EDI EDI Shipment 856 OTC | AR34: WOR002 Worldpay Payment Capture OTC
A35: SPS Commerce EDI | B35: EDI003 | C35: EDI Sales Order Ack | D35: No | E35: OTC | F35: Infor | G35: Melissa | H35: Jeff | I35: Development | K35: Speccing (ANA-050) | M35: 20 | N35: =VLOOKUP(K35,'Drop Down'!$I$2:$K$14,3,FALSE) -> 30 | O35: =SUM(M35:N35) -> 50 | P35: =TODAY()+O35 -> 46345 | Q35: Cheska | R35: Complete | S35: Completed | T35: Complete | U35: Completed | W35: Martin | AL35: 9/18/24: tested Grainger, SPS to send down MSC and PACCAR 8/29/24: finished development from SPS end, WIP development from Infor. 8/20/24: need to align development from Infor end 8/7/24: meeting with barnes finished, need to send acknowledgement codes. need to validate with Martin if the current standard bod is using the newest version of the 855 mapping uploaded in concierge. 8/6/24: to be discussed on 8/7/24 with Barnes •Barnes working to get contract with SPS | AM35: Infor | AQ35: =CONCATENATE(B35, " ", A35, " ",C35, " ", E35) -> EDI003 SPS Commerce EDI EDI Sales Order Ack OTC | AR35: OPT001 Optimizely Customer and Addresses OTC
A36: SPS Commerce EDI | B36: EDI004 | C36: EDI Invoice | D36: No | E36: OTC | F36: Infor | G36: Melissa | H36: Jeff | I36: Development | K36: Tech Spec (TAR-040) | M36: 20 | N36: =VLOOKUP(K36,'Drop Down'!$I$2:$K$14,3,FALSE) -> 25 | O36: =SUM(M36:N36) -> 45 | P36: =TODAY()+O36 -> 46340 | Q36: Cheska | R36: Complete | S36: Completed | T36: 45519 | U36: Completed | W36: Martin | AL36: 9/18/24: tested Grainger, SPS to send down MSC and PACCAR 8/29/ 24: development done from SPS, testing in progress. asked SPS commerce to send down one trading partner for testing, cheska to check if there are any issues and process file until invoice 8/20/24: SPS to confirm if build is done 8/16/24: ANA050 approved 8/12/24: ANA050 completed, current build is with SPS Commerce 8/6/24: SPS commerce is doing the build as of today •Barnes working to get contract with SPS | AM36: Infor | AQ36: =CONCATENATE(B36, " ", A36, " ",C36, " ", E36) -> EDI004 SPS Commerce EDI EDI Invoice OTC | AR36: OPT002 Optimizely Items OTC
A37: SPS Commerce EDI | B37: EDI005 | C37: EDI Shipment Schedule EDI 862 | D37: No | E37: OTC | F37: Infor | G37: Melissa | H37: Jeff | I37: Pre Development | K37: Tech Spec (TAR-040) | M37: 20 | N37: =VLOOKUP(K37,'Drop Down'!$I$2:$K$14,3,FALSE) -> 25 | O37: =SUM(M37:N37) -> 45 | P37: =TODAY()+O37 -> 46340 | Q37: Cheska | R37: Complete | S37: Completed | T37: 45460 | U37: Completed | V37: 45474 | W37: Martin | AL37: 9/18/24: tested Grainger, SPS to send down MSC and PACCAR 8/29/24: asked SPS commerce to send down one trading partner for testing, cheska to check if there are any issues and process file until invoice 8/20/24: SPS clarifications cleared, need to send down test data 8/16/24: need more raw data to test 8/7/24:: infor mec mapping changes done, Infor functional to test SPS to send more data for more customers 8/6/24: SPS dev completed, SPS commerce to send in more data for more testing Barnes working to get contract with SPS | AM37: Infor | AQ37: =CONCATENATE(B37, " ", A37, " ",C37, " ", E37) -> EDI005 SPS Commerce EDI EDI Shipment Schedule EDI 862 OTC | AR37: OPT003 Optimizely Std Price, Cust price, Disc OTC
A38: SPS Commerce EDI | B38: TBD | C38: DSV | AQ38: =CONCATENATE(B38, " ", A38, " ",C38, " ", E38) -> TBD SPS Commerce EDI DSV | AR38: OPT004 Optimizely Tax exemption OTC
A39: SPS Commerce EDI | B39: EDI006 | C39: Planning Schedule EDI 830 | D39: No | E39: OTC | F39: Infor | G39: Melissa | H39: Jeff | I39: Pre Development | K39: Tech Spec (TAR-040) | L39: Testing | M39: 10 | N39: =VLOOKUP(K39,'Drop Down'!$I$2:$K$14,3,FALSE) -> 25 | O39: =SUM(M39:N39) -> 35 | P39: =TODAY()+O39 -> 46330 | Q39: Cheska | R39: Complete | S39: Completed | T39: 45460 | U39: Completed | V39: 45483 | W39: Martin | AH39: 45492 | AL39: 9/18/24: tested Grainger, SPS to send down MSC and PACCAR 8/29/24: asked SPS commerce to send down one trading partner for testing, cheska to check if there are any issues and process file until invoice 8/20/24: SPS clarifications cleared, need to send down test data 8/16/24: need more raw data to test 8/7/24:: infor mec mapping changes done, Infor functional to test SPS to send more data for more customers 8/6/24: SPS dev completed, SPS commerce to send in more data for more testing , only firmed orders are integrated. •Barnes working to get contract with SPS | AM39: Infor | AQ39: =CONCATENATE(B39, " ", A39, " ",C39, " ", E39) -> EDI006 SPS Commerce EDI Planning Schedule EDI 830 OTC | AR39: OPT005 Optimizely Stock OTC
A40: UPS | B40: UPS002 | C40: UPS Shipping Information | D40: No | E40: Supply chain | F40: Barnes | G40: Dan | H40: Jeff | I40: Pre Development | K40: Tech Spec (TAR-040) | N40: =VLOOKUP(K40,'Drop Down'!$I$2:$K$14,3,FALSE) -> 25 | O40: =SUM(M40:N40) -> 25 | P40: =TODAY()+O40 -> 46320 | Q40: Cheska | R40: WIP | S40: Completed | T40: 45457 | U40: Completed | V40: 45407 | X40: Completed | AK40: Jeff | AN40: Contact Cheska(Infor) for latest updates | AQ40: =CONCATENATE(B40, " ", A40, " ",C40, " ", E40) -> UPS002 UPS UPS Shipping Information Supply chain | AR40: OPT006 Optimizely Order (email) OTC
A41: UPS | B41: UPS001 | C41: UPS Tracking Number Update | D41: No | E41: Supply chain | F41: Infor | G41: Lori | H41: Jeff | I41: Pre Development | K41: Tech Spec (TAR-040) | N41: =VLOOKUP(K41,'Drop Down'!$I$2:$K$14,3,FALSE) -> 25 | O41: =SUM(M41:N41) -> 25 | P41: =TODAY()+O41 -> 46320 | Q41: Cheska | R41: WIP | S41: Completed | T41: 45457 | U41: Completed | V41: 45407 | W41: Martin | X41: Completed | AL41: 9/25 - UPS to M3 Integration Interface is completed, ANA-50 and TAR-40 in Sharepoint under "UPS_FedEx" folder 9/18 - open questions re database pull from Dean, cheska to reply 8/29 - Daniel has replied that there is only a configuration in both systems to convert the files from CSV to XML, awaiting dean's reply 8/27 - Sent follow up to Dean for the requested shared folder connection details. Dean will try to do it next week if not busy. Aug 20 Martin have tested but need test data and test from server 8/6/24: need to have the picking list editted to reflect the barcode scan will follow up with Peter and Karin for their time | AM41: Barnes (Dean) | AQ41: =CONCATENATE(B41, " ", A41, " ",C41, " ", E41) -> UPS001 UPS UPS Tracking Number Update Supply chain

Sheet Action Items
A1: Date Added | B1: Integration | C1: Priority | D1: Action | E1: Owner | F1: Due Date | G1: Status | H1: Comment | J1: =TODAY() -> 46295
A2: 45303 | B2: SPS Commerce EDI | D2: Determine if need to add FYX to project team 1/19: Jeff determined not needed | E2: Jeff | F2: 45310 | G2: Closed
A3: 45303 | B3: Optimizely | D3: Add Petter E to weekly meetings? | E3: Petter S | F3: 45310 | G3: Closed
A4: 45303 | B4: Worldpay | D4: Should Petter be added to Worldpay integration? He was working on Worldpay account creation | E4: Petter S | F4: 45310 | G4: Closed
A5: 45303 | B5: SPS Commerce EDI | D5: Jeff has a quote from SPS Commerce, need to schedule follow up meeting to review details with Daniel and team | E5: Jeff | F5: 45317 | G5: Closed
A6: 45310 | B6: Concur | D6: Schedule Barnes/Infor Meeting for week of 1/22 to align team | E6: Daniel | F6: 45317 | G6: Closed
A7: 45366 | B7: All | D7: Switch testing to 910 | E7: Daniel | F7: 45387 | G7: Closed | H7: =CONCATENATE(Table1[[#This Row],[Integration]], ", ", Table1[[#This Row],[Action]], ", ", Table1[[#This Row],[Owner]]) -> All, Switch testing to 910, Daniel
A8: 45366 | B8: All | D8: Need service account created in M3 for file drop | E8: Jeff | F8: 45373 | G8: closed | H8: =CONCATENATE(Table1[[#This Row],[Integration]], ", ", Table1[[#This Row],[Action]], ", ", Table1[[#This Row],[Owner]]) -> All, Need service account created in M3 for file drop, Jeff
A9: 45310 | B9: Worldpay | D9: Need info from Erik on contact info within Barnes/Worldpay | E9: Jeff | F9: 45317 | G9: Closed
A10: 45317 | B10: PNC Lockbox EDI820 flat file ACH ad wires | D10: Can we add PNC lockbox 820 to SPS commerce - Add Kim and Dean 2/2: Jeff will instruct SPS to include this | E10: Jeff | F10: 45324 | G10: closed
A11: 45324 | B11: Concur | D11: Emailed Steve to add to packaging standard / packing slip | E11: Sonja | F11: 45345 | G11: closed | H11: =CONCATENATE(Table1[[#This Row],[Integration]], ", ", Table1[[#This Row],[Action]], ", ", Table1[[#This Row],[Owner]]) -> Concur, Emailed Steve to add to packaging standard / packing slip , Sonja
A12: 45324 | B12: Concur | D12: Sync of data to Azure | E12: Petter | F12: 45330 | G12: Closed
A13: 45527 | B13: Concur | D13: Create Deployment Spec | E13: Dean | F13: 45627
A14: 45527 | B14: Salesforce | D14: Need to assign Torbjorn and Martin for Deployment | E14: Martin/Torbjorn | F14: 45627
A15: 45324 | B15: Concur | D15: Need to specify which fields from supplier invoice need to match (Delivery note field - PPS300) | E15: Daniel | F15: 45331 | G15: closed
A16: 45310 | B16: Fedex / UPS | D16: Need sample files to test 2/16: Jeff will send files going up today. | E16: Jeff | F16: 45317 | G16: Closed | H16: =CONCATENATE(Table1[[#This Row],[Integration]], ", ", Table1[[#This Row],[Action]], ", ", Table1[[#This Row],[Owner]]) -> Fedex / UPS, Need sample files to test 2/16: Jeff will send files going up today. , Jeff
A17: 45527 | B17: Concur | D17: Need test script for integration | E17: Dan Tuller | F17: 45566
A18: 45310 | B18: Fedex / UPS | C18: 1 | D18: Draft functional spec ready to review with Barnes | E18: Cheska | F18: 45366 | G18: closed | H18: =CONCATENATE(Table1[[#This Row],[Integration]], ", ", Table1[[#This Row],[Action]], ", ", Table1[[#This Row],[Owner]]) -> Fedex / UPS, Draft functional spec ready to review with Barnes, Cheska
A19: 45527 | B19: (SPS) PNC Bank (AR) | D19: Need to complete ANA-050 | E19: Dennis | F19: 45538
A20: 45345 | B20: Concur | D20: Setup SFTP for data transfer | E20: Karin | F20: 45352 | G20: Closed | H20: =CONCATENATE(Table1[[#This Row],[Integration]], ", ", Table1[[#This Row],[Action]], ", ", Table1[[#This Row],[Owner]]) -> Concur, Setup SFTP for data transfer, Karin
A21: 45530 | B21: (SPS) PNC Bank (AR) | D21: Complete TAR | F21: 45538
A22: 45359 | B22: Fedex / UPS | D22: Need to review mapping to/from JBA | E22: Cheska | F22: 45366 | G22: closed | H22: =CONCATENATE(Table1[[#This Row],[Integration]], ", ", Table1[[#This Row],[Action]], ", ", Table1[[#This Row],[Owner]]) -> Fedex / UPS, Need to review mapping to/from JBA, Cheska
A23: 45310 | B23: Salesforce | D23: Martin working on specs, will review with functional team when ready with Barnes | E23: Martin | F23: 45338 | G23: closed
A24: 45324 | B24: Salesforce | C24: 1 | D24: Need to review with Torbjörn when he returns | E24: Martin | F24: 45342 | G24: closed | H24: =CONCATENATE(Table1[[#This Row],[Integration]], ", ", Table1[[#This Row],[Action]], ", ", Table1[[#This Row],[Owner]]) -> Salesforce, Need to review with Torbjörn when he returns, Martin
A25: 45338 | B25: Salesforce | C25: 1 | D25: Daniel sent out functional spec, need Barnes review/approval | E25: Dean | F25: 45345 | G25: closed | H25: =CONCATENATE(Table1[[#This Row],[Integration]], ", ", Table1[[#This Row],[Action]], ", ", Table1[[#This Row],[Owner]]) -> Salesforce, Daniel sent out functional spec, need Barnes review/approval, Dean
A26: 45530 | B26: BoA Shared Service (AP) | D26: Complete TAR | E26: Isaiha | F26: 45548
A27: 45527 | B27: BoA Shared Service (AP) (details | D27: Need to complete ANA-050 | E27: Dennis | F27: 45538
A28: 45373 | B28: Optimizely | D28: Send M3 Project Timeline to Optimizely | E28: Sonja | F28: 45379 | G28: closed
A29: 45310 | B29: Worldpay | D29: Need a call with Worldpay to understand technical details & setup account - Jeff, Amy B, Daniel, Catherine L, Sonja | E29: Annastasia | F29: 45345 | G29: closed | H29: =CONCATENATE(Table1[[#This Row],[Integration]], ", ", Table1[[#This Row],[Action]], ", ", Table1[[#This Row],[Owner]]) -> Worldpay, Need a call with Worldpay to understand technical details & setup account - Jeff, Amy B, Daniel, Catherine L, Sonja, Annastasia
A30: 45338 | B30: Worldpay | D30: functional spec | E30: Daniel | F30: 45366 | G30: closed | H30: =CONCATENATE(Table1[[#This Row],[Integration]], ", ", Table1[[#This Row],[Action]], ", ", Table1[[#This Row],[Owner]]) -> Worldpay, functional spec, Daniel
A31: 45310 | B31: BoA Shared Service (AP) (header) | C31: 3 | D31: Will start functional spec after Cforia | E31: Dennis | F31: 45538
A32: 45530 | B32: BoA Shared Service (AP) (header) | D32: Complete TAR | E32: isiaha | F32: 45538
A33: 45530 | B33: CenPos | D33: ready for testing | E33: Hubert | F33: 45538
A34: 45366 | B34: Fedex / UPS | D34: Schedule functional spec review 4/12 was reviewed, but need functional Barnes approval. Will add Lori to meeting | E34: Sonja | F34: 45401 | G34: closed | H34: Dean to get signoff from Aaron
A35: 45359 | B35: Salesforce | D35: Identify new functional lead to replace lindsey listing Robert as replacement until another is identified | E35: Sonja | F35: 45366 | G35: closed
A36: 45310 | B36: Cforia | C36: 4 | D36: Start functional spec in Feb, not started, will start after Concur & PNC | E36: Dennis | F36: 45538 | G36: Not Started | H36: =CONCATENATE(Table1[[#This Row],[Integration]], ", ", Table1[[#This Row],[Action]], ", ", Table1[[#This Row],[Owner]]) -> Cforia, Start functional spec in Feb, not started, will start after Concur & PNC, Dennis
A37: 45366 | B37: Fedex / UPS | D37: Jeff to set up test machine with both UPS and Fedex, send machine name to Dean 8/26: Dean has machine name and IP address | E37: Jeff | F37: 45373 | G37: closed | H37: UPS - Jeff - Still in registration process, Jeff will send IP
A38: 45317 | B38: Cforia | C38: 4 | D38: Kevin is starting the technical spec, next step to find missing fields | E38: Kevin | F38: 45538 | G38: Started | H38: =CONCATENATE(Table1[[#This Row],[Integration]], ", ", Table1[[#This Row],[Action]], ", ", Table1[[#This Row],[Owner]]) -> Cforia, Kevin is starting the technical spec, next step to find missing fields, Kevin
A39: 45317 | B39: Concur | C39: 1 | D39: Jane W is starting technical spec, mapping in process | E39: Jane | F39: 45538 | G39: Started | H39: =CONCATENATE(Table1[[#This Row],[Integration]], ", ", Table1[[#This Row],[Action]], ", ", Table1[[#This Row],[Owner]]) -> Concur, Jane W is starting technical spec, mapping in process, Jane
A40: 45366 | B40: SPS Commerce EDI | D40: Finalize agreement with SPS | E40: Sonja | F40: 45373 | G40: Closed
A41: 45345 | B41: Worldpay | D41: Getting transaction & value info from Maumee. Qty sent, waiting on $ | E41: Annastasia | F41: 45373 | G41: Closed
A42: 45338 | B42: Concur | C42: 1 | D42: functional spec - schedule review for week of 3/18 4/12 - did this happen last week? 8/26: Schedule approval/review of ANA-050 | E42: Kim | F42: 45538 | H42: =CONCATENATE(Table1[[#This Row],[Integration]], ", ", Table1[[#This Row],[Action]], ", ", Table1[[#This Row],[Owner]]) -> Concur, functional spec - schedule review for week of 3/18 4/12 - did this happen last week? 8/26: Schedule approval/review of ANA-050, Kim
A43: 45338 | B43: Optimizely | C43: 1 | D43: Sales order automation option? follow up sent 3/8 3/22: Glenn will be sending Europe setup to model the same | E43: Annastasia | F43: 45387 | G43: closed | H43: =CONCATENATE(Table1[[#This Row],[Integration]], ", ", Table1[[#This Row],[Action]], ", ", Table1[[#This Row],[Owner]]) -> Optimizely, Sales order automation option? follow up sent 3/8 3/22: Glenn will be sending Europe setup to model the same, Annastasia
A44: 45530 | B44: Fedex / UPS | D44: Schedule separate meeting with Dean, Jeff, Daniel, Cheska, Petter, cc Sonja | E44: Jeff | F44: 45538
A45: 45310 | B45: Optimizely | C45: 1 | D45: Start on extracts / technical spec | E45: Dean | F45: 45538 | G45: working through current bugs | H45: =CONCATENATE(Table1[[#This Row],[Integration]], ", ", Table1[[#This Row],[Action]], ", ", Table1[[#This Row],[Owner]]) -> Optimizely, Start on extracts / technical spec, Dean
A46: 45310 | B46: Optimizely | C46: 1 | D46: Start on functional spec 3/22: Need more info on how new customers are handled (dummy acct or all new?) | E46: Hubert | F46: 45538 | H46: =CONCATENATE(Table1[[#This Row],[Integration]], ", ", Table1[[#This Row],[Action]], ", ", Table1[[#This Row],[Owner]]) -> Optimizely, Start on functional spec 3/22: Need more info on how new customers are handled (dummy acct or all new?), Hubert
A47: 45366 | B47: Optimizely | D47: Need test environment setup | E47: Robert Thompson | F47: 45538
A48: 45527 | B48: PNC Bank (AR) | D48: Need to complete ANA-050 | E48: Dennis | F48: 45538
A49: 45530 | B49: PNC Bank (AR) | D49: Complete TAR | E49: Martin | F49: 45538
A50: 45530 | B50: SPS Commerce EDI | D50: Need data files | E50: Jeff | F50: 45538
A51: 45530 | B51: SPS Commerce EDI | D51: Need approval/review of ANA-050 | E51: Melissa/Jeff | F51: 45538
A52: 45359 | B52: Salesforce | D52: Need to create connection from Salesforce and Azure, low priority | E52: Dean | F52: 45394 | G52: closed
A53: 45527 | B53: Salesforce | D53: Need to schedule testing with Torbjorn | E53: Torbjorn | F53: 45534
A54: 45527 | B54: Salesforce | D54: Need to approve TAR | E54: Torbjorn | F54: 45534
A55: 45533 | B55: CenPos | D55: Hubert to verify with Daniel if ANA-050 is needed, this is standard for M3 | E55: Hubert | F55: 45534
A56: 45310 | B56: SPS Commerce EDI | D56: Need to start the functional spec | E56: Cheska | F56: 45394 | G56: closed
A57: 45359 | B57: Salesforce | D57: Finalize for testing, Torbjörn requested additional testing Need pricing and products addressed | E57: Martin | F57: 45531 | H57: In process, see List for comments
A58: 45527 | B58: Concur | D58: testing scheduled for 8/26 | E58: Sonja | F58: 45530
A59: 45338 | B59: Fedex / UPS | C59: 1 | D59: Can we connect UPS/Fedex to Azure? - Schedule call with Dean | E59: Dean | F59: 45387 | G59: Need test machine | H59: =CONCATENATE(Table1[[#This Row],[Integration]], ", ", Table1[[#This Row],[Action]], ", ", Table1[[#This Row],[Owner]]) -> Fedex / UPS, Can we connect UPS/Fedex to Azure? - Schedule call with Dean , Dean
A60: 45457 | B60: SPS Commerce EDI | D60: Amazon interface today is a homegrown system, need to identify who knows about this interface | E60: Dean

Sheet Sheet2
C1: CON001 Concur SupplierInvoice Finance | D1: CON001
C2: CON001 - ANA-50 - Func Spec | D2: CON002 | I2: CON001 | J2: - ANA-50 - Func Spec | M2: =CONCATENATE(I2," ",J2) -> CON001 - ANA-50 - Func Spec
C3: CON001 - TAR-040 - Tech Spec | D3: CON003 | I3: CON001 | J3: - TAR-040 - Tech Spec | M3: =CONCATENATE(I3," ",J3) -> CON001 - TAR-040 - Tech Spec
C4: CON001 - TES-070 - Tech Spec | D4: CON004 | I4: CON001 | J4: - TES-070 - Tech Spec | M4: =CONCATENATE(I4," ",J4) -> CON001 - TES-070 - Tech Spec
C5: CON001 - DES-030 - Tech Spec | D5: CON005 | I5: CON001 | J5: - DES-030 - Tech Spec | M5: =CONCATENATE(I5," ",J5) -> CON001 - DES-030 - Tech Spec
C6: CON002 Concur Goods Receipts Finance | D6: SFDC01 | I6: CON002 | J6: - ANA-50 - Func Spec | M6: =CONCATENATE(I6," ",J6) -> CON002 - ANA-50 - Func Spec
C7: CON002 - ANA-50 - Func Spec | D7: SFDC02 | I7: CON002 | J7: - TAR-040 - Tech Spec | M7: =CONCATENATE(I7," ",J7) -> CON002 - TAR-040 - Tech Spec
C8: CON002 - TAR-040 - Tech Spec | D8: SFDC03 | I8: CON002 | J8: - TES-070 - Tech Spec | M8: =CONCATENATE(I8," ",J8) -> CON002 - TES-070 - Tech Spec
C9: CON002 - TES-070 - Tech Spec | D9: SFDC04 | I9: CON002 | J9: - DES-030 - Tech Spec | M9: =CONCATENATE(I9," ",J9) -> CON002 - DES-030 - Tech Spec
C10: CON002 - DES-030 - Tech Spec | D10: EDI001 | I10: CON003 | J10: - ANA-50 - Func Spec | M10: =CONCATENATE(I10," ",J10) -> CON003 - ANA-50 - Func Spec
C11: CON003 Concur PO Header Finance | D11: EDI002 | I11: CON003 | J11: - TAR-040 - Tech Spec | M11: =CONCATENATE(I11," ",J11) -> CON003 - TAR-040 - Tech Spec
C12: CON003 - ANA-50 - Func Spec | D12: EDI003 | I12: CON003 | J12: - TES-070 - Tech Spec | M12: =CONCATENATE(I12," ",J12) -> CON003 - TES-070 - Tech Spec
C13: CON003 - TAR-040 - Tech Spec | D13: EDI004 | I13: CON003 | J13: - DES-030 - Tech Spec | M13: =CONCATENATE(I13," ",J13) -> CON003 - DES-030 - Tech Spec
C14: CON003 - TES-070 - Tech Spec | I14: CON004 | J14: - ANA-50 - Func Spec | M14: =CONCATENATE(I14," ",J14) -> CON004 - ANA-50 - Func Spec
C15: CON003 - DES-030 - Tech Spec | I15: CON004 | J15: - TAR-040 - Tech Spec | M15: =CONCATENATE(I15," ",J15) -> CON004 - TAR-040 - Tech Spec
C16: CON004 Concur PO Lines Finance | I16: CON004 | J16: - TES-070 - Tech Spec | M16: =CONCATENATE(I16," ",J16) -> CON004 - TES-070 - Tech Spec
C17: CON004 - ANA-50 - Func Spec | I17: CON004 | J17: - DES-030 - Tech Spec | M17: =CONCATENATE(I17," ",J17) -> CON004 - DES-030 - Tech Spec
C18: CON004 - TAR-040 - Tech Spec | I18: CON005 | J18: - ANA-50 - Func Spec | M18: =CONCATENATE(I18," ",J18) -> CON005 - ANA-50 - Func Spec
C19: CON004 - TES-070 - Tech Spec | I19: CON005 | J19: - TAR-040 - Tech Spec | M19: =CONCATENATE(I19," ",J19) -> CON005 - TAR-040 - Tech Spec
C20: CON004 - DES-030 - Tech Spec | I20: CON005 | J20: - TES-070 - Tech Spec | M20: =CONCATENATE(I20," ",J20) -> CON005 - TES-070 - Tech Spec
C21: CON005 Concur Vendor Infor Finance | I21: CON005 | J21: - DES-030 - Tech Spec | M21: =CONCATENATE(I21," ",J21) -> CON005 - DES-030 - Tech Spec
C22: CON005 - ANA-50 - Func Spec | I22: SFDC01 | J22: - ANA-50 - Func Spec | M22: =CONCATENATE(I22," ",J22) -> SFDC01 - ANA-50 - Func Spec
C23: CON005 - TAR-040 - Tech Spec | I23: SFDC01 | J23: - TAR-040 - Tech Spec | M23: =CONCATENATE(I23," ",J23) -> SFDC01 - TAR-040 - Tech Spec
C24: CON005 - TES-070 - Tech Spec | I24: SFDC01 | J24: - TES-070 - Tech Spec | M24: =CONCATENATE(I24," ",J24) -> SFDC01 - TES-070 - Tech Spec
C25: CON005 - DES-030 - Tech Spec | I25: SFDC01 | J25: - DES-030 - Tech Spec | M25: =CONCATENATE(I25," ",J25) -> SFDC01 - DES-030 - Tech Spec
... C56: EDI003 SPS Commerce EDI EDI Sales Order Ack OTC | I56: EDI005 | J56: - TES-070 - Tech Spec | M56: =CONCATENATE(I56," ",J56) -> EDI005 - TES-070 - Tech Spec
C57: EDI003 - ANA-50 - Func Spec | G57: EDI005 | I57: EDI005 | J57: - DES-030 - Tech Spec | M57: =CONCATENATE(I57," ",J57) -> EDI005 - DES-030 - Tech Spec
C58: EDI003 - TAR-040 - Tech Spec | G58: EDI006 | I58: EDI006 | J58: - ANA-50 - Func Spec | M58: =CONCATENATE(I58," ",J58) -> EDI006 - ANA-50 - Func Spec
C59: EDI003 - TES-070 - Tech Spec | G59: EDI007 | I59: EDI006 | J59: - TAR-040 - Tech Spec | M59: =CONCATENATE(I59," ",J59) -> EDI006 - TAR-040 - Tech Spec
C60: EDI003 - DES-030 - Tech Spec | G60: FIN001 | I60: EDI006 | J60: - TES-070 - Tech Spec | M60: =CONCATENATE(I60," ",J60) -> EDI006 - TES-070 - Tech Spec
C61: EDI004 SPS Commerce EDI EDI Invoice OTC | G61: FIN002 | I61: EDI006 | J61: - DES-030 - Tech Spec | M61: =CONCATENATE(I61," ",J61) -> EDI006 - DES-030 - Tech Spec
C62: EDI004 - ANA-50 - Func Spec | G62: FIN003 | I62: EDI007 | J62: - ANA-50 - Func Spec | M62: =CONCATENATE(I62," ",J62) -> EDI007 - ANA-50 - Func Spec
C63: EDI004 - TAR-040 - Tech Spec | G63: FIN004 | I63: EDI007 | J63: - TAR-040 - Tech Spec | M63: =CONCATENATE(I63," ",J63) -> EDI007 - TAR-040 - Tech Spec
C64: EDI004 - TES-070 - Tech Spec | G64: CFO001 | I64: EDI007 | J64: - TES-070 - Tech Spec | M64: =CONCATENATE(I64," ",J64) -> EDI007 - TES-070 - Tech Spec
C65: EDI004 - DES-030 - Tech Spec | G65: CFO002 | I65: EDI007 | J65: - DES-030 - Tech Spec | M65: =CONCATENATE(I65," ",J65) -> EDI007 - DES-030 - Tech Spec
C66: EDI005 SPS Commerce EDI EDI Shipment Schedule EDI 862 OTC | G66: CFO003 | I66: FIN001 | J66: - ANA-50 - Func Spec | M66: =CONCATENATE(I66," ",J66) -> FIN001 - ANA-50 - Func Spec
C67: EDI005 - ANA-50 - Func Spec | I67: FIN001 | J67: - TAR-040 - Tech Spec | M67: =CONCATENATE(I67," ",J67) -> FIN001 - TAR-040 - Tech Spec
C68: EDI005 - TAR-040 - Tech Spec | I68: FIN001 | J68: - TES-070 - Tech Spec | M68: =CONCATENATE(I68," ",J68) -> FIN001 - TES-070 - Tech Spec
C69: EDI005 - TES-070 - Tech Spec | I69: FIN001 | J69: - DES-030 - Tech Spec | M69: =CONCATENATE(I69," ",J69) -> FIN001 - DES-030 - Tech Spec
C70: EDI005 - DES-030 - Tech Spec | I70: FIN002 | J70: - ANA-50 - Func Spec | M70: =CONCATENATE(I70," ",J70) -> FIN002 - ANA-50 - Func Spec
C71: EDI006 SPS Commerce EDI Planning Schedule EDI 830 OTC | I71: FIN002 | J71: - TAR-040 - Tech Spec | M71: =CONCATENATE(I71," ",J71) -> FIN002 - TAR-040 - Tech Spec
C72: EDI006 - ANA-50 - Func Spec | I72: FIN002 | J72: - TES-070 - Tech Spec | M72: =CONCATENATE(I72," ",J72) -> FIN002 - TES-070 - Tech Spec
C73: EDI006 - TAR-040 - Tech Spec | I73: FIN002 | J73: - DES-030 - Tech Spec | M73: =CONCATENATE(I73," ",J73) -> FIN002 - DES-030 - Tech Spec
C74: EDI006 - TES-070 - Tech Spec | I74: FIN003 | J74: - ANA-50 - Func Spec | M74: =CONCATENATE(I74," ",J74) -> FIN003 - ANA-50 - Func Spec
C75: EDI006 - DES-030 - Tech Spec | I75: FIN003 | J75: - TAR-040 - Tech Spec | M75: =CONCATENATE(I75," ",J75) -> FIN003 - TAR-040 - Tech Spec
C76: EDI007 SPS Commerce EDI Application Advice EDI 824 OTC | I76: FIN003 | J76: - TES-070 - Tech Spec | M76: =CONCATENATE(I76," ",J76) -> FIN003 - TES-070 - Tech Spec
C77: EDI007 - ANA-50 - Func Spec | I77: FIN003 | J77: - DES-030 - Tech Spec | M77: =CONCATENATE(I77," ",J77) -> FIN003 - DES-030 - Tech Spec
C78: EDI007 - TAR-040 - Tech Spec | I78: FIN004 | J78: - ANA-50 - Func Spec | M78: =CONCATENATE(I78," ",J78) -> FIN004 - ANA-50 - Func Spec
... C93: FIN003 - TAR-040 - Tech Spec | I93: CFO003 | J93: - DES-030 - Tech Spec | M93: =CONCATENATE(I93," ",J93) -> CFO003 - DES-030 - Tech Spec
C94: FIN003 - TES-070 - Tech Spec | G94: CFO004 | I94: CFO004 | J94: - ANA-50 - Func Spec | M94: =CONCATENATE(I94," ",J94) -> CFO004 - ANA-50 - Func Spec
C95: FIN003 - DES-030 - Tech Spec | G95: CFO005 | I95: CFO004 | J95: - TAR-040 - Tech Spec | M95: =CONCATENATE(I95," ",J95) -> CFO004 - TAR-040 - Tech Spec
C96: FIN004 Shared Service (AP) Check Run Details Finance | G96: FED001 | I96: CFO004 | J96: - TES-070 - Tech Spec | M96: =CONCATENATE(I96," ",J96) -> CFO004 - TES-070 - Tech Spec
C97: FIN004 - ANA-50 - Func Spec | G97: FED002 | I97: CFO004 | J97: - DES-030 - Tech Spec | M97: =CONCATENATE(I97," ",J97) -> CFO004 - DES-030 - Tech Spec
C98: FIN004 - TAR-040 - Tech Spec | G98: UPS001 | I98: CFO005 | J98: - ANA-50 - Func Spec | M98: =CONCATENATE(I98," ",J98) -> CFO005 - ANA-50 - Func Spec
C99: FIN004 - TES-070 - Tech Spec | G99: UPS002 | I99: CFO005 | J99: - TAR-040 - Tech Spec | M99: =CONCATENATE(I99," ",J99) -> CFO005 - TAR-040 - Tech Spec
C100: FIN004 - DES-030 - Tech Spec | G100: WOR001 | I100: CFO005 | J100: - TES-070 - Tech Spec | M100: =CONCATENATE(I100," ",J100) -> CFO005 - TES-070 - Tech Spec
C101: CFO001 Cforia Customer Payments & Credits Finance | G101: WOR002 | I101: CFO005 | J101: - DES-030 - Tech Spec | M101: =CONCATENATE(I101," ",J101) -> CFO005 - DES-030 - Tech Spec
C102: CFO001 - ANA-50 - Func Spec | I102: FED001 | J102: - ANA-50 - Func Spec | M102: =CONCATENATE(I102," ",J102) -> FED001 - ANA-50 - Func Spec
C103: CFO001 - TAR-040 - Tech Spec | I103: FED001 | J103: - TAR-040 - Tech Spec | M103: =CONCATENATE(I103," ",J103) -> FED001 - TAR-040 - Tech Spec
C104: CFO001 - TES-070 - Tech Spec | I104: FED001 | J104: - TES-070 - Tech Spec | M104: =CONCATENATE(I104," ",J104) -> FED001 - TES-070 - Tech Spec
C105: CFO001 - DES-030 - Tech Spec | I105: FED001 | J105: - DES-030 - Tech Spec | M105: =CONCATENATE(I105," ",J105) -> FED001 - DES-030 - Tech Spec
C106: CFO002 Cforia Customer Order Finance | I106: FED002 | J106: - ANA-50 - Func Spec | M106: =CONCATENATE(I106," ",J106) -> FED002 - ANA-50 - Func Spec
C107: CFO002 - ANA-50 - Func Spec | I107: FED002 | J107: - TAR-040 - Tech Spec | M107: =CONCATENATE(I107," ",J107) -> FED002 - TAR-040 - Tech Spec
C108: CFO002 - TAR-040 - Tech Spec | I108: FED002 | J108: - TES-070 - Tech Spec | M108: =CONCATENATE(I108," ",J108) -> FED002 - TES-070 - Tech Spec
C109: CFO002 - TES-070 - Tech Spec | I109: FED002 | J109: - DES-030 - Tech Spec | M109: =CONCATENATE(I109," ",J109) -> FED002 - DES-030 - Tech Spec
C110: CFO002 - DES-030 - Tech Spec | I110: UPS001 | J110: - ANA-50 - Func Spec | M110: =CONCATENATE(I110," ",J110) -> UPS001 - ANA-50 - Func Spec
C111: CFO003 Cforia Customer Master Finance | I111: UPS001 | J111: - TAR-040 - Tech Spec | M111: =CONCATENATE(I111," ",J111) -> UPS001 - TAR-040 - Tech Spec
C112: CFO003 - ANA-50 - Func Spec | I112: UPS001 | J112: - TES-070 - Tech Spec | M112: =CONCATENATE(I112," ",J112) -> UPS001 - TES-070 - Tech Spec
C113: CFO003 - TAR-040 - Tech Spec | I113: UPS001 | J113: - DES-030 - Tech Spec | M113: =CONCATENATE(I113," ",J113) -> UPS001 - DES-030 - Tech Spec
... C127: FED001 - ANA-50 - Func Spec | I127: OPT001 | J127: - TAR-040 - Tech Spec | M127: =CONCATENATE(I127," ",J127) -> OPT001 - TAR-040 - Tech Spec
C128: FED001 - TAR-040 - Tech Spec | F128: OPT001 | I128: OPT001 | J128: - TES-070 - Tech Spec | M128: =CONCATENATE(I128," ",J128) -> OPT001 - TES-070 - Tech Spec
C129: FED001 - TES-070 - Tech Spec | F129: OPT002 | I129: OPT001 | J129: - DES-030 - Tech Spec | M129: =CONCATENATE(I129," ",J129) -> OPT001 - DES-030 - Tech Spec
C130: FED001 - DES-030 - Tech Spec | F130: OPT003 | I130: OPT002 | J130: - ANA-50 - Func Spec | M130: =CONCATENATE(I130," ",J130) -> OPT002 - ANA-50 - Func Spec
C131: FED002 Fedex FedEx Shipping information Supply chain | F131: OPT004 | I131: OPT002 | J131: - TAR-040 - Tech Spec | M131: =CONCATENATE(I131," ",J131) -> OPT002 - TAR-040 - Tech Spec
C132: FED002 - ANA-50 - Func Spec | F132: OPT005 | I132: OPT002 | J132: - TES-070 - Tech Spec | M132: =CONCATENATE(I132," ",J132) -> OPT002 - TES-070 - Tech Spec
C133: FED002 - TAR-040 - Tech Spec | F133: OPT006 | I133: OPT002 | J133: - DES-030 - Tech Spec | M133: =CONCATENATE(I133," ",J133) -> OPT002 - DES-030 - Tech Spec
C134: FED002 - TES-070 - Tech Spec | I134: OPT003 | J134: - ANA-50 - Func Spec | M134: =CONCATENATE(I134," ",J134) -> OPT003 - ANA-50 - Func Spec
C135: FED002 - DES-030 - Tech Spec | I135: OPT003 | J135: - TAR-040 - Tech Spec | M135: =CONCATENATE(I135," ",J135) -> OPT003 - TAR-040 - Tech Spec
C136: UPS001 UPS UPS Tracking Number Update Supply chain | I136: OPT003 | J136: - TES-070 - Tech Spec | M136: =CONCATENATE(I136," ",J136) -> OPT003 - TES-070 - Tech Spec
C137: UPS001 - ANA-50 - Func Spec | I137: OPT003 | J137: - DES-030 - Tech Spec | M137: =CONCATENATE(I137," ",J137) -> OPT003 - DES-030 - Tech Spec
C138: UPS001 - TAR-040 - Tech Spec | I138: OPT004 | J138: - ANA-50 - Func Spec | M138: =CONCATENATE(I138," ",J138) -> OPT004 - ANA-50 - Func Spec
C139: UPS001 - TES-070 - Tech Spec | I139: OPT004 | J139: - TAR-040 - Tech Spec | M139: =CONCATENATE(I139," ",J139) -> OPT004 - TAR-040 - Tech Spec
C140: UPS001 - DES-030 - Tech Spec | I140: OPT004 | J140: - TES-070 - Tech Spec | M140: =CONCATENATE(I140," ",J140) -> OPT004 - TES-070 - Tech Spec
C141: UPS002 UPS UPS Shipping Information Supply chain | I141: OPT004 | J141: - DES-030 - Tech Spec | M141: =CONCATENATE(I141," ",J141) -> OPT004 - DES-030 - Tech Spec
C142: UPS002 - ANA-50 - Func Spec | I142: OPT005 | J142: - ANA-50 - Func Spec | M142: =CONCATENATE(I142," ",J142) -> OPT005 - ANA-50 - Func Spec
C143: UPS002 - TAR-040 - Tech Spec | I143: OPT005 | J143: - TAR-040 - Tech Spec | M143: =CONCATENATE(I143," ",J143) -> OPT005 - TAR-040 - Tech Spec
C144: UPS002 - TES-070 - Tech Spec | I144: OPT005 | J144: - TES-070 - Tech Spec | M144: =CONCATENATE(I144," ",J144) -> OPT005 - TES-070 - Tech Spec
C145: UPS002 - DES-030 - Tech Spec | I145: OPT005 | J145: - DES-030 - Tech Spec | M145: =CONCATENATE(I145," ",J145) -> OPT005 - DES-030 - Tech Spec
... C149: WOR001 - TES-070 - Tech Spec | I149: OPT006 | J149: - DES-030 - Tech Spec | M149: =CONCATENATE(I149," ",J149) -> OPT006 - DES-030 - Tech Spec
C150: WOR001 - DES-030 - Tech Spec
C151: WOR002 Worldpay Payment Capture OTC
C152: WOR002 - ANA-50 - Func Spec
C153: WOR002 - TAR-040 - Tech Spec
C154: WOR002 - TES-070 - Tech Spec
C155: WOR002 - DES-030 - Tech Spec
C156: OPT001 Optimizely Customer and Addresses OTC
C157: OPT001 - ANA-50 - Func Spec
C158: OPT001 - TAR-040 - Tech Spec
C159: OPT001 - TES-070 - Tech Spec
C160: OPT001 - DES-030 - Tech Spec
...

Sheet Barnes Project Plan
A1: Interface | B1: Priority | C1: Phase | D1: Category | E1: Task | F1: Status | G1: Due Date | H1: Org | I1: Owner | J1: Note
A2: Bank of America (AP) | C2: 0 - Doc | D2: 0 - ANA-050 | E2: ANA-050 - Ready for Review | F2: Complete | G2: 45534 | H2: I | I2: Carlo Alcazar
A3: Bank of America (AP) | B3: * | C3: 0 - Doc | D3: 1 - ANA-050 | E3: ANA-050 - Signoff | F3: Complete | G3: 45541 | H3: B | I3: Kim Diorio | J3: Agreed approved in Meeting 9/23/2024
A4: Bank of America (AP) | C4: 0 - Doc | D4: 2 - TAR-040 | E4: TAR-040 - Ready for Review | F4: Complete | G4: 45548 | H4: I | I4: Isaiah Tolentino
A5: Bank of America (AP) | C5: 0 - Doc | D5: 3 - TEST-070 | E5: Unit Test Plan | F5: Not Started | G5: 45583 | H5: B | I5: Kim Diorio
A6: Bank of America (AP) | C6: 0 - Doc | D6: 4- DOC COMPLETE | F6: In Progress
A7: Bank of America (AP) | C7: 1 - Dev | D7: Dev | E7: Header file for checks | F7: Complete | H7: I | I7: Isaiah Tolentino | J7: 10/2 Wed - Martin on 9/30 9a call
A8: Bank of America (AP) | B8: * | C8: 1 - Dev | D8: Dev | E8: Detail file for checks | F8: Complete | G8: 45562 | H8: I | I8: Isaiah Tolentino | J8: 10/2 Wed - Martin on 9/30 9a call
A9: Bank of America (AP) | B9: * | C9: 1 - Dev | D9: Dev | E9: Header file for ACH | F9: Complete | G9: 45562 | H9: I | I9: Isaiah Tolentino | J9: 10/2 Wed - Martin on 9/30 9a call
A10: Bank of America (AP) | B10: * | C10: 1 - Dev | D10: Dev | E10: Detail file for ACH | F10: Complete | G10: 45562 | H10: I | I10: Isaiah Tolentino | J10: 10/2 Wed - Martin on 9/30 9a call
A11: Bank of America (AP) | C11: 1 - Deb | D11: Dev | E11: Send sample files to Barnes | F11: In Progress | G11: 45566 | H11: I | I11: Isaiah Tolentino
A12: Bank of America (AP) | B12: * | C12: 1 - Dev | D12: Dev | E12: SSIS: Transfer files to Industrial JBA box for transmission (weekly) | F12: Await files | G12: 45576 | H12: B | I12: Kevin Alexander
A13: Bank of America (AP) | C13: 2 - Test | D13: UAT | E13: UAT Ready | F13: On Track | G13: 45583 | H13: B | I13: Dean Amo
A14: Bank of America (AP) | C14: 2 - Test | D14: Unit Test 001 | E14: Makes it to Barnes Industrial AS/400 - users are able to confirm the details | F14: Not Started | G14: 45583 | H14: B | I14: Kim Diorio
A15: Bank of America (AP) | B15: Risk | C15: 2 - Test | D15: Unit Test 002 | E15: Test transmission to bank has long lead time | F15: Not Started | G15: 45583 | H15: B | I15: Kim Diorio
A16: CenPOS | C16: 0 - Doc | D16: 0 - ANA-050 | E16: ANA-050 - Ready for Review | F16: Not Required | H16: I
A17: CenPOS | C17: 0 - Doc | D17: 1 - ANA-050 | E17: ANA-050 - Signoff | F17: Not Required | H17: I
A18: CenPOS | C18: 0 - Doc | D18: 2 - TAR-040 | E18: TAR-040 Reviewed and approved | F18: Not Required | H18: I
A19: CenPOS | B19: * | C19: 0 - Doc | D19: 3 - TEST-070 | E19: Unit Test Plan - CenPOS - contact Hubert for M3 functional questions | F19: Overdue | G19: 45548 | H19: B | I19: Amy Burgard | J19: *Meeting scheduled Thur 9/26
A20: CenPOS | C20: 0 - Doc | D20: 4- DOC COMPLETE
A21: CenPOS | B21: Low | C21: 1 - Dev | D21: Dev | E21: Review test portal login | F21: Complete | G21: 45562 | H21: B | I21: Dean Amo
A22: CenPOS | B22: Low | C22: 1 - Dev | D22: Dev | E22: Change service account from @infor.com to @asraymond.com | F22: In Progress | G22: 45562 | H22: B | I22: Dean Amo | J22: Need a DL_CenPos_Administration@onebarnes.com
A23: CenPOS | B23: Low | C23: 1 - Dev | D23: Dev | E23: Update M3 CenPOS connector configuration after account change | F23: Not Started | I23: Hubert Santos
A24: CenPOS | C24: 2 - Test | D24: UAT | E24: Ready for testing | F24: Complete | G24: 45444 | H24: I | I24: Daniel Lindblad
A25: CenPOS | C25: 2 - Test | D25: Unit Test 001 | E25: Charge customer order to test credit card | F25: Complete - Success | H25: B | I25: Amy, Melissa
A26: Cforia | B26: * | C26: 0 - Doc | D26: 0 - ANA-050 | E26: ANA-050 - Ready for Review | F26: Overdue | G26: 45548 | H26: B | I26: Dennis Garrero, Rachelle | J26: 9/30/2024 - New Due Date. 10/9/2024 latest due date from 9/26.
A27: Cforia | B27: * | C27: 0 - Doc | D27: 1 - ANA-050 | E27: ANA-050 - Sign off | F27: Await Dependancy | G27: 45569 | H27: B | I27: Kim Diorio / Kevin Alexander
A28: Cforia | B28: * | C28: 0 - Doc | D28: 2 - TAR-040 | E28: TAR-040 Reviewed and approved | F28: Await Dependancy | G28: 45569 | H28: I | I28: Carlo Alcazar | J28: Awaiting ANA-050
A29: Cforia | C29: 0 - Doc | D29: 3 - TEST-070 | E29: Unit Test Plan | F29: Not Started | G29: 45590 | H29: B | I29: Dean / Kim | J29: *Need output of open A/R report from M3 -Dennis tried on call, output not working
A30: Cforia | C30: 0 - Doc | D30: 4 - DOC COMPLETE
A31: Cforia | C31: 00 - Doc Req | D31: 2 - TAR-040 | E31: Meeting for missing AR details | F31: Complete | H31: T | I31: Dennis / Kevin | J31: Search 'Acc Re' in M3 for open A/R screens
A32: Cforia | B32: * | C32: 1 - Dev | D32: Dev | E32: Modify DW Job, BGIDW_M3_ASR to include AR files | F32: In Progress | G32: 45583 | H32: B | I32: Kevin Alexander
A33: Cforia | C33: 1 - Dev | D33: Dev | E33: Contact Cdoria - ensure test environment is ready | G33: 45569 | H33: B | I33: Kevin Alexander
A34: Cforia | C34: 1 - Dev | D34: Dev | E34: Build ARCASH.TXT exoport | F34: In Progress | G34: 45590 | H34: B | I34: Kevin Alexander
A35: Cforia | C35: 1 - Dev | D35: Dev | E35: Build ARCUST.TXT exoport | F35: In Progress | G35: 45590 | H35: B | I35: Kevin Alexander
A36: Cforia | C36: 1 - Dev | D36: Dev | E36: Build AREXTI.TXT exoport | F36: In Progress | G36: 45590 | H36: B | I36: Kevin Alexander
A37: Cforia | C37: 1 - Dev | D37: Dev | E37: Build ARMAST.TXT exoport | F37: In Progress | G37: 45590 | H37: B | I37: Kevin Alexander
A38: Cforia | C38: 1 - Dev | D38: Dev | E38: Build ARTRAN.TXT exoport | F38: In Progress | G38: 45590 | H38: B | I38: Kevin Alexander
A39: Cforia | C39: 1 - Dev | D39: Dev - Enahnce | E39: Invoice PDF to archive folder | F39: Not Started | H39: B | I39: Karin Fransson
C40: 1 - Dev | D40: Dev | E40: Transmit to Cforia | F40: Not Started | G40: 45597 | H40: B | I40: Kevin Alexander
A41: Cforia | C41: 2 - Test | D41: UAT | E41: UAT Ready | F41: Late | G41: 45600 | H41: B | I41: Dean Amo
A42: Cforia | C42: 2 - Test | D42: Unit Test 001 | E42: Balance to M3 Open A/R report | F42: Not Started
A43: Cforia | C43: 2 - Test | D43: Unit Test 001 | E43: View in Cforia for missing details | F43: Not Started
A44: Concur - Invoice | B44: * | C44: 0 - Doc | D44: 0 - ANA-050 | E44: ANA-050 - Payments to M3 - Ready for Review | F44: Overdue | G44: 45555 | H44: I | I44: Dennis Garrero | J44: 45559
A45: Concur - Invoice | B45: * | C45: 0 - Doc | D45: 1 - ANA-050 | E45: ANA-050 - Reviewed and approved | F45: Await Dependancy | G45: 45562 | H45: B | I45: Kim Diorio
A46: Concur - Invoice | C46: 0 - Doc | D46: 2 - TAR-040 | E46: TAR-040 Reviewed and approved | F46: Not Started | I46: Martin
A47: Concur - Invoice | C47: 0 - Doc | D47: 3 - TEST-070 | E47: Unit Test Plan | F47: Not Started
A48: Concur - Invoice | C48: 0 - Doc | D48: 4 - DOC COMPLETE | F48: In Progress
A49: Concur - Invoice | C49: 1 - Dev | D49: Dev | E49: OUT: Produce PO Header, Lines, Receipts, Vendor files | F49: Complete | G49: 45484 | H49: B | I49: Kevin Alexander
A50: Concur - Invoice | B50: * | C50: 1 - Dev | D50: Dev | E50: OUT: Ensure files ingest into Concur | F50: In Progress | G50: 45562 | H50: B | I50: Dean Amo | J50: Sep-20 - Last import successful, turning on feed Monday (Sep-23) evening run
A51: Concur - Invoice | C51: 1 - Dev | D51: Dev | E51: Inbound - Matched Payments to XML BOD drop off | F51: Complete | G51: 45484 | H51: B | I51: Kevin Alexander
A52: Concur - Invoice | C52: 1 - Dev | D52: DEV COMPLETE | F52: Complete | G52: 45526 | H52: B
A53: Concur - Invoice | C53: 2 - Test | D53: UAT | E53: UAT Ready | F53: Late | G53: 45597 | H53: B | I53: Dean Amo
A54: Concur - Invoice | C54: 2 - Test | D54: Unit Test 001 | E54: Enter POs in M3 - Compay 910 | F54: Complete | I54: Kyle Outhouse / Amy McGuire
A55: Concur - Invoice | C55: 2 - Test | D55: Unit Test 001 | E55: Receive POs in M3 - Compay 910 | F55: Complete | I55: Kyle Outhouse / Amy McGuire
A56: Concur - Invoice | C56: 2 - Test | D56: Unit Test 001 | E56: Send files to Concur | F56: Complete | I56: Kevin Alexander
A57: Concur - Invoice | C57: 2 - Test | D57: Unit Test 001 | E57: Input simulated vendor Invoice | F57: Complete | I57: Kim Diorio
A58: Concur - Invoice | C58: 2 - Test | D58: Unit Test 001 | E58: Receive matched payments | F58: In Progress | G58: 45534 | H58: B | I58: Kim Diorio / Keven Alexander
A59: Concur - Invoice | C59: 2 - Test | D59: Unit Test 001 | E59: Matched payments to XML BOD in drop off location | F59: Not Started | G59: 45534 | H59: B | I59: Kevin Alexander
A60: Concur - Invoice | C60: 2 - Test | D60: Unit Test 001 | E60: Verify Payments processed into M3 | F60: Not Started | G60: 45534 | H60: I | I60: Daniel ?
A61: Concur - Invoice | C61: 2 - Test | D61: Unit Test 001 | E61: Review Payables | F61: Not Started | H61: B | I61: Daniel Tuller
A62: Concur - Invoice | C62: 2 - Test | D62: Unit Test 001 COMPLETE | F62: In Progress
A63: Concur - Travel & Expense | B63: * | C63: 0 - Doc | D63: 0 - ANA-050 | E63: ANA-050 - Ready for Review | F63: Overdue | G63: 45565 | H63: I | I63: Dennis Garrero, Rachelle
A64: Concur - Travel & Expense | B64: * | C64: 0 - Doc | D64: 1 - ANA-050 | E64: ANA-050 - Reviewed and approved | F64: Await Dependancy | G64: 45565 | H64: B | I64: Jesse Keech, Kim Diorio | J64: Review @9a
A65: Concur - Travel & Expense | B65: * | C65: 0 - Doc | D65: 2 - TAR-040 | E65: Concur TAR-040 | F65: In Progress | G65: 45576 | H65: I | I65: Martin Bautista
A66: Concur - Travel & Expense | C66: 0 - Doc | D66: 3 - TEST-070 | E66: Unit Test Plan | F66: Not Started
A67: Concur - Travel & Expense | C67: 0 - Doc | D67: 4 - DOC COMPLETE | F67: In Progress
A68: Concur - Travel & Expense | C68: 00 - Doc Req | D68: 1 - ANA-050 | E68: Schedule overview call with Infor/Finance | F68: Complete | H68: B | I68: Dean Amo [Dennis]
A69: Concur - Travel & Expense | B69: * | C69: 00 - Doc Req | D69: 1 - ANA-050 | E69: GLS 840 - Can we use existing format or do we need new? | F69: Not Started | G69: 45565 | H69: I | I69: Rachelle
A70: Concur - Travel & Expense | C70: 00 - Doc Req | D70: 2 - TAR-040 | E70: Sample data with field explainations | F70: Complete | H70: B | I70: Kevin Alexander
A71: Concur - Travel & Expense | C71: 1 - Dev | D71: Dev | E71: Import flat file into M3 | F71: Not Started | H71: I | I71: Rachelle
A72: Concur - Travel & Expense | C72: 1 - Dev | D72: Dev | E72: Import flat file into M3 | F72: Not Started | H72: B | I72: Kevin Alexander
A73: Concur - Travel & Expense | C73: 2 - Test | D73: UAT | E73: UAT Ready | F73: Late | G73: 45590 | H73: B | I73: Dean Amo
A74: Concur - Travel & Expense | C74: 2 - Test | D74: Unit Test 001 | E74: Run production expense through test integration | F74: Not Started | H74: B | I74: Kevin Alexander
A75: Concur - Travel & Expense | C75: 2 - Test | D75: Unit Test 001 | E75: Validate Process to post data to M3 | F75: Not Started | H75: I | I75: ?
A76: Concur - Travel & Expense | C76: 2 - Test | D76: Unit Test 001 | E76: Review Payables | F76: Not Started | H76: B | I76: Daniel Tuller
A77: FedEx | C77: 0 - Doc | D77: 0 - ANA-050 | E77: ANA-050 - Payments to M3 - Ready for Review | F77: Complete | G77: 45457 | H77: I
A78: FedEx | C78: 0 - Doc | D78: 1 - ANA-050 | E78: ANA-050 - Reviewed and approved | F78: Complete | G78: 45457 | H78: B | I78: Jack Adoline
A79: FedEx | C79: 0 - Doc | D79: 2 - TAR-040 | E79: TAR-040 Reviewed and approved | F79: Not Started | G79: 45541 | I79: Martin Bautista
A80: FedEx | C80: 0 - Doc | D80: 3 - TEST-070 | E80: Unit Test Plan | F80: Not Started | H80: B | I80: Jeff Finch
A81: FedEx | C81: 0 - Doc | D81: 4 - DOC COMPLETE | F81: In Progress
A82: FedEx | B82: * | C82: 00 - Doc Req | D82: 2 - TAR-040 | E82: Need sample shipments file XML from FedEx production | F82: Complete | G82: 45562 | H82: B | I82: Dean Amo
A83: FedEx | C83: 1 - Dev | D83: Dev | E83: Develop address pull query from data lake | F83: In Progress | G83: 45555 | H83: B | I83: Dean Amo
A84: FedEx | B84: * | C84: 1 - Dev | D84: Dev | E84: Configure address pull from M3 | F84: In Progress | G84: 45562 | H84: B | I84: Dean Amo
A85: FedEx | B85: * | C85: 1 - Dev | D85: Dev | E85: Configure XML output and drop off location | F85: In Progress | G85: 45569 | H85: B | I85: Dean Amo
A86: FedEx | C86: 2 - Test | D86: UAT | E86: UAT Ready | F86: On Track - Issue | G86: 45586 | H86: B | I86: Dean Amo
A87: FedEx | C87: 2 - Test | D87: Unit Test 001 | E87: Print pick list from M3 and scan in Ship Manager to pull address/FedEx account | F87: Not Started | G87: 45576 | H87: B | I87: ?? Process Owner ??
A88: FedEx | C88: 2 - Test | D88: Unit Test 002 | E88: Extract XML from shipment of order | F88: Not Started | G88: 45576 | H88: B | I88: Jeff Finch
A89: FedEx | C89: 2 - Test | D89: Unit Test 002 | E89: Load XML into M3 and verify information on order | F89: Not Started | G89: 45576 | H89: I | I89: Daniel
A90: Optimizely | B90: * | C90: 0 - Doc | D90: 0 - ANA-050 | E90: ANA-050 - Ready for Review | F90: Complete | G90: 45541 | H90: I | I90: Cheska Acance
A91: Optimizely | B91: * | C91: 0 - Doc | D91: 1 - ANA-050 | E91: ANA-050 - Reviewed and approved | F91: Complete | G91: 45555 | I91: Beth Wilkerson | J91: Approved 9/23/2024 via email
A92: Optimizely | C92: 0 - Doc | D92: 2 - TAR-040 | E92: TAR-040 Reviewed and approved | F92: Not Started | H92: B | I92: Dean Amo
A93: Optimizely | C93: 0 - Doc | D93: 3 - TEST-070 | E93: Unit Test Plan | F93: Not Started | H93: B | I93: Beth Wilkerson
A94: Optimizely | C94: 0 - Doc | D94: 4 - DOC COMPLETE | F94: In Progress
A95: Optimizely | C95: 1 - Dev | D95: Dev | E95: OUT: Add price list extract to BGIDW_M3_ASR_Daily.dtsx | F95: Complete | G95: 45534 | H95: B | I95: Dean Amo
A96: Optimizely | B96: * | C96: 1 - Dev | D96: Dev | E96: OUT: Add inventory extract with gas charge logic | F96: Complete | G96: 45562 | H96: B | I96: Dean Amo
A97: Optimizely | B97: * | C97: 1 - Dev | D97: Dev | E97: OUT: Produce files from M3 company 910 and load to test | F97: In Progress | G97: 45569 | H97: B | I97: Dean Amo, Jane Woytach
A98: Optimizely | B98: * | C98: 1 - Dev | D98: Dev | E98: IN: CenPOS integration - schedule CONSID meeting | F98: Overdue | G98: 45541 | H98: B | I98: Dean Amo, Beth Wilkerson | J98: 9/20 - Discussing requirements
A99: Optimizely | C99: 1 - Dev | D99: Dev | E99: IN: CONSID - Update sales order file | F99: In Progress | G99: 45583 | H99: B | J99: 9/20 - Currently analyzing missing data (CC ref. identified)
A100: Optimizely | C100: 1 - Dev | D100: Dev | E100: IN: Convert CSV to XML BOD | F100: Not Started | G100: 45583 | H100: B
...

Sheet Barnes UAT Pivot
A1: Phase | B1: 2 - Test
A3: Row Labels | B3: Category | C3: Task | D3: Status | E3: Due Date | F3: Dev Owner | G3: Next Action Due
A4: Bank of America (AP) | B4: UAT | C4: UAT Ready | D4: On Track | E4: 45583 | F4: Dean Amo | G4: 10/2 - Isiah to deliver 4 files on: ACH header/detail, check header/detail
A5: CenPOS | B5: UAT | C5: Ready for testing | D5: Complete | E5: 45444 | F5: Daniel Lindblad
A6: Cforia | B6: UAT | C6: UAT Ready | D6: Late | E6: 45600 | F6: Dean Amo | G6: 10/9 - ANA-050. 10/25 - Kevin - Balance extracts to M3 Open A/R
A7: Concur - Invoice | B7: UAT | C7: UAT Ready | D7: Late | E7: 45597 | F7: Dean Amo | G7: 9/27 - Dean/Kim/Jesse - Ticket open with Concur, waiting for resource to be assigned. Data not loading under policy.
A8: Concur - Travel & Expense | B8: UAT | C8: UAT Ready | D8: Late | E8: 45590 | F8: Dean Amo | G8: 9/27 - ANA to be reviewed 9/30 - that could get us back on track. Need to understand schedule.
A9: FedEx | B9: UAT | C9: UAT Ready | D9: On Track - Issue | E9: 45586 | F9: Dean Amo | G9: 9/27 - FedEx not filling. A. Need production review, B. Call FedEx Support, C. Try another machine.
A10: Optimizely - Current State | B10: UAT | C10: UAT Ready | D10: On Track | E10: 45572 | F10: Dean Amo
A11: Optimizely - Order Auto. | B11: UAT | C11: UAT Ready | D11: On Track | E11: 45593 | F11: Dean Amo
A12: PNC Bank (AR) | B12: UAT | C12: UAT Ready | D12: On Track - Issue | E12: 45600 | F12: Dean Amo | G12: Need matcher file - higher priorty than ANA
A13: Salesforce | B13: UAT | C13: UAT Ready | D13: Complete | E13: 45544 | F13: Daniel Lindblad
A14: SPS Commerce - EDI | B14: UAT | C14: UAT Phase 1 Ready: PACCAR, Granger, Caterpillar, PNC | D14: Late | E14: 45600 | F14: Keith Sims | G14: 9/27 - Keith Assessing
C15: UAT Phase 2 Ready: All EDI | D15: Late | E15: 45663 | F15: Keith Sims | G15: 9/27 - Keith Assessing
A16: UPS | B16: UAT | C16: UAT Ready | D16: On Track - Issue | E16: 45586 | F16: Dean Amo | G16: 9/27 - Not clear how scanning works
A18: Finance
A19: Sales/Customer Service
A20: Shipping/Warehouse

Sheet Barnes Doc Pivot
A1: Phase | B1: 0 - Doc
A3: Row Labels | B3: Task | C3: Status | D3: Due Date | E3: Owner
A4: Bank of America (AP)
A5: 0 - ANA-050 | B5: ANA-050 - Ready for Review | C5: Complete | D5: 45534 | E5: Carlo Alcazar
A6: 1 - ANA-050 | B6: ANA-050 - Signoff | C6: Complete | D6: 45541 | E6: Kim Diorio
A7: 2 - TAR-040 | B7: TAR-040 - Ready for Review | C7: Complete | D7: 45548 | E7: Isaiah Tolentino
A8: 3 - TEST-070 | B8: Unit Test Plan | C8: Not Started | D8: 45583 | E8: Kim Diorio
A9: CenPOS
A10: 0 - ANA-050 | B10: ANA-050 - Ready for Review | C10: Not Required | D10: (blank) | E10: (blank)
A11: 1 - ANA-050 | B11: ANA-050 - Signoff | C11: Not Required | D11: (blank) | E11: (blank)
A12: 2 - TAR-040 | B12: TAR-040 Reviewed and approved | C12: Not Required | D12: (blank) | E12: (blank)
A13: 3 - TEST-070 | B13: Unit Test Plan - CenPOS - contact Hubert for M3 functional questions | C13: Overdue | D13: 45548 | E13: Amy Burgard
A14: Cforia
A15: 0 - ANA-050 | B15: ANA-050 - Ready for Review | C15: Overdue | D15: 45548 | E15: Dennis Garrero, Rachelle
A16: 1 - ANA-050 | B16: ANA-050 - Sign off | C16: Await Dependancy | D16: 45569 | E16: Kim Diorio / Kevin Alexander
A17: 2 - TAR-040 | B17: TAR-040 Reviewed and approved | C17: Await Dependancy | D17: 45569 | E17: Carlo Alcazar
A18: 3 - TEST-070 | B18: Unit Test Plan | C18: Not Started | D18: 45590 | E18: Dean / Kim
A19: Concur - Invoice
A20: 0 - ANA-050 | B20: ANA-050 - Payments to M3 - Ready for Review | C20: Overdue | D20: 45555 | E20: Dennis Garrero
A21: 1 - ANA-050 | B21: ANA-050 - Reviewed and approved | C21: Await Dependancy | D21: 45562 | E21: Kim Diorio
A22: 2 - TAR-040 | B22: TAR-040 Reviewed and approved | C22: Not Started | D22: (blank) | E22: Martin
A23: 3 - TEST-070 | B23: Unit Test Plan | C23: Not Started | D23: (blank) | E23: (blank)
A24: Concur - Travel & Expense
A25: 0 - ANA-050 | B25: ANA-050 - Ready for Review | C25: Overdue | D25: 45565 | E25: Dennis Garrero, Rachelle
A26: 1 - ANA-050 | B26: ANA-050 - Reviewed and approved | C26: Await Dependancy | D26: 45565 | E26: Jesse Keech, Kim Diorio
A27: 2 - TAR-040 | B27: Concur TAR-040 | C27: In Progress | D27: 45576 | E27: Martin Bautista
A28: 3 - TEST-070 | B28: Unit Test Plan | C28: Not Started | D28: (blank) | E28: (blank)
A29: FedEx
A30: 0 - ANA-050 | B30: ANA-050 - Payments to M3 - Ready for Review | C30: Complete | D30: 45457 | E30: (blank)
A31: 1 - ANA-050 | B31: ANA-050 - Reviewed and approved | C31: Complete | D31: 45457 | E31: Jack Adoline
A32: 2 - TAR-040 | B32: TAR-040 Reviewed and approved | C32: Not Started | D32: 45541 | E32: Martin Bautista
A33: 3 - TEST-070 | B33: Unit Test Plan | C33: Not Started | D33: (blank) | E33: Jeff Finch
A34: Optimizely
A35: 0 - ANA-050 | B35: ANA-050 - Ready for Review | C35: Complete | D35: 45541 | E35: Cheska Acance
A36: 1 - ANA-050 | B36: ANA-050 - Reviewed and approved | C36: Complete | D36: 45555 | E36: Beth Wilkerson
A37: 2 - TAR-040 | B37: TAR-040 Reviewed and approved | C37: Not Started | D37: (blank) | E37: Dean Amo | F37: XML delivered 9/23
A38: 3 - TEST-070 | B38: Unit Test Plan | C38: Not Started | D38: (blank) | E38: Beth Wilkerson
A39: PNC Bank (AR)
A40: 0 - ANA-050 | B40: ANA-050 - Payments to M3 - Ready for Review | C40: In Progress | D40: 45562 | E40: Dennis Garrero
A41: 1 - ANA-050 | B41: ANA-050 - Reviewed and approved | C41: Await Dependancy | D41: 45569 | E41: Kim Diorio
A42: 2 - TAR-040 | B42: TAR-040 Reviewed and approved | C42: In Progress | D42: 45576 | E42: Martin Bautista
A43: 3 - TEST-070 | B43: Unit Test Plan | C43: Not Started | D43: (blank) | E43: (blank)
A44: Salesforce
A45: 0 - ANA-050 | B45: ANA-050 - Ready for Review | C45: Complete | D45: 45541 | E45: Martin Bautista
A46: 1 - ANA-050 | B46: ANA-050 - Reviewed and approved | C46: Complete | D46: (blank) | E46: Torbjörn Sundbrandt
A47: 2 - TAR-040 | B47: TAR-040 Reviewed and approved | C47: Complete | D47: (blank) | E47: Martin Bautista
A48: 3 - TEST-070 | B48: Unit Test Plan | C48: In Progress | D48: 45562 | E48: Torbjörn Sundbrandt
A49: SPS Commerce - EDI
A50: 1 - ANA-050 | B50: ANA-050 - EDI 810 - Reviewed and approved | C50: Complete | D50: 45520 | E50: Cheska Acance
B51: ANA-050 - EDI 830-862 - Reviewed and approved | C51: Complete | D51: 45541 | E51: Melissa Byron
B52: ANA-050 - EDI 850 - Reviewed and approved | C52: Complete | D52: 45489 | E52: Cheska Acance
B53: ANA-050 - EDI 855 - Reviewed and approved | C53: Complete | D53: 45524 | E53: Cheska Acance
B54: ANA-050 - EDI 856 - Reviewed and approved | C54: Complete | D54: 45541 | E54: Melissa Byron
A55: 2 - TAR-040 | B55: TAR-040 Reviewed and approved | C55: In Progress | D55: 45576 | E55: Cheska Acance
A56: 3 - TEST-070 | B56: Unit Test Plan | C56: Not Started | D56: (blank) | E56: (blank)
A57: UPS
A58: 0 - ANA-050 | B58: ANA-050 - Ready for Review | C58: Complete | D58: 45457 | E58: (blank)
A59: 1 - ANA-050 | B59: ANA-050 - Reviewed and approved | C59: Complete | D59: 45457 | E59: Jack Adoline
A60: 2 - TAR-040 | B60: TAR-040 Reviewed and approved | C60: Complete | D60: 45541 | E60: Martin Bautista
A61: 3 - TEST-070 | B61: Unit Test Plan | C61: Not Started | D61: (blank) | E61: <Shipping / Warehouse>
A62: Grand Total

Sheet Barnes Dev Pivot
A1: Phase | B1: 1 - Dev
A3: Row Labels | B3: Task | C3: Status | D3: Due Date | E3: Priority | F3: Owner
A4: Bank of America (AP)
A5: Dev | B5: Detail file for ACH | C5: Complete | D5: 45562 | E5: * | F5: Isaiah Tolentino
B6: Detail file for checks | C6: Complete | D6: 45562 | E6: * | F6: Isaiah Tolentino
B7: Header file for ACH | C7: Complete | D7: 45562 | E7: * | F7: Isaiah Tolentino
B8: Header file for checks | C8: Complete | D8: (blank) | E8: (blank) | F8: Isaiah Tolentino
B9: SSIS: Transfer files to Industrial JBA box for transmission (weekly) | C9: Await files | D9: 45576 | E9: * | F9: Kevin Alexander
A10: CenPOS
A11: Dev | B11: Change service account from @infor.com to @asraymond.com | C11: In Progress | D11: 45562 | E11: Low | F11: Dean Amo
B12: Review test portal login | C12: Complete | D12: 45562 | E12: Low | F12: Dean Amo
B13: Update M3 CenPOS connector configuration after account change | C13: Not Started | D13: (blank) | E13: Low | F13: Hubert Santos
A14: Cforia
A15: Dev | B15: Build ARCASH.TXT exoport | C15: In Progress | D15: 45590 | E15: (blank) | F15: Kevin Alexander
B16: Build ARCUST.TXT exoport | C16: In Progress | D16: 45590 | E16: (blank) | F16: Kevin Alexander
B17: Build AREXTI.TXT exoport | C17: In Progress | D17: 45590 | E17: (blank) | F17: Kevin Alexander
B18: Build ARMAST.TXT exoport | C18: In Progress | D18: 45590 | E18: (blank) | F18: Kevin Alexander
B19: Build ARTRAN.TXT exoport | C19: In Progress | D19: 45590 | E19: (blank) | F19: Kevin Alexander
B20: Modify DW Job, BGIDW_M3_ASR to include AR files | C20: In Progress | D20: 45583 | E20: * | F20: Kevin Alexander
B21: Contact Cdoria - ensure test environment is ready | C21: (blank)
A22: Dev - Enahnce | B22: Invoice PDF to archive folder | C22: Not Started | D22: (blank) | E22: (blank) | F22: Karin Fransson
A23: Concur - Invoice
A24: Dev | B24: Inbound - Matched Payments to XML BOD drop off | C24: Complete | D24: 45484 | E24: (blank) | F24: Kevin Alexander
B25: OUT: Produce PO Header, Lines, Receipts, Vendor files | C25: Complete | D25: 45484 | E25: (blank) | F25: Kevin Alexander
B26: OUT: Ensure files ingest into Concur | C26: In Progress | D26: 45562 | E26: * | F26: Dean Amo
A27: DEV COMPLETE | B27: (blank) | C27: Complete | D27: 45526 | E27: (blank) | F27: (blank)
A28: Concur - Travel & Expense
A29: Dev | B29: Import flat file into M3 | C29: Not Started | D29: (blank) | E29: (blank) | F29: Kevin Alexander
F30: Rachelle
A31: FedEx
A32: Dev | B32: Configure address pull from M3 | C32: In Progress | D32: 45562 | E32: * | F32: Dean Amo
B33: Develop address pull query from data lake | C33: In Progress | D33: 45555 | E33: (blank) | F33: Dean Amo
B34: Configure XML output and drop off location | C34: In Progress | D34: 45569 | E34: * | F34: Dean Amo
A35: Optimizely
A36: Dev | B36: OUT: Add price list extract to BGIDW_M3_ASR_Daily.dtsx | C36: Complete | D36: 45534 | E36: (blank) | F36: Dean Amo
B37: OUT: Add inventory extract with gas charge logic | C37: Complete | D37: 45562 | E37: * | F37: Dean Amo
B38: OUT: Produce files from M3 company 910 and load to test | C38: In Progress | D38: 45569 | E38: * | F38: Dean Amo, Jane Woytach
B39: IN: CenPOS integration - schedule CONSID meeting | C39: Overdue | D39: 45541 | E39: * | F39: Dean Amo, Beth Wilkerson
B40: IN: CONSID - Update sales order file | C40: In Progress | D40: 45583 | E40: (blank) | F40: (blank)
B41: IN: Convert CSV to XML BOD | C41: Not Started | D41: 45583 | E41: (blank) | F41: (blank)
B42: IN: Verify ingestion of sales order BOD | C42: Not Started | D42: 45590 | E42: (blank) | F42: (blank)
B43: Contingency - May need to work with CONSID on data load | C43: In Progress | D43: 45569 | E43: (blank) | F43: Dean Amo
A44: PNC Bank (AR)
A45: Dev | B45: Bank test environment | C45: In Progress | D45: (blank) | E45: (blank) | F45: (blank)
B46: EDI 820/823 - To SPS Commerce Project Plan | C46: In Progress | D46: (blank) | E46: (blank) | F46: (blank)
B47: Matcher file to CSV | C47: Not Started | D47: 45576 | E47: ! | F47: Dennis Garrero
A48: Salesforce
A49: Dev | B49: Configure M3 to Salesforce connector | C49: Complete | D49: (blank) | E49: (blank) | F49: Martin Bautista
B50: Verify any open items agains ANA/TAR | C50: Not Started | D50: 45539 | E50: (blank) | F50: Dean, Torborjn, Martin
A51: SPS Commerce - EDI
A52: Dev | B52: Missing documents focus | C52: In Progress | D52: (blank) | E52: (blank) | F52: Jeff Finch, Rich Ostry, Melissa
B53: To SPS Commerce project plan | C53: In Progress | D53: (blank) | E53: (blank) | F53: Courtney Pribyl, Cheska
A54: UPS
A55: Dev | B55: Configure address pull from M3 | C55: In Progress | D55: 45562 | E55: * | F55: Dean Amo
B56: Develop address pull query from data lake | C56: In Progress | D56: 45555 | E56: (blank) | F56: Dean Amo
B57: Configure XML output and drop off location | C57: Not Started | D57: 45569 | E57: * | F57: Dean Amo
A58: (blank)
A59: Dev | B59: Transmit to Cforia | C59: Not Started | D59: 45597 | E59: (blank) | F59: Kevin Alexander
A60: Grand Total

Sheet Pivot
A3: Row Labels
A4: Development
A5: SPS Commerce EDI
A6: EDI Invoice
A7: EDI Sales Order Ack
A8: Not Started
A9: Cforia
A10: Customer Master
A11: Customer Order
A12: Customer Payments & Credits
A13: Invoice Copies IDM (PDF)
A14: Invoice Payment History
... A71: Grand Total

Sheet Current Week
A1: Priority | B1: *
A3: Owner/Interface | B3: Task | C3: Due Date | D3: Status | E3: Note
A4: Amy Burgard
A5: CenPOS | B5: Unit Test Plan - CenPOS - contact Hubert for M3 functional questions | C5: 45548 | D5: Overdue | E5: *Meeting scheduled Thur 9/26
A6: Carlo Alcazar
A7: Cforia | B7: TAR-040 Reviewed and approved | C7: 45569 | D7: Await Dependancy | E7: Awaiting ANA-050
A8: Cheska Acance
A9: Optimizely | B9: ANA-050 - Ready for Review | C9: 45541 | D9: Complete | E9: (blank)
A10: SPS Commerce - EDI | B10: TAR-040 Reviewed and approved | C10: 45576 | D10: In Progress | E10: *Sep-20 - Verify Owner
A11: Dean Amo
A12: Concur - Invoice | B12: OUT: Ensure files ingest into Concur | C12: 45562 | D12: In Progress | E12: Sep-20 - Last import successful, turning on feed Monday (Sep-23) evening run
A13: FedEx | B13: Configure address pull from M3 | C13: 45562 | D13: In Progress | E13: (blank)
B14: Configure XML output and drop off location | C14: 45569 | D14: In Progress | E14: (blank)
B15: Need sample shipments file XML from FedEx production | C15: 45562 | D15: Complete | E15: (blank)
A16: Optimizely | B16: OUT: Add inventory extract with gas charge logic | C16: 45562 | D16: Complete | E16: (blank)
A17: UPS | B17: Configure address pull from M3 | C17: 45562 | D17: In Progress | E17: Awaiting network connectivity - CHG
B18: Configure XML output and drop off location | C18: 45569 | D18: Not Started | E18: (blank)
A19: Dean Amo, Beth Wilkerson
A20: Optimizely | B20: IN: CenPOS integration - schedule CONSID meeting | C20: 45541 | D20: Overdue | E20: 9/20 - Discussing requirements
A21: Dean Amo, Jane Woytach
A22: Optimizely | B22: OUT: Produce files from M3 company 910 and load to test | C22: 45569 | D22: In Progress | E22: (blank)
A23: Dennis Garrero
A24: Concur - Invoice | B24: ANA-050 - Payments to M3 - Ready for Review | C24: 45555 | D24: Overdue | E24: 45559
A25: PNC Bank (AR) | B25: ANA-050 - Payments to M3 - Ready for Review | C25: 45562 | D25: In Progress | E25: (blank)
A26: Isaiah Tolentino
A27: Bank of America (AP) | B27: Detail file for ACH | C27: 45562 | D27: Complete | E27: 10/2 Wed - Martin on 9/30 9a call
B28: Detail file for checks | C28: 45562 | D28: Complete | E28: 10/2 Wed - Martin on 9/30 9a call
B29: Header file for ACH | C29: 45562 | D29: Complete | E29: 10/2 Wed - Martin on 9/30 9a call
A30: Kevin Alexander
A31: Bank of America (AP) | B31: SSIS: Transfer files to Industrial JBA box for transmission (weekly) | C31: 45576 | D31: Await files | E31: (blank)
A32: Cforia | B32: Modify DW Job, BGIDW_M3_ASR to include AR files | C32: 45583 | D32: In Progress | E32: (blank)
A33: Kim Diorio
A34: Bank of America (AP) | B34: ANA-050 - Signoff | C34: 45541 | D34: Complete | E34: Agreed approved in Meeting 9/23/2024
A35: Concur - Invoice | B35: ANA-050 - Reviewed and approved | C35: 45562 | D35: Await Dependancy | E35: (blank)
A36: PNC Bank (AR) | B36: ANA-050 - Reviewed and approved | C36: 45569 | D36: Await Dependancy | E36: (blank)
A37: Kim Diorio / Kevin Alexander
A38: Cforia | B38: ANA-050 - Sign off | C38: 45569 | D38: Await Dependancy | E38: (blank)
A39: Martin Bautista
A40: Concur - Travel & Expense | B40: Concur TAR-040 | C40: 45576 | D40: In Progress | E40: (blank)
A41: Torbjörn Sundbrandt
A42: Salesforce | B42: Unit Test Plan | C42: 45562 | D42: In Progress | E42: (blank)
A43: Beth Wilkerson
A44: Optimizely | B44: ANA-050 - Reviewed and approved | C44: 45555 | D44: Complete | E44: Approved 9/23/2024 via email
A45: Jesse Keech, Kim Diorio
A46: Concur - Travel & Expense | B46: ANA-050 - Reviewed and approved | C46: 45565 | D46: Await Dependancy | E46: Review @9a
A47: Dennis Garrero, Rachelle
A48: Cforia | B48: ANA-050 - Ready for Review | C48: 45548 | D48: Overdue | E48: 9/30/2024 - New Due Date
A49: Concur - Travel & Expense | B49: ANA-050 - Ready for Review | C49: 45565 | D49: Overdue | E49: (blank)
A50: Rachelle
A51: Concur - Travel & Expense | B51: GLS 840 - Can we use existing format or do we need new? | C51: 45565 | D51: Not Started | E51: (blank)
A52: Grand Total

Sheet Drop Down
B1: Status | F1: Status | I1: Sub Category | J1: Days | K1: Days to complete Integration | N1: Deploy
B2: New Interface | D2: Completed | F2: Not Started | I2: N-New Interface | J2: 10 | K2: 60 | N2: TST
B3: Not Started | D3: NA | F3: Out of Scope | I3: Not Started | J3: 10 | K3: 60 | N3: TRN
B4: Out of Scope | D4: Not Started | F4: Pre Development | I4: Out of Scope | J4: 10 | K4: 60 | N4: PRD
B5: Pre Development | D5: Pending Approval | G5: Solution Unknown | I5: Solution Unknown | J5: 10 | K5: 60
B6: Development | D6: Pending Confirmation | G6: Research | I6: Research | J6: 10 | K6: 35
B7: Testing | D7: WIP | G7: Speccing (ANA-050) | I7: Speccing (ANA-050) | J7: 5 | K7: =K6-J7 -> 30
B8: Infor Standard Integration (OOB) | G8: Tech Spec (TAR-040) | I8: Tech Spec (TAR-040) | J8: 5 | K8: =K7-J8 -> 25
B9: Integration Approved for Deployment | F9: Development | I9: Development | J9: 10 | K9: =K8-J9 -> 15
F10: Testing | I10: Development Testing | J10: 3 | K10: =K9-J10 -> 12
G11: Development Testing | I11: Functional Testing | J11: 5 | K11: =K10-J11 -> 7
G12: Functional Testing | I12: Business Testing | J12: 5 | K12: =K11-J12 -> 2
G13: Business Testing | I13: Break/Fix/Retest | J13: 2 | K13: =K12-J13 -> 0
F14: Integration Approved for Deployment | I14: Approved/Complete | J14: 0 | K14: =K13-J14 -> 0
F15: New Interface
F16: Infor Standard Integration (OOB)
