Workbook

Sheet Multiple Payrolls
A1: Details for Count of Payroll Company Code
A3: Payroll Company Code | B3: Legal First Name | C3: Middle Initial | D3: Legal Last Name | E3: Preferred or Chosen First Name | F3: Preferred or Chosen Last Name | G3: Reports To Legal Name | H3: Supervisor ID | I3: Work Contact: Work Email | J3: Personal Contact: Personal Email | K3: Job Title Description | L3: Hire Date | M3: Termination Date | N3: Rehire Date | O3: Position Status | P3: File Number | Q3: Pay Frequency | R3: Employee Type | S3: Business Unit Code | T3: Business Unit Description | U3: Home Department Description | V3: Home Department Code | W3: Location Description | X3: Language Description | Y3: Language Code | Z3: Legal / Preferred Address: Country Code | AA3: Pay Grade Code | AB3: Pay Grade Description | AC3: SupervisorID Formatted | AD3: Org Unit 1 | AE3: Org Unit 2 | AF3: Concur Profile | AG3: Travel Profile | AH3: Legal Country | AI3: Local Code | AJ3: Reumbursement Currency | AK3: Perferred Name | AL3: Status | AM3: Term Date | AN3: 7/20/26 | AO3: Name | AP3: SupervisorLastName | AQ3: Lookup Supervisor ID | AR3: SupervisorName=Supervisor ID
A4: KSX | B4: Abdellatef | C4: M | D4: Mahmoud | G4: Burchell, Mathew | H4: KSY211756 | J4: oomer77@yahoo.com | K4: Assistant, Warehouse II | L4: 45208 | O4: Active | P4: 210316 | Q4: Biweekly | R4: Full Time | S4: 088 | T4: 088-AS Raymond | U4: Assembly | V4: 005100 | W4: AS Raymond | Z4: USA | AA4: S05 | AB4: FMG-S05 | AC4: 211756 | AD4: 0088 | AE4: 5100 | AF4: Default | AG4: General | AH4: US | AI4: en_US | AJ4: USD | AL4: Y | AO4: AbdellatefMMahmoud | AP4: Burchell | AQ4: 211756 | AR4: TRUE
A5: KSY | B5: Alex | D5: Palicki | G5: Creager, Andrew | H5: KSY212699 | I5: apalicki@onebarnes.com | J5: alexpalicki4@gmail.com | K5: Buyer III | L5: 45831 | O5: Active | P5: 212119 | Q5: Monthly | R5: Full Time | S5: 088 | T5: 088-AS Raymond | U5: Admin-Material Management | V5: 009400 | W5: AS Raymond | Z5: USA | AA5: S13 | AB5: FMG-S13 | AC5: 212699 | AD5: 0088 | AE5: 9400 | AF5: Default | AG5: General | AH5: US | AI5: en_US | AJ5: USD | AL5: Y | AO5: AlexPalicki | AP5: Creager | AQ5: 212699 | AR5: TRUE
A6: KSX | B6: Amir | D6: Dillard | G6: Burchell, Mathew | H6: KSY211756 | I6: adillard1@onebarnes.com | J6: amirdillard4@gmail.com | K6: Assistant, Warehouse II | L6: 45754 | O6: Active | P6: 211895 | Q6: Biweekly | R6: Full Time | S6: 088 | T6: 088-AS Raymond | U6: Assembly | V6: 005100 | W6: AS Raymond | Z6: USA | AA6: S05 | AB6: FMG-S05 | AC6: 211756 | AD6: 0088 | AE6: 5100 | AF6: Default | AG6: General | AH6: US | AI6: en_US | AJ6: USD | AL6: Y | AO6: AmirDillard | AP6: Burchell | AQ6: 211756 | AR6: TRUE
A7: V0U | B7: Amy | C7: C | D7: McGuire | G7: Warner, Dwight | H7: V0U008750 | I7: AMcGuire@onebarnes.com | J7: RedAmyMcG@gmail.com | K7: Accountant III | L7: 35338 | O7: Active | P7: 007861 | Q7: Monthly | R7: Full Time | S7: 025 | T7: 025-NGP Hyson Products | U7: Finance | V7: 000910 | W7: Hyson Products | Z7: USA | AA7: S13 | AB7: FMG-S13 | AC7: 008750 | AD7: 0096 | AE7: 910 | AF7: Default | AG7: General | AH7: US | AI7: en_US | AJ7: USD | AL7: Y | AO7: AmyCMcGuire | AP7: Warner | AQ7: 008750 | AR7: TRUE
A8: KSY | B8: Andrew | C8: J | D8: Creager | G8: Bailey, Jason | H8: KSY211766 | I8: acreager@onebarnes.com | K8: Mgr, Supply Chain III | L8: 45957 | O8: Active | P8: 212699 | Q8: Monthly | R8: Full Time | S8: 088 | T8: 088-AS Raymond | U8: Admin-Material Management | V8: 009400 | W8: AS Raymond | Z8: USA | AA8: S17 | AB8: FMG-S17 | AC8: 211766 | AD8: 0088 | AE8: 9400 | AF8: Default | AG8: General | AH8: US | AI8: en_US | AJ8: USD | AL8: Y | AO8: AndrewJCreager | AP8: Bailey | AQ8: 902688 | AR8: FALSE
A9: KSX | B9: Angela | D9: Myers | G9: Burchell, Mathew | H9: KSY211756 | J9: amm823@bex.net | K9: Assistant, Warehouse II | L9: 45881 | O9: Active | P9: 212349 | Q9: Biweekly | R9: Full Time | S9: 088 | T9: 088-AS Raymond | U9: Assembly | V9: 005100 | W9: AS Raymond | Z9: USA | AA9: S05 | AB9: FMG-S05 | AC9: 211756 | AD9: 0088 | AE9: 5100 | AF9: Default | AG9: General | AH9: US | AI9: en_US | AJ9: USD | AL9: Y | AO9: AngelaMyers | AP9: Burchell | AQ9: 211756 | AR9: TRUE
A10: V0U | B10: Anne | C10: M | D10: Garber | G10: Bate, Natalie | I10: agarber@onebarnes.com | J10: anne.michael00@gmail.com | K10: Mgr, Program | L10: 46265 | O10: Active | P10: 902627 | Q10: Monthly | R10: Full Time | S10: 025 | T10: 025-NGP Hyson Products | U10: Administration | V10: 000917 | W10: Hyson Products | Z10: USA | AA10: S17 | AB10: FMG-S17 | AD10: 0096 | AE10: 0007 | AF10: Default | AG10: General | AH10: US | AI10: en_US | AJ10: USD | AL10: Y | AO10: AnneMGarber | AP10: Bate | AQ10: 213037 | AR10: FALSE
A11: KSW | B11: Anthony | D11: Desillas | J11: desillasa@yahoo.com | K11: Lathe Operator | L11: 45859 | M11: 46046 | O11: Terminated | P11: 212244 | Q11: Biweekly | R11: Full Time | S11: 025 | T11: 025-NGP Hyson Products | U11: CNC Lathe Hyson | V11: 000100 | W11: Hyson Products | Z11: USA | AA11: H07 | AB11: FMG-H07 | AD11: 0096 | AE11: 100 | AF11: Default | AG11: General | AH11: US | AI11: en_US | AJ11: USD | AL11: N | AM11: 20260124 | AN11: Exclude record termination over 45 days ago | AO11: AnthonyDesillas | AP11: #VALUE! | AQ11: No Reports to Name | AR11: FALSE
A12: KSW | B12: Anthony | C12: J | D12: Frimel | G12: Steen, Michael | H12: V0U211062 | I12: afrimel@onebarnes.com | J12: tfrimel@att.net | K12: Tech, Manufacturing A | L12: 37410 | O12: Active | P12: 004352 | Q12: Biweekly | R12: Full Time | S12: 025 | T12: 025-NGP Hyson Products | U12: CNC Lathe Hyson | V12: 000100 | W12: Hyson Products | Z12: USA | AA12: H08 | AB12: FMG-H08 | AC12: 211062 | AD12: 0096 | AE12: 100 | AF12: Default | AG12: General | AH12: US | AI12: en_US | AJ12: USD | AL12: Y | AO12: AnthonyJFrimel | AP12: Steen | AQ12: 211062 | AR12: TRUE
A13: V0U | B13: Anthony | C13: J | D13: Moavero | G13: Brower, James | I13: amoavero1@onebarnes.com | K13: Intern, Engineering Indir | L13: 45810 | M13: 46176 | O13: Terminated | P13: 212052 | Q13: Monthly | R13: Intern | S13: 025 | T13: 025-NGP Hyson Products | U13: Sustaining Engineering | V13: 000900 | W13: Hyson Products | Z13: USA | AA13: H05 | AB13: FMG-H05 | AD13: 0096 | AE13: 900 | AF13: Default | AG13: General | AH13: US | AI13: en_US | AJ13: USD | AL13: N | AM13: 20260603 | AN13: Fix and Include Record | AO13: AnthonyJMoavero | AP13: Brower | AQ13: 006769 | AR13: FALSE
A14: KSX | B14: Anthony | C14: J | D14: Moavero | I14: amoavero1@onebarnes.com | L14: 45810 | M14: 45878 | O14: Terminated | P14: 212052 | Q14: Biweekly | R14: Full Time | W14: AS Raymond | Z14: USA | AD14: BU Description Not Mapped | AE14: Home Department Code Not Mapped | AF14: Salary Code Not Mapped | AG14: Salary Code Not Mapped | AH14: US | AI14: ADP and BU Language Code Not MappedUS | AJ14: BU Currency Not Mapped | AL14: N | AM14: 20250809 | AN14: Exclude record termination over 45 days ago | AO14: AnthonyJMoavero | AP14: #VALUE! | AQ14: No Reports to Name | AR14: FALSE
A15: KSW | B15: Anthony | C15: J | D15: Moavero | G15: Brower, James | H15: V0U006769 | I15: amoavero1@onebarnes.com | K15: Intern, Engineering Indir | L15: 45810 | M15: 46248 | O15: Terminated | P15: 212052 | Q15: Biweekly | R15: Intern | S15: 025 | T15: 025-NGP Hyson Products | U15: Sustaining Engineering | V15: 000900 | W15: Hyson Products | Z15: USA | AA15: H05 | AB15: FMG-H05 | AC15: 006769 | AD15: 0096 | AE15: 900 | AF15: Default | AG15: General | AH15: US | AI15: en_US | AJ15: USD | AL15: N | AM15: 20260814 | AN15: Exclude record termination over 45 days ago | AO15: AnthonyJMoavero | AP15: Brower | AQ15: 006769 | AR15: TRUE
A16: V0U | B16: Anthony | C16: J | D16: Moavero | G16: Brower, James | I16: amoavero1@onebarnes.com | K16: Intern, Engineering Indir | L16: 45810 | M16: 46176 | O16: Terminated | P16: 212052 | Q16: Biweekly | R16: Intern | S16: 025 | T16: 025-NGP Hyson Products | U16: Sustaining Engineering | V16: 000900 | W16: Hyson Products | Z16: USA | AA16: H05 | AB16: FMG-H05 | AD16: 0096 | AE16: 900 | AF16: Default | AG16: General | AH16: US | AI16: en_US | AJ16: USD | AL16: N | AM16: 20260603 | AN16: Fix and Include Record | AO16: AnthonyJMoavero | AP16: Brower | AQ16: 006769 | AR16: FALSE
A17: KSX | B17: Asia | D17: Sexton | G17: Burchell, Mathew | H17: KSY211756 | J17: asexton@yahoo.com | K17: Assistant, Warehouse II | L17: 46190 | M17: 46251 | O17: Terminated | Q17: Biweekly | R17: Temporary | S17: 088 | T17: 088-AS Raymond | U17: Assembly | V17: 005100 | W17: AS Raymond | Z17: USA | AA17: S05 | AB17: FMG-S05 | AC17: 211756 | AD17: 0088 | AE17: 5100 | AF17: Default | AG17: General | AH17: US | AI17: en_US | AJ17: USD | AL17: N | AM17: 20260817 | AN17: Fix and Include Record | AO17: AsiaSexton | AP17: Burchell | AQ17: 211756 | AR17: TRUE
A18: KSX | B18: Aydrian | C18: M | D18: Ahrens | G18: Burchell, Mathew | H18: KSY211756 | J18: aydrian0323@yahoo.com | K18: Assistant, Warehouse II | L18: 45754 | O18: Active | P18: 211901 | Q18: Biweekly | R18: Full Time | S18: 088 | T18: 088-AS Raymond | U18: Assembly | V18: 005100 | W18: AS Raymond | Z18: USA | AA18: S05 | AB18: FMG-S05 | AC18: 211756 | AD18: 0088 | AE18: 5100 | AF18: Default | AG18: General | AH18: US | AI18: en_US | AJ18: USD | AL18: Y | AO18: AydrianMAhrens | AP18: Burchell | AQ18: 211756 | AR18: TRUE
A19: KSX | B19: Barbara | C19: C | D19: Wilkinson | G19: Burchell, Mathew | H19: KSY211756 | J19: wilkinsonb518@gmail.com | K19: Assistant, Warehouse II | L19: 44942 | O19: Active | P19: 209539 | Q19: Biweekly | R19: Full Time | S19: 088 | T19: 088-AS Raymond | U19: Assembly | V19: 005100 | W19: AS Raymond | Z19: USA | AA19: S05 | AB19: FMG-S05 | AC19: 211756 | AD19: 0088 | AE19: 5100 | AF19: Default | AG19: General | AH19: US | AI19: en_US | AJ19: USD | AL19: Y | AO19: BarbaraCWilkinson | AP19: Burchell | AQ19: 211756 | AR19: TRUE
A20: KSX | B20: Benjamin | C20: D | D20: Uncapher | G20: Rafferty, Jonathan | H20: KSY211131 | I20: buncapher@onebarnes.com | K20: Rep, Customer Service III | L20: 45867 | O20: Active | P20: 212254 | Q20: Biweekly | R20: Full Time | S20: 088 | T20: 088-AS Raymond | U20: Inside Sales | V20: 008100 | W20: AS Raymond | Z20: USA | AA20: S11 | AB20: FMG-S11 | AC20: 211131 | AD20: 0088 | AE20: 8100 | AF20: Default | AG20: General | AH20: US | AI20: en_US | AJ20: USD | AL20: Y | AO20: BenjaminDUncapher | AP20: Rafferty | AQ20: 211131 | AR20: TRUE
A21: KSY | B21: Benjamin | C21: D | D21: Uncapher | I21: buncapher@onebarnes.com | K21: Rep, Customer Service III | L21: 45867 | M21: 46175 | O21: Terminated | P21: 212254 | Q21: Monthly | R21: Full Time | S21: 088 | T21: 088-AS Raymond | U21: Inside Sales | V21: 008100 | W21: AS Raymond | Z21: USA | AA21: S11 | AB21: FMG-S11 | AD21: 0088 | AE21: 8100 | AF21: Default | AG21: General | AH21: US | AI21: en_US | AJ21: USD | AL21: N | AM21: 20260602 | AN21: Fix and Include Record | AO21: BenjaminDUncapher | AP21: #VALUE! | AQ21: No Reports to Name | AR21: FALSE
A22: KSY | B22: Benjamin | D22: Sullivan | G22: Creager, Andrew | H22: KSY212699 | I22: bsullivan@onebarnes.com | K22: Planner, Production II | L22: 45131 | O22: Active | P22: 210103 | Q22: Monthly | R22: Full Time | S22: 088 | T22: 088-AS Raymond | U22: Admin-Material Management | V22: 009400 | W22: AS Raymond | Z22: USA | AA22: S12 | AB22: FMG-S12 | AC22: 212699 | AD22: 0088 | AE22: 9400 | AF22: Default | AG22: General | AH22: US | AI22: en_US | AJ22: USD | AL22: Y | AO22: BenjaminSullivan | AP22: Creager | AQ22: 212699 | AR22: TRUE
A23: KSW | B23: Bobby | D23: Hicks | G23: Wallace, Derron | H23: V0U211998 | I23: bhicks@onebarnes.com | J23: bhicks1@me.com | K23: Lead, Unit Team | L23: 45481 | O23: Active | P23: 211145 | Q23: Biweekly | R23: Full Time | S23: 025 | T23: 025-NGP Hyson Products | U23: Assembly Hyson | V23: 000200 | W23: Hyson Products | Z23: USA | AA23: H08 | AB23: FMG-H08 | AC23: 211998 | AD23: 0096 | AE23: 200 | AF23: Default | AG23: General | AH23: US | AI23: en_US | AJ23: USD | AL23: Y | AO23: BobbyHicks | AP23: Wallace | AQ23: 211998 | AR23: TRUE
A24: KSY | B24: Bonnetta | C24: D | D24: Warren | G24: Oleksa, Laura | H24: V0U209181 | I24: bwarren@onebarnes.com | K24: Mgr, HR I | L24: 45958 | O24: Active | P24: 212705 | Q24: Monthly | R24: Full Time | S24: 088 | T24: 088-AS Raymond | U24: HR CU | V24: 009210 | W24: Works from home - Ohio | Z24: USA | AA24: S15 | AB24: FMG-S15 | AC24: 209181 | AD24: 0088 | AE24: 9210 | AF24: Default | AG24: General | AH24: US | AI24: en_US | AJ24: USD | AL24: Y | AO24: BonnettaDWarren | AP24: Oleksa | AQ24: 209181 | AR24: TRUE
A25: KSY | B25: Bradley | D25: Masters | E25: Brad | F25: Masters | G25: Rodriguez, Siobhan | H25: V0U207588 | I25: bmasters@onebarnes.com | J25: brad.a.masters@gmail.com | K25: Mgr, Sales | L25: 46223 | O25: Active | P25: 902437 | Q25: Monthly | R25: Full Time | S25: 088 | T25: 088-AS Raymond | U25: Outside Sales | V25: 008200 | W25: Works from home - Ohio | Z25: USA | AA25: S16 | AB25: FMG-S16 | AC25: 207588 | AD25: 0088 | AE25: 8200 | AF25: Default | AG25: General | AH25: US | AI25: en_US | AJ25: USD | AK25: Brad Masters | AL25: Y | AO25: BradleyMasters | AP25: Rodriguez | AQ25: 212338 | AR25: FALSE
A26: KSX | B26: Brandon | D26: Hibbitts | H26: KSY900848 | I26: bhibbitts@onebarnes.com | J26: hibbitts.brandon@gmail.com | K26: Intern, IT Indirect | L26: 45502 | M26: 46203 | O26: Terminated | P26: 211181 | Q26: Biweekly | R26: Part Time | S26: 088 | T26: 088-AS Raymond | U26: Business Applications | V26: 009150 | W26: AS Raymond | Z26: USA | AA26: H05 | AB26: FMG-H05 | AC26: 900848 | AD26: 0088 | AE26: 9150 | AF26: Default | AG26: General | AH26: US | AI26: en_US | AJ26: USD | AL26: N | AM26: 20260630 | AN26: Fix and Include Record | AO26: BrandonHibbitts | AP26: #VALUE! | AQ26: No Reports to Name | AR26: FALSE
A27: KSY | B27: Brandon | D27: Hibbitts | G27: Erdogan, Mehmet | H27: 000207199N | I27: bhibbitts@onebarnes.com | J27: hibbitts.brandon@gmail.com | K27: Analyst, Help Desk II | L27: 45502 | O27: Active | P27: 211181 | Q27: Monthly | R27: Full Time | S27: 088 | T27: 088-AS Raymond | U27: Business Applications | V27: 009150 | W27: AS Raymond | Z27: USA | AA27: S12 | AB27: FMG-S12 | AC27: 207199 | AD27: 0088 | AE27: 9150 | AF27: Default | AG27: General | AH27: US | AI27: en_US | AJ27: USD | AL27: Y | AO27: BrandonHibbitts | AP27: Erdogan | AQ27: No Reports to Name | AR27: FALSE
A28: KSX | B28: Brandon | D28: Kelly | G28: Alexander, Thomas | H28: KSY210892 | J28: bkelly8@rockets.utoledo.edu | K28: Intern, Operations Direct | L28: 46155 | M28: 46248 | O28: Terminated | P28: 213235 | Q28: Biweekly | R28: Intern | S28: 088 | T28: 088-AS Raymond | U28: Admin-Quality | V28: 009500 | W28: AS Raymond | Z28: USA | AA28: H05 | AB28: FMG-H05 | AC28: 210892 | AD28: 0088 | AE28: 9500 | AF28: Default | AG28: General | AH28: US | AI28: en_US | AJ28: USD | AL28: N | AM28: 20260814 | AN28: Exclude record termination over 45 days ago | AO28: BrandonKelly | AP28: Alexander | AQ28: 210892 | AR28: TRUE
A29: KSX | B29: Brenda | D29: Bixler | G29: LaPlante, Derek | H29: KSY211736 | I29: bbixler@onebarnes.com | J29: beebix911@gmail.com | K29: Expeditor, Warehouse | L29: 45502 | O29: Active | P29: 211174 | Q29: Biweekly | R29: Full Time | S29: 088 | T29: 088-AS Raymond | U29: FG Warehouse | V29: 005200 | W29: AS Raymond | Z29: USA | AA29: S06 | AB29: FMG-S06 | AC29: 211736 | AD29: 0088 | AE29: 5200 | AF29: Default | AG29: General | AH29: US | AI29: en_US | AJ29: USD | AL29: Y | AO29: BrendaBixler | AP29: LaPlante | AQ29: 211736 | AR29: TRUE
A30: KSX | B30: Brenda | C30: J | D30: Daniel | H30: KSY202533 | J30: brendajdaniel@gmail.com | K30: Rep, Customer Service I | L30: 46160 | M30: 46181 | O30: Terminated | P30: 213236 | Q30: Biweekly | R30: Full Time | S30: 088 | T30: 088-AS Raymond | U30: Inside Sales | V30: 008100 | W30: AS Raymond | Z30: USA | AA30: S08 | AB30: FMG-S08 | AC30: 202533 | AD30: 0088 | AE30: 8100 | AF30: Default | AG30: General | AH30: US | AI30: en_US | AJ30: USD | AL30: N | AM30: 20260608 | AN30: Fix and Include Record | AO30: BrendaJDaniel | AP30: #VALUE! | AQ30: No Reports to Name | AR30: FALSE
A31: KSW | B31: Brennen | C31: G | D31: Valley | G31: Steen, Michael | H31: V0U211062 | I31: bvalley@onebarnes.com | K31: Machinist, CNC | L31: 44361 | O31: Active | P31: 206287 | Q31: Biweekly | R31: Part Time | S31: 025 | T31: 025-NGP Hyson Products | U31: CNC Lathe Hyson | V31: 000100 | W31: Hyson Products | Z31: USA | AA31: H04 | AB31: FMG-H04 | AC31: 211062 | AD31: 0096 | AE31: 100 | AF31: Default | AG31: General | AH31: US | AI31: en_US | AJ31: USD | AL31: Y | AO31: BrennenGValley | AP31: Steen | AQ31: 211062 | AR31: TRUE
A32: KSY | B32: Brittany | C32: M | D32: Velner | I32: bvelner@onebarnes.com | K32: Lead, Cust Serv | L32: 45951 | M32: 46136 | O32: Terminated | P32: 212687 | Q32: Monthly | R32: Full Time | S32: 088 | T32: 088-AS Raymond | U32: Inside Sales | V32: 008100 | W32: AS Raymond | Z32: USA | AA32: S12 | AB32: FMG-S12 | AD32: 0088 | AE32: 8100 | AF32: Default | AG32: General | AH32: US | AI32: en_US | AJ32: USD | AL32: N | AM32: 20260424 | AN32: Fix and Include Record | AO32: BrittanyMVelner | AP32: #VALUE! | AQ32: No Reports to Name | AR32: FALSE
A33: KSX | B33: Candi | C33: M | D33: Morales | G33: Alexander, Thomas | H33: KSY210892 | I33: cburris@onebarnes.com | J33: cmorales6132015@gmail.com | K33: Admin, Document Control | L33: 35947 | O33: Active | P33: 007630 | Q33: Biweekly | R33: Full Time | S33: 088 | T33: 088-AS Raymond | U33: Admin-Quality | V33: 009500 | W33: AS Raymond | Z33: USA | AA33: S10 | AB33: FMG-S10 | AC33: 210892 | AD33: 0088 | AE33: 9500 | AF33: Default | AG33: General | AH33: US | AI33: en_US | AJ33: USD | AL33: Y | AO33: CandiMMorales | AP33: Alexander | AQ33: 210892 | AR33: TRUE
A34: KSY | B34: Carla | C34: J | D34: Cunningham | I34: ccunningham@onebarnes.com | J34: springgirl3@sbcglobal.net | L34: 46022 | M34: 46022 | O34: Terminated | P34: 007633 | Q34: Monthly | R34: Full Time | W34: AS Raymond | Z34: USA | AD34: BU Description Not Mapped | AE34: Home Department Code Not Mapped | AF34: Salary Code Not Mapped | AG34: Salary Code Not Mapped | AH34: US | AI34: ADP and BU Language Code Not MappedUS | AJ34: BU Currency Not Mapped | AL34: N | AM34: 20251231 | AN34: Fix and Include Record | AO34: CarlaJCunningham | AP34: #VALUE! | AQ34: No Reports to Name | AR34: FALSE
B35: Carla | C35: J | D35: Cunningham | I35: ccunningham@onebarnes.com | J35: springgirl3@sbcglobal.net | L35: 46022 | M35: 46023 | O35: Terminated | Q35: Weekly | Z35: USA | AD35: BU Description Not Mapped | AE35: Home Department Code Not Mapped | AF35: Salary Code Not Mapped | AG35: Salary Code Not Mapped | AH35: US | AI35: ADP and BU Language Code Not MappedUS | AJ35: BU Currency Not Mapped | AL35: N | AM35: 20260101 | AN35: Exclude record termination over 45 days ago | AO35: CarlaJCunningham | AP35: #VALUE! | AQ35: No Reports to Name | AR35: FALSE
A36: KSY | B36: Carol | D36: Phillips | G36: Rodriguez, Siobhan | H36: V0U207588 | I36: cphillips1@onebarnes.com | J36: cphillips1226@icloud.com | K36: Mgr, Sales | L36: 45909 | O36: Active | P36: 212478 | Q36: Monthly | R36: Full Time | S36: 088 | T36: 088-AS Raymond | U36: Outside Sales | V36: 008200 | W36: Works from home - Ohio | Z36: USA | AA36: S16 | AB36: FMG-S16 | AC36: 207588 | AD36: 0088 | AE36: 8200 | AF36: Default | AG36: General | AH36: US | AI36: en_US | AJ36: USD | AL36: Y | AO36: CarolPhillips | AP36: Rodriguez | AQ36: 212338 | AR36: FALSE
A37: KSY | B37: Carrie | C37: M | D37: Hoffman | G37: Oleksa, Laura | H37: V0U209181 | I37: choffman@onebarnes.com | J37: Carriehoffman89@gmail.com | K37: HR Coordinator | L37: 43101 | O37: Active | P37: 902349 | Q37: Monthly | R37: Full Time | S37: 088 | T37: 088-AS Raymond | U37: HR General | V37: 009200 | W37: AS Raymond | Z37: USA | AA37: S11 | AB37: FMG-S11 | AC37: 209181 | AD37: 0088 | AE37: 9200 | AF37: Default | AG37: General | AH37: US | AI37: en_US | AJ37: USD | AL37: Y | AO37: CarrieMHoffman | AP37: Oleksa | AQ37: 209181 | AR37: TRUE
A38: KSX | B38: Cassandra | C38: G | D38: Richards | G38: LaPlante, Derek | H38: KSY211736 | I38: crichards@onebarnes.com | J38: cassandrarichards13@gmail.com | K38: Assistant, Warehouse II | L38: 45334 | M38: 46262 | O38: Terminated | P38: 210727 | Q38: Biweekly | R38: Full Time | S38: 088 | T38: 088-AS Raymond | U38: FG Warehouse | V38: 005200 | W38: AS Raymond | Z38: USA | AA38: S05 | AB38: FMG-S05 | AC38: 211736 | AD38: 0088 | AE38: 5200 | AF38: Default | AG38: General | AH38: US | AI38: en_US | AJ38: USD | AL38: N | AM38: 20260828 | AN38: Fix and Include Record | AO38: CassandraGRichards | AP38: LaPlante | AQ38: 211736 | AR38: TRUE
A39: V0U | B39: Chad | D39: Phillips | G39: Wilkins, William | H39: V0U901934 | I39: cphillips@onebarnes.com | J39: phillipsx2@verizon.net | K39: Mgr, Sales | L39: 45243 | M39: 46248 | O39: Terminated | P39: 210402 | Q39: Monthly | R39: Full Time | S39: 025 | T39: 025-NGP Hyson Products | U39: Outside Sales | V39: 000820 | W39: Hyson Products | Z39: USA | AA39: S15 | AB39: FMG-S15 | AC39: 901934 | AD39: 0096 | AE39: 820 | AF39: Default | AG39: General | AH39: US | AI39: en_US | AJ39: USD | AL39: N | AM39: 20260814 | AN39: Fix and Include Record | AO39: ChadPhillips | AP39: Wilkins | AQ39: 901934 | AR39: TRUE
A40: KSW | B40: Charles | D40: McDavid | H40: V0U211062 | J40: chuckmcdavid1999@icloud.com | K40: Lathe Operator | L40: 46202 | O40: Active | P40: 213332 | Q40: Biweekly | R40: Full Time | S40: 025 | T40: 025-NGP Hyson Products | U40: CNC Lathe Hyson | V40: 000100 | W40: Hyson Products | Z40: USA | AA40: H07 | AB40: FMG-H07 | AC40: 211062 | AD40: 0096 | AE40: 100 | AF40: Default | AG40: General | AH40: US | AI40: en_US | AJ40: USD | AL40: Y | AO40: CharlesMcDavid | AP40: #VALUE! | AQ40: No Reports to Name | AR40: FALSE
A41: KSW | B41: Cherie | D41: Hassey | G41: Wallace, Derron | H41: V0U211998 | I41: chassey@onebarnes.com | J41: c.hassey@att.net | K41: Rep, Customer Service II | L41: 46125 | O41: Active | P41: 213144 | Q41: Biweekly | R41: Full Time | S41: 025 | T41: 025-NGP Hyson Products | U41: Inside Sales | V41: 000850 | W41: Hyson Products | Z41: USA | AA41: S10 | AB41: FMG-S10 | AC41: 211998 | AD41: 0096 | AE41: 850 | AF41: Default | AG41: General | AH41: US | AI41: en_US | AJ41: USD | AL41: Y | AO41: CherieHassey | AP41: Wallace | AQ41: 211998 | AR41: TRUE
A42: V0U | B42: Cherie | D42: Hassey | I42: chassey@onebarnes.com | J42: c.hassey@att.net | K42: Rep, Customer Service II | L42: 46125 | M42: 46176 | O42: Terminated | P42: 213144 | Q42: Biweekly | R42: Full Time | S42: 025 | T42: 025-NGP Hyson Products | U42: Inside Sales | V42: 000850 | W42: Hyson Products | Z42: USA | AA42: S10 | AB42: FMG-S10 | AD42: 0096 | AE42: 850 | AF42: Default | AG42: General | AH42: US | AI42: en_US | AJ42: USD | AL42: N | AM42: 20260603 | AN42: Fix and Include Record | AO42: CherieHassey | AP42: #VALUE! | AQ42: No Reports to Name | AR42: FALSE
A43: V0U | B43: Chris | C43: F | D43: Martin | G43: Leftrict, Wayne | H43: V0U210910 | I43: cmartin@onebarnes.com | J43: 3martmojo@gmail.com | K43: Coord, Quality & Environ | L43: 44270 | O43: Active | P43: 202609 | Q43: Monthly | R43: Full Time | S43: 025 | T43: 025-NGP Hyson Products | U43: Quality | V43: 000500 | W43: Hyson Products | Z43: USA | AA43: S15 | AB43: FMG-S15 | AC43: 210910 | AD43: 0096 | AE43: 500 | AF43: Default | AG43: General | AH43: US | AI43: en_US | AJ43: USD | AL43: Y | AO43: ChrisFMartin | AP43: Leftrict | AQ43: 210910 | AR43: TRUE
A44: KSX | B44: Christopher | C44: D | D44: Sanderson | G44: Rogers, Wayne | H44: KSY207487 | J44: sandecd@gmail.com | K44: Assistant, Warehouse II | L44: 46104 | O44: Active | P44: 213091 | Q44: Biweekly | R44: Full Time | S44: 088 | T44: 088-AS Raymond | U44: FG Warehouse | V44: 005200 | W44: AS Raymond | Z44: USA | AA44: S05 | AB44: FMG-S05 | AC44: 207487 | AD44: 0088 | AE44: 5200 | AF44: Default | AG44: General | AH44: US | AI44: en_US | AJ44: USD | AL44: Y | AO44: ChristopherDSanderson | AP44: Rogers | AQ44: 207487 | AR44: TRUE
A45: KSY | B45: Christopher | C45: G | D45: Jablonsky | I45: cjablonsky@onebarnes.com | K45: Mgr, Sales | L45: 45915 | M45: 46122 | O45: Terminated | P45: 212479 | Q45: Monthly | R45: Full Time | S45: 088 | T45: 088-AS Raymond | U45: Outside Sales | V45: 008200 | W45: Work from home - Ohio - New | Z45: USA | AA45: S16 | AB45: FMG-S16 | AD45: 0088 | AE45: 8200 | AF45: Default | AG45: General | AH45: US | AI45: en_US | AJ45: USD | AL45: N | AM45: 20260410 | AN45: Fix and Include Record | AO45: ChristopherGJablonsky | AP45: #VALUE! | AQ45: No Reports to Name | AR45: FALSE
A46: KSW | B46: Christopher | C46: J | D46: Kostohryz | G46: Steen, Michael | H46: V0U211062 | J46: cjkgoat@cox.net | K46: Machinist B | L46: 32405 | O46: Active | P46: 006805 | Q46: Biweekly | R46: Full Time | S46: 025 | T46: 025-NGP Hyson Products | U46: CNC Lathe Hyson | V46: 000100 | W46: Hyson Products | Z46: USA | AA46: H07 | AB46: FMG-H07 | AC46: 211062 | AD46: 0096 | AE46: 100 | AF46: Default | AG46: General | AH46: US | AI46: en_US | AJ46: USD | AL46: Y | AO46: ChristopherJKostohryz | AP46: Steen | AQ46: 211062 | AR46: TRUE
A47: KSX | B47: Conner | C47: J | D47: Frankforther | G47: Burchell, Mathew | H47: KSY211756 | I47: cfrankforther@onebarnes.com | J47: frankfortherconner@gmail.com | K47: Assistant, Warehouse II | L47: 45838 | O47: Active | P47: 212151 | Q47: Biweekly | R47: Full Time | S47: 088 | T47: 088-AS Raymond | U47: Assembly | V47: 005100 | W47: AS Raymond | Z47: USA | AA47: S05 | AB47: FMG-S05 | AC47: 211756 | AD47: 0088 | AE47: 5100 | AF47: Default | AG47: General | AH47: US | AI47: en_US | AJ47: USD | AL47: Y | AO47: ConnerJFrankforther | AP47: Burchell | AQ47: 211756 | AR47: TRUE
A48: KSX | B48: Craig | D48: Mata | G48: LaPlante, Derek | H48: KSY211736 | I48: cmata@onebarnes.com | J48: CRAIGMATA51@YAHOO.COM | K48: Assistant, Warehouse II | L48: 43388 | O48: Active | P48: 201343 | Q48: Biweekly | R48: Full Time | S48: 088 | T48: 088-AS Raymond | U48: FG Warehouse | V48: 005200 | W48: AS Raymond | Z48: USA | AA48: S05 | AB48: FMG-S05 | AC48: 211736 | AD48: 0088 | AE48: 5200 | AF48: Default | AG48: General | AH48: US | AI48: en_US | AJ48: USD | AL48: Y | AO48: CraigMata | AP48: LaPlante | AQ48: 211736 | AR48: TRUE
A49: KSX | B49: Craig | D49: Wagner | G49: Burchell, Mathew | H49: KSY211756 | I49: cwagner@onebarnes.com | J49: mich_n_trum84@yahoo.com | K49: Assistant, Warehouse | L49: 44348 | O49: Active | P49: 206272 | Q49: Biweekly | R49: Full Time | S49: 088 | T49: 088-AS Raymond | U49: Assembly | V49: 005100 | W49: AS Raymond | Z49: USA | AA49: S08 | AB49: FMG-S08 | AC49: 211756 | AD49: 0088 | AE49: 5100 | AF49: Default | AG49: General | AH49: US | AI49: en_US | AJ49: USD | AL49: Y | AO49: CraigWagner | AP49: Burchell | AQ49: 211756 | AR49: TRUE
A50: KSX | B50: Cristel | D50: Grandowicz | G50: Burchell, Mathew | H50: KSY211756 | I50: cgrandowicz@onebarnes.com | J50: grandowicz.cristel@gmail.com | K50: Assistant, Warehouse II | L50: 45789 | O50: Active | P50: 211991 | Q50: Biweekly | R50: Full Time | S50: 088 | T50: 088-AS Raymond | U50: Assembly | V50: 005100 | W50: AS Raymond | Z50: USA | AA50: S05 | AB50: FMG-S05 | AC50: 211756 | AD50: 0088 | AE50: 5100 | AF50: Default | AG50: General | AH50: US | AI50: en_US | AJ50: USD | AL50: Y | AO50: CristelGrandowicz | AP50: Burchell | AQ50: 211756 | AR50: TRUE
A51: KSX | B51: Crystal | D51: Dedes | G51: LaPlante, Derek | H51: KSY211736 | I51: cdedes@onebarnes.com | J51: criss4200@yahoo.com | K51: Assistant, Warehouse II | L51: 44620 | O51: Active | P51: 207391 | Q51: Biweekly | R51: Full Time | S51: 088 | T51: 088-AS Raymond | U51: FG Warehouse | V51: 005200 | W51: AS Raymond | Z51: USA | AA51: S05 | AB51: FMG-S05 | AC51: 211736 | AD51: 0088 | AE51: 5200 | AF51: Default | AG51: General | AH51: US | AI51: en_US | AJ51: USD | AL51: Y | AO51: CrystalDedes | AP51: LaPlante | AQ51: 211736 | AR51: TRUE
A52: KSY | B52: Daniel | C52: P | D52: Tuller | H52: V0U008750 | I52: dtuller@onebarnes.com | J52: dptuller@gmail.com | K52: Controller, Division II | L52: 45208 | M52: 46227 | O52: Terminated | P52: 210339 | Q52: Monthly | R52: Full Time | S52: 088 | T52: 088-AS Raymond | U52: Finance General | V52: 009100 | W52: AS Raymond | Z52: USA | AA52: S17 | AB52: FMG-S17 | AC52: 008750 | AD52: 0088 | AE52: 9100 | AF52: Default | AG52: General | AH52: US | AI52: en_US | AJ52: USD | AL52: N | AM52: 20260724 | AN52: Fix and Include Record | AO52: DanielPTuller | AP52: #VALUE! | AQ52: No Reports to Name | AR52: FALSE
A53: KSW | B53: Daniel | D53: White | G53: Wallace, Derron | H53: V0U211998 | I53: dwhite@onebarnes.com | J53: tntwhite33@aol.com | K53: Rep, Customer Service II | L53: 45769 | O53: Active | P53: 211939 | Q53: Biweekly | R53: Full Time | S53: 025 | T53: 025-NGP Hyson Products | U53: Inside Sales | V53: 000850 | W53: Hyson Products | Z53: USA | AA53: S10 | AB53: FMG-S10 | AC53: 211998 | AD53: 0096 | AE53: 850 | AF53: Default | AG53: General | AH53: US | AI53: en_US | AJ53: USD | AL53: Y | AO53: DanielWhite | AP53: Wallace | AQ53: 211998 | AR53: TRUE
A54: V0U | B54: Daniel | D54: White | I54: dwhite@onebarnes.com | J54: tntwhite33@aol.com | K54: Rep, Customer Service II | L54: 45769 | M54: 46175 | O54: Terminated | P54: 211939 | Q54: Biweekly | R54: Full Time | S54: 025 | T54: 025-NGP Hyson Products | U54: Inside Sales | V54: 000850 | W54: Hyson Products | Z54: USA | AA54: S10 | AB54: FMG-S10 | AD54: 0096 | AE54: 850 | AF54: Default | AG54: General | AH54: US | AI54: en_US | AJ54: USD | AL54: N | AM54: 20260602 | AN54: Fix and Include Record | AO54: DanielWhite | AP54: #VALUE! | AQ54: No Reports to Name | AR54: FALSE
A55: V0U | B55: Daniel | D55: White | I55: dwhite@onebarnes.com | J55: tntwhite33@aol.com | K55: Rep, Customer Service II | L55: 45769 | M55: 46175 | O55: Terminated | P55: 211939 | Q55: Monthly | R55: Full Time | S55: 025 | T55: 025-NGP Hyson Products | U55: Inside Sales | V55: 000850 | W55: Hyson Products | Z55: USA | AA55: S10 | AB55: FMG-S10 | AD55: 0096 | AE55: 850 | AF55: Default | AG55: General | AH55: US | AI55: en_US | AJ55: USD | AL55: N | AM55: 20260602 | AN55: Exclude record termination over 45 days ago | AO55: DanielWhite | AP55: #VALUE! | AQ55: No Reports to Name | AR55: FALSE
A56: KSW | B56: Darin | D56: Hitti | G56: Gang, Terry | H56: V0U006780 | I56: DHitti@onebarnes.com | K56: Mechanic, Maintenance A | L56: 31049 | O56: Active | P56: 006792 | Q56: Biweekly | R56: Full Time | S56: 025 | T56: 025-NGP Hyson Products | U56: Maintenance-Hyson | V56: 000450 | W56: Hyson Products | Z56: USA | AA56: H08 | AB56: FMG-H08 | AC56: 006780 | AD56: 0096 | AE56: 450 | AF56: Default | AG56: General | AH56: US | AI56: en_US | AJ56: USD | AL56: Y | AO56: DarinHitti | AP56: Gang | AQ56: 006780 | AR56: TRUE
A57: KSW | B57: David | C57: A | D57: Dixon | G57: Steen, Michael | H57: V0U211062 | J57: chevelle2212@aol.com | K57: Machinist A | L57: 35604 | O57: Active | P57: 004330 | Q57: Biweekly | R57: Full Time | S57: 025 | T57: 025-NGP Hyson Products | U57: CNC Lathe Hyson | V57: 000100 | W57: Hyson Products | Z57: USA | AA57: H08 | AB57: FMG-H08 | AC57: 211062 | AD57: 0096 | AE57: 100 | AF57: Default | AG57: General | AH57: US | AI57: en_US | AJ57: USD | AL57: Y | AO57: DavidADixon | AP57: Steen | AQ57: 211062 | AR57: TRUE
A58: KSX | B58: David | C58: J | D58: Page | G58: Bate, Natalie | H58: V0U213037 | I58: dpage@onebarnes.com | J58: davidjpage@sbcglobal.net | K58: Mgr, Project II | L58: 45964 | O58: Active | P58: 212725 | Q58: Biweekly | R58: Part Time | S58: 088 | T58: 088-AS Raymond | U58: Admin-Engineering | V58: 009450 | W58: AS Raymond | Z58: USA | AA58: S16 | AB58: FMG-S16 | AC58: 213037 | AD58: 0088 | AE58: 9450 | AF58: Default | AG58: General | AH58: US | AI58: en_US | AJ58: USD | AL58: Y | AO58: DavidJPage | AP58: Bate | AQ58: 213037 | AR58: TRUE
A59: V0U | B59: David | D59: Valetta | G59: Bair, Teresa | H59: KSY207709 | I59: dvaletta@onebarnes.com | J59: dval8200@yahoo.com | K59: Dir, Pricing | L59: 45642 | O59: Active | P59: 211601 | Q59: Monthly | R59: Full Time | S59: 025 | T59: 025-NGP Hyson Products | U59: Outside Sales | V59: 000820 | W59: Works from home - Ohio | Z59: USA | AA59: S19 | AB59: FMG-S19 | AC59: 207709 | AD59: 0096 | AE59: 820 | AF59: Default | AG59: General | AH59: US | AI59: en_US | AJ59: USD | AL59: Y | AO59: DavidValetta | AP59: Bair | AQ59: 207709 | AR59: TRUE
A60: KSY | B60: David | D60: Wilson | G60: Alexander, Thomas | H60: KSY210892 | I60: dwilson@onebarnes.com | K60: Tech, Quality III | L60: 44767 | O60: Active | P60: 207809 | Q60: Monthly | R60: Full Time | S60: 088 | T60: 088-AS Raymond | U60: Admin-Quality | V60: 009500 | W60: AS Raymond | Z60: USA | AA60: S12 | AB60: FMG-S12 | AC60: 210892 | AD60: 0088 | AE60: 9500 | AF60: Default | AG60: General | AH60: US | AI60: en_US | AJ60: USD | AL60: Y | AO60: DavidWilson | AP60: Alexander | AQ60: 210892 | AR60: TRUE
A61: KSX | B61: DayShawn | D61: Rome | H61: KSY207487 | J61: dayshawnrome16@yahoo.com | K61: Assistant, Warehouse II | L61: 46190 | M61: 46205 | O61: Terminated | Q61: Biweekly | R61: Temporary | S61: 088 | T61: 088-AS Raymond | U61: FG Warehouse | V61: 005200 | W61: AS Raymond | Z61: USA | AA61: S05 | AB61: FMG-S05 | AC61: 207487 | AD61: 0088 | AE61: 5200 | AF61: Default | AG61: General | AH61: US | AI61: en_US | AJ61: USD | AL61: N | AM61: 20260702 | AN61: Exclude record termination over 45 days ago | AO61: DayShawnRome | AP61: #VALUE! | AQ61: No Reports to Name | AR61: FALSE
A62: V0U | B62: Demetrius | C62: A | D62: Daniels | I62: ddaniels@kaller.com | J62: mrtruth75@gmail.com | K62: Rep, Customer Service II | L62: 37424 | M62: 46175 | O62: Terminated | P62: 006774 | Q62: Biweekly | R62: Full Time | S62: 025 | T62: 025-NGP Hyson Products | U62: Inside Sales | V62: 000850 | W62: Hyson Products | Z62: USA | AA62: S10 | AB62: FMG-S10 | AD62: 0096 | AE62: 850 | AF62: Default | AG62: General | AH62: US | AI62: en_US | AJ62: USD | AL62: N | AM62: 20260602 | AN62: Exclude record termination over 45 days ago | AO62: DemetriusADaniels | AP62: #VALUE! | AQ62: No Reports to Name | AR62: FALSE
A63: V0U | B63: Demetrius | C63: A | D63: Daniels | I63: ddaniels@kaller.com | J63: mrtruth75@gmail.com | K63: Rep, Customer Service II | L63: 37424 | M63: 46175 | O63: Terminated | P63: 006774 | Q63: Monthly | R63: Full Time | S63: 025 | T63: 025-NGP Hyson Products | U63: Inside Sales | V63: 000850 | W63: Hyson Products | Z63: USA | AA63: S10 | AB63: FMG-S10 | AD63: 0096 | AE63: 850 | AF63: Default | AG63: General | AH63: US | AI63: en_US | AJ63: USD | AL63: N | AM63: 20260602 | AN63: Fix and Include Record | AO63: DemetriusADaniels | AP63: #VALUE! | AQ63: No Reports to Name | AR63: FALSE
A64: KSW | B64: Demetrius | C64: A | D64: Daniels | G64: Wallace, Derron | H64: V0U211998 | I64: ddaniels@kaller.com | J64: mrtruth75@gmail.com | K64: Rep, Customer Service II | L64: 37424 | O64: Active | P64: 006774 | Q64: Biweekly | R64: Full Time | S64: 025 | T64: 025-NGP Hyson Products | U64: Inside Sales | V64: 000850 | W64: Hyson Products | Z64: USA | AA64: S10 | AB64: FMG-S10 | AC64: 211998 | AD64: 0096 | AE64: 850 | AF64: Default | AG64: General | AH64: US | AI64: en_US | AJ64: USD | AL64: Y | AO64: DemetriusADaniels | AP64: Wallace | AQ64: 211998 | AR64: TRUE
A65: KSY | B65: Derek | D65: LaPlante | G65: Bailey, Jason | H65: KSY211464 | I65: dlaplante@onebarnes.com | K65: Supv, Warehouse I | L65: 45705 | O65: Active | P65: 211736 | Q65: Monthly | R65: Full Time | S65: 088 | T65: 088-AS Raymond | U65: FG Warehouse | V65: 005200 | W65: AS Raymond | Z65: USA | AA65: S11 | AB65: FMG-S11 | AC65: 211464 | AD65: 0088 | AE65: 5200 | AF65: Default | AG65: General | AH65: US | AI65: en_US | AJ65: USD | AL65: Y | AO65: DerekLaPlante | AP65: Bailey | AQ65: 902688 | AR65: FALSE
A66: V0U | B66: Derron | D66: Wallace | G66: Bate, Natalie | H66: V0U213037 | I66: dwallace@onebarnes.com | J66: derronw@gmail.com | K66: Mgr, Cust Srvc, Assembly | L66: 45789 | O66: Active | P66: 211998 | Q66: Monthly | R66: Full Time | S66: 025 | T66: 025-NGP Hyson Products | U66: Inside Sales | V66: 000850 | W66: Hyson Products | Z66: USA | AA66: S15 | AB66: FMG-S15 | AC66: 213037 | AD66: 0096 | AE66: 850 | AF66: Default | AG66: General | AH66: US | AI66: en_US | AJ66: USD | AL66: Y | AO66: DerronWallace | AP66: Bate | AQ66: 213037 | AR66: TRUE
A67: KSX | B67: Dillon | C67: M | D67: Frankforther | G67: LaPlante, Derek | H67: KSY211736 | I67: dfrankforther@onebarnes.com | J67: frankfortherdillon@gmail.com | K67: Assistant, Warehouse II | L67: 45719 | O67: Active | P67: 211779 | Q67: Biweekly | R67: Full Time | S67: 088 | T67: 088-AS Raymond | U67: FG Warehouse | V67: 005200 | W67: AS Raymond | Z67: USA | AA67: S05 | AB67: FMG-S05 | AC67: 211736 | AD67: 0088 | AE67: 5200 | AF67: Default | AG67: General | AH67: US | AI67: en_US | AJ67: USD | AL67: Y | AO67: DillonMFrankforther | AP67: LaPlante | AQ67: 211736 | AR67: TRUE
A68: V0U | B68: Donald | C68: C | D68: Felts | G68: Wilkins, William | H68: V0U901934 | I68: cfelts@onebarnes.com | J68: dcfelts@comcast.net | K68: Mgr, Sales | L68: 43885 | O68: Active | P68: 201958 | Q68: Monthly | R68: Full Time | S68: 025 | T68: 025-NGP Hyson Products | U68: Outside Sales | V68: 000820 | W68: Hyson Products | Z68: USA | AA68: S15 | AB68: FMG-S15 | AC68: 901934 | AD68: 0096 | AE68: 820 | AF68: Default | AG68: General | AH68: US | AI68: en_US | AJ68: USD | AL68: Y | AO68: DonaldCFelts | AP68: Wilkins | AQ68: 901934 | AR68: TRUE
A69: KSW | B69: Duane | C69: A | D69: Turner | G69: Steen, Michael | H69: V0U211062 | J69: ugkone10@yahoo.com | K69: Machinist B | L69: 44312 | O69: Active | P69: 206110 | Q69: Biweekly | R69: Full Time | S69: 025 | T69: 025-NGP Hyson Products | U69: CNC Lathe Hyson | V69: 000100 | W69: Hyson Products | Z69: USA | AA69: H07 | AB69: FMG-H07 | AC69: 211062 | AD69: 0096 | AE69: 100 | AF69: Default | AG69: General | AH69: US | AI69: en_US | AJ69: USD | AL69: Y | AO69: DuaneATurner | AP69: Steen | AQ69: 211062 | AR69: TRUE
A70: V0U | B70: Dwight | C70: A | D70: Warner | G70: Bair, Teresa | H70: KSY207709 | I70: DWarner@onebarnes.com | K70: Dir, Finance I | L70: 38691 | O70: Active | P70: 008750 | Q70: Monthly | R70: Full Time | S70: 025 | T70: 025-NGP Hyson Products | U70: Finance | V70: 000910 | W70: Hyson Products | Z70: USA | AA70: S18 | AB70: FMG-S18 | AC70: 207709 | AD70: 0096 | AE70: 910 | AF70: Default | AG70: General | AH70: US | AI70: en_US | AJ70: USD | AL70: Y | AO70: DwightAWarner | AP70: Bair | AQ70: 207709 | AR70: TRUE
A71: KSX | B71: Ella Renae | C71: E | D71: Beatrice | G71: LaPlante, Derek | H71: KSY211736 | I71: ebeatrice@onebarnes.com | J71: thatellachick@gmail.com | K71: Assistant, Warehouse II | L71: 45929 | O71: Active | P71: 212626 | Q71: Biweekly | R71: Full Time | S71: 088 | T71: 088-AS Raymond | U71: FG Warehouse | V71: 005200 | W71: AS Raymond | Z71: USA | AA71: S05 | AB71: FMG-S05 | AC71: 211736 | AD71: 0088 | AE71: 5200 | AF71: Default | AG71: General | AH71: US | AI71: en_US | AJ71: USD | AL71: Y | AO71: Ella RenaeEBeatrice | AP71: LaPlante | AQ71: 211736 | AR71: TRUE
A72: KSY | B72: Emma | D72: Halpin | G72: Kemenah, Greg | H72: KSY211766 | I72: ehalpin@onebarnes.com | J72: sampson.emma17@gmail.com | K72: Mgr, Product III | L72: 45566 | O72: Active | P72: 211489 | Q72: Monthly | R72: Full Time | S72: 088 | T72: 088-AS Raymond | U72: Marketing | V72: 008300 | W72: AS Raymond | Z72: USA | AA72: S16 | AB72: FMG-S16 | AC72: 211766 | AD72: 0088 | AE72: 8300 | AF72: Default | AG72: General | AH72: US | AI72: en_US | AJ72: USD | AL72: Y | AO72: EmmaHalpin | AP72: Kemenah | AQ72: 211766 | AR72: TRUE
A73: KSX | B73: Evelyn | D73: Gonzalez | I73: EGonzalez@onebarnes.com | K73: Assistant, Warehouse II | L73: 44942 | M73: 46148 | O73: Terminated | P73: 209540 | Q73: Biweekly | R73: Full Time | S73: 088 | T73: 088-AS Raymond | U73: Supply Chain | V73: 000004 | W73: AS Raymond | Z73: USA | AA73: S05 | AB73: FMG-S05 | AD73: 0088 | AE73: Home Department Code Not Mapped | AF73: Default | AG73: General | AH73: US | AI73: en_US | AJ73: USD | AL73: N | AM73: 20260506 | AN73: Fix and Include Record | AO73: EvelynGonzalez | AP73: #VALUE! | AQ73: No Reports to Name | AR73: FALSE
A74: KSW | B74: Frank | D74: Izzo | G74: Valetta, David | H74: V0U211601 | I74: FIzzo@onebarnes.com | K74: Mgr, Finance II | L74: 44410 | O74: Active | P74: 206442 | Q74: Biweekly | R74: Part Time Long Term EE | S74: 025 | T74: 025-NGP Hyson Products | U74: Project Management | V74: 000801 | W74: Hyson Products | Z74: USA | AA74: S16 | AB74: FMG-S16 | AC74: 211601 | AD74: 0096 | AE74: 801 | AF74: Default | AG74: General | AH74: US | AI74: en_US | AJ74: USD | AL74: Y | AO74: FrankIzzo | AP74: Valetta | AQ74: 211601 | AR74: TRUE
A75: V0U | B75: Frank | D75: Izzo | H75: V0U211601 | I75: FIzzo@onebarnes.com | K75: Mgr, Finance II | L75: 44410 | M75: 46204 | O75: Terminated | P75: 206442 | Q75: Monthly | R75: Full Time | S75: 025 | T75: 025-NGP Hyson Products | U75: Project Management | V75: 000801 | W75: Hyson Products | Z75: USA | AA75: S16 | AB75: FMG-S16 | AC75: 211601 | AD75: 0096 | AE75: 801 | AF75: Default | AG75: General | AH75: US | AI75: en_US | AJ75: USD | AL75: N | AM75: 20260701 | AN75: Exclude record termination over 45 days ago | AO75: FrankIzzo | AP75: #VALUE! | AQ75: No Reports to Name | AR75: FALSE
A76: KSY | B76: Greg | D76: Kemenah | G76: Bair, Teresa | H76: KSY207709 | I76: gkemenah@onebarnes.com | J76: kemenah@live.com | K76: Mgr, General I | L76: 45712 | O76: Active | P76: 211766 | Q76: Monthly | R76: Full Time | S76: 088 | T76: 088-AS Raymond | U76: Admin-Engineering | V76: 009450 | W76: AS Raymond | Z76: USA | AA76: S19 | AB76: FMG-S19 | AC76: 207709 | AD76: 0088 | AE76: 9450 | AF76: Default | AG76: General | AH76: US | AI76: en_US | AJ76: USD | AL76: Y | AO76: GregKemenah | AP76: Bair | AQ76: 207709 | AR76: TRUE
A77: KSY | B77: Gregory | C77: S | D77: Adams | G77: Rodriguez, Siobhan | H77: V0U207588 | I77: gadams@onebarnes.com | J77: gdsad.adams@cox.net | K77: Mgr, Sales | L77: 46188 | O77: Active | P77: 213331 | Q77: Monthly | R77: Full Time | S77: 088 | T77: 088-AS Raymond | U77: Outside Sales | V77: 008200 | W77: Work from home - Connecticut | Z77: USA | AA77: S16 | AB77: FMG-S16 | AC77: 207588 | AD77: 0088 | AE77: 8200 | AF77: Default | AG77: General | AH77: US | AI77: en_US | AJ77: USD | AL77: Y | AO77: GregorySAdams | AP77: Rodriguez | AQ77: 212338 | AR77: FALSE
A78: KSY | B78: Gwendolyn | C78: L | D78: Rome | G78: Warner, Dwight | H78: V0U008750 | I78: grome@onebarnes.com | J78: gwenlr2013@gmail.com | K78: Analyst, Shared Services | L78: 36535 | N78: 46119 | O78: Active | P78: 007647 | Q78: Monthly | R78: Full Time | S78: 088 | T78: 088-AS Raymond | U78: Finance General | V78: 009100 | W78: AS Raymond | Z78: USA | AA78: S11 | AB78: FMG-S11 | AC78: 008750 | AD78: 0088 | AE78: 9100 | AF78: Default | AG78: General | AH78: US | AI78: en_US | AJ78: USD | AL78: Y | AO78: GwendolynLRome | AP78: Warner | AQ78: 008750 | AR78: TRUE
A79: KSX | B79: Heather | C79: A | D79: Schmidt | G79: LaPlante, Derek | H79: KSY211736 | I79: hschmidt2@onebarnes.com | K79: Assistant, Warehouse | L79: 45138 | O79: Active | P79: 210127 | Q79: Biweekly | R79: Full Time | S79: 088 | T79: 088-AS Raymond | U79: FG Warehouse | V79: 005200 | W79: AS Raymond | Z79: USA | AA79: S08 | AB79: FMG-S08 | AC79: 211736 | AD79: 0088 | AE79: 5200 | AF79: Default | AG79: General | AH79: US | AI79: en_US | AJ79: USD | AL79: Y | AO79: HeatherASchmidt | AP79: LaPlante | AQ79: 211736 | AR79: TRUE
A80: KSW | B80: Isaak | C80: R | D80: Taiclet | G80: Leftrict, Wayne | H80: V0U210910 | I80: itaiclet@onebarnes.com | K80: Intern, Engineering Indir | L80: 46153 | M80: 46255 | O80: Terminated | P80: 213227 | Q80: Biweekly | R80: Intern | S80: 025 | T80: 025-NGP Hyson Products | U80: Quality | V80: 000500 | W80: Hyson Products | Z80: USA | AA80: H05 | AB80: FMG-H05 | AC80: 210910 | AD80: 0096 | AE80: 500 | AF80: Default | AG80: General | AH80: US | AI80: en_US | AJ80: USD | AL80: N | AM80: 20260821 | AN80: Exclude record termination over 45 days ago | AO80: IsaakRTaiclet | AP80: Leftrict | AQ80: 210910 | AR80: TRUE
A81: V0U | B81: Isaak | C81: R | D81: Taiclet | I81: itaiclet@onebarnes.com | K81: Intern, Engineering Indir | L81: 46153 | M81: 46176 | O81: Terminated | P81: 213227 | Q81: Biweekly | R81: Intern | S81: 025 | T81: 025-NGP Hyson Products | U81: Quality | V81: 000500 | W81: Hyson Products | Z81: USA | AA81: H05 | AB81: FMG-H05 | AD81: 0096 | AE81: 500 | AF81: Default | AG81: General | AH81: US | AI81: en_US | AJ81: USD | AL81: N | AM81: 20260603 | AN81: Fix and Include Record | AO81: IsaakRTaiclet | AP81: #VALUE! | AQ81: No Reports to Name | AR81: FALSE
A82: V0U | B82: Isaak | C82: R | D82: Taiclet | I82: itaiclet@onebarnes.com | K82: Intern, Engineering Indir | L82: 46153 | M82: 46176 | O82: Terminated | P82: 213227 | Q82: Monthly | R82: Intern | S82: 025 | T82: 025-NGP Hyson Products | U82: Quality | V82: 000500 | W82: Hyson Products | Z82: USA | AA82: H05 | AB82: FMG-H05 | AD82: 0096 | AE82: 500 | AF82: Default | AG82: General | AH82: US | AI82: en_US | AJ82: USD | AL82: N | AM82: 20260603 | AN82: Fix and Include Record | AO82: IsaakRTaiclet | AP82: #VALUE! | AQ82: No Reports to Name | AR82: FALSE
A83: KSX | B83: Ivy | C83: J | D83: Grant | G83: Warner, Dwight | H83: V0U008750 | I83: igrant1@onebarnes.com | J83: igrant1453@yahoo.com | K83: Spec, Accounts Rec III | L83: 46181 | O83: Active | P83: 209642 | Q83: Biweekly | R83: Full Time | S83: 088 | T83: 088-AS Raymond | U83: Finance General | V83: 009100 | W83: Work from home - Virginia | Z83: USA | AA83: S10 | AB83: FMG-S10 | AC83: 008750 | AD83: 0088 | AE83: 9100 | AF83: Default | AG83: General | AH83: US | AI83: en_US | AJ83: USD | AL83: Y | AO83: IvyJGrant | AP83: Warner | AQ83: 008750 | AR83: TRUE
A84: KSX | B84: Jack | C84: O | D84: Bradford | G84: Halpin, Emma | H84: KSY211489 | J84: jb7222222@gmail.com | K84: Intern, Project Mgr Indir | L84: 46153 | M84: 46241 | O84: Terminated | P84: 213234 | Q84: Biweekly | R84: Intern | S84: 088 | T84: 088-AS Raymond | U84: Marketing | V84: 008300 | W84: AS Raymond | Z84: USA | AA84: H05 | AB84: FMG-H05 | AC84: 211489 | AD84: 0088 | AE84: 8300 | AF84: Default | AG84: General | AH84: US | AI84: en_US | AJ84: USD | AL84: N | AM84: 20260807 | AN84: Fix and Include Record | AO84: JackOBradford | AP84: Halpin | AQ84: 211489 | AR84: TRUE
A85: KSX | B85: Jacob | C85: A | D85: Kemenah | G85: Warner, Dwight | H85: V0U008750 | J85: jkemenah@outlook.com | K85: Intern, Finance Indirect | L85: 46153 | M85: 46248 | O85: Terminated | P85: 213229 | Q85: Biweekly | R85: Intern | S85: 088 | T85: 088-AS Raymond | U85: Finance General | V85: 009100 | W85: AS Raymond | Z85: USA | AA85: H05 | AB85: FMG-H05 | AC85: 008750 | AD85: 0088 | AE85: 9100 | AF85: Default | AG85: General | AH85: US | AI85: en_US | AJ85: USD | AL85: N | AM85: 20260814 | AN85: Fix and Include Record | AO85: JacobAKemenah | AP85: Warner | AQ85: 008750 | AR85: TRUE
A86: KSX | B86: Jacqueline | C86: M | D86: Reed | G86: LaPlante, Derek | H86: KSY211736 | I86: jfoggyrobinson@onebarnes.com | J86: shower781@yahoo.com | K86: Assistant, Warehouse II | L86: 45117 | O86: Active | P86: 210035 | Q86: Biweekly | R86: Full Time | S86: 088 | T86: 088-AS Raymond | U86: FG Warehouse | V86: 005200 | W86: AS Raymond | Z86: USA | AA86: S05 | AB86: FMG-S05 | AC86: 211736 | AD86: 0088 | AE86: 5200 | AF86: Default | AG86: General | AH86: US | AI86: en_US | AJ86: USD | AL86: Y | AO86: JacquelineMReed | AP86: LaPlante | AQ86: 211736 | AR86: TRUE
A87: KSW | B87: James | D87: Biss | G87: Steen, Michael | H87: V0U211062 | J87: jlbjr7784@gmail.com | K87: Assembler B | L87: 45232 | O87: Active | P87: 210375 | Q87: Biweekly | R87: Full Time | S87: 025 | T87: 025-NGP Hyson Products | U87: Assembly Hyson | V87: 000200 | W87: Hyson Products | Z87: USA | AA87: H05 | AB87: FMG-H05 | AC87: 211062 | AD87: 0096 | AE87: 200 | AF87: Default | AG87: General | AH87: US | AI87: en_US | AJ87: USD | AL87: Y | AO87: JamesBiss | AP87: Steen | AQ87: 211062 | AR87: TRUE
A88: V0U | B88: James | D88: Brower | G88: Bate, Natalie | H88: V0U213037 | I88: JBrower@onebarnes.com | J88: browerj@cox.net | K88: Engineer, Application III | L88: 34736 | O88: Active | P88: 006769 | Q88: Monthly | R88: Full Time | S88: 025 | T88: 025-NGP Hyson Products | U88: Engineering | V88: 000718 | W88: Hyson Products | Z88: USA | AA88: S15 | AB88: FMG-S15 | AC88: 213037 | AD88: 0096 | AE88: 718 | AF88: Default | AG88: General | AH88: US | AI88: en_US | AJ88: USD | AL88: Y | AO88: JamesBrower | AP88: Bate | AQ88: 213037 | AR88: TRUE
A89: KSW | B89: James | D89: McConnell | G89: Steen, Michael | H89: V0U211062 | J89: nonyiot2.0@yahoo.com | K89: Machinist B | L89: 31130 | O89: Active | P89: 006811 | Q89: Biweekly | R89: Full Time | S89: 025 | T89: 025-NGP Hyson Products | U89: Edgework- Hyson | V89: 000350 | W89: Hyson Products | Z89: USA | AA89: H07 | AB89: FMG-H07 | AC89: 211062 | AD89: 0096 | AE89: 350 | AF89: Default | AG89: General | AH89: US | AI89: en_US | AJ89: USD | AL89: Y | AO89: JamesMcConnell | AP89: Steen | AQ89: 211062 | AR89: TRUE
A90: KSY | B90: James | D90: Stefancin | G90: Valetta, David | H90: V0U211601 | I90: jstefancin@onebarnes.com | J90: jimstefancin@gmail.com | K90: Mgr, Supply Chain III | L90: 45840 | M90: 46235 | O90: Terminated | P90: 212191 | Q90: Monthly | R90: Full Time | S90: 088 | T90: 088-AS Raymond | U90: Admin-Material Management | V90: 009400 | W90: Work from home - Ohio - New | Z90: USA | AA90: S17 | AB90: FMG-S17 | AC90: 211601 | AD90: 0088 | AE90: 9400 | AF90: Default | AG90: General | AH90: US | AI90: en_US | AJ90: USD | AL90: N | AM90: 20260801 | AN90: Exclude record termination over 45 days ago | AO90: JamesStefancin | AP90: Valetta | AQ90: 211601 | AR90: TRUE
A91: V0U | B91: James | D91: Stefancin | G91: Bate, Natalie | H91: V0U213037 | I91: jstefancin@onebarnes.com | J91: jimstefancin@gmail.com | K91: Mgr, Supply Chain III | L91: 45840 | O91: Active | P91: 212191 | Q91: Monthly | R91: Full Time | S91: 025 | T91: 025-NGP Hyson Products | U91: Administration | V91: 000917 | W91: Works from home - Ohio | Z91: USA | AA91: S17 | AB91: FMG-S17 | AC91: 213037 | AD91: 0096 | AE91: 0007 | AF91: Default | AG91: General | AH91: US | AI91: en_US | AJ91: USD | AL91: Y | AO91: JamesStefancin | AP91: Bate | AQ91: 213037 | AR91: TRUE
A92: KSY | B92: Jason | C92: J | D92: Bailey | G92: Kemenah, Greg | I92: jbailey@onebarnes.com | J92: jjbailey08@gmail.com | K92: Senior Mgr, Operations | L92: 46258 | O92: Active | P92: 902688 | Q92: Monthly | R92: Full Time | S92: 088 | T92: 088-AS Raymond | U92: Operations 5200 5200 | V92: 000007 | W92: AS Raymond | Z92: USA | AA92: S18 | AB92: FMG-S18 | AD92: 0088 | AE92: Home Department Code Not Mapped | AF92: Default | AG92: General | AH92: US | AI92: en_US | AJ92: USD | AL92: Y | AO92: JasonJBailey | AP92: Kemenah | AQ92: 211766 | AR92: FALSE
A93: KSY | B93: Jason | D93: Majewski | G93: Creager, Andrew | H93: KSY212699 | I93: JMajewski@onebarnes.com | J93: jmajewski06@yahoo.com | K93: Mgr, Materials | L93: 34869 | O93: Active | P93: 006809 | Q93: Monthly | R93: Full Time | S93: 088 | T93: 088-AS Raymond | U93: Admin-Material Management | V93: 009400 | W93: AS Raymond | Z93: USA | AA93: S17 | AB93: FMG-S17 | AC93: 212699 | AD93: 0088 | AE93: 9400 | AF93: Default | AG93: General | AH93: US | AI93: en_US | AJ93: USD | AL93: Y | AO93: JasonMajewski | AP93: Creager | AQ93: 212699 | AR93: TRUE
A94: V0U | B94: Jason | D94: Majewski | G94: Bate, Natalie | H94: V0U213037 | I94: JMajewski@onebarnes.com | J94: jmajewski06@yahoo.com | K94: Mgr, Purchasing III | L94: 34869 | M94: 46235 | O94: Terminated | P94: 006809 | Q94: Monthly | R94: Full Time | S94: 025 | T94: 025-NGP Hyson Products | U94: Warehouse | V94: 000555 | W94: Hyson Products | Z94: USA | AA94: S17 | AB94: FMG-S17 | AC94: 213037 | AD94: 0096 | AE94: 555 | AF94: Default | AG94: General | AH94: US | AI94: en_US | AJ94: USD | AL94: N | AM94: 20260801 | AN94: Exclude record termination over 45 days ago | AO94: JasonMajewski | AP94: Bate | AQ94: 213037 | AR94: TRUE
A95: KSY | B95: Jeff | D95: Raese | G95: Rodriguez, Siobhan | H95: V0U207588 | I95: jraese@onebarnes.com | J95: jraese@hotmail.com | K95: Mgr, Sales I | L95: 45113 | O95: Active | P95: 210018 | Q95: Monthly | R95: Full Time | S95: 088 | T95: 088-AS Raymond | U95: Outside Sales | V95: 008200 | W95: Works from home - Ohio | Z95: USA | AA95: S16 | AB95: FMG-S16 | AC95: 207588 | AD95: 0088 | AE95: 8200 | AF95: Default | AG95: General | AH95: US | AI95: en_US | AJ95: USD | AL95: Y | AO95: JeffRaese | AP95: Rodriguez | AQ95: 212338 | AR95: FALSE
A96: KSY | B96: Jeffrey | C96: L | D96: Finch | G96: Erdogan, Mehmet | I96: Jfinch@onebarnes.com | J96: jefffinch@bex.net | K96: Mgr, IT I | L96: 41422 | O96: Active | P96: 900848 | Q96: Monthly | R96: Full Time | S96: 088 | T96: 088-AS Raymond | U96: Business Applications | V96: 009150 | W96: AS Raymond | Z96: USA | AA96: S15 | AB96: FMG-S15 | AD96: 0088 | AE96: 9150 | AF96: Default | AG96: General | AH96: US | AI96: en_US | AJ96: USD | AL96: Y | AO96: JeffreyLFinch | AP96: Erdogan | AQ96: No Reports to Name | AR96: FALSE
A97: KSW | B97: Jermey | D97: McKinney | H97: V0U211998 | J97: jeremyy92600@gmail.com | K97: Assembler C | L97: 46190 | M97: 46234 | O97: Terminated | Q97: Biweekly | R97: Temporary | S97: 025 | T97: 025-NGP Hyson Products | U97: Assembly Hyson | V97: 000200 | W97: Hyson Products | Z97: USA | AA97: H05 | AB97: FMG-H05 | AC97: 211998 | AD97: 0096 | AE97: 200 | AF97: Default | AG97: General | AH97: US | AI97: en_US | AJ97: USD | AL97: N | AM97: 20260731 | AN97: Fix and Include Record | AO97: JermeyMcKinney | AP97: #VALUE! | AQ97: No Reports to Name | AR97: FALSE
B98: Jill | D98: Rockow | J98: JMROCKOW@YAHOO.COM | L98: 46053 | M98: 46054 | O98: Terminated | Q98: Weekly | Z98: USA | AD98: BU Description Not Mapped | AE98: Home Department Code Not Mapped | AF98: Salary Code Not Mapped | AG98: Salary Code Not Mapped | AH98: US | AI98: ADP and BU Language Code Not MappedUS | AJ98: BU Currency Not Mapped | AL98: N | AM98: 20260201 | AN98: Exclude record termination over 45 days ago | AO98: JillRockow | AP98: #VALUE! | AQ98: No Reports to Name | AR98: FALSE
A99: KSX | B99: Joann | D99: Whaley | G99: Valetta, David | H99: V0U211601 | J99: subjetta@icloud.com | K99: Admin, Sales Support II | L99: 44776 | O99: Active | P99: 207850 | Q99: Biweekly | R99: Full Time | S99: 088 | T99: 088-AS Raymond | U99: Outside Sales | V99: 008200 | W99: AS Raymond | Z99: USA | AA99: S10 | AB99: FMG-S10 | AC99: 211601 | AD99: 0088 | AE99: 8200 | AF99: Default | AG99: General | AH99: US | AI99: en_US | AJ99: USD | AL99: Y | AO99: JoannWhaley | AP99: Valetta | AQ99: 211601 | AR99: TRUE
A100: KSY | B100: Joel | C100: E | D100: McCoy | G100: Kemenah, Greg | H100: KSY211766 | I100: jmccoy@onebarnes.com | J100: joelmccoy@hotmail.com | K100: Engineer, Product III | L100: 41771 | O100: Active | P100: 901213 | Q100: Monthly | R100: Full Time | S100: 088 | T100: 088-AS Raymond | U100: Admin-Engineering | V100: 009450 | W100: AS Raymond | Z100: USA | AA100: S15 | AB100: FMG-S15 | AC100: 211766 | AD100: 0088 | AE100: 9450 | AF100: Default | AG100: General | AH100: US | AI100: en_US | AJ100: USD | AL100: Y | AO100: JoelEMcCoy | AP100: Kemenah | AQ100: 211766 | AR100: TRUE
A101: KSX | B101: John | D101: Bentz | G101: LaPlante, Derek | H101: KSY211736 | I101: jbentz@onebarnes.com | J101: xjbm13@yahoo.com | K101: Assistant, Warehouse II | L101: 45937 | O101: Active | P101: 212639 | Q101: Biweekly | R101: Full Time | S101: 088 | T101: 088-AS Raymond | U101: FG Warehouse | V101: 005200 | W101: AS Raymond | Z101: USA | AA101: S05 | AB101: FMG-S05 | AC101: 211736 | AD101: 0088 | AE101: 5200 | AF101: Default | AG101: General | AH101: US | AI101: en_US | AJ101: USD | AL101: Y | AO101: JohnBentz | AP101: LaPlante | AQ101: 211736 | AR101: TRUE
...

Sheet Sheet2
A3: Row Labels | B3: Count of Payroll Company Code
A4: AnthonyJMoavero | B4: 4
A5: IsaakRTaiclet | B5: 3
A6: MichaelMolnar | B6: 3
A7: JosephMLorenz | B7: 3
A8: DanielWhite | B8: 3
A9: TerryWagner | B9: 3
A10: DemetriusADaniels | B10: 3
A11: TimothyEClifton | B11: 3
A12: CherieHassey | B12: 2
A13: CarlaJCunningham | B13: 2
A14: BrandonHibbitts | B14: 2
A15: JamesStefancin | B15: 2
... A20: Grand Total | B20: 41

Sheet 1
A1: Employment Profile - Effective Date | B1: Effective as of 08/31/2026 | H1: Non US Temp Employee | I1: Missing work email address | R1: Do we want to filter here | T1: Map and Filter | V1: Map based on ERP length | X1: Will be filled in | Y1: Will be filled in | AC1: Fix Supervisor ID | AD1: Assign an Org correctly | AE1: Fix to valid GL Company codes | AF1: Assign Salary Code | AG1: Assign Salary Code | AR1: Where false validate the actual supervisor id is correct
A2: Employment Profile - Time & Attendance - Effective Date | B2: All records independent of date | H2: Missing Supervisor
A3: Employment Profile - Pay Rates - Effective Date | B3: All records independent of date | H3: Top of food chain
A4: Payroll Company Code | B4: Legal First Name | C4: Middle Initial | D4: Legal Last Name | E4: Preferred or Chosen First Name | F4: Preferred or Chosen Last Name | G4: Reports To Legal Name | H4: Supervisor ID | I4: Work Contact: Work Email | J4: Personal Contact: Personal Email | K4: Job Title Description | L4: Hire Date | M4: Termination Date | N4: Rehire Date | O4: Position Status | P4: File Number | Q4: Pay Frequency | R4: Employee Type | S4: Business Unit Code | T4: Business Unit Description | U4: Home Department Description | V4: Home Department Code | W4: Location Description | X4: Language Description | Y4: Language Code | Z4: Legal / Preferred Address: Country Code | AA4: Pay Grade Code | AB4: Pay Grade Description | AC4: SupervisorID Formatted | AD4: Org Unit 1 | AE4: Org Unit 2 | AF4: Concur Profile | AG4: Travel Profile | AH4: Legal Country | AI4: Local Code | AJ4: Reumbursement Currency | AK4: Perferred Name | AL4: Status | AM4: Term Date | AN4: =TODAY()-45 -> 46223 | AO4: Name | AP4: SupervisorLastName | AQ4: Lookup Supervisor ID | AR4: SupervisorName=Supervisor ID
A5: KSX | B5: Tammie | D5: Abitua | G5: Burchell, Mathew | H5: KSY211756 | I5: tabitua1@onebarnes.com | J5: abituatammie@gmail.com | K5: Assistant, Warehouse II | L5: 45733 | O5: Active | P5: 211837 | Q5: Biweekly | R5: Full Time | S5: 088 | T5: 088-AS Raymond | U5: Assembly | V5: 005100 | W5: AS Raymond | Z5: USA | AA5: S05 | AB5: FMG-S05 | AC5: =IF(ISBLANK(H5),VLOOKUP(P5,'US Supervisor Map'!A:D,4,FALSE),MID(H5,4,6)) -> 211756 | AD5: =IFERROR(VLOOKUP(T5,'Org Map'!A:E,4),"BU Description Not Mapped") -> 0088 | AE5: =IFERROR(VLOOKUP(V5,'Org Map'!C:E,3),"Home Department Code Not Mapped") -> 5100 | AF5: =IFERROR(VLOOKUP(AA5,'Salary Map'!A:D,3,FALSE),"Salary Code Not Mapped") -> Default | AG5: =IFERROR(VLOOKUP(AA5,'Salary Map'!A:D,4,FALSE),"Salary Code Not Mapped") -> General | AH5: =IFERROR(VLOOKUP(Z5,'Country Map'!A:B,2,FALSE),"Legal Country Not Mapped") -> US | AI5: =IFERROR(VLOOKUP(X5,'Language Map'!A:C,3,FALSE),IFERROR(VLOOKUP(T5,'Org Map'!A:F,6,FALSE),"ADP and BU Language Code Not Mapped"))&AH5 -> en_US | AJ5: =IFERROR(VLOOKUP(T5,'Org Map'!A:G,7),"BU Currency Not Mapped") -> USD | AK5: =IF(ISBLANK(E5),"",TRIM(E5&" "&F5)) | AL5: =IFERROR(VLOOKUP(O5,'Status Map'!A:B,2,FALSE),"Position Status Not Mapped") -> Y | AM5: =IF(AL5="N",TEXT(M5,"yyyymmdd"),"") | AO5: =B5&C5&D5 -> TammieAbitua | AP5: =LEFT(G5,FIND(",",G5)-1) -> Burchell | AQ5: =IFERROR(VLOOKUP(AP5,D:P,13,FALSE),"No Reports to Name") -> 211756 | AR5: =AQ5=MID(H5,4,6) -> TRUE
A6: KSY | B6: Gregory | C6: S | D6: Adams | G6: Rodriguez, Siobhan | H6: V0U207588 | I6: gadams@onebarnes.com | J6: gdsad.adams@cox.net | K6: Mgr, Sales | L6: 46188 | O6: Active | P6: 213331 | Q6: Monthly | R6: Full Time | S6: 088 | T6: 088-AS Raymond | U6: Outside Sales | V6: 008200 | W6: Work from home - Connecticut | Z6: USA | AA6: S16 | AB6: FMG-S16 | AC6: =IF(ISBLANK(H6),VLOOKUP(P6,'US Supervisor Map'!A:D,4,FALSE),MID(H6,4,6)) -> 207588 | AD6: =IFERROR(VLOOKUP(T6,'Org Map'!A:E,4),"BU Description Not Mapped") -> 0088 | AE6: =IFERROR(VLOOKUP(V6,'Org Map'!C:E,3),"Home Department Code Not Mapped") -> 8200 | AF6: =IFERROR(VLOOKUP(AA6,'Salary Map'!A:D,3,FALSE),"Salary Code Not Mapped") -> Default | AG6: =IFERROR(VLOOKUP(AA6,'Salary Map'!A:D,4,FALSE),"Salary Code Not Mapped") -> General | AH6: =IFERROR(VLOOKUP(Z6,'Country Map'!A:B,2,FALSE),"Legal Country Not Mapped") -> US | AI6: =IFERROR(VLOOKUP(X6,'Language Map'!A:C,3,FALSE),IFERROR(VLOOKUP(T6,'Org Map'!A:F,6,FALSE),"ADP and BU Language Code Not Mapped"))&AH6 -> en_US | AJ6: =IFERROR(VLOOKUP(T6,'Org Map'!A:G,7),"BU Currency Not Mapped") -> USD | AK6: =IF(ISBLANK(E6),"",TRIM(E6&" "&F6)) | AL6: =IFERROR(VLOOKUP(O6,'Status Map'!A:B,2,FALSE),"Position Status Not Mapped") -> Y | AM6: =IF(AL6="N",TEXT(M6,"yyyymmdd"),"") | AO6: =B6&C6&D6 -> GregorySAdams | AP6: =LEFT(G6,FIND(",",G6)-1) -> Rodriguez | AQ6: =IFERROR(VLOOKUP(AP6,D:P,13,FALSE),"No Reports to Name") -> 212338 | AR6: =AQ6=MID(H6,4,6) -> FALSE
A7: KSY | B7: Krystle | D7: Agler | G7: Kemenah, Greg | H7: KSY211766 | J7: krystle.agler@gmail.com | K7: Mgr, Marketing II | L7: 46160 | O7: Active | P7: 213226 | Q7: Monthly | R7: Full Time | S7: 088 | T7: 088-AS Raymond | U7: Marketing | V7: 008300 | W7: AS Raymond | Z7: USA | AA7: S16 | AB7: FMG-S16 | AC7: =IF(ISBLANK(H7),VLOOKUP(P7,'US Supervisor Map'!A:D,4,FALSE),MID(H7,4,6)) -> 211766 | AD7: =IFERROR(VLOOKUP(T7,'Org Map'!A:E,4),"BU Description Not Mapped") -> 0088 | AE7: =IFERROR(VLOOKUP(V7,'Org Map'!C:E,3),"Home Department Code Not Mapped") -> 8300 | AF7: =IFERROR(VLOOKUP(AA7,'Salary Map'!A:D,3,FALSE),"Salary Code Not Mapped") -> Default | AG7: =IFERROR(VLOOKUP(AA7,'Salary Map'!A:D,4,FALSE),"Salary Code Not Mapped") -> General | AH7: =IFERROR(VLOOKUP(Z7,'Country Map'!A:B,2,FALSE),"Legal Country Not Mapped") -> US | AI7: =IFERROR(VLOOKUP(X7,'Language Map'!A:C,3,FALSE),IFERROR(VLOOKUP(T7,'Org Map'!A:F,6,FALSE),"ADP and BU Language Code Not Mapped"))&AH7 -> en_US | AJ7: =IFERROR(VLOOKUP(T7,'Org Map'!A:G,7),"BU Currency Not Mapped") -> USD | AK7: =IF(ISBLANK(E7),"",TRIM(E7&" "&F7)) | AL7: =IFERROR(VLOOKUP(O7,'Status Map'!A:B,2,FALSE),"Position Status Not Mapped") -> Y | AM7: =IF(AL7="N",TEXT(M7,"yyyymmdd"),"") | AO7: =B7&C7&D7 -> KrystleAgler | AP7: =LEFT(G7,FIND(",",G7)-1) -> Kemenah | AQ7: =IFERROR(VLOOKUP(AP7,D:P,13,FALSE),"No Reports to Name") -> 211766 | AR7: =AQ7=MID(H7,4,6) -> TRUE
A8: KSX | B8: Aydrian | C8: M | D8: Ahrens | G8: Burchell, Mathew | H8: KSY211756 | J8: aydrian0323@yahoo.com | K8: Assistant, Warehouse II | L8: 45754 | O8: Active | P8: 211901 | Q8: Biweekly | R8: Full Time | S8: 088 | T8: 088-AS Raymond | U8: Assembly | V8: 005100 | W8: AS Raymond | Z8: USA | AA8: S05 | AB8: FMG-S05 | AC8: =IF(ISBLANK(H8),VLOOKUP(P8,'US Supervisor Map'!A:D,4,FALSE),MID(H8,4,6)) -> 211756 | AD8: =IFERROR(VLOOKUP(T8,'Org Map'!A:E,4),"BU Description Not Mapped") -> 0088 | AE8: =IFERROR(VLOOKUP(V8,'Org Map'!C:E,3),"Home Department Code Not Mapped") -> 5100 | AF8: =IFERROR(VLOOKUP(AA8,'Salary Map'!A:D,3,FALSE),"Salary Code Not Mapped") -> Default | AG8: =IFERROR(VLOOKUP(AA8,'Salary Map'!A:D,4,FALSE),"Salary Code Not Mapped") -> General | AH8: =IFERROR(VLOOKUP(Z8,'Country Map'!A:B,2,FALSE),"Legal Country Not Mapped") -> US | AI8: =IFERROR(VLOOKUP(X8,'Language Map'!A:C,3,FALSE),IFERROR(VLOOKUP(T8,'Org Map'!A:F,6,FALSE),"ADP and BU Language Code Not Mapped"))&AH8 -> en_US | AJ8: =IFERROR(VLOOKUP(T8,'Org Map'!A:G,7),"BU Currency Not Mapped") -> USD | AK8: =IF(ISBLANK(E8),"",TRIM(E8&" "&F8)) | AL8: =IFERROR(VLOOKUP(O8,'Status Map'!A:B,2,FALSE),"Position Status Not Mapped") -> Y | AM8: =IF(AL8="N",TEXT(M8,"yyyymmdd"),"") | AO8: =B8&C8&D8 -> AydrianMAhrens | AP8: =LEFT(G8,FIND(",",G8)-1) -> Burchell | AQ8: =IFERROR(VLOOKUP(AP8,D:P,13,FALSE),"No Reports to Name") -> 211756 | AR8: =AQ8=MID(H8,4,6) -> TRUE
A9: KSX | B9: Matthew | D9: Ahrens | G9: Burchell, Mathew | H9: KSY211756 | J9: mattcjahrens89@yahoo.com | K9: Assistant, Warehouse II | L9: 46176 | M9: 46182 | O9: Terminated | P9: 213306 | Q9: Biweekly | R9: Full Time | S9: 088 | T9: 088-AS Raymond | U9: WH Material Management | V9: 005300 | W9: AS Raymond | Z9: USA | AA9: S05 | AB9: FMG-S05 | AC9: =IF(ISBLANK(H9),VLOOKUP(P9,'US Supervisor Map'!A:D,4,FALSE),MID(H9,4,6)) -> 211756 | AD9: =IFERROR(VLOOKUP(T9,'Org Map'!A:E,4),"BU Description Not Mapped") -> 0088 | AE9: =IFERROR(VLOOKUP(V9,'Org Map'!C:E,3),"Home Department Code Not Mapped") -> 5300 | AF9: =IFERROR(VLOOKUP(AA9,'Salary Map'!A:D,3,FALSE),"Salary Code Not Mapped") -> Default | AG9: =IFERROR(VLOOKUP(AA9,'Salary Map'!A:D,4,FALSE),"Salary Code Not Mapped") -> General | AH9: =IFERROR(VLOOKUP(Z9,'Country Map'!A:B,2,FALSE),"Legal Country Not Mapped") -> US | AI9: =IFERROR(VLOOKUP(X9,'Language Map'!A:C,3,FALSE),IFERROR(VLOOKUP(T9,'Org Map'!A:F,6,FALSE),"ADP and BU Language Code Not Mapped"))&AH9 -> en_US | AJ9: =IFERROR(VLOOKUP(T9,'Org Map'!A:G,7),"BU Currency Not Mapped") -> USD | AK9: =IF(ISBLANK(E9),"",TRIM(E9&" "&F9)) | AL9: =IFERROR(VLOOKUP(O9,'Status Map'!A:B,2,FALSE),"Position Status Not Mapped") -> N | AM9: =IF(AL9="N",TEXT(M9,"yyyymmdd"),"") -> 20260609 | AN9: =IF(M9>AN4,"Fix and Include Record","Exclude record termination over 45 days ago") -> Exclude record termination over 45 days ago | AO9: =B9&C9&D9 -> MatthewAhrens | AP9: =LEFT(G9,FIND(",",G9)-1) -> Burchell | AQ9: =IFERROR(VLOOKUP(AP9,D:P,13,FALSE),"No Reports to Name") -> 211756 | AR9: =AQ9=MID(H9,4,6) -> TRUE
A10: KSY | B10: Thomas | C10: E | D10: Alexander | G10: Kemenah, Greg | H10: KSY211766 | I10: talexander@onebarnes.com | J10: tom5683alexander@gmail.com | K10: Mgr, Quality II | L10: 45392 | O10: Active | P10: 210892 | Q10: Monthly | R10: Full Time | S10: 088 | T10: 088-AS Raymond | U10: Admin-Quality | V10: 009500 | W10: AS Raymond | Z10: USA | AA10: S16 | AB10: FMG-S16 | AC10: =IF(ISBLANK(H10),VLOOKUP(P10,'US Supervisor Map'!A:D,4,FALSE),MID(H10,4,6)) -> 211766 | AD10: =IFERROR(VLOOKUP(T10,'Org Map'!A:E,4),"BU Description Not Mapped") -> 0088 | AE10: =IFERROR(VLOOKUP(V10,'Org Map'!C:E,3),"Home Department Code Not Mapped") -> 9500 | AF10: =IFERROR(VLOOKUP(AA10,'Salary Map'!A:D,3,FALSE),"Salary Code Not Mapped") -> Default | AG10: =IFERROR(VLOOKUP(AA10,'Salary Map'!A:D,4,FALSE),"Salary Code Not Mapped") -> General | AH10: =IFERROR(VLOOKUP(Z10,'Country Map'!A:B,2,FALSE),"Legal Country Not Mapped") -> US | AI10: =IFERROR(VLOOKUP(X10,'Language Map'!A:C,3,FALSE),IFERROR(VLOOKUP(T10,'Org Map'!A:F,6,FALSE),"ADP and BU Language Code Not Mapped"))&AH10 -> en_US | AJ10: =IFERROR(VLOOKUP(T10,'Org Map'!A:G,7),"BU Currency Not Mapped") -> USD | AK10: =IF(ISBLANK(E10),"",TRIM(E10&" "&F10)) | AL10: =IFERROR(VLOOKUP(O10,'Status Map'!A:B,2,FALSE),"Position Status Not Mapped") -> Y | AM10: =IF(AL10="N",TEXT(M10,"yyyymmdd"),"") | AO10: =B10&C10&D10 -> ThomasEAlexander | AP10: =LEFT(G10,FIND(",",G10)-1) -> Kemenah | AQ10: =IFERROR(VLOOKUP(AP10,D:P,13,FALSE),"No Reports to Name") -> 211766 | AR10: =AQ10=MID(H10,4,6) -> TRUE
A11: KSX | B11: Tina | C11: M | D11: Allen | G11: LaPlante, Derek | H11: KSY211736 | I11: TAllen2@onebarnes.com | J11: tinaallen908@gmail.com | K11: Assistant, Warehouse II | L11: 44550 | O11: Active | P11: 206848 | Q11: Biweekly | R11: Full Time | S11: 088 | T11: 088-AS Raymond | U11: FG Warehouse | V11: 005200 | W11: AS Raymond | Z11: USA | AA11: S05 | AB11: FMG-S05 | AC11: =IF(ISBLANK(H11),VLOOKUP(P11,'US Supervisor Map'!A:D,4,FALSE),MID(H11,4,6)) -> 211736 | AD11: =IFERROR(VLOOKUP(T11,'Org Map'!A:E,4),"BU Description Not Mapped") -> 0088 | AE11: =IFERROR(VLOOKUP(V11,'Org Map'!C:E,3),"Home Department Code Not Mapped") -> 5200 | AF11: =IFERROR(VLOOKUP(AA11,'Salary Map'!A:D,3,FALSE),"Salary Code Not Mapped") -> Default | AG11: =IFERROR(VLOOKUP(AA11,'Salary Map'!A:D,4,FALSE),"Salary Code Not Mapped") -> General | AH11: =IFERROR(VLOOKUP(Z11,'Country Map'!A:B,2,FALSE),"Legal Country Not Mapped") -> US | AI11: =IFERROR(VLOOKUP(X11,'Language Map'!A:C,3,FALSE),IFERROR(VLOOKUP(T11,'Org Map'!A:F,6,FALSE),"ADP and BU Language Code Not Mapped"))&AH11 -> en_US | AJ11: =IFERROR(VLOOKUP(T11,'Org Map'!A:G,7),"BU Currency Not Mapped") -> USD | AK11: =IF(ISBLANK(E11),"",TRIM(E11&" "&F11)) | AL11: =IFERROR(VLOOKUP(O11,'Status Map'!A:B,2,FALSE),"Position Status Not Mapped") -> Y | AM11: =IF(AL11="N",TEXT(M11,"yyyymmdd"),"") | AO11: =B11&C11&D11 -> TinaMAllen | AP11: =LEFT(G11,FIND(",",G11)-1) -> LaPlante | AQ11: =IFERROR(VLOOKUP(AP11,D:P,13,FALSE),"No Reports to Name") -> 211736 | AR11: =AQ11=MID(H11,4,6) -> TRUE
A12: KSY | B12: Kimberly | D12: Ashley | G12: Warner, Dwight | H12: V0U008750 | I12: KAshley@onebarnes.com | K12: Accountant III | L12: 43710 | O12: Active | P12: 201688 | Q12: Monthly | R12: Full Time | S12: 088 | T12: 088-AS Raymond | U12: Finance General | V12: 009100 | W12: Work from home - Connecticut | Z12: USA | AA12: S13 | AB12: FMG-S13 | AC12: =IF(ISBLANK(H12),VLOOKUP(P12,'US Supervisor Map'!A:D,4,FALSE),MID(H12,4,6)) -> 008750 | AD12: =IFERROR(VLOOKUP(T12,'Org Map'!A:E,4),"BU Description Not Mapped") -> 0088 | AE12: =IFERROR(VLOOKUP(V12,'Org Map'!C:E,3),"Home Department Code Not Mapped") -> 9100 | AF12: =IFERROR(VLOOKUP(AA12,'Salary Map'!A:D,3,FALSE),"Salary Code Not Mapped") -> Default | AG12: =IFERROR(VLOOKUP(AA12,'Salary Map'!A:D,4,FALSE),"Salary Code Not Mapped") -> General | AH12: =IFERROR(VLOOKUP(Z12,'Country Map'!A:B,2,FALSE),"Legal Country Not Mapped") -> US | AI12: =IFERROR(VLOOKUP(X12,'Language Map'!A:C,3,FALSE),IFERROR(VLOOKUP(T12,'Org Map'!A:F,6,FALSE),"ADP and BU Language Code Not Mapped"))&AH12 -> en_US | AJ12: =IFERROR(VLOOKUP(T12,'Org Map'!A:G,7),"BU Currency Not Mapped") -> USD | AK12: =IF(ISBLANK(E12),"",TRIM(E12&" "&F12)) | AL12: =IFERROR(VLOOKUP(O12,'Status Map'!A:B,2,FALSE),"Position Status Not Mapped") -> Y | AM12: =IF(AL12="N",TEXT(M12,"yyyymmdd"),"") | AO12: =B12&C12&D12 -> KimberlyAshley | AP12: =LEFT(G12,FIND(",",G12)-1) -> Warner | AQ12: =IFERROR(VLOOKUP(AP12,D:P,13,FALSE),"No Reports to Name") -> 008750 | AR12: =AQ12=MID(H12,4,6) -> TRUE
A13: KSY | B13: Jason | C13: J | D13: Bailey | G13: Kemenah, Greg | I13: jbailey@onebarnes.com | J13: jjbailey08@gmail.com | K13: Senior Mgr, Operations | L13: 46258 | O13: Active | P13: 902688 | Q13: Monthly | R13: Full Time | S13: 088 | T13: 088-AS Raymond | U13: Operations 5200 5200 | V13: 000007 | W13: AS Raymond | Z13: USA | AA13: S18 | AB13: FMG-S18 | AC13: =IF(ISBLANK(H13),VLOOKUP(P13,'US Supervisor Map'!A:D,4,FALSE),MID(H13,4,6)) | AD13: =IFERROR(VLOOKUP(T13,'Org Map'!A:E,4),"BU Description Not Mapped") -> 0088 | AE13: =IFERROR(VLOOKUP(V13,'Org Map'!C:E,3),"Home Department Code Not Mapped") -> Home Department Code Not Mapped | AF13: =IFERROR(VLOOKUP(AA13,'Salary Map'!A:D,3,FALSE),"Salary Code Not Mapped") -> Default | AG13: =IFERROR(VLOOKUP(AA13,'Salary Map'!A:D,4,FALSE),"Salary Code Not Mapped") -> General | AH13: =IFERROR(VLOOKUP(Z13,'Country Map'!A:B,2,FALSE),"Legal Country Not Mapped") -> US | AI13: =IFERROR(VLOOKUP(X13,'Language Map'!A:C,3,FALSE),IFERROR(VLOOKUP(T13,'Org Map'!A:F,6,FALSE),"ADP and BU Language Code Not Mapped"))&AH13 -> en_US | AJ13: =IFERROR(VLOOKUP(T13,'Org Map'!A:G,7),"BU Currency Not Mapped") -> USD | AK13: =IF(ISBLANK(E13),"",TRIM(E13&" "&F13)) | AL13: =IFERROR(VLOOKUP(O13,'Status Map'!A:B,2,FALSE),"Position Status Not Mapped") -> Y | AM13: =IF(AL13="N",TEXT(M13,"yyyymmdd"),"") | AO13: =B13&C13&D13 -> JasonJBailey | AP13: =LEFT(G13,FIND(",",G13)-1) -> Kemenah | AQ13: =IFERROR(VLOOKUP(AP13,D:P,13,FALSE),"No Reports to Name") -> 211766 | AR13: =AQ13=MID(H13,4,6) -> FALSE
A14: KSY | B14: Teresa | D14: Bair | I14: TBair@onebarnes.com | K14: President, SBU II | L14: 44732 | O14: Active | P14: 207709 | Q14: Monthly | R14: Full Time | S14: 088 | T14: 088-AS Raymond | U14: Bus Execs CU | V14: 009310 | W14: AS Raymond | Z14: USA | AA14: S22 | AB14: FMG-S22 | AC14: =IF(ISBLANK(H14),VLOOKUP(P14,'US Supervisor Map'!A:D,4,FALSE),MID(H14,4,6)) | AD14: =IFERROR(VLOOKUP(T14,'Org Map'!A:E,4),"BU Description Not Mapped") -> 0088 | AE14: =IFERROR(VLOOKUP(V14,'Org Map'!C:E,3),"Home Department Code Not Mapped") -> 9310 | AF14: =IFERROR(VLOOKUP(AA14,'Salary Map'!A:D,3,FALSE),"Salary Code Not Mapped") -> Grade 20 | AG14: =IFERROR(VLOOKUP(AA14,'Salary Map'!A:D,4,FALSE),"Salary Code Not Mapped") -> Senior Leadership | AH14: =IFERROR(VLOOKUP(Z14,'Country Map'!A:B,2,FALSE),"Legal Country Not Mapped") -> US | AI14: =IFERROR(VLOOKUP(X14,'Language Map'!A:C,3,FALSE),IFERROR(VLOOKUP(T14,'Org Map'!A:F,6,FALSE),"ADP and BU Language Code Not Mapped"))&AH14 -> en_US | AJ14: =IFERROR(VLOOKUP(T14,'Org Map'!A:G,7),"BU Currency Not Mapped") -> USD | AK14: =IF(ISBLANK(E14),"",TRIM(E14&" "&F14)) | AL14: =IFERROR(VLOOKUP(O14,'Status Map'!A:B,2,FALSE),"Position Status Not Mapped") -> Y | AM14: =IF(AL14="N",TEXT(M14,"yyyymmdd"),"") | AO14: =B14&C14&D14 -> TeresaBair | AP14: =LEFT(G14,FIND(",",G14)-1) -> #VALUE! | AQ14: =IFERROR(VLOOKUP(AP14,D:P,13,FALSE),"No Reports to Name") -> No Reports to Name | AR14: =AQ14=MID(H14,4,6) -> FALSE
A15: V0U | B15: Kirsten | C15: V | D15: Barry | G15: Rodriguez, Siobhan | I15: kbarry@onebarnes.com | K15: Mgr, Project I | L15: 44949 | O15: Active | P15: 209579 | Q15: Monthly | R15: Full Time | S15: 025 | T15: 025-NGP Hyson Products | U15: Outside Sales | V15: 000820 | W15: Hyson Products | Z15: USA | AA15: S15 | AB15: FMG-S15 | AC15: =IF(ISBLANK(H15),VLOOKUP(P15,'US Supervisor Map'!A:D,4,FALSE),MID(H15,4,6)) | AD15: =IFERROR(VLOOKUP(T15,'Org Map'!A:E,4),"BU Description Not Mapped") -> 0096 | AE15: =IFERROR(VLOOKUP(V15,'Org Map'!C:E,3),"Home Department Code Not Mapped") -> 820 | AF15: =IFERROR(VLOOKUP(AA15,'Salary Map'!A:D,3,FALSE),"Salary Code Not Mapped") -> Default | AG15: =IFERROR(VLOOKUP(AA15,'Salary Map'!A:D,4,FALSE),"Salary Code Not Mapped") -> General | AH15: =IFERROR(VLOOKUP(Z15,'Country Map'!A:B,2,FALSE),"Legal Country Not Mapped") -> US | AI15: =IFERROR(VLOOKUP(X15,'Language Map'!A:C,3,FALSE),IFERROR(VLOOKUP(T15,'Org Map'!A:F,6,FALSE),"ADP and BU Language Code Not Mapped"))&AH15 -> en_US | AJ15: =IFERROR(VLOOKUP(T15,'Org Map'!A:G,7),"BU Currency Not Mapped") -> USD | AK15: =IF(ISBLANK(E15),"",TRIM(E15&" "&F15)) | AL15: =IFERROR(VLOOKUP(O15,'Status Map'!A:B,2,FALSE),"Position Status Not Mapped") -> Y | AM15: =IF(AL15="N",TEXT(M15,"yyyymmdd"),"") | AO15: =B15&C15&D15 -> KirstenVBarry | AP15: =LEFT(G15,FIND(",",G15)-1) -> Rodriguez | AQ15: =IFERROR(VLOOKUP(AP15,D:P,13,FALSE),"No Reports to Name") -> 212338 | AR15: =AQ15=MID(H15,4,6) -> FALSE
A16: V0U | B16: Natalie | D16: Bate | G16: Bair, Teresa | H16: KSY207709 | I16: nbate@onebarnes.com | J16: natalie.m.bate@gmail.com | K16: Mgr, Division II | L16: 46083 | O16: Active | P16: 213037 | Q16: Monthly | R16: Full Time | S16: 025 | T16: 025-NGP Hyson Products | U16: Administration | V16: 000917 | W16: Hyson Products | Z16: USA | AA16: S19 | AB16: FMG-S19 | AC16: =IF(ISBLANK(H16),VLOOKUP(P16,'US Supervisor Map'!A:D,4,FALSE),MID(H16,4,6)) -> 207709 | AD16: =IFERROR(VLOOKUP(T16,'Org Map'!A:E,4),"BU Description Not Mapped") -> 0096 | AE16: =IFERROR(VLOOKUP(V16,'Org Map'!C:E,3),"Home Department Code Not Mapped") -> 0007 | AF16: =IFERROR(VLOOKUP(AA16,'Salary Map'!A:D,3,FALSE),"Salary Code Not Mapped") -> Default | AG16: =IFERROR(VLOOKUP(AA16,'Salary Map'!A:D,4,FALSE),"Salary Code Not Mapped") -> General | AH16: =IFERROR(VLOOKUP(Z16,'Country Map'!A:B,2,FALSE),"Legal Country Not Mapped") -> US | AI16: =IFERROR(VLOOKUP(X16,'Language Map'!A:C,3,FALSE),IFERROR(VLOOKUP(T16,'Org Map'!A:F,6,FALSE),"ADP and BU Language Code Not Mapped"))&AH16 -> en_US | AJ16: =IFERROR(VLOOKUP(T16,'Org Map'!A:G,7),"BU Currency Not Mapped") -> USD | AK16: =IF(ISBLANK(E16),"",TRIM(E16&" "&F16)) | AL16: =IFERROR(VLOOKUP(O16,'Status Map'!A:B,2,FALSE),"Position Status Not Mapped") -> Y | AM16: =IF(AL16="N",TEXT(M16,"yyyymmdd"),"") | AO16: =B16&C16&D16 -> NatalieBate | AP16: =LEFT(G16,FIND(",",G16)-1) -> Bair | AQ16: =IFERROR(VLOOKUP(AP16,D:P,13,FALSE),"No Reports to Name") -> 207709 | AR16: =AQ16=MID(H16,4,6) -> TRUE
A17: KSY | B17: Michael | C17: J | D17: Beasley | G17: Rodriguez, Siobhan | H17: V0U207588 | I17: mbeasley@onebarnes.com | J17: gqnbeasley@comcast.net | K17: Mgr, Sales | L17: 46202 | O17: Active | P17: 213333 | Q17: Monthly | R17: Full Time | S17: 088 | T17: 088-AS Raymond | U17: Outside Sales | V17: 008200 | W17: Work from home - Washington | Z17: USA | AA17: S16 | AB17: FMG-S16 | AC17: =IF(ISBLANK(H17),VLOOKUP(P17,'US Supervisor Map'!A:D,4,FALSE),MID(H17,4,6)) -> 207588 | AD17: =IFERROR(VLOOKUP(T17,'Org Map'!A:E,4),"BU Description Not Mapped") -> 0088 | AE17: =IFERROR(VLOOKUP(V17,'Org Map'!C:E,3),"Home Department Code Not Mapped") -> 8200 | AF17: =IFERROR(VLOOKUP(AA17,'Salary Map'!A:D,3,FALSE),"Salary Code Not Mapped") -> Default | AG17: =IFERROR(VLOOKUP(AA17,'Salary Map'!A:D,4,FALSE),"Salary Code Not Mapped") -> General | AH17: =IFERROR(VLOOKUP(Z17,'Country Map'!A:B,2,FALSE),"Legal Country Not Mapped") -> US | AI17: =IFERROR(VLOOKUP(X17,'Language Map'!A:C,3,FALSE),IFERROR(VLOOKUP(T17,'Org Map'!A:F,6,FALSE),"ADP and BU Language Code Not Mapped"))&AH17 -> en_US | AJ17: =IFERROR(VLOOKUP(T17,'Org Map'!A:G,7),"BU Currency Not Mapped") -> USD | AK17: =IF(ISBLANK(E17),"",TRIM(E17&" "&F17)) | AL17: =IFERROR(VLOOKUP(O17,'Status Map'!A:B,2,FALSE),"Position Status Not Mapped") -> Y | AM17: =IF(AL17="N",TEXT(M17,"yyyymmdd"),"") | AO17: =B17&C17&D17 -> MichaelJBeasley | AP17: =LEFT(G17,FIND(",",G17)-1) -> Rodriguez | AQ17: =IFERROR(VLOOKUP(AP17,D:P,13,FALSE),"No Reports to Name") -> 212338 | AR17: =AQ17=MID(H17,4,6) -> FALSE
A18: KSX | B18: Ella Renae | C18: E | D18: Beatrice | G18: LaPlante, Derek | H18: KSY211736 | I18: ebeatrice@onebarnes.com | J18: thatellachick@gmail.com | K18: Assistant, Warehouse II | L18: 45929 | O18: Active | P18: 212626 | Q18: Biweekly | R18: Full Time | S18: 088 | T18: 088-AS Raymond | U18: FG Warehouse | V18: 005200 | W18: AS Raymond | Z18: USA | AA18: S05 | AB18: FMG-S05 | AC18: =IF(ISBLANK(H18),VLOOKUP(P18,'US Supervisor Map'!A:D,4,FALSE),MID(H18,4,6)) -> 211736 | AD18: =IFERROR(VLOOKUP(T18,'Org Map'!A:E,4),"BU Description Not Mapped") -> 0088 | AE18: =IFERROR(VLOOKUP(V18,'Org Map'!C:E,3),"Home Department Code Not Mapped") -> 5200 | AF18: =IFERROR(VLOOKUP(AA18,'Salary Map'!A:D,3,FALSE),"Salary Code Not Mapped") -> Default | AG18: =IFERROR(VLOOKUP(AA18,'Salary Map'!A:D,4,FALSE),"Salary Code Not Mapped") -> General | AH18: =IFERROR(VLOOKUP(Z18,'Country Map'!A:B,2,FALSE),"Legal Country Not Mapped") -> US | AI18: =IFERROR(VLOOKUP(X18,'Language Map'!A:C,3,FALSE),IFERROR(VLOOKUP(T18,'Org Map'!A:F,6,FALSE),"ADP and BU Language Code Not Mapped"))&AH18 -> en_US | AJ18: =IFERROR(VLOOKUP(T18,'Org Map'!A:G,7),"BU Currency Not Mapped") -> USD | AK18: =IF(ISBLANK(E18),"",TRIM(E18&" "&F18)) | AL18: =IFERROR(VLOOKUP(O18,'Status Map'!A:B,2,FALSE),"Position Status Not Mapped") -> Y | AM18: =IF(AL18="N",TEXT(M18,"yyyymmdd"),"") | AO18: =B18&C18&D18 -> Ella RenaeEBeatrice | AP18: =LEFT(G18,FIND(",",G18)-1) -> LaPlante | AQ18: =IFERROR(VLOOKUP(AP18,D:P,13,FALSE),"No Reports to Name") -> 211736 | AR18: =AQ18=MID(H18,4,6) -> TRUE
A19: KSX | B19: John | D19: Bentz | G19: LaPlante, Derek | H19: KSY211736 | I19: jbentz@onebarnes.com | J19: xjbm13@yahoo.com | K19: Assistant, Warehouse II | L19: 45937 | O19: Active | P19: 212639 | Q19: Biweekly | R19: Full Time | S19: 088 | T19: 088-AS Raymond | U19: FG Warehouse | V19: 005200 | W19: AS Raymond | Z19: USA | AA19: S05 | AB19: FMG-S05 | AC19: =IF(ISBLANK(H19),VLOOKUP(P19,'US Supervisor Map'!A:D,4,FALSE),MID(H19,4,6)) -> 211736 | AD19: =IFERROR(VLOOKUP(T19,'Org Map'!A:E,4),"BU Description Not Mapped") -> 0088 | AE19: =IFERROR(VLOOKUP(V19,'Org Map'!C:E,3),"Home Department Code Not Mapped") -> 5200 | AF19: =IFERROR(VLOOKUP(AA19,'Salary Map'!A:D,3,FALSE),"Salary Code Not Mapped") -> Default | AG19: =IFERROR(VLOOKUP(AA19,'Salary Map'!A:D,4,FALSE),"Salary Code Not Mapped") -> General | AH19: =IFERROR(VLOOKUP(Z19,'Country Map'!A:B,2,FALSE),"Legal Country Not Mapped") -> US | AI19: =IFERROR(VLOOKUP(X19,'Language Map'!A:C,3,FALSE),IFERROR(VLOOKUP(T19,'Org Map'!A:F,6,FALSE),"ADP and BU Language Code Not Mapped"))&AH19 -> en_US | AJ19: =IFERROR(VLOOKUP(T19,'Org Map'!A:G,7),"BU Currency Not Mapped") -> USD | AK19: =IF(ISBLANK(E19),"",TRIM(E19&" "&F19)) | AL19: =IFERROR(VLOOKUP(O19,'Status Map'!A:B,2,FALSE),"Position Status Not Mapped") -> Y | AM19: =IF(AL19="N",TEXT(M19,"yyyymmdd"),"") | AO19: =B19&C19&D19 -> JohnBentz | AP19: =LEFT(G19,FIND(",",G19)-1) -> LaPlante | AQ19: =IFERROR(VLOOKUP(AP19,D:P,13,FALSE),"No Reports to Name") -> 211736 | AR19: =AQ19=MID(H19,4,6) -> TRUE
A20: KSY | B20: Michael | D20: Biniecki | G20: Bailey, Jason | H20: KSY211766 | I20: mbiniecki@onebarnes.com | J20: mbineck@frontier.com | K20: Supv, CI | L20: 45565 | O20: Active | P20: 211464 | Q20: Monthly | R20: Full Time | S20: 088 | T20: 088-AS Raymond | U20: FG Warehouse | V20: 005200 | W20: AS Raymond | Z20: USA | AA20: S16 | AB20: FMG-S16 | AC20: =IF(ISBLANK(H20),VLOOKUP(P20,'US Supervisor Map'!A:D,4,FALSE),MID(H20,4,6)) -> 211766 | AD20: =IFERROR(VLOOKUP(T20,'Org Map'!A:E,4),"BU Description Not Mapped") -> 0088 | AE20: =IFERROR(VLOOKUP(V20,'Org Map'!C:E,3),"Home Department Code Not Mapped") -> 5200 | AF20: =IFERROR(VLOOKUP(AA20,'Salary Map'!A:D,3,FALSE),"Salary Code Not Mapped") -> Default | AG20: =IFERROR(VLOOKUP(AA20,'Salary Map'!A:D,4,FALSE),"Salary Code Not Mapped") -> General | AH20: =IFERROR(VLOOKUP(Z20,'Country Map'!A:B,2,FALSE),"Legal Country Not Mapped") -> US | AI20: =IFERROR(VLOOKUP(X20,'Language Map'!A:C,3,FALSE),IFERROR(VLOOKUP(T20,'Org Map'!A:F,6,FALSE),"ADP and BU Language Code Not Mapped"))&AH20 -> en_US | AJ20: =IFERROR(VLOOKUP(T20,'Org Map'!A:G,7),"BU Currency Not Mapped") -> USD | AK20: =IF(ISBLANK(E20),"",TRIM(E20&" "&F20)) | AL20: =IFERROR(VLOOKUP(O20,'Status Map'!A:B,2,FALSE),"Position Status Not Mapped") -> Y | AM20: =IF(AL20="N",TEXT(M20,"yyyymmdd"),"") | AO20: =B20&C20&D20 -> MichaelBiniecki | AP20: =LEFT(G20,FIND(",",G20)-1) -> Bailey | AQ20: =IFERROR(VLOOKUP(AP20,D:P,13,FALSE),"No Reports to Name") -> 902688 | AR20: =AQ20=MID(H20,4,6) -> FALSE
A21: V0U | B21: Nathan | D21: Bird | G21: Wilkins, William | H21: V0U901934 | I21: nbird@onebarnes.com | J21: bird.nathan@icloud.com | K21: Mgr, Sales | L21: 45131 | O21: Active | P21: 210102 | Q21: Monthly | R21: Full Time | S21: 025 | T21: 025-NGP Hyson Products | U21: Outside Sales | V21: 000820 | W21: Work from home - Arizona | Z21: USA | AA21: S15 | AB21: FMG-S15 | AC21: =IF(ISBLANK(H21),VLOOKUP(P21,'US Supervisor Map'!A:D,4,FALSE),MID(H21,4,6)) -> 901934 | AD21: =IFERROR(VLOOKUP(T21,'Org Map'!A:E,4),"BU Description Not Mapped") -> 0096 | AE21: =IFERROR(VLOOKUP(V21,'Org Map'!C:E,3),"Home Department Code Not Mapped") -> 820 | AF21: =IFERROR(VLOOKUP(AA21,'Salary Map'!A:D,3,FALSE),"Salary Code Not Mapped") -> Default | AG21: =IFERROR(VLOOKUP(AA21,'Salary Map'!A:D,4,FALSE),"Salary Code Not Mapped") -> General | AH21: =IFERROR(VLOOKUP(Z21,'Country Map'!A:B,2,FALSE),"Legal Country Not Mapped") -> US | AI21: =IFERROR(VLOOKUP(X21,'Language Map'!A:C,3,FALSE),IFERROR(VLOOKUP(T21,'Org Map'!A:F,6,FALSE),"ADP and BU Language Code Not Mapped"))&AH21 -> en_US | AJ21: =IFERROR(VLOOKUP(T21,'Org Map'!A:G,7),"BU Currency Not Mapped") -> USD | AK21: =IF(ISBLANK(E21),"",TRIM(E21&" "&F21)) | AL21: =IFERROR(VLOOKUP(O21,'Status Map'!A:B,2,FALSE),"Position Status Not Mapped") -> Y | AM21: =IF(AL21="N",TEXT(M21,"yyyymmdd"),"") | AO21: =B21&C21&D21 -> NathanBird | AP21: =LEFT(G21,FIND(",",G21)-1) -> Wilkins | AQ21: =IFERROR(VLOOKUP(AP21,D:P,13,FALSE),"No Reports to Name") -> 901934 | AR21: =AQ21=MID(H21,4,6) -> TRUE
A22: KSW | B22: James | D22: Biss | G22: Steen, Michael | H22: V0U211062 | J22: jlbjr7784@gmail.com | K22: Assembler B | L22: 45232 | O22: Active | P22: 210375 | Q22: Biweekly | R22: Full Time | S22: 025 | T22: 025-NGP Hyson Products | U22: Assembly Hyson | V22: 000200 | W22: Hyson Products | Z22: USA | AA22: H05 | AB22: FMG-H05 | AC22: =IF(ISBLANK(H22),VLOOKUP(P22,'US Supervisor Map'!A:D,4,FALSE),MID(H22,4,6)) -> 211062 | AD22: =IFERROR(VLOOKUP(T22,'Org Map'!A:E,4),"BU Description Not Mapped") -> 0096 | AE22: =IFERROR(VLOOKUP(V22,'Org Map'!C:E,3),"Home Department Code Not Mapped") -> 200 | AF22: =IFERROR(VLOOKUP(AA22,'Salary Map'!A:D,3,FALSE),"Salary Code Not Mapped") -> Default | AG22: =IFERROR(VLOOKUP(AA22,'Salary Map'!A:D,4,FALSE),"Salary Code Not Mapped") -> General | AH22: =IFERROR(VLOOKUP(Z22,'Country Map'!A:B,2,FALSE),"Legal Country Not Mapped") -> US | AI22: =IFERROR(VLOOKUP(X22,'Language Map'!A:C,3,FALSE),IFERROR(VLOOKUP(T22,'Org Map'!A:F,6,FALSE),"ADP and BU Language Code Not Mapped"))&AH22 -> en_US | AJ22: =IFERROR(VLOOKUP(T22,'Org Map'!A:G,7),"BU Currency Not Mapped") -> USD | AK22: =IF(ISBLANK(E22),"",TRIM(E22&" "&F22)) | AL22: =IFERROR(VLOOKUP(O22,'Status Map'!A:B,2,FALSE),"Position Status Not Mapped") -> Y | AM22: =IF(AL22="N",TEXT(M22,"yyyymmdd"),"") | AO22: =B22&C22&D22 -> JamesBiss | AP22: =LEFT(G22,FIND(",",G22)-1) -> Steen | AQ22: =IFERROR(VLOOKUP(AP22,D:P,13,FALSE),"No Reports to Name") -> 211062 | AR22: =AQ22=MID(H22,4,6) -> TRUE
A23: KSX | B23: Brenda | D23: Bixler | G23: LaPlante, Derek | H23: KSY211736 | I23: bbixler@onebarnes.com | J23: beebix911@gmail.com | K23: Expeditor, Warehouse | L23: 45502 | O23: Active | P23: 211174 | Q23: Biweekly | R23: Full Time | S23: 088 | T23: 088-AS Raymond | U23: FG Warehouse | V23: 005200 | W23: AS Raymond | Z23: USA | AA23: S06 | AB23: FMG-S06 | AC23: =IF(ISBLANK(H23),VLOOKUP(P23,'US Supervisor Map'!A:D,4,FALSE),MID(H23,4,6)) -> 211736 | AD23: =IFERROR(VLOOKUP(T23,'Org Map'!A:E,4),"BU Description Not Mapped") -> 0088 | AE23: =IFERROR(VLOOKUP(V23,'Org Map'!C:E,3),"Home Department Code Not Mapped") -> 5200 | AF23: =IFERROR(VLOOKUP(AA23,'Salary Map'!A:D,3,FALSE),"Salary Code Not Mapped") -> Default | AG23: =IFERROR(VLOOKUP(AA23,'Salary Map'!A:D,4,FALSE),"Salary Code Not Mapped") -> General | AH23: =IFERROR(VLOOKUP(Z23,'Country Map'!A:B,2,FALSE),"Legal Country Not Mapped") -> US | AI23: =IFERROR(VLOOKUP(X23,'Language Map'!A:C,3,FALSE),IFERROR(VLOOKUP(T23,'Org Map'!A:F,6,FALSE),"ADP and BU Language Code Not Mapped"))&AH23 -> en_US | AJ23: =IFERROR(VLOOKUP(T23,'Org Map'!A:G,7),"BU Currency Not Mapped") -> USD | AK23: =IF(ISBLANK(E23),"",TRIM(E23&" "&F23)) | AL23: =IFERROR(VLOOKUP(O23,'Status Map'!A:B,2,FALSE),"Position Status Not Mapped") -> Y | AM23: =IF(AL23="N",TEXT(M23,"yyyymmdd"),"") | AO23: =B23&C23&D23 -> BrendaBixler | AP23: =LEFT(G23,FIND(",",G23)-1) -> LaPlante | AQ23: =IFERROR(VLOOKUP(AP23,D:P,13,FALSE),"No Reports to Name") -> 211736 | AR23: =AQ23=MID(H23,4,6) -> TRUE
A24: KSX | B24: Robert | D24: Bordner | G24: Burchell, Mathew | H24: KSY211756 | J24: robertbordner@gmail.com | K24: Assistant, Warehouse II | L24: 46190 | O24: Active | Q24: Biweekly | R24: Temporary | S24: 088 | T24: 088-AS Raymond | U24: Assembly | V24: 005100 | W24: AS Raymond | Z24: USA | AA24: S05 | AB24: FMG-S05 | AC24: =IF(ISBLANK(H24),VLOOKUP(P24,'US Supervisor Map'!A:D,4,FALSE),MID(H24,4,6)) -> 211756 | AD24: =IFERROR(VLOOKUP(T24,'Org Map'!A:E,4),"BU Description Not Mapped") -> 0088 | AE24: =IFERROR(VLOOKUP(V24,'Org Map'!C:E,3),"Home Department Code Not Mapped") -> 5100 | AF24: =IFERROR(VLOOKUP(AA24,'Salary Map'!A:D,3,FALSE),"Salary Code Not Mapped") -> Default | AG24: =IFERROR(VLOOKUP(AA24,'Salary Map'!A:D,4,FALSE),"Salary Code Not Mapped") -> General | AH24: =IFERROR(VLOOKUP(Z24,'Country Map'!A:B,2,FALSE),"Legal Country Not Mapped") -> US | AI24: =IFERROR(VLOOKUP(X24,'Language Map'!A:C,3,FALSE),IFERROR(VLOOKUP(T24,'Org Map'!A:F,6,FALSE),"ADP and BU Language Code Not Mapped"))&AH24 -> en_US | AJ24: =IFERROR(VLOOKUP(T24,'Org Map'!A:G,7),"BU Currency Not Mapped") -> USD | AK24: =IF(ISBLANK(E24),"",TRIM(E24&" "&F24)) | AL24: =IFERROR(VLOOKUP(O24,'Status Map'!A:B,2,FALSE),"Position Status Not Mapped") -> Y | AM24: =IF(AL24="N",TEXT(M24,"yyyymmdd"),"") | AO24: =B24&C24&D24 -> RobertBordner | AP24: =LEFT(G24,FIND(",",G24)-1) -> Burchell | AQ24: =IFERROR(VLOOKUP(AP24,D:P,13,FALSE),"No Reports to Name") -> 211756 | AR24: =AQ24=MID(H24,4,6) -> TRUE
A25: KSX | B25: Jack | C25: O | D25: Bradford | G25: Halpin, Emma | H25: KSY211489 | J25: jb7222222@gmail.com | K25: Intern, Project Mgr Indir | L25: 46153 | M25: 46241 | O25: Terminated | P25: 213234 | Q25: Biweekly | R25: Intern | S25: 088 | T25: 088-AS Raymond | U25: Marketing | V25: 008300 | W25: AS Raymond | Z25: USA | AA25: H05 | AB25: FMG-H05 | AC25: =IF(ISBLANK(H25),VLOOKUP(P25,'US Supervisor Map'!A:D,4,FALSE),MID(H25,4,6)) -> 211489 | AD25: =IFERROR(VLOOKUP(T25,'Org Map'!A:E,4),"BU Description Not Mapped") -> 0088 | AE25: =IFERROR(VLOOKUP(V25,'Org Map'!C:E,3),"Home Department Code Not Mapped") -> 8300 | AF25: =IFERROR(VLOOKUP(AA25,'Salary Map'!A:D,3,FALSE),"Salary Code Not Mapped") -> Default | AG25: =IFERROR(VLOOKUP(AA25,'Salary Map'!A:D,4,FALSE),"Salary Code Not Mapped") -> General | AH25: =IFERROR(VLOOKUP(Z25,'Country Map'!A:B,2,FALSE),"Legal Country Not Mapped") -> US | AI25: =IFERROR(VLOOKUP(X25,'Language Map'!A:C,3,FALSE),IFERROR(VLOOKUP(T25,'Org Map'!A:F,6,FALSE),"ADP and BU Language Code Not Mapped"))&AH25 -> en_US | AJ25: =IFERROR(VLOOKUP(T25,'Org Map'!A:G,7),"BU Currency Not Mapped") -> USD | AK25: =IF(ISBLANK(E25),"",TRIM(E25&" "&F25)) | AL25: =IFERROR(VLOOKUP(O25,'Status Map'!A:B,2,FALSE),"Position Status Not Mapped") -> N | AM25: =IF(AL25="N",TEXT(M25,"yyyymmdd"),"") -> 20260807 | AN25: =IF(M25>AN20,"Fix and Include Record","Exclude record termination over 45 days ago") -> Fix and Include Record | AO25: =B25&C25&D25 -> JackOBradford | AP25: =LEFT(G25,FIND(",",G25)-1) -> Halpin | AQ25: =IFERROR(VLOOKUP(AP25,D:P,13,FALSE),"No Reports to Name") -> 211489 | AR25: =AQ25=MID(H25,4,6) -> TRUE
A26: KSW | B26: John | D26: Brewer | G26: Steen, Michael | H26: V0U211062 | J26: maddenbeast09@gmail.com | K26: Boring Mill Operator | L26: 46230 | O26: Active | Q26: Biweekly | R26: Temporary | AA26: H07 | AB26: FMG-H07 | AC26: =IF(ISBLANK(H26),VLOOKUP(P26,'US Supervisor Map'!A:D,4,FALSE),MID(H26,4,6)) -> 211062 | AD26: =IFERROR(VLOOKUP(T26,'Org Map'!A:E,4),"BU Description Not Mapped") -> BU Description Not Mapped | AE26: =IFERROR(VLOOKUP(V26,'Org Map'!C:E,3),"Home Department Code Not Mapped") -> Home Department Code Not Mapped | AF26: =IFERROR(VLOOKUP(AA26,'Salary Map'!A:D,3,FALSE),"Salary Code Not Mapped") -> Default | AG26: =IFERROR(VLOOKUP(AA26,'Salary Map'!A:D,4,FALSE),"Salary Code Not Mapped") -> General | AH26: =IFERROR(VLOOKUP(Z26,'Country Map'!A:B,2,FALSE),"Legal Country Not Mapped") -> Legal Country Not Mapped | AI26: =IFERROR(VLOOKUP(X26,'Language Map'!A:C,3,FALSE),IFERROR(VLOOKUP(T26,'Org Map'!A:F,6,FALSE),"ADP and BU Language Code Not Mapped"))&AH26 -> ADP and BU Language Code Not MappedLegal Country Not Mapped | AJ26: =IFERROR(VLOOKUP(T26,'Org Map'!A:G,7),"BU Currency Not Mapped") -> BU Currency Not Mapped | AK26: =IF(ISBLANK(E26),"",TRIM(E26&" "&F26)) | AL26: =IFERROR(VLOOKUP(O26,'Status Map'!A:B,2,FALSE),"Position Status Not Mapped") -> Y | AM26: =IF(AL26="N",TEXT(M26,"yyyymmdd"),"") | AO26: =B26&C26&D26 -> JohnBrewer | AP26: =LEFT(G26,FIND(",",G26)-1) -> Steen | AQ26: =IFERROR(VLOOKUP(AP26,D:P,13,FALSE),"No Reports to Name") -> 211062 | AR26: =AQ26=MID(H26,4,6) -> TRUE
A27: V0U | B27: James | D27: Brower | G27: Bate, Natalie | H27: V0U213037 | I27: JBrower@onebarnes.com | J27: browerj@cox.net | K27: Engineer, Application III | L27: 34736 | O27: Active | P27: 006769 | Q27: Monthly | R27: Full Time | S27: 025 | T27: 025-NGP Hyson Products | U27: Engineering | V27: 000718 | W27: Hyson Products | Z27: USA | AA27: S15 | AB27: FMG-S15 | AC27: =IF(ISBLANK(H27),VLOOKUP(P27,'US Supervisor Map'!A:D,4,FALSE),MID(H27,4,6)) -> 213037 | AD27: =IFERROR(VLOOKUP(T27,'Org Map'!A:E,4),"BU Description Not Mapped") -> 0096 | AE27: =IFERROR(VLOOKUP(V27,'Org Map'!C:E,3),"Home Department Code Not Mapped") -> 718 | AF27: =IFERROR(VLOOKUP(AA27,'Salary Map'!A:D,3,FALSE),"Salary Code Not Mapped") -> Default | AG27: =IFERROR(VLOOKUP(AA27,'Salary Map'!A:D,4,FALSE),"Salary Code Not Mapped") -> General | AH27: =IFERROR(VLOOKUP(Z27,'Country Map'!A:B,2,FALSE),"Legal Country Not Mapped") -> US | AI27: =IFERROR(VLOOKUP(X27,'Language Map'!A:C,3,FALSE),IFERROR(VLOOKUP(T27,'Org Map'!A:F,6,FALSE),"ADP and BU Language Code Not Mapped"))&AH27 -> en_US | AJ27: =IFERROR(VLOOKUP(T27,'Org Map'!A:G,7),"BU Currency Not Mapped") -> USD | AK27: =IF(ISBLANK(E27),"",TRIM(E27&" "&F27)) | AL27: =IFERROR(VLOOKUP(O27,'Status Map'!A:B,2,FALSE),"Position Status Not Mapped") -> Y | AM27: =IF(AL27="N",TEXT(M27,"yyyymmdd"),"") | AO27: =B27&C27&D27 -> JamesBrower | AP27: =LEFT(G27,FIND(",",G27)-1) -> Bate | AQ27: =IFERROR(VLOOKUP(AP27,D:P,13,FALSE),"No Reports to Name") -> 213037 | AR27: =AQ27=MID(H27,4,6) -> TRUE
A28: KSW | B28: R | C28: T | D28: Brown | J28: rtaeveis@gmail.com | K28: Assembler C | L28: 45887 | M28: 46031 | O28: Terminated | P28: 212370 | Q28: Biweekly | R28: Full Time | S28: 025 | T28: 025-NGP Hyson Products | U28: Assembly Hyson | V28: 000200 | W28: Hyson Products | Z28: USA | AA28: H05 | AB28: FMG-H05 | AC28: =IF(ISBLANK(H28),VLOOKUP(P28,'US Supervisor Map'!A:D,4,FALSE),MID(H28,4,6)) | AD28: =IFERROR(VLOOKUP(T28,'Org Map'!A:E,4),"BU Description Not Mapped") -> 0096 | AE28: =IFERROR(VLOOKUP(V28,'Org Map'!C:E,3),"Home Department Code Not Mapped") -> 200 | AF28: =IFERROR(VLOOKUP(AA28,'Salary Map'!A:D,3,FALSE),"Salary Code Not Mapped") -> Default | AG28: =IFERROR(VLOOKUP(AA28,'Salary Map'!A:D,4,FALSE),"Salary Code Not Mapped") -> General | AH28: =IFERROR(VLOOKUP(Z28,'Country Map'!A:B,2,FALSE),"Legal Country Not Mapped") -> US | AI28: =IFERROR(VLOOKUP(X28,'Language Map'!A:C,3,FALSE),IFERROR(VLOOKUP(T28,'Org Map'!A:F,6,FALSE),"ADP and BU Language Code Not Mapped"))&AH28 -> en_US | AJ28: =IFERROR(VLOOKUP(T28,'Org Map'!A:G,7),"BU Currency Not Mapped") -> USD | AK28: =IF(ISBLANK(E28),"",TRIM(E28&" "&F28)) | AL28: =IFERROR(VLOOKUP(O28,'Status Map'!A:B,2,FALSE),"Position Status Not Mapped") -> N | AM28: =IF(AL28="N",TEXT(M28,"yyyymmdd"),"") -> 20260109 | AN28: =IF(M28>AN23,"Fix and Include Record","Exclude record termination over 45 days ago") -> Fix and Include Record | AO28: =B28&C28&D28 -> RTBrown | AP28: =LEFT(G28,FIND(",",G28)-1) -> #VALUE! | AQ28: =IFERROR(VLOOKUP(AP28,D:P,13,FALSE),"No Reports to Name") -> No Reports to Name | AR28: =AQ28=MID(H28,4,6) -> FALSE
A29: KSY | B29: Trevor | D29: Bunch | G29: Valetta, David | H29: V0U211601 | I29: Tbunch@onebarnes.com | K29: Analyst, Pricing | L29: 45033 | O29: Active | P29: 209735 | Q29: Monthly | R29: Full Time | S29: 088 | T29: 088-AS Raymond | U29: Marketing | V29: 008300 | W29: AS Raymond | Z29: USA | AA29: S13 | AB29: FMG-S13 | AC29: =IF(ISBLANK(H29),VLOOKUP(P29,'US Supervisor Map'!A:D,4,FALSE),MID(H29,4,6)) -> 211601 | AD29: =IFERROR(VLOOKUP(T29,'Org Map'!A:E,4),"BU Description Not Mapped") -> 0088 | AE29: =IFERROR(VLOOKUP(V29,'Org Map'!C:E,3),"Home Department Code Not Mapped") -> 8300 | AF29: =IFERROR(VLOOKUP(AA29,'Salary Map'!A:D,3,FALSE),"Salary Code Not Mapped") -> Default | AG29: =IFERROR(VLOOKUP(AA29,'Salary Map'!A:D,4,FALSE),"Salary Code Not Mapped") -> General | AH29: =IFERROR(VLOOKUP(Z29,'Country Map'!A:B,2,FALSE),"Legal Country Not Mapped") -> US | AI29: =IFERROR(VLOOKUP(X29,'Language Map'!A:C,3,FALSE),IFERROR(VLOOKUP(T29,'Org Map'!A:F,6,FALSE),"ADP and BU Language Code Not Mapped"))&AH29 -> en_US | AJ29: =IFERROR(VLOOKUP(T29,'Org Map'!A:G,7),"BU Currency Not Mapped") -> USD | AK29: =IF(ISBLANK(E29),"",TRIM(E29&" "&F29)) | AL29: =IFERROR(VLOOKUP(O29,'Status Map'!A:B,2,FALSE),"Position Status Not Mapped") -> Y | AM29: =IF(AL29="N",TEXT(M29,"yyyymmdd"),"") | AO29: =B29&C29&D29 -> TrevorBunch | AP29: =LEFT(G29,FIND(",",G29)-1) -> Valetta | AQ29: =IFERROR(VLOOKUP(AP29,D:P,13,FALSE),"No Reports to Name") -> 211601 | AR29: =AQ29=MID(H29,4,6) -> TRUE
A30: KSY | B30: Mathew | C30: A | D30: Burchell | G30: Bailey, Jason | H30: KSY211464 | I30: mburchell@onebarnes.com | J30: mathew121709@outlook.com | K30: Supv, Warehouse I | L30: 45719 | O30: Active | P30: 211756 | Q30: Monthly | R30: Full Time | S30: 088 | T30: 088-AS Raymond | U30: Assembly | V30: 005100 | W30: AS Raymond | Z30: USA | AA30: S11 | AB30: FMG-S11 | AC30: =IF(ISBLANK(H30),VLOOKUP(P30,'US Supervisor Map'!A:D,4,FALSE),MID(H30,4,6)) -> 211464 | AD30: =IFERROR(VLOOKUP(T30,'Org Map'!A:E,4),"BU Description Not Mapped") -> 0088 | AE30: =IFERROR(VLOOKUP(V30,'Org Map'!C:E,3),"Home Department Code Not Mapped") -> 5100 | AF30: =IFERROR(VLOOKUP(AA30,'Salary Map'!A:D,3,FALSE),"Salary Code Not Mapped") -> Default | AG30: =IFERROR(VLOOKUP(AA30,'Salary Map'!A:D,4,FALSE),"Salary Code Not Mapped") -> General | AH30: =IFERROR(VLOOKUP(Z30,'Country Map'!A:B,2,FALSE),"Legal Country Not Mapped") -> US | AI30: =IFERROR(VLOOKUP(X30,'Language Map'!A:C,3,FALSE),IFERROR(VLOOKUP(T30,'Org Map'!A:F,6,FALSE),"ADP and BU Language Code Not Mapped"))&AH30 -> en_US | AJ30: =IFERROR(VLOOKUP(T30,'Org Map'!A:G,7),"BU Currency Not Mapped") -> USD | AK30: =IF(ISBLANK(E30),"",TRIM(E30&" "&F30)) | AL30: =IFERROR(VLOOKUP(O30,'Status Map'!A:B,2,FALSE),"Position Status Not Mapped") -> Y | AM30: =IF(AL30="N",TEXT(M30,"yyyymmdd"),"") | AO30: =B30&C30&D30 -> MathewABurchell | AP30: =LEFT(G30,FIND(",",G30)-1) -> Bailey | AQ30: =IFERROR(VLOOKUP(AP30,D:P,13,FALSE),"No Reports to Name") -> 902688 | AR30: =AQ30=MID(H30,4,6) -> FALSE
A31: KSW | B31: Kenneth | C31: D | D31: Butler | G31: Steen, Michael | H31: V0U211062 | J31: kennethbutler6459@yahoo.com | K31: Coord, Material B | L31: 44529 | O31: Active | P31: 206741 | Q31: Biweekly | R31: Full Time | S31: 025 | T31: 025-NGP Hyson Products | U31: Indirect General -Hyson | V31: 000400 | W31: Hyson Products | Z31: USA | AA31: H05 | AB31: FMG-H05 | AC31: =IF(ISBLANK(H31),VLOOKUP(P31,'US Supervisor Map'!A:D,4,FALSE),MID(H31,4,6)) -> 211062 | AD31: =IFERROR(VLOOKUP(T31,'Org Map'!A:E,4),"BU Description Not Mapped") -> 0096 | AE31: =IFERROR(VLOOKUP(V31,'Org Map'!C:E,3),"Home Department Code Not Mapped") -> 400 | AF31: =IFERROR(VLOOKUP(AA31,'Salary Map'!A:D,3,FALSE),"Salary Code Not Mapped") -> Default | AG31: =IFERROR(VLOOKUP(AA31,'Salary Map'!A:D,4,FALSE),"Salary Code Not Mapped") -> General | AH31: =IFERROR(VLOOKUP(Z31,'Country Map'!A:B,2,FALSE),"Legal Country Not Mapped") -> US | AI31: =IFERROR(VLOOKUP(X31,'Language Map'!A:C,3,FALSE),IFERROR(VLOOKUP(T31,'Org Map'!A:F,6,FALSE),"ADP and BU Language Code Not Mapped"))&AH31 -> en_US | AJ31: =IFERROR(VLOOKUP(T31,'Org Map'!A:G,7),"BU Currency Not Mapped") -> USD | AK31: =IF(ISBLANK(E31),"",TRIM(E31&" "&F31)) | AL31: =IFERROR(VLOOKUP(O31,'Status Map'!A:B,2,FALSE),"Position Status Not Mapped") -> Y | AM31: =IF(AL31="N",TEXT(M31,"yyyymmdd"),"") | AO31: =B31&C31&D31 -> KennethDButler | AP31: =LEFT(G31,FIND(",",G31)-1) -> Steen | AQ31: =IFERROR(VLOOKUP(AP31,D:P,13,FALSE),"No Reports to Name") -> 211062 | AR31: =AQ31=MID(H31,4,6) -> TRUE
A32: V0U | B32: Timothy | C32: D | D32: Carmichael | G32: Valetta, David | H32: V0U211601 | I32: TCarmichael@onebarnes.com | J32: tritectim@yahoo.com | K32: Analyst, Pricing | L32: 41386 | O32: Active | P32: 900826 | Q32: Monthly | R32: Full Time | S32: 025 | T32: 025-NGP Hyson Products | U32: Inside Sales | V32: 000850 | W32: Hyson Products | Z32: USA | AA32: S13 | AB32: FMG-S13 | AC32: =IF(ISBLANK(H32),VLOOKUP(P32,'US Supervisor Map'!A:D,4,FALSE),MID(H32,4,6)) -> 211601 | AD32: =IFERROR(VLOOKUP(T32,'Org Map'!A:E,4),"BU Description Not Mapped") -> 0096 | AE32: =IFERROR(VLOOKUP(V32,'Org Map'!C:E,3),"Home Department Code Not Mapped") -> 850 | AF32: =IFERROR(VLOOKUP(AA32,'Salary Map'!A:D,3,FALSE),"Salary Code Not Mapped") -> Default | AG32: =IFERROR(VLOOKUP(AA32,'Salary Map'!A:D,4,FALSE),"Salary Code Not Mapped") -> General | AH32: =IFERROR(VLOOKUP(Z32,'Country Map'!A:B,2,FALSE),"Legal Country Not Mapped") -> US | AI32: =IFERROR(VLOOKUP(X32,'Language Map'!A:C,3,FALSE),IFERROR(VLOOKUP(T32,'Org Map'!A:F,6,FALSE),"ADP and BU Language Code Not Mapped"))&AH32 -> en_US | AJ32: =IFERROR(VLOOKUP(T32,'Org Map'!A:G,7),"BU Currency Not Mapped") -> USD | AK32: =IF(ISBLANK(E32),"",TRIM(E32&" "&F32)) | AL32: =IFERROR(VLOOKUP(O32,'Status Map'!A:B,2,FALSE),"Position Status Not Mapped") -> Y | AM32: =IF(AL32="N",TEXT(M32,"yyyymmdd"),"") | AO32: =B32&C32&D32 -> TimothyDCarmichael | AP32: =LEFT(G32,FIND(",",G32)-1) -> Valetta | AQ32: =IFERROR(VLOOKUP(AP32,D:P,13,FALSE),"No Reports to Name") -> 211601 | AR32: =AQ32=MID(H32,4,6) -> TRUE
A33: V0U | B33: Jonathan | D33: Carter | G33: Bate, Natalie | H33: V0U213037 | I33: jcarter@onebarnes.com | J33: Jonathancarter201157@gmail.com | K33: Engineer, Production II | L33: 45971 | O33: Active | P33: 212737 | Q33: Monthly | R33: Full Time | S33: 025 | T33: 025-NGP Hyson Products | U33: Engineering | V33: 000718 | W33: Hyson Products | Z33: USA | AA33: S14 | AB33: FMG-S14 | AC33: =IF(ISBLANK(H33),VLOOKUP(P33,'US Supervisor Map'!A:D,4,FALSE),MID(H33,4,6)) -> 213037 | AD33: =IFERROR(VLOOKUP(T33,'Org Map'!A:E,4),"BU Description Not Mapped") -> 0096 | AE33: =IFERROR(VLOOKUP(V33,'Org Map'!C:E,3),"Home Department Code Not Mapped") -> 718 | AF33: =IFERROR(VLOOKUP(AA33,'Salary Map'!A:D,3,FALSE),"Salary Code Not Mapped") -> Default | AG33: =IFERROR(VLOOKUP(AA33,'Salary Map'!A:D,4,FALSE),"Salary Code Not Mapped") -> General | AH33: =IFERROR(VLOOKUP(Z33,'Country Map'!A:B,2,FALSE),"Legal Country Not Mapped") -> US | AI33: =IFERROR(VLOOKUP(X33,'Language Map'!A:C,3,FALSE),IFERROR(VLOOKUP(T33,'Org Map'!A:F,6,FALSE),"ADP and BU Language Code Not Mapped"))&AH33 -> en_US | AJ33: =IFERROR(VLOOKUP(T33,'Org Map'!A:G,7),"BU Currency Not Mapped") -> USD | AK33: =IF(ISBLANK(E33),"",TRIM(E33&" "&F33)) | AL33: =IFERROR(VLOOKUP(O33,'Status Map'!A:B,2,FALSE),"Position Status Not Mapped") -> Y | AM33: =IF(AL33="N",TEXT(M33,"yyyymmdd"),"") | AO33: =B33&C33&D33 -> JonathanCarter | AP33: =LEFT(G33,FIND(",",G33)-1) -> Bate | AQ33: =IFERROR(VLOOKUP(AP33,D:P,13,FALSE),"No Reports to Name") -> 213037 | AR33: =AQ33=MID(H33,4,6) -> TRUE
A34: KSY | B34: Tyler | D34: Cler | G34: Kemenah, Greg | H34: KSY211766 | I34: tcler@onebarnes.com | J34: tyler.cler@gmail.com | K34: Engineer, Production II | L34: 43192 | O34: Active | P34: 902435 | Q34: Monthly | R34: Full Time | S34: 088 | T34: 088-AS Raymond | U34: Admin-Engineering | V34: 009450 | W34: AS Raymond | X34: English | Y34: 4 | Z34: USA | AA34: S14 | AB34: FMG-S14 | AC34: =IF(ISBLANK(H34),VLOOKUP(P34,'US Supervisor Map'!A:D,4,FALSE),MID(H34,4,6)) -> 211766 | AD34: =IFERROR(VLOOKUP(T34,'Org Map'!A:E,4),"BU Description Not Mapped") -> 0088 | AE34: =IFERROR(VLOOKUP(V34,'Org Map'!C:E,3),"Home Department Code Not Mapped") -> 9450 | AF34: =IFERROR(VLOOKUP(AA34,'Salary Map'!A:D,3,FALSE),"Salary Code Not Mapped") -> Default | AG34: =IFERROR(VLOOKUP(AA34,'Salary Map'!A:D,4,FALSE),"Salary Code Not Mapped") -> General | AH34: =IFERROR(VLOOKUP(Z34,'Country Map'!A:B,2,FALSE),"Legal Country Not Mapped") -> US | AI34: =IFERROR(VLOOKUP(X34,'Language Map'!A:C,3,FALSE),IFERROR(VLOOKUP(T34,'Org Map'!A:F,6,FALSE),"ADP and BU Language Code Not Mapped"))&AH34 -> en_US | AJ34: =IFERROR(VLOOKUP(T34,'Org Map'!A:G,7),"BU Currency Not Mapped") -> USD | AK34: =IF(ISBLANK(E34),"",TRIM(E34&" "&F34)) | AL34: =IFERROR(VLOOKUP(O34,'Status Map'!A:B,2,FALSE),"Position Status Not Mapped") -> Y | AM34: =IF(AL34="N",TEXT(M34,"yyyymmdd"),"") | AO34: =B34&C34&D34 -> TylerCler | AP34: =LEFT(G34,FIND(",",G34)-1) -> Kemenah | AQ34: =IFERROR(VLOOKUP(AP34,D:P,13,FALSE),"No Reports to Name") -> 211766 | AR34: =AQ34=MID(H34,4,6) -> TRUE
A35: V0U | B35: Timothy | C35: E | D35: Clifton | I35: tclifton1@onebarnes.com | J35: clifford43431t@yahoo.com | K35: Tech, Quality I | L35: 46160 | M35: 46176 | O35: Terminated | P35: 213265 | Q35: Biweekly | R35: Full Time | S35: 025 | T35: 025-NGP Hyson Products | U35: Quality | V35: 000500 | W35: Hyson Products | Z35: USA | AA35: S10 | AB35: FMG-S10 | AC35: =IF(ISBLANK(H35),VLOOKUP(P35,'US Supervisor Map'!A:D,4,FALSE),MID(H35,4,6)) | AD35: =IFERROR(VLOOKUP(T35,'Org Map'!A:E,4),"BU Description Not Mapped") -> 0096 | AE35: =IFERROR(VLOOKUP(V35,'Org Map'!C:E,3),"Home Department Code Not Mapped") -> 500 | AF35: =IFERROR(VLOOKUP(AA35,'Salary Map'!A:D,3,FALSE),"Salary Code Not Mapped") -> Default | AG35: =IFERROR(VLOOKUP(AA35,'Salary Map'!A:D,4,FALSE),"Salary Code Not Mapped") -> General | AH35: =IFERROR(VLOOKUP(Z35,'Country Map'!A:B,2,FALSE),"Legal Country Not Mapped") -> US | AI35: =IFERROR(VLOOKUP(X35,'Language Map'!A:C,3,FALSE),IFERROR(VLOOKUP(T35,'Org Map'!A:F,6,FALSE),"ADP and BU Language Code Not Mapped"))&AH35 -> en_US | AJ35: =IFERROR(VLOOKUP(T35,'Org Map'!A:G,7),"BU Currency Not Mapped") -> USD | AK35: =IF(ISBLANK(E35),"",TRIM(E35&" "&F35)) | AL35: =IFERROR(VLOOKUP(O35,'Status Map'!A:B,2,FALSE),"Position Status Not Mapped") -> N | AM35: =IF(AL35="N",TEXT(M35,"yyyymmdd"),"") -> 20260603 | AN35: =IF(M35>AN30,"Fix and Include Record","Exclude record termination over 45 days ago") -> Fix and Include Record | AO35: =B35&C35&D35 -> TimothyEClifton | AP35: =LEFT(G35,FIND(",",G35)-1) -> #VALUE! | AQ35: =IFERROR(VLOOKUP(AP35,D:P,13,FALSE),"No Reports to Name") -> No Reports to Name | AR35: =AQ35=MID(H35,4,6) -> FALSE
A36: KSW | B36: Timothy | C36: E | D36: Clifton | G36: Leftrict, Wayne | H36: V0U210910 | I36: tclifton1@onebarnes.com | J36: clifford43431t@yahoo.com | K36: Tech, Quality I | L36: 46160 | O36: Active | P36: 213265 | Q36: Biweekly | R36: Full Time | S36: 025 | T36: 025-NGP Hyson Products | U36: Quality | V36: 000500 | W36: Hyson Products | Z36: USA | AA36: S10 | AB36: FMG-S10 | AC36: =IF(ISBLANK(H36),VLOOKUP(P36,'US Supervisor Map'!A:D,4,FALSE),MID(H36,4,6)) -> 210910 | AD36: =IFERROR(VLOOKUP(T36,'Org Map'!A:E,4),"BU Description Not Mapped") -> 0096 | AE36: =IFERROR(VLOOKUP(V36,'Org Map'!C:E,3),"Home Department Code Not Mapped") -> 500 | AF36: =IFERROR(VLOOKUP(AA36,'Salary Map'!A:D,3,FALSE),"Salary Code Not Mapped") -> Default | AG36: =IFERROR(VLOOKUP(AA36,'Salary Map'!A:D,4,FALSE),"Salary Code Not Mapped") -> General | AH36: =IFERROR(VLOOKUP(Z36,'Country Map'!A:B,2,FALSE),"Legal Country Not Mapped") -> US | AI36: =IFERROR(VLOOKUP(X36,'Language Map'!A:C,3,FALSE),IFERROR(VLOOKUP(T36,'Org Map'!A:F,6,FALSE),"ADP and BU Language Code Not Mapped"))&AH36 -> en_US | AJ36: =IFERROR(VLOOKUP(T36,'Org Map'!A:G,7),"BU Currency Not Mapped") -> USD | AK36: =IF(ISBLANK(E36),"",TRIM(E36&" "&F36)) | AL36: =IFERROR(VLOOKUP(O36,'Status Map'!A:B,2,FALSE),"Position Status Not Mapped") -> Y | AM36: =IF(AL36="N",TEXT(M36,"yyyymmdd"),"") | AO36: =B36&C36&D36 -> TimothyEClifton | AP36: =LEFT(G36,FIND(",",G36)-1) -> Leftrict | AQ36: =IFERROR(VLOOKUP(AP36,D:P,13,FALSE),"No Reports to Name") -> 210910 | AR36: =AQ36=MID(H36,4,6) -> TRUE
A37: V0U | B37: Timothy | C37: E | D37: Clifton | I37: tclifton1@onebarnes.com | J37: clifford43431t@yahoo.com | K37: Tech, Quality I | L37: 46160 | M37: 46176 | O37: Terminated | P37: 213265 | Q37: Monthly | R37: Full Time | S37: 025 | T37: 025-NGP Hyson Products | U37: Quality | V37: 000500 | W37: Hyson Products | Z37: USA | AA37: S10 | AB37: FMG-S10 | AC37: =IF(ISBLANK(H37),VLOOKUP(P37,'US Supervisor Map'!A:D,4,FALSE),MID(H37,4,6)) | AD37: =IFERROR(VLOOKUP(T37,'Org Map'!A:E,4),"BU Description Not Mapped") -> 0096 | AE37: =IFERROR(VLOOKUP(V37,'Org Map'!C:E,3),"Home Department Code Not Mapped") -> 500 | AF37: =IFERROR(VLOOKUP(AA37,'Salary Map'!A:D,3,FALSE),"Salary Code Not Mapped") -> Default | AG37: =IFERROR(VLOOKUP(AA37,'Salary Map'!A:D,4,FALSE),"Salary Code Not Mapped") -> General | AH37: =IFERROR(VLOOKUP(Z37,'Country Map'!A:B,2,FALSE),"Legal Country Not Mapped") -> US | AI37: =IFERROR(VLOOKUP(X37,'Language Map'!A:C,3,FALSE),IFERROR(VLOOKUP(T37,'Org Map'!A:F,6,FALSE),"ADP and BU Language Code Not Mapped"))&AH37 -> en_US | AJ37: =IFERROR(VLOOKUP(T37,'Org Map'!A:G,7),"BU Currency Not Mapped") -> USD | AK37: =IF(ISBLANK(E37),"",TRIM(E37&" "&F37)) | AL37: =IFERROR(VLOOKUP(O37,'Status Map'!A:B,2,FALSE),"Position Status Not Mapped") -> N | AM37: =IF(AL37="N",TEXT(M37,"yyyymmdd"),"") -> 20260603 | AN37: =IF(M37>AN32,"Fix and Include Record","Exclude record termination over 45 days ago") -> Fix and Include Record | AO37: =B37&C37&D37 -> TimothyEClifton | AP37: =LEFT(G37,FIND(",",G37)-1) -> #VALUE! | AQ37: =IFERROR(VLOOKUP(AP37,D:P,13,FALSE),"No Reports to Name") -> No Reports to Name | AR37: =AQ37=MID(H37,4,6) -> FALSE
A38: KSY | B38: Andrew | C38: J | D38: Creager | G38: Bailey, Jason | H38: KSY211766 | I38: acreager@onebarnes.com | K38: Mgr, Supply Chain III | L38: 45957 | O38: Active | P38: 212699 | Q38: Monthly | R38: Full Time | S38: 088 | T38: 088-AS Raymond | U38: Admin-Material Management | V38: 009400 | W38: AS Raymond | Z38: USA | AA38: S17 | AB38: FMG-S17 | AC38: =IF(ISBLANK(H38),VLOOKUP(P38,'US Supervisor Map'!A:D,4,FALSE),MID(H38,4,6)) -> 211766 | AD38: =IFERROR(VLOOKUP(T38,'Org Map'!A:E,4),"BU Description Not Mapped") -> 0088 | AE38: =IFERROR(VLOOKUP(V38,'Org Map'!C:E,3),"Home Department Code Not Mapped") -> 9400 | AF38: =IFERROR(VLOOKUP(AA38,'Salary Map'!A:D,3,FALSE),"Salary Code Not Mapped") -> Default | AG38: =IFERROR(VLOOKUP(AA38,'Salary Map'!A:D,4,FALSE),"Salary Code Not Mapped") -> General | AH38: =IFERROR(VLOOKUP(Z38,'Country Map'!A:B,2,FALSE),"Legal Country Not Mapped") -> US | AI38: =IFERROR(VLOOKUP(X38,'Language Map'!A:C,3,FALSE),IFERROR(VLOOKUP(T38,'Org Map'!A:F,6,FALSE),"ADP and BU Language Code Not Mapped"))&AH38 -> en_US | AJ38: =IFERROR(VLOOKUP(T38,'Org Map'!A:G,7),"BU Currency Not Mapped") -> USD | AK38: =IF(ISBLANK(E38),"",TRIM(E38&" "&F38)) | AL38: =IFERROR(VLOOKUP(O38,'Status Map'!A:B,2,FALSE),"Position Status Not Mapped") -> Y | AM38: =IF(AL38="N",TEXT(M38,"yyyymmdd"),"") | AO38: =B38&C38&D38 -> AndrewJCreager | AP38: =LEFT(G38,FIND(",",G38)-1) -> Bailey | AQ38: =IFERROR(VLOOKUP(AP38,D:P,13,FALSE),"No Reports to Name") -> 902688 | AR38: =AQ38=MID(H38,4,6) -> FALSE
A39: KSY | B39: Carla | C39: J | D39: Cunningham | I39: ccunningham@onebarnes.com | J39: springgirl3@sbcglobal.net | L39: 46022 | M39: 46022 | O39: Terminated | P39: 007633 | Q39: Monthly | R39: Full Time | W39: AS Raymond | Z39: USA | AC39: =IF(ISBLANK(H39),VLOOKUP(P39,'US Supervisor Map'!A:D,4,FALSE),MID(H39,4,6)) | AD39: =IFERROR(VLOOKUP(T39,'Org Map'!A:E,4),"BU Description Not Mapped") -> BU Description Not Mapped | AE39: =IFERROR(VLOOKUP(V39,'Org Map'!C:E,3),"Home Department Code Not Mapped") -> Home Department Code Not Mapped | AF39: =IFERROR(VLOOKUP(AA39,'Salary Map'!A:D,3,FALSE),"Salary Code Not Mapped") -> Salary Code Not Mapped | AG39: =IFERROR(VLOOKUP(AA39,'Salary Map'!A:D,4,FALSE),"Salary Code Not Mapped") -> Salary Code Not Mapped | AH39: =IFERROR(VLOOKUP(Z39,'Country Map'!A:B,2,FALSE),"Legal Country Not Mapped") -> US | AI39: =IFERROR(VLOOKUP(X39,'Language Map'!A:C,3,FALSE),IFERROR(VLOOKUP(T39,'Org Map'!A:F,6,FALSE),"ADP and BU Language Code Not Mapped"))&AH39 -> ADP and BU Language Code Not MappedUS | AJ39: =IFERROR(VLOOKUP(T39,'Org Map'!A:G,7),"BU Currency Not Mapped") -> BU Currency Not Mapped | AK39: =IF(ISBLANK(E39),"",TRIM(E39&" "&F39)) | AL39: =IFERROR(VLOOKUP(O39,'Status Map'!A:B,2,FALSE),"Position Status Not Mapped") -> N | AM39: =IF(AL39="N",TEXT(M39,"yyyymmdd"),"") -> 20251231 | AN39: =IF(M39>AN34,"Fix and Include Record","Exclude record termination over 45 days ago") -> Fix and Include Record | AO39: =B39&C39&D39 -> CarlaJCunningham | AP39: =LEFT(G39,FIND(",",G39)-1) -> #VALUE! | AQ39: =IFERROR(VLOOKUP(AP39,D:P,13,FALSE),"No Reports to Name") -> No Reports to Name | AR39: =AQ39=MID(H39,4,6) -> FALSE
B40: Carla | C40: J | D40: Cunningham | I40: ccunningham@onebarnes.com | J40: springgirl3@sbcglobal.net | L40: 46022 | M40: 46023 | O40: Terminated | Q40: Weekly | Z40: USA | AC40: =IF(ISBLANK(H40),VLOOKUP(P40,'US Supervisor Map'!A:D,4,FALSE),MID(H40,4,6)) | AD40: =IFERROR(VLOOKUP(T40,'Org Map'!A:E,4),"BU Description Not Mapped") -> BU Description Not Mapped | AE40: =IFERROR(VLOOKUP(V40,'Org Map'!C:E,3),"Home Department Code Not Mapped") -> Home Department Code Not Mapped | AF40: =IFERROR(VLOOKUP(AA40,'Salary Map'!A:D,3,FALSE),"Salary Code Not Mapped") -> Salary Code Not Mapped | AG40: =IFERROR(VLOOKUP(AA40,'Salary Map'!A:D,4,FALSE),"Salary Code Not Mapped") -> Salary Code Not Mapped | AH40: =IFERROR(VLOOKUP(Z40,'Country Map'!A:B,2,FALSE),"Legal Country Not Mapped") -> US | AI40: =IFERROR(VLOOKUP(X40,'Language Map'!A:C,3,FALSE),IFERROR(VLOOKUP(T40,'Org Map'!A:F,6,FALSE),"ADP and BU Language Code Not Mapped"))&AH40 -> ADP and BU Language Code Not MappedUS | AJ40: =IFERROR(VLOOKUP(T40,'Org Map'!A:G,7),"BU Currency Not Mapped") -> BU Currency Not Mapped | AK40: =IF(ISBLANK(E40),"",TRIM(E40&" "&F40)) | AL40: =IFERROR(VLOOKUP(O40,'Status Map'!A:B,2,FALSE),"Position Status Not Mapped") -> N | AM40: =IF(AL40="N",TEXT(M40,"yyyymmdd"),"") -> 20260101 | AN40: =IF(M40>AN35,"Fix and Include Record","Exclude record termination over 45 days ago") -> Exclude record termination over 45 days ago | AO40: =B40&C40&D40 -> CarlaJCunningham | AP40: =LEFT(G40,FIND(",",G40)-1) -> #VALUE! | AQ40: =IFERROR(VLOOKUP(AP40,D:P,13,FALSE),"No Reports to Name") -> No Reports to Name | AR40: =AQ40=MID(H40,4,6) -> FALSE
A41: KSX | B41: Brenda | C41: J | D41: Daniel | H41: KSY202533 | J41: brendajdaniel@gmail.com | K41: Rep, Customer Service I | L41: 46160 | M41: 46181 | O41: Terminated | P41: 213236 | Q41: Biweekly | R41: Full Time | S41: 088 | T41: 088-AS Raymond | U41: Inside Sales | V41: 008100 | W41: AS Raymond | Z41: USA | AA41: S08 | AB41: FMG-S08 | AC41: =IF(ISBLANK(H41),VLOOKUP(P41,'US Supervisor Map'!A:D,4,FALSE),MID(H41,4,6)) -> 202533 | AD41: =IFERROR(VLOOKUP(T41,'Org Map'!A:E,4),"BU Description Not Mapped") -> 0088 | AE41: =IFERROR(VLOOKUP(V41,'Org Map'!C:E,3),"Home Department Code Not Mapped") -> 8100 | AF41: =IFERROR(VLOOKUP(AA41,'Salary Map'!A:D,3,FALSE),"Salary Code Not Mapped") -> Default | AG41: =IFERROR(VLOOKUP(AA41,'Salary Map'!A:D,4,FALSE),"Salary Code Not Mapped") -> General | AH41: =IFERROR(VLOOKUP(Z41,'Country Map'!A:B,2,FALSE),"Legal Country Not Mapped") -> US | AI41: =IFERROR(VLOOKUP(X41,'Language Map'!A:C,3,FALSE),IFERROR(VLOOKUP(T41,'Org Map'!A:F,6,FALSE),"ADP and BU Language Code Not Mapped"))&AH41 -> en_US | AJ41: =IFERROR(VLOOKUP(T41,'Org Map'!A:G,7),"BU Currency Not Mapped") -> USD | AK41: =IF(ISBLANK(E41),"",TRIM(E41&" "&F41)) | AL41: =IFERROR(VLOOKUP(O41,'Status Map'!A:B,2,FALSE),"Position Status Not Mapped") -> N | AM41: =IF(AL41="N",TEXT(M41,"yyyymmdd"),"") -> 20260608 | AN41: =IF(M41>AN36,"Fix and Include Record","Exclude record termination over 45 days ago") -> Fix and Include Record | AO41: =B41&C41&D41 -> BrendaJDaniel | AP41: =LEFT(G41,FIND(",",G41)-1) -> #VALUE! | AQ41: =IFERROR(VLOOKUP(AP41,D:P,13,FALSE),"No Reports to Name") -> No Reports to Name | AR41: =AQ41=MID(H41,4,6) -> FALSE
A42: V0U | B42: Demetrius | C42: A | D42: Daniels | I42: ddaniels@kaller.com | J42: mrtruth75@gmail.com | K42: Rep, Customer Service II | L42: 37424 | M42: 46175 | O42: Terminated | P42: 006774 | Q42: Biweekly | R42: Full Time | S42: 025 | T42: 025-NGP Hyson Products | U42: Inside Sales | V42: 000850 | W42: Hyson Products | Z42: USA | AA42: S10 | AB42: FMG-S10 | AC42: =IF(ISBLANK(H42),VLOOKUP(P42,'US Supervisor Map'!A:D,4,FALSE),MID(H42,4,6)) | AD42: =IFERROR(VLOOKUP(T42,'Org Map'!A:E,4),"BU Description Not Mapped") -> 0096 | AE42: =IFERROR(VLOOKUP(V42,'Org Map'!C:E,3),"Home Department Code Not Mapped") -> 850 | AF42: =IFERROR(VLOOKUP(AA42,'Salary Map'!A:D,3,FALSE),"Salary Code Not Mapped") -> Default | AG42: =IFERROR(VLOOKUP(AA42,'Salary Map'!A:D,4,FALSE),"Salary Code Not Mapped") -> General | AH42: =IFERROR(VLOOKUP(Z42,'Country Map'!A:B,2,FALSE),"Legal Country Not Mapped") -> US | AI42: =IFERROR(VLOOKUP(X42,'Language Map'!A:C,3,FALSE),IFERROR(VLOOKUP(T42,'Org Map'!A:F,6,FALSE),"ADP and BU Language Code Not Mapped"))&AH42 -> en_US | AJ42: =IFERROR(VLOOKUP(T42,'Org Map'!A:G,7),"BU Currency Not Mapped") -> USD | AK42: =IF(ISBLANK(E42),"",TRIM(E42&" "&F42)) | AL42: =IFERROR(VLOOKUP(O42,'Status Map'!A:B,2,FALSE),"Position Status Not Mapped") -> N | AM42: =IF(AL42="N",TEXT(M42,"yyyymmdd"),"") -> 20260602 | AN42: =IF(M42>AN37,"Fix and Include Record","Exclude record termination over 45 days ago") -> Exclude record termination over 45 days ago | AO42: =B42&C42&D42 -> DemetriusADaniels | AP42: =LEFT(G42,FIND(",",G42)-1) -> #VALUE! | AQ42: =IFERROR(VLOOKUP(AP42,D:P,13,FALSE),"No Reports to Name") -> No Reports to Name | AR42: =AQ42=MID(H42,4,6) -> FALSE
A43: V0U | B43: Demetrius | C43: A | D43: Daniels | I43: ddaniels@kaller.com | J43: mrtruth75@gmail.com | K43: Rep, Customer Service II | L43: 37424 | M43: 46175 | O43: Terminated | P43: 006774 | Q43: Monthly | R43: Full Time | S43: 025 | T43: 025-NGP Hyson Products | U43: Inside Sales | V43: 000850 | W43: Hyson Products | Z43: USA | AA43: S10 | AB43: FMG-S10 | AC43: =IF(ISBLANK(H43),VLOOKUP(P43,'US Supervisor Map'!A:D,4,FALSE),MID(H43,4,6)) | AD43: =IFERROR(VLOOKUP(T43,'Org Map'!A:E,4),"BU Description Not Mapped") -> 0096 | AE43: =IFERROR(VLOOKUP(V43,'Org Map'!C:E,3),"Home Department Code Not Mapped") -> 850 | AF43: =IFERROR(VLOOKUP(AA43,'Salary Map'!A:D,3,FALSE),"Salary Code Not Mapped") -> Default | AG43: =IFERROR(VLOOKUP(AA43,'Salary Map'!A:D,4,FALSE),"Salary Code Not Mapped") -> General | AH43: =IFERROR(VLOOKUP(Z43,'Country Map'!A:B,2,FALSE),"Legal Country Not Mapped") -> US | AI43: =IFERROR(VLOOKUP(X43,'Language Map'!A:C,3,FALSE),IFERROR(VLOOKUP(T43,'Org Map'!A:F,6,FALSE),"ADP and BU Language Code Not Mapped"))&AH43 -> en_US | AJ43: =IFERROR(VLOOKUP(T43,'Org Map'!A:G,7),"BU Currency Not Mapped") -> USD | AK43: =IF(ISBLANK(E43),"",TRIM(E43&" "&F43)) | AL43: =IFERROR(VLOOKUP(O43,'Status Map'!A:B,2,FALSE),"Position Status Not Mapped") -> N | AM43: =IF(AL43="N",TEXT(M43,"yyyymmdd"),"") -> 20260602 | AN43: =IF(M43>AN38,"Fix and Include Record","Exclude record termination over 45 days ago") -> Fix and Include Record | AO43: =B43&C43&D43 -> DemetriusADaniels | AP43: =LEFT(G43,FIND(",",G43)-1) -> #VALUE! | AQ43: =IFERROR(VLOOKUP(AP43,D:P,13,FALSE),"No Reports to Name") -> No Reports to Name | AR43: =AQ43=MID(H43,4,6) -> FALSE
A44: KSW | B44: Demetrius | C44: A | D44: Daniels | G44: Wallace, Derron | H44: V0U211998 | I44: ddaniels@kaller.com | J44: mrtruth75@gmail.com | K44: Rep, Customer Service II | L44: 37424 | O44: Active | P44: 006774 | Q44: Biweekly | R44: Full Time | S44: 025 | T44: 025-NGP Hyson Products | U44: Inside Sales | V44: 000850 | W44: Hyson Products | Z44: USA | AA44: S10 | AB44: FMG-S10 | AC44: =IF(ISBLANK(H44),VLOOKUP(P44,'US Supervisor Map'!A:D,4,FALSE),MID(H44,4,6)) -> 211998 | AD44: =IFERROR(VLOOKUP(T44,'Org Map'!A:E,4),"BU Description Not Mapped") -> 0096 | AE44: =IFERROR(VLOOKUP(V44,'Org Map'!C:E,3),"Home Department Code Not Mapped") -> 850 | AF44: =IFERROR(VLOOKUP(AA44,'Salary Map'!A:D,3,FALSE),"Salary Code Not Mapped") -> Default | AG44: =IFERROR(VLOOKUP(AA44,'Salary Map'!A:D,4,FALSE),"Salary Code Not Mapped") -> General | AH44: =IFERROR(VLOOKUP(Z44,'Country Map'!A:B,2,FALSE),"Legal Country Not Mapped") -> US | AI44: =IFERROR(VLOOKUP(X44,'Language Map'!A:C,3,FALSE),IFERROR(VLOOKUP(T44,'Org Map'!A:F,6,FALSE),"ADP and BU Language Code Not Mapped"))&AH44 -> en_US | AJ44: =IFERROR(VLOOKUP(T44,'Org Map'!A:G,7),"BU Currency Not Mapped") -> USD | AK44: =IF(ISBLANK(E44),"",TRIM(E44&" "&F44)) | AL44: =IFERROR(VLOOKUP(O44,'Status Map'!A:B,2,FALSE),"Position Status Not Mapped") -> Y | AM44: =IF(AL44="N",TEXT(M44,"yyyymmdd"),"") | AO44: =B44&C44&D44 -> DemetriusADaniels | AP44: =LEFT(G44,FIND(",",G44)-1) -> Wallace | AQ44: =IFERROR(VLOOKUP(AP44,D:P,13,FALSE),"No Reports to Name") -> 211998 | AR44: =AQ44=MID(H44,4,6) -> TRUE
A45: KSX | B45: Crystal | D45: Dedes | G45: LaPlante, Derek | H45: KSY211736 | I45: cdedes@onebarnes.com | J45: criss4200@yahoo.com | K45: Assistant, Warehouse II | L45: 44620 | O45: Active | P45: 207391 | Q45: Biweekly | R45: Full Time | S45: 088 | T45: 088-AS Raymond | U45: FG Warehouse | V45: 005200 | W45: AS Raymond | Z45: USA | AA45: S05 | AB45: FMG-S05 | AC45: =IF(ISBLANK(H45),VLOOKUP(P45,'US Supervisor Map'!A:D,4,FALSE),MID(H45,4,6)) -> 211736 | AD45: =IFERROR(VLOOKUP(T45,'Org Map'!A:E,4),"BU Description Not Mapped") -> 0088 | AE45: =IFERROR(VLOOKUP(V45,'Org Map'!C:E,3),"Home Department Code Not Mapped") -> 5200 | AF45: =IFERROR(VLOOKUP(AA45,'Salary Map'!A:D,3,FALSE),"Salary Code Not Mapped") -> Default | AG45: =IFERROR(VLOOKUP(AA45,'Salary Map'!A:D,4,FALSE),"Salary Code Not Mapped") -> General | AH45: =IFERROR(VLOOKUP(Z45,'Country Map'!A:B,2,FALSE),"Legal Country Not Mapped") -> US | AI45: =IFERROR(VLOOKUP(X45,'Language Map'!A:C,3,FALSE),IFERROR(VLOOKUP(T45,'Org Map'!A:F,6,FALSE),"ADP and BU Language Code Not Mapped"))&AH45 -> en_US | AJ45: =IFERROR(VLOOKUP(T45,'Org Map'!A:G,7),"BU Currency Not Mapped") -> USD | AK45: =IF(ISBLANK(E45),"",TRIM(E45&" "&F45)) | AL45: =IFERROR(VLOOKUP(O45,'Status Map'!A:B,2,FALSE),"Position Status Not Mapped") -> Y | AM45: =IF(AL45="N",TEXT(M45,"yyyymmdd"),"") | AO45: =B45&C45&D45 -> CrystalDedes | AP45: =LEFT(G45,FIND(",",G45)-1) -> LaPlante | AQ45: =IFERROR(VLOOKUP(AP45,D:P,13,FALSE),"No Reports to Name") -> 211736 | AR45: =AQ45=MID(H45,4,6) -> TRUE
A46: KSW | B46: Anthony | D46: Desillas | J46: desillasa@yahoo.com | K46: Lathe Operator | L46: 45859 | M46: 46046 | O46: Terminated | P46: 212244 | Q46: Biweekly | R46: Full Time | S46: 025 | T46: 025-NGP Hyson Products | U46: CNC Lathe Hyson | V46: 000100 | W46: Hyson Products | Z46: USA | AA46: H07 | AB46: FMG-H07 | AC46: =IF(ISBLANK(H46),VLOOKUP(P46,'US Supervisor Map'!A:D,4,FALSE),MID(H46,4,6)) | AD46: =IFERROR(VLOOKUP(T46,'Org Map'!A:E,4),"BU Description Not Mapped") -> 0096 | AE46: =IFERROR(VLOOKUP(V46,'Org Map'!C:E,3),"Home Department Code Not Mapped") -> 100 | AF46: =IFERROR(VLOOKUP(AA46,'Salary Map'!A:D,3,FALSE),"Salary Code Not Mapped") -> Default | AG46: =IFERROR(VLOOKUP(AA46,'Salary Map'!A:D,4,FALSE),"Salary Code Not Mapped") -> General | AH46: =IFERROR(VLOOKUP(Z46,'Country Map'!A:B,2,FALSE),"Legal Country Not Mapped") -> US | AI46: =IFERROR(VLOOKUP(X46,'Language Map'!A:C,3,FALSE),IFERROR(VLOOKUP(T46,'Org Map'!A:F,6,FALSE),"ADP and BU Language Code Not Mapped"))&AH46 -> en_US | AJ46: =IFERROR(VLOOKUP(T46,'Org Map'!A:G,7),"BU Currency Not Mapped") -> USD | AK46: =IF(ISBLANK(E46),"",TRIM(E46&" "&F46)) | AL46: =IFERROR(VLOOKUP(O46,'Status Map'!A:B,2,FALSE),"Position Status Not Mapped") -> N | AM46: =IF(AL46="N",TEXT(M46,"yyyymmdd"),"") -> 20260124 | AN46: =IF(M46>AN41,"Fix and Include Record","Exclude record termination over 45 days ago") -> Exclude record termination over 45 days ago | AO46: =B46&C46&D46 -> AnthonyDesillas | AP46: =LEFT(G46,FIND(",",G46)-1) -> #VALUE! | AQ46: =IFERROR(VLOOKUP(AP46,D:P,13,FALSE),"No Reports to Name") -> No Reports to Name | AR46: =AQ46=MID(H46,4,6) -> FALSE
A47: KSX | B47: Amir | D47: Dillard | G47: Burchell, Mathew | H47: KSY211756 | I47: adillard1@onebarnes.com | J47: amirdillard4@gmail.com | K47: Assistant, Warehouse II | L47: 45754 | O47: Active | P47: 211895 | Q47: Biweekly | R47: Full Time | S47: 088 | T47: 088-AS Raymond | U47: Assembly | V47: 005100 | W47: AS Raymond | Z47: USA | AA47: S05 | AB47: FMG-S05 | AC47: =IF(ISBLANK(H47),VLOOKUP(P47,'US Supervisor Map'!A:D,4,FALSE),MID(H47,4,6)) -> 211756 | AD47: =IFERROR(VLOOKUP(T47,'Org Map'!A:E,4),"BU Description Not Mapped") -> 0088 | AE47: =IFERROR(VLOOKUP(V47,'Org Map'!C:E,3),"Home Department Code Not Mapped") -> 5100 | AF47: =IFERROR(VLOOKUP(AA47,'Salary Map'!A:D,3,FALSE),"Salary Code Not Mapped") -> Default | AG47: =IFERROR(VLOOKUP(AA47,'Salary Map'!A:D,4,FALSE),"Salary Code Not Mapped") -> General | AH47: =IFERROR(VLOOKUP(Z47,'Country Map'!A:B,2,FALSE),"Legal Country Not Mapped") -> US | AI47: =IFERROR(VLOOKUP(X47,'Language Map'!A:C,3,FALSE),IFERROR(VLOOKUP(T47,'Org Map'!A:F,6,FALSE),"ADP and BU Language Code Not Mapped"))&AH47 -> en_US | AJ47: =IFERROR(VLOOKUP(T47,'Org Map'!A:G,7),"BU Currency Not Mapped") -> USD | AK47: =IF(ISBLANK(E47),"",TRIM(E47&" "&F47)) | AL47: =IFERROR(VLOOKUP(O47,'Status Map'!A:B,2,FALSE),"Position Status Not Mapped") -> Y | AM47: =IF(AL47="N",TEXT(M47,"yyyymmdd"),"") | AO47: =B47&C47&D47 -> AmirDillard | AP47: =LEFT(G47,FIND(",",G47)-1) -> Burchell | AQ47: =IFERROR(VLOOKUP(AP47,D:P,13,FALSE),"No Reports to Name") -> 211756 | AR47: =AQ47=MID(H47,4,6) -> TRUE
A48: KSW | B48: David | C48: A | D48: Dixon | G48: Steen, Michael | H48: V0U211062 | J48: chevelle2212@aol.com | K48: Machinist A | L48: 35604 | O48: Active | P48: 004330 | Q48: Biweekly | R48: Full Time | S48: 025 | T48: 025-NGP Hyson Products | U48: CNC Lathe Hyson | V48: 000100 | W48: Hyson Products | Z48: USA | AA48: H08 | AB48: FMG-H08 | AC48: =IF(ISBLANK(H48),VLOOKUP(P48,'US Supervisor Map'!A:D,4,FALSE),MID(H48,4,6)) -> 211062 | AD48: =IFERROR(VLOOKUP(T48,'Org Map'!A:E,4),"BU Description Not Mapped") -> 0096 | AE48: =IFERROR(VLOOKUP(V48,'Org Map'!C:E,3),"Home Department Code Not Mapped") -> 100 | AF48: =IFERROR(VLOOKUP(AA48,'Salary Map'!A:D,3,FALSE),"Salary Code Not Mapped") -> Default | AG48: =IFERROR(VLOOKUP(AA48,'Salary Map'!A:D,4,FALSE),"Salary Code Not Mapped") -> General | AH48: =IFERROR(VLOOKUP(Z48,'Country Map'!A:B,2,FALSE),"Legal Country Not Mapped") -> US | AI48: =IFERROR(VLOOKUP(X48,'Language Map'!A:C,3,FALSE),IFERROR(VLOOKUP(T48,'Org Map'!A:F,6,FALSE),"ADP and BU Language Code Not Mapped"))&AH48 -> en_US | AJ48: =IFERROR(VLOOKUP(T48,'Org Map'!A:G,7),"BU Currency Not Mapped") -> USD | AK48: =IF(ISBLANK(E48),"",TRIM(E48&" "&F48)) | AL48: =IFERROR(VLOOKUP(O48,'Status Map'!A:B,2,FALSE),"Position Status Not Mapped") -> Y | AM48: =IF(AL48="N",TEXT(M48,"yyyymmdd"),"") | AO48: =B48&C48&D48 -> DavidADixon | AP48: =LEFT(G48,FIND(",",G48)-1) -> Steen | AQ48: =IFERROR(VLOOKUP(AP48,D:P,13,FALSE),"No Reports to Name") -> 211062 | AR48: =AQ48=MID(H48,4,6) -> TRUE
A49: KSW | B49: Michael | C49: D | D49: Ellison | G49: Wallace, Derron | H49: V0U211998 | J49: ellison.d.mike.me@gmail.com | K49: Assembler C | L49: 45806 | O49: Active | P49: 212072 | Q49: Biweekly | R49: Full Time | S49: 025 | T49: 025-NGP Hyson Products | U49: Assembly Hyson | V49: 000200 | W49: Hyson Products | Z49: USA | AA49: H05 | AB49: FMG-H05 | AC49: =IF(ISBLANK(H49),VLOOKUP(P49,'US Supervisor Map'!A:D,4,FALSE),MID(H49,4,6)) -> 211998 | AD49: =IFERROR(VLOOKUP(T49,'Org Map'!A:E,4),"BU Description Not Mapped") -> 0096 | AE49: =IFERROR(VLOOKUP(V49,'Org Map'!C:E,3),"Home Department Code Not Mapped") -> 200 | AF49: =IFERROR(VLOOKUP(AA49,'Salary Map'!A:D,3,FALSE),"Salary Code Not Mapped") -> Default | AG49: =IFERROR(VLOOKUP(AA49,'Salary Map'!A:D,4,FALSE),"Salary Code Not Mapped") -> General | AH49: =IFERROR(VLOOKUP(Z49,'Country Map'!A:B,2,FALSE),"Legal Country Not Mapped") -> US | AI49: =IFERROR(VLOOKUP(X49,'Language Map'!A:C,3,FALSE),IFERROR(VLOOKUP(T49,'Org Map'!A:F,6,FALSE),"ADP and BU Language Code Not Mapped"))&AH49 -> en_US | AJ49: =IFERROR(VLOOKUP(T49,'Org Map'!A:G,7),"BU Currency Not Mapped") -> USD | AK49: =IF(ISBLANK(E49),"",TRIM(E49&" "&F49)) | AL49: =IFERROR(VLOOKUP(O49,'Status Map'!A:B,2,FALSE),"Position Status Not Mapped") -> Y | AM49: =IF(AL49="N",TEXT(M49,"yyyymmdd"),"") | AO49: =B49&C49&D49 -> MichaelDEllison | AP49: =LEFT(G49,FIND(",",G49)-1) -> Wallace | AQ49: =IFERROR(VLOOKUP(AP49,D:P,13,FALSE),"No Reports to Name") -> 211998 | AR49: =AQ49=MID(H49,4,6) -> TRUE
A50: KSX | B50: John | D50: Eward | G50: Rogers, Wayne | H50: KSY207487 | I50: jeward@onebarnes.com | J50: johneward88@gmail.com | K50: Coord, Inventory Ctrl I | L50: 46034 | O50: Active | P50: 212921 | Q50: Biweekly | R50: Full Time | S50: 088 | T50: 088-AS Raymond | U50: FG Warehouse | V50: 005200 | W50: AS Raymond | Z50: USA | AA50: S08 | AB50: FMG-S08 | AC50: =IF(ISBLANK(H50),VLOOKUP(P50,'US Supervisor Map'!A:D,4,FALSE),MID(H50,4,6)) -> 207487 | AD50: =IFERROR(VLOOKUP(T50,'Org Map'!A:E,4),"BU Description Not Mapped") -> 0088 | AE50: =IFERROR(VLOOKUP(V50,'Org Map'!C:E,3),"Home Department Code Not Mapped") -> 5200 | AF50: =IFERROR(VLOOKUP(AA50,'Salary Map'!A:D,3,FALSE),"Salary Code Not Mapped") -> Default | AG50: =IFERROR(VLOOKUP(AA50,'Salary Map'!A:D,4,FALSE),"Salary Code Not Mapped") -> General | AH50: =IFERROR(VLOOKUP(Z50,'Country Map'!A:B,2,FALSE),"Legal Country Not Mapped") -> US | AI50: =IFERROR(VLOOKUP(X50,'Language Map'!A:C,3,FALSE),IFERROR(VLOOKUP(T50,'Org Map'!A:F,6,FALSE),"ADP and BU Language Code Not Mapped"))&AH50 -> en_US | AJ50: =IFERROR(VLOOKUP(T50,'Org Map'!A:G,7),"BU Currency Not Mapped") -> USD | AK50: =IF(ISBLANK(E50),"",TRIM(E50&" "&F50)) | AL50: =IFERROR(VLOOKUP(O50,'Status Map'!A:B,2,FALSE),"Position Status Not Mapped") -> Y | AM50: =IF(AL50="N",TEXT(M50,"yyyymmdd"),"") | AO50: =B50&C50&D50 -> JohnEward | AP50: =LEFT(G50,FIND(",",G50)-1) -> Rogers | AQ50: =IFERROR(VLOOKUP(AP50,D:P,13,FALSE),"No Reports to Name") -> 207487 | AR50: =AQ50=MID(H50,4,6) -> TRUE
A51: V0U | B51: Donald | C51: C | D51: Felts | G51: Wilkins, William | H51: V0U901934 | I51: cfelts@onebarnes.com | J51: dcfelts@comcast.net | K51: Mgr, Sales | L51: 43885 | O51: Active | P51: 201958 | Q51: Monthly | R51: Full Time | S51: 025 | T51: 025-NGP Hyson Products | U51: Outside Sales | V51: 000820 | W51: Hyson Products | Z51: USA | AA51: S15 | AB51: FMG-S15 | AC51: =IF(ISBLANK(H51),VLOOKUP(P51,'US Supervisor Map'!A:D,4,FALSE),MID(H51,4,6)) -> 901934 | AD51: =IFERROR(VLOOKUP(T51,'Org Map'!A:E,4),"BU Description Not Mapped") -> 0096 | AE51: =IFERROR(VLOOKUP(V51,'Org Map'!C:E,3),"Home Department Code Not Mapped") -> 820 | AF51: =IFERROR(VLOOKUP(AA51,'Salary Map'!A:D,3,FALSE),"Salary Code Not Mapped") -> Default | AG51: =IFERROR(VLOOKUP(AA51,'Salary Map'!A:D,4,FALSE),"Salary Code Not Mapped") -> General | AH51: =IFERROR(VLOOKUP(Z51,'Country Map'!A:B,2,FALSE),"Legal Country Not Mapped") -> US | AI51: =IFERROR(VLOOKUP(X51,'Language Map'!A:C,3,FALSE),IFERROR(VLOOKUP(T51,'Org Map'!A:F,6,FALSE),"ADP and BU Language Code Not Mapped"))&AH51 -> en_US | AJ51: =IFERROR(VLOOKUP(T51,'Org Map'!A:G,7),"BU Currency Not Mapped") -> USD | AK51: =IF(ISBLANK(E51),"",TRIM(E51&" "&F51)) | AL51: =IFERROR(VLOOKUP(O51,'Status Map'!A:B,2,FALSE),"Position Status Not Mapped") -> Y | AM51: =IF(AL51="N",TEXT(M51,"yyyymmdd"),"") | AO51: =B51&C51&D51 -> DonaldCFelts | AP51: =LEFT(G51,FIND(",",G51)-1) -> Wilkins | AQ51: =IFERROR(VLOOKUP(AP51,D:P,13,FALSE),"No Reports to Name") -> 901934 | AR51: =AQ51=MID(H51,4,6) -> TRUE
A52: KSY | B52: Jeffrey | C52: L | D52: Finch | G52: Erdogan, Mehmet | I52: Jfinch@onebarnes.com | J52: jefffinch@bex.net | K52: Mgr, IT I | L52: 41422 | O52: Active | P52: 900848 | Q52: Monthly | R52: Full Time | S52: 088 | T52: 088-AS Raymond | U52: Business Applications | V52: 009150 | W52: AS Raymond | Z52: USA | AA52: S15 | AB52: FMG-S15 | AC52: =IF(ISBLANK(H52),VLOOKUP(P52,'US Supervisor Map'!A:D,4,FALSE),MID(H52,4,6)) | AD52: =IFERROR(VLOOKUP(T52,'Org Map'!A:E,4),"BU Description Not Mapped") -> 0088 | AE52: =IFERROR(VLOOKUP(V52,'Org Map'!C:E,3),"Home Department Code Not Mapped") -> 9150 | AF52: =IFERROR(VLOOKUP(AA52,'Salary Map'!A:D,3,FALSE),"Salary Code Not Mapped") -> Default | AG52: =IFERROR(VLOOKUP(AA52,'Salary Map'!A:D,4,FALSE),"Salary Code Not Mapped") -> General | AH52: =IFERROR(VLOOKUP(Z52,'Country Map'!A:B,2,FALSE),"Legal Country Not Mapped") -> US | AI52: =IFERROR(VLOOKUP(X52,'Language Map'!A:C,3,FALSE),IFERROR(VLOOKUP(T52,'Org Map'!A:F,6,FALSE),"ADP and BU Language Code Not Mapped"))&AH52 -> en_US | AJ52: =IFERROR(VLOOKUP(T52,'Org Map'!A:G,7),"BU Currency Not Mapped") -> USD | AK52: =IF(ISBLANK(E52),"",TRIM(E52&" "&F52)) | AL52: =IFERROR(VLOOKUP(O52,'Status Map'!A:B,2,FALSE),"Position Status Not Mapped") -> Y | AM52: =IF(AL52="N",TEXT(M52,"yyyymmdd"),"") | AO52: =B52&C52&D52 -> JeffreyLFinch | AP52: =LEFT(G52,FIND(",",G52)-1) -> Erdogan | AQ52: =IFERROR(VLOOKUP(AP52,D:P,13,FALSE),"No Reports to Name") -> No Reports to Name | AR52: =AQ52=MID(H52,4,6) -> FALSE
A53: V0U | B53: John | D53: Foisel | G53: Wilkins, William | H53: V0U901934 | I53: jfoisel@onebarnes.com | J53: Jfoisel1@att.net | K53: Mgr, Sales II | L53: 37599 | O53: Active | P53: 007863 | Q53: Monthly | R53: Full Time | S53: 025 | T53: 025-NGP Hyson Products | U53: Outside Sales | V53: 000820 | W53: Hyson Products | Z53: USA | AA53: S17 | AB53: FMG-S17 | AC53: =IF(ISBLANK(H53),VLOOKUP(P53,'US Supervisor Map'!A:D,4,FALSE),MID(H53,4,6)) -> 901934 | AD53: =IFERROR(VLOOKUP(T53,'Org Map'!A:E,4),"BU Description Not Mapped") -> 0096 | AE53: =IFERROR(VLOOKUP(V53,'Org Map'!C:E,3),"Home Department Code Not Mapped") -> 820 | AF53: =IFERROR(VLOOKUP(AA53,'Salary Map'!A:D,3,FALSE),"Salary Code Not Mapped") -> Default | AG53: =IFERROR(VLOOKUP(AA53,'Salary Map'!A:D,4,FALSE),"Salary Code Not Mapped") -> General | AH53: =IFERROR(VLOOKUP(Z53,'Country Map'!A:B,2,FALSE),"Legal Country Not Mapped") -> US | AI53: =IFERROR(VLOOKUP(X53,'Language Map'!A:C,3,FALSE),IFERROR(VLOOKUP(T53,'Org Map'!A:F,6,FALSE),"ADP and BU Language Code Not Mapped"))&AH53 -> en_US | AJ53: =IFERROR(VLOOKUP(T53,'Org Map'!A:G,7),"BU Currency Not Mapped") -> USD | AK53: =IF(ISBLANK(E53),"",TRIM(E53&" "&F53)) | AL53: =IFERROR(VLOOKUP(O53,'Status Map'!A:B,2,FALSE),"Position Status Not Mapped") -> Y | AM53: =IF(AL53="N",TEXT(M53,"yyyymmdd"),"") | AO53: =B53&C53&D53 -> JohnFoisel | AP53: =LEFT(G53,FIND(",",G53)-1) -> Wilkins | AQ53: =IFERROR(VLOOKUP(AP53,D:P,13,FALSE),"No Reports to Name") -> 901934 | AR53: =AQ53=MID(H53,4,6) -> TRUE
A54: KSX | B54: Conner | C54: J | D54: Frankforther | G54: Burchell, Mathew | H54: KSY211756 | I54: cfrankforther@onebarnes.com | J54: frankfortherconner@gmail.com | K54: Assistant, Warehouse II | L54: 45838 | O54: Active | P54: 212151 | Q54: Biweekly | R54: Full Time | S54: 088 | T54: 088-AS Raymond | U54: Assembly | V54: 005100 | W54: AS Raymond | Z54: USA | AA54: S05 | AB54: FMG-S05 | AC54: =IF(ISBLANK(H54),VLOOKUP(P54,'US Supervisor Map'!A:D,4,FALSE),MID(H54,4,6)) -> 211756 | AD54: =IFERROR(VLOOKUP(T54,'Org Map'!A:E,4),"BU Description Not Mapped") -> 0088 | AE54: =IFERROR(VLOOKUP(V54,'Org Map'!C:E,3),"Home Department Code Not Mapped") -> 5100 | AF54: =IFERROR(VLOOKUP(AA54,'Salary Map'!A:D,3,FALSE),"Salary Code Not Mapped") -> Default | AG54: =IFERROR(VLOOKUP(AA54,'Salary Map'!A:D,4,FALSE),"Salary Code Not Mapped") -> General | AH54: =IFERROR(VLOOKUP(Z54,'Country Map'!A:B,2,FALSE),"Legal Country Not Mapped") -> US | AI54: =IFERROR(VLOOKUP(X54,'Language Map'!A:C,3,FALSE),IFERROR(VLOOKUP(T54,'Org Map'!A:F,6,FALSE),"ADP and BU Language Code Not Mapped"))&AH54 -> en_US | AJ54: =IFERROR(VLOOKUP(T54,'Org Map'!A:G,7),"BU Currency Not Mapped") -> USD | AK54: =IF(ISBLANK(E54),"",TRIM(E54&" "&F54)) | AL54: =IFERROR(VLOOKUP(O54,'Status Map'!A:B,2,FALSE),"Position Status Not Mapped") -> Y | AM54: =IF(AL54="N",TEXT(M54,"yyyymmdd"),"") | AO54: =B54&C54&D54 -> ConnerJFrankforther | AP54: =LEFT(G54,FIND(",",G54)-1) -> Burchell | AQ54: =IFERROR(VLOOKUP(AP54,D:P,13,FALSE),"No Reports to Name") -> 211756 | AR54: =AQ54=MID(H54,4,6) -> TRUE
A55: KSX | B55: Dillon | C55: M | D55: Frankforther | G55: LaPlante, Derek | H55: KSY211736 | I55: dfrankforther@onebarnes.com | J55: frankfortherdillon@gmail.com | K55: Assistant, Warehouse II | L55: 45719 | O55: Active | P55: 211779 | Q55: Biweekly | R55: Full Time | S55: 088 | T55: 088-AS Raymond | U55: FG Warehouse | V55: 005200 | W55: AS Raymond | Z55: USA | AA55: S05 | AB55: FMG-S05 | AC55: =IF(ISBLANK(H55),VLOOKUP(P55,'US Supervisor Map'!A:D,4,FALSE),MID(H55,4,6)) -> 211736 | AD55: =IFERROR(VLOOKUP(T55,'Org Map'!A:E,4),"BU Description Not Mapped") -> 0088 | AE55: =IFERROR(VLOOKUP(V55,'Org Map'!C:E,3),"Home Department Code Not Mapped") -> 5200 | AF55: =IFERROR(VLOOKUP(AA55,'Salary Map'!A:D,3,FALSE),"Salary Code Not Mapped") -> Default | AG55: =IFERROR(VLOOKUP(AA55,'Salary Map'!A:D,4,FALSE),"Salary Code Not Mapped") -> General | AH55: =IFERROR(VLOOKUP(Z55,'Country Map'!A:B,2,FALSE),"Legal Country Not Mapped") -> US | AI55: =IFERROR(VLOOKUP(X55,'Language Map'!A:C,3,FALSE),IFERROR(VLOOKUP(T55,'Org Map'!A:F,6,FALSE),"ADP and BU Language Code Not Mapped"))&AH55 -> en_US | AJ55: =IFERROR(VLOOKUP(T55,'Org Map'!A:G,7),"BU Currency Not Mapped") -> USD | AK55: =IF(ISBLANK(E55),"",TRIM(E55&" "&F55)) | AL55: =IFERROR(VLOOKUP(O55,'Status Map'!A:B,2,FALSE),"Position Status Not Mapped") -> Y | AM55: =IF(AL55="N",TEXT(M55,"yyyymmdd"),"") | AO55: =B55&C55&D55 -> DillonMFrankforther | AP55: =LEFT(G55,FIND(",",G55)-1) -> LaPlante | AQ55: =IFERROR(VLOOKUP(AP55,D:P,13,FALSE),"No Reports to Name") -> 211736 | AR55: =AQ55=MID(H55,4,6) -> TRUE
A56: KSW | B56: Anthony | C56: J | D56: Frimel | G56: Steen, Michael | H56: V0U211062 | I56: afrimel@onebarnes.com | J56: tfrimel@att.net | K56: Tech, Manufacturing A | L56: 37410 | O56: Active | P56: 004352 | Q56: Biweekly | R56: Full Time | S56: 025 | T56: 025-NGP Hyson Products | U56: CNC Lathe Hyson | V56: 000100 | W56: Hyson Products | Z56: USA | AA56: H08 | AB56: FMG-H08 | AC56: =IF(ISBLANK(H56),VLOOKUP(P56,'US Supervisor Map'!A:D,4,FALSE),MID(H56,4,6)) -> 211062 | AD56: =IFERROR(VLOOKUP(T56,'Org Map'!A:E,4),"BU Description Not Mapped") -> 0096 | AE56: =IFERROR(VLOOKUP(V56,'Org Map'!C:E,3),"Home Department Code Not Mapped") -> 100 | AF56: =IFERROR(VLOOKUP(AA56,'Salary Map'!A:D,3,FALSE),"Salary Code Not Mapped") -> Default | AG56: =IFERROR(VLOOKUP(AA56,'Salary Map'!A:D,4,FALSE),"Salary Code Not Mapped") -> General | AH56: =IFERROR(VLOOKUP(Z56,'Country Map'!A:B,2,FALSE),"Legal Country Not Mapped") -> US | AI56: =IFERROR(VLOOKUP(X56,'Language Map'!A:C,3,FALSE),IFERROR(VLOOKUP(T56,'Org Map'!A:F,6,FALSE),"ADP and BU Language Code Not Mapped"))&AH56 -> en_US | AJ56: =IFERROR(VLOOKUP(T56,'Org Map'!A:G,7),"BU Currency Not Mapped") -> USD | AK56: =IF(ISBLANK(E56),"",TRIM(E56&" "&F56)) | AL56: =IFERROR(VLOOKUP(O56,'Status Map'!A:B,2,FALSE),"Position Status Not Mapped") -> Y | AM56: =IF(AL56="N",TEXT(M56,"yyyymmdd"),"") | AO56: =B56&C56&D56 -> AnthonyJFrimel | AP56: =LEFT(G56,FIND(",",G56)-1) -> Steen | AQ56: =IFERROR(VLOOKUP(AP56,D:P,13,FALSE),"No Reports to Name") -> 211062 | AR56: =AQ56=MID(H56,4,6) -> TRUE
A57: V0U | B57: Terry | C57: L | D57: Gang | G57: Bate, Natalie | H57: V0U213037 | I57: TGang@onebarnes.com | J57: Terrygang1987@gmail.com | K57: Mgr, Engineering II | L57: 37704 | O57: Active | P57: 006780 | Q57: Monthly | R57: Full Time | S57: 025 | T57: 025-NGP Hyson Products | U57: Warehouse | V57: 000555 | W57: Hyson Products | Z57: USA | AA57: S17 | AB57: FMG-S17 | AC57: =IF(ISBLANK(H57),VLOOKUP(P57,'US Supervisor Map'!A:D,4,FALSE),MID(H57,4,6)) -> 213037 | AD57: =IFERROR(VLOOKUP(T57,'Org Map'!A:E,4),"BU Description Not Mapped") -> 0096 | AE57: =IFERROR(VLOOKUP(V57,'Org Map'!C:E,3),"Home Department Code Not Mapped") -> 555 | AF57: =IFERROR(VLOOKUP(AA57,'Salary Map'!A:D,3,FALSE),"Salary Code Not Mapped") -> Default | AG57: =IFERROR(VLOOKUP(AA57,'Salary Map'!A:D,4,FALSE),"Salary Code Not Mapped") -> General | AH57: =IFERROR(VLOOKUP(Z57,'Country Map'!A:B,2,FALSE),"Legal Country Not Mapped") -> US | AI57: =IFERROR(VLOOKUP(X57,'Language Map'!A:C,3,FALSE),IFERROR(VLOOKUP(T57,'Org Map'!A:F,6,FALSE),"ADP and BU Language Code Not Mapped"))&AH57 -> en_US | AJ57: =IFERROR(VLOOKUP(T57,'Org Map'!A:G,7),"BU Currency Not Mapped") -> USD | AK57: =IF(ISBLANK(E57),"",TRIM(E57&" "&F57)) | AL57: =IFERROR(VLOOKUP(O57,'Status Map'!A:B,2,FALSE),"Position Status Not Mapped") -> Y | AM57: =IF(AL57="N",TEXT(M57,"yyyymmdd"),"") | AO57: =B57&C57&D57 -> TerryLGang | AP57: =LEFT(G57,FIND(",",G57)-1) -> Bate | AQ57: =IFERROR(VLOOKUP(AP57,D:P,13,FALSE),"No Reports to Name") -> 213037 | AR57: =AQ57=MID(H57,4,6) -> TRUE
A58: V0U | B58: Anne | C58: M | D58: Garber | G58: Bate, Natalie | I58: agarber@onebarnes.com | J58: anne.michael00@gmail.com | K58: Mgr, Program | L58: 46265 | O58: Active | P58: 902627 | Q58: Monthly | R58: Full Time | S58: 025 | T58: 025-NGP Hyson Products | U58: Administration | V58: 000917 | W58: Hyson Products | Z58: USA | AA58: S17 | AB58: FMG-S17 | AC58: =IF(ISBLANK(H58),VLOOKUP(P58,'US Supervisor Map'!A:D,4,FALSE),MID(H58,4,6)) | AD58: =IFERROR(VLOOKUP(T58,'Org Map'!A:E,4),"BU Description Not Mapped") -> 0096 | AE58: =IFERROR(VLOOKUP(V58,'Org Map'!C:E,3),"Home Department Code Not Mapped") -> 0007 | AF58: =IFERROR(VLOOKUP(AA58,'Salary Map'!A:D,3,FALSE),"Salary Code Not Mapped") -> Default | AG58: =IFERROR(VLOOKUP(AA58,'Salary Map'!A:D,4,FALSE),"Salary Code Not Mapped") -> General | AH58: =IFERROR(VLOOKUP(Z58,'Country Map'!A:B,2,FALSE),"Legal Country Not Mapped") -> US | AI58: =IFERROR(VLOOKUP(X58,'Language Map'!A:C,3,FALSE),IFERROR(VLOOKUP(T58,'Org Map'!A:F,6,FALSE),"ADP and BU Language Code Not Mapped"))&AH58 -> en_US | AJ58: =IFERROR(VLOOKUP(T58,'Org Map'!A:G,7),"BU Currency Not Mapped") -> USD | AK58: =IF(ISBLANK(E58),"",TRIM(E58&" "&F58)) | AL58: =IFERROR(VLOOKUP(O58,'Status Map'!A:B,2,FALSE),"Position Status Not Mapped") -> Y | AM58: =IF(AL58="N",TEXT(M58,"yyyymmdd"),"") | AO58: =B58&C58&D58 -> AnneMGarber | AP58: =LEFT(G58,FIND(",",G58)-1) -> Bate | AQ58: =IFERROR(VLOOKUP(AP58,D:P,13,FALSE),"No Reports to Name") -> 213037 | AR58: =AQ58=MID(H58,4,6) -> FALSE
A59: KSX | B59: Evelyn | D59: Gonzalez | I59: EGonzalez@onebarnes.com | K59: Assistant, Warehouse II | L59: 44942 | M59: 46148 | O59: Terminated | P59: 209540 | Q59: Biweekly | R59: Full Time | S59: 088 | T59: 088-AS Raymond | U59: Supply Chain | V59: 000004 | W59: AS Raymond | Z59: USA | AA59: S05 | AB59: FMG-S05 | AC59: =IF(ISBLANK(H59),VLOOKUP(P59,'US Supervisor Map'!A:D,4,FALSE),MID(H59,4,6)) | AD59: =IFERROR(VLOOKUP(T59,'Org Map'!A:E,4),"BU Description Not Mapped") -> 0088 | AE59: =IFERROR(VLOOKUP(V59,'Org Map'!C:E,3),"Home Department Code Not Mapped") -> Home Department Code Not Mapped | AF59: =IFERROR(VLOOKUP(AA59,'Salary Map'!A:D,3,FALSE),"Salary Code Not Mapped") -> Default | AG59: =IFERROR(VLOOKUP(AA59,'Salary Map'!A:D,4,FALSE),"Salary Code Not Mapped") -> General | AH59: =IFERROR(VLOOKUP(Z59,'Country Map'!A:B,2,FALSE),"Legal Country Not Mapped") -> US | AI59: =IFERROR(VLOOKUP(X59,'Language Map'!A:C,3,FALSE),IFERROR(VLOOKUP(T59,'Org Map'!A:F,6,FALSE),"ADP and BU Language Code Not Mapped"))&AH59 -> en_US | AJ59: =IFERROR(VLOOKUP(T59,'Org Map'!A:G,7),"BU Currency Not Mapped") -> USD | AK59: =IF(ISBLANK(E59),"",TRIM(E59&" "&F59)) | AL59: =IFERROR(VLOOKUP(O59,'Status Map'!A:B,2,FALSE),"Position Status Not Mapped") -> N | AM59: =IF(AL59="N",TEXT(M59,"yyyymmdd"),"") -> 20260506 | AN59: =IF(M59>AN54,"Fix and Include Record","Exclude record termination over 45 days ago") -> Fix and Include Record | AO59: =B59&C59&D59 -> EvelynGonzalez | AP59: =LEFT(G59,FIND(",",G59)-1) -> #VALUE! | AQ59: =IFERROR(VLOOKUP(AP59,D:P,13,FALSE),"No Reports to Name") -> No Reports to Name | AR59: =AQ59=MID(H59,4,6) -> FALSE
A60: KSX | B60: Cristel | D60: Grandowicz | G60: Burchell, Mathew | H60: KSY211756 | I60: cgrandowicz@onebarnes.com | J60: grandowicz.cristel@gmail.com | K60: Assistant, Warehouse II | L60: 45789 | O60: Active | P60: 211991 | Q60: Biweekly | R60: Full Time | S60: 088 | T60: 088-AS Raymond | U60: Assembly | V60: 005100 | W60: AS Raymond | Z60: USA | AA60: S05 | AB60: FMG-S05 | AC60: =IF(ISBLANK(H60),VLOOKUP(P60,'US Supervisor Map'!A:D,4,FALSE),MID(H60,4,6)) -> 211756 | AD60: =IFERROR(VLOOKUP(T60,'Org Map'!A:E,4),"BU Description Not Mapped") -> 0088 | AE60: =IFERROR(VLOOKUP(V60,'Org Map'!C:E,3),"Home Department Code Not Mapped") -> 5100 | AF60: =IFERROR(VLOOKUP(AA60,'Salary Map'!A:D,3,FALSE),"Salary Code Not Mapped") -> Default | AG60: =IFERROR(VLOOKUP(AA60,'Salary Map'!A:D,4,FALSE),"Salary Code Not Mapped") -> General | AH60: =IFERROR(VLOOKUP(Z60,'Country Map'!A:B,2,FALSE),"Legal Country Not Mapped") -> US | AI60: =IFERROR(VLOOKUP(X60,'Language Map'!A:C,3,FALSE),IFERROR(VLOOKUP(T60,'Org Map'!A:F,6,FALSE),"ADP and BU Language Code Not Mapped"))&AH60 -> en_US | AJ60: =IFERROR(VLOOKUP(T60,'Org Map'!A:G,7),"BU Currency Not Mapped") -> USD | AK60: =IF(ISBLANK(E60),"",TRIM(E60&" "&F60)) | AL60: =IFERROR(VLOOKUP(O60,'Status Map'!A:B,2,FALSE),"Position Status Not Mapped") -> Y | AM60: =IF(AL60="N",TEXT(M60,"yyyymmdd"),"") | AO60: =B60&C60&D60 -> CristelGrandowicz | AP60: =LEFT(G60,FIND(",",G60)-1) -> Burchell | AQ60: =IFERROR(VLOOKUP(AP60,D:P,13,FALSE),"No Reports to Name") -> 211756 | AR60: =AQ60=MID(H60,4,6) -> TRUE
A61: KSX | B61: Ivy | C61: J | D61: Grant | G61: Warner, Dwight | H61: V0U008750 | I61: igrant1@onebarnes.com | J61: igrant1453@yahoo.com | K61: Spec, Accounts Rec III | L61: 46181 | O61: Active | P61: 209642 | Q61: Biweekly | R61: Full Time | S61: 088 | T61: 088-AS Raymond | U61: Finance General | V61: 009100 | W61: Work from home - Virginia | Z61: USA | AA61: S10 | AB61: FMG-S10 | AC61: =IF(ISBLANK(H61),VLOOKUP(P61,'US Supervisor Map'!A:D,4,FALSE),MID(H61,4,6)) -> 008750 | AD61: =IFERROR(VLOOKUP(T61,'Org Map'!A:E,4),"BU Description Not Mapped") -> 0088 | AE61: =IFERROR(VLOOKUP(V61,'Org Map'!C:E,3),"Home Department Code Not Mapped") -> 9100 | AF61: =IFERROR(VLOOKUP(AA61,'Salary Map'!A:D,3,FALSE),"Salary Code Not Mapped") -> Default | AG61: =IFERROR(VLOOKUP(AA61,'Salary Map'!A:D,4,FALSE),"Salary Code Not Mapped") -> General | AH61: =IFERROR(VLOOKUP(Z61,'Country Map'!A:B,2,FALSE),"Legal Country Not Mapped") -> US | AI61: =IFERROR(VLOOKUP(X61,'Language Map'!A:C,3,FALSE),IFERROR(VLOOKUP(T61,'Org Map'!A:F,6,FALSE),"ADP and BU Language Code Not Mapped"))&AH61 -> en_US | AJ61: =IFERROR(VLOOKUP(T61,'Org Map'!A:G,7),"BU Currency Not Mapped") -> USD | AK61: =IF(ISBLANK(E61),"",TRIM(E61&" "&F61)) | AL61: =IFERROR(VLOOKUP(O61,'Status Map'!A:B,2,FALSE),"Position Status Not Mapped") -> Y | AM61: =IF(AL61="N",TEXT(M61,"yyyymmdd"),"") | AO61: =B61&C61&D61 -> IvyJGrant | AP61: =LEFT(G61,FIND(",",G61)-1) -> Warner | AQ61: =IFERROR(VLOOKUP(AP61,D:P,13,FALSE),"No Reports to Name") -> 008750 | AR61: =AQ61=MID(H61,4,6) -> TRUE
A62: KSW | B62: Michael | C62: W | D62: Haas | I62: MHaas@onebarnes.com | K62: Mechanic, Maintenance A | L62: 33742 | M62: 46027 | O62: Retired | P62: 006785 | Q62: Biweekly | R62: Full Time | S62: 025 | T62: 025-NGP Hyson Products | U62: Maintenance-Hyson | V62: 000450 | W62: Hyson Products | Z62: USA | AA62: H08 | AB62: FMG-H08 | AC62: =IF(ISBLANK(H62),VLOOKUP(P62,'US Supervisor Map'!A:D,4,FALSE),MID(H62,4,6)) | AD62: =IFERROR(VLOOKUP(T62,'Org Map'!A:E,4),"BU Description Not Mapped") -> 0096 | AE62: =IFERROR(VLOOKUP(V62,'Org Map'!C:E,3),"Home Department Code Not Mapped") -> 450 | AF62: =IFERROR(VLOOKUP(AA62,'Salary Map'!A:D,3,FALSE),"Salary Code Not Mapped") -> Default | AG62: =IFERROR(VLOOKUP(AA62,'Salary Map'!A:D,4,FALSE),"Salary Code Not Mapped") -> General | AH62: =IFERROR(VLOOKUP(Z62,'Country Map'!A:B,2,FALSE),"Legal Country Not Mapped") -> US | AI62: =IFERROR(VLOOKUP(X62,'Language Map'!A:C,3,FALSE),IFERROR(VLOOKUP(T62,'Org Map'!A:F,6,FALSE),"ADP and BU Language Code Not Mapped"))&AH62 -> en_US | AJ62: =IFERROR(VLOOKUP(T62,'Org Map'!A:G,7),"BU Currency Not Mapped") -> USD | AK62: =IF(ISBLANK(E62),"",TRIM(E62&" "&F62)) | AL62: =IFERROR(VLOOKUP(O62,'Status Map'!A:B,2,FALSE),"Position Status Not Mapped") -> N | AM62: =IF(AL62="N",TEXT(M62,"yyyymmdd"),"") -> 20260105 | AN62: =IF(M62>AN57,"Fix and Include Record","Exclude record termination over 45 days ago") -> Fix and Include Record | AO62: =B62&C62&D62 -> MichaelWHaas | AP62: =LEFT(G62,FIND(",",G62)-1) -> #VALUE! | AQ62: =IFERROR(VLOOKUP(AP62,D:P,13,FALSE),"No Reports to Name") -> No Reports to Name | AR62: =AQ62=MID(H62,4,6) -> FALSE
A63: KSX | B63: Tirani | C63: J | D63: Hague | G63: Rafferty, Jonathan | H63: KSY211131 | J63: tirani.hague@gmail.com | K63: Rep, Customer Service III | L63: 46153 | O63: Active | P63: 213224 | Q63: Biweekly | R63: Full Time | S63: 088 | T63: 088-AS Raymond | U63: Inside Sales | V63: 008100 | W63: AS Raymond | Z63: USA | AA63: S11 | AB63: FMG-S11 | AC63: =IF(ISBLANK(H63),VLOOKUP(P63,'US Supervisor Map'!A:D,4,FALSE),MID(H63,4,6)) -> 211131 | AD63: =IFERROR(VLOOKUP(T63,'Org Map'!A:E,4),"BU Description Not Mapped") -> 0088 | AE63: =IFERROR(VLOOKUP(V63,'Org Map'!C:E,3),"Home Department Code Not Mapped") -> 8100 | AF63: =IFERROR(VLOOKUP(AA63,'Salary Map'!A:D,3,FALSE),"Salary Code Not Mapped") -> Default | AG63: =IFERROR(VLOOKUP(AA63,'Salary Map'!A:D,4,FALSE),"Salary Code Not Mapped") -> General | AH63: =IFERROR(VLOOKUP(Z63,'Country Map'!A:B,2,FALSE),"Legal Country Not Mapped") -> US | AI63: =IFERROR(VLOOKUP(X63,'Language Map'!A:C,3,FALSE),IFERROR(VLOOKUP(T63,'Org Map'!A:F,6,FALSE),"ADP and BU Language Code Not Mapped"))&AH63 -> en_US | AJ63: =IFERROR(VLOOKUP(T63,'Org Map'!A:G,7),"BU Currency Not Mapped") -> USD | AK63: =IF(ISBLANK(E63),"",TRIM(E63&" "&F63)) | AL63: =IFERROR(VLOOKUP(O63,'Status Map'!A:B,2,FALSE),"Position Status Not Mapped") -> Y | AM63: =IF(AL63="N",TEXT(M63,"yyyymmdd"),"") | AO63: =B63&C63&D63 -> TiraniJHague | AP63: =LEFT(G63,FIND(",",G63)-1) -> Rafferty | AQ63: =IFERROR(VLOOKUP(AP63,D:P,13,FALSE),"No Reports to Name") -> 211131 | AR63: =AQ63=MID(H63,4,6) -> TRUE
A64: KSX | B64: Kimberly | D64: Hall | G64: Alexander, Thomas | H64: KSY210892 | I64: KHall@onebarnes.com | K64: Tech, Quality I | L64: 44333 | O64: Active | P64: 206228 | Q64: Biweekly | R64: Full Time | S64: 088 | T64: 088-AS Raymond | U64: Admin-Quality | V64: 009500 | W64: AS Raymond | Z64: USA | AA64: S10 | AB64: FMG-S10 | AC64: =IF(ISBLANK(H64),VLOOKUP(P64,'US Supervisor Map'!A:D,4,FALSE),MID(H64,4,6)) -> 210892 | AD64: =IFERROR(VLOOKUP(T64,'Org Map'!A:E,4),"BU Description Not Mapped") -> 0088 | AE64: =IFERROR(VLOOKUP(V64,'Org Map'!C:E,3),"Home Department Code Not Mapped") -> 9500 | AF64: =IFERROR(VLOOKUP(AA64,'Salary Map'!A:D,3,FALSE),"Salary Code Not Mapped") -> Default | AG64: =IFERROR(VLOOKUP(AA64,'Salary Map'!A:D,4,FALSE),"Salary Code Not Mapped") -> General | AH64: =IFERROR(VLOOKUP(Z64,'Country Map'!A:B,2,FALSE),"Legal Country Not Mapped") -> US | AI64: =IFERROR(VLOOKUP(X64,'Language Map'!A:C,3,FALSE),IFERROR(VLOOKUP(T64,'Org Map'!A:F,6,FALSE),"ADP and BU Language Code Not Mapped"))&AH64 -> en_US | AJ64: =IFERROR(VLOOKUP(T64,'Org Map'!A:G,7),"BU Currency Not Mapped") -> USD | AK64: =IF(ISBLANK(E64),"",TRIM(E64&" "&F64)) | AL64: =IFERROR(VLOOKUP(O64,'Status Map'!A:B,2,FALSE),"Position Status Not Mapped") -> Y | AM64: =IF(AL64="N",TEXT(M64,"yyyymmdd"),"") | AO64: =B64&C64&D64 -> KimberlyHall | AP64: =LEFT(G64,FIND(",",G64)-1) -> Alexander | AQ64: =IFERROR(VLOOKUP(AP64,D:P,13,FALSE),"No Reports to Name") -> 210892 | AR64: =AQ64=MID(H64,4,6) -> TRUE
A65: KSY | B65: Emma | D65: Halpin | G65: Kemenah, Greg | H65: KSY211766 | I65: ehalpin@onebarnes.com | J65: sampson.emma17@gmail.com | K65: Mgr, Product III | L65: 45566 | O65: Active | P65: 211489 | Q65: Monthly | R65: Full Time | S65: 088 | T65: 088-AS Raymond | U65: Marketing | V65: 008300 | W65: AS Raymond | Z65: USA | AA65: S16 | AB65: FMG-S16 | AC65: =IF(ISBLANK(H65),VLOOKUP(P65,'US Supervisor Map'!A:D,4,FALSE),MID(H65,4,6)) -> 211766 | AD65: =IFERROR(VLOOKUP(T65,'Org Map'!A:E,4),"BU Description Not Mapped") -> 0088 | AE65: =IFERROR(VLOOKUP(V65,'Org Map'!C:E,3),"Home Department Code Not Mapped") -> 8300 | AF65: =IFERROR(VLOOKUP(AA65,'Salary Map'!A:D,3,FALSE),"Salary Code Not Mapped") -> Default | AG65: =IFERROR(VLOOKUP(AA65,'Salary Map'!A:D,4,FALSE),"Salary Code Not Mapped") -> General | AH65: =IFERROR(VLOOKUP(Z65,'Country Map'!A:B,2,FALSE),"Legal Country Not Mapped") -> US | AI65: =IFERROR(VLOOKUP(X65,'Language Map'!A:C,3,FALSE),IFERROR(VLOOKUP(T65,'Org Map'!A:F,6,FALSE),"ADP and BU Language Code Not Mapped"))&AH65 -> en_US | AJ65: =IFERROR(VLOOKUP(T65,'Org Map'!A:G,7),"BU Currency Not Mapped") -> USD | AK65: =IF(ISBLANK(E65),"",TRIM(E65&" "&F65)) | AL65: =IFERROR(VLOOKUP(O65,'Status Map'!A:B,2,FALSE),"Position Status Not Mapped") -> Y | AM65: =IF(AL65="N",TEXT(M65,"yyyymmdd"),"") | AO65: =B65&C65&D65 -> EmmaHalpin | AP65: =LEFT(G65,FIND(",",G65)-1) -> Kemenah | AQ65: =IFERROR(VLOOKUP(AP65,D:P,13,FALSE),"No Reports to Name") -> 211766 | AR65: =AQ65=MID(H65,4,6) -> TRUE
A66: KSW | B66: Michael | C66: J | D66: Hamar | G66: Wallace, Derron | H66: V0U211998 | I66: mhamar@onebarnes.com | K66: Shipping/Receiving ClerkB | L66: 42072 | O66: Active | P66: 901454 | Q66: Biweekly | R66: Full Time | S66: 025 | T66: 025-NGP Hyson Products | U66: Assembly Hyson | V66: 000200 | W66: Hyson Products | Z66: USA | AA66: H06 | AB66: FMG-H06 | AC66: =IF(ISBLANK(H66),VLOOKUP(P66,'US Supervisor Map'!A:D,4,FALSE),MID(H66,4,6)) -> 211998 | AD66: =IFERROR(VLOOKUP(T66,'Org Map'!A:E,4),"BU Description Not Mapped") -> 0096 | AE66: =IFERROR(VLOOKUP(V66,'Org Map'!C:E,3),"Home Department Code Not Mapped") -> 200 | AF66: =IFERROR(VLOOKUP(AA66,'Salary Map'!A:D,3,FALSE),"Salary Code Not Mapped") -> Default | AG66: =IFERROR(VLOOKUP(AA66,'Salary Map'!A:D,4,FALSE),"Salary Code Not Mapped") -> General | AH66: =IFERROR(VLOOKUP(Z66,'Country Map'!A:B,2,FALSE),"Legal Country Not Mapped") -> US | AI66: =IFERROR(VLOOKUP(X66,'Language Map'!A:C,3,FALSE),IFERROR(VLOOKUP(T66,'Org Map'!A:F,6,FALSE),"ADP and BU Language Code Not Mapped"))&AH66 -> en_US | AJ66: =IFERROR(VLOOKUP(T66,'Org Map'!A:G,7),"BU Currency Not Mapped") -> USD | AK66: =IF(ISBLANK(E66),"",TRIM(E66&" "&F66)) | AL66: =IFERROR(VLOOKUP(O66,'Status Map'!A:B,2,FALSE),"Position Status Not Mapped") -> Y | AM66: =IF(AL66="N",TEXT(M66,"yyyymmdd"),"") | AO66: =B66&C66&D66 -> MichaelJHamar | AP66: =LEFT(G66,FIND(",",G66)-1) -> Wallace | AQ66: =IFERROR(VLOOKUP(AP66,D:P,13,FALSE),"No Reports to Name") -> 211998 | AR66: =AQ66=MID(H66,4,6) -> TRUE
A67: KSX | B67: Patsy | D67: Hamby | G67: Burchell, Mathew | H67: KSY211756 | I67: PHamby@onebarnes.com | J67: phamby456@gmail.com | K67: Assistant, Warehouse II | L67: 44893 | O67: Active | P67: 209425 | Q67: Biweekly | R67: Full Time | S67: 088 | T67: 088-AS Raymond | U67: Assembly | V67: 005100 | W67: AS Raymond | Z67: USA | AA67: S05 | AB67: FMG-S05 | AC67: =IF(ISBLANK(H67),VLOOKUP(P67,'US Supervisor Map'!A:D,4,FALSE),MID(H67,4,6)) -> 211756 | AD67: =IFERROR(VLOOKUP(T67,'Org Map'!A:E,4),"BU Description Not Mapped") -> 0088 | AE67: =IFERROR(VLOOKUP(V67,'Org Map'!C:E,3),"Home Department Code Not Mapped") -> 5100 | AF67: =IFERROR(VLOOKUP(AA67,'Salary Map'!A:D,3,FALSE),"Salary Code Not Mapped") -> Default | AG67: =IFERROR(VLOOKUP(AA67,'Salary Map'!A:D,4,FALSE),"Salary Code Not Mapped") -> General | AH67: =IFERROR(VLOOKUP(Z67,'Country Map'!A:B,2,FALSE),"Legal Country Not Mapped") -> US | AI67: =IFERROR(VLOOKUP(X67,'Language Map'!A:C,3,FALSE),IFERROR(VLOOKUP(T67,'Org Map'!A:F,6,FALSE),"ADP and BU Language Code Not Mapped"))&AH67 -> en_US | AJ67: =IFERROR(VLOOKUP(T67,'Org Map'!A:G,7),"BU Currency Not Mapped") -> USD | AK67: =IF(ISBLANK(E67),"",TRIM(E67&" "&F67)) | AL67: =IFERROR(VLOOKUP(O67,'Status Map'!A:B,2,FALSE),"Position Status Not Mapped") -> Y | AM67: =IF(AL67="N",TEXT(M67,"yyyymmdd"),"") | AO67: =B67&C67&D67 -> PatsyHamby | AP67: =LEFT(G67,FIND(",",G67)-1) -> Burchell | AQ67: =IFERROR(VLOOKUP(AP67,D:P,13,FALSE),"No Reports to Name") -> 211756 | AR67: =AQ67=MID(H67,4,6) -> TRUE
A68: V0U | B68: Jon | D68: Hartman | H68: V0U901934 | I68: jhartman@onebarnes.com | J68: jhartman8890@gmail.com | K68: Mgr, Sales I | L68: 45442 | M68: 46183 | O68: Terminated | P68: 211045 | Q68: Monthly | R68: Full Time | S68: 025 | T68: 025-NGP Hyson Products | U68: Outside Sales | V68: 000820 | W68: Hyson Products | Z68: USA | AA68: S16 | AB68: FMG-S16 | AC68: =IF(ISBLANK(H68),VLOOKUP(P68,'US Supervisor Map'!A:D,4,FALSE),MID(H68,4,6)) -> 901934 | AD68: =IFERROR(VLOOKUP(T68,'Org Map'!A:E,4),"BU Description Not Mapped") -> 0096 | AE68: =IFERROR(VLOOKUP(V68,'Org Map'!C:E,3),"Home Department Code Not Mapped") -> 820 | AF68: =IFERROR(VLOOKUP(AA68,'Salary Map'!A:D,3,FALSE),"Salary Code Not Mapped") -> Default | AG68: =IFERROR(VLOOKUP(AA68,'Salary Map'!A:D,4,FALSE),"Salary Code Not Mapped") -> General | AH68: =IFERROR(VLOOKUP(Z68,'Country Map'!A:B,2,FALSE),"Legal Country Not Mapped") -> US | AI68: =IFERROR(VLOOKUP(X68,'Language Map'!A:C,3,FALSE),IFERROR(VLOOKUP(T68,'Org Map'!A:F,6,FALSE),"ADP and BU Language Code Not Mapped"))&AH68 -> en_US | AJ68: =IFERROR(VLOOKUP(T68,'Org Map'!A:G,7),"BU Currency Not Mapped") -> USD | AK68: =IF(ISBLANK(E68),"",TRIM(E68&" "&F68)) | AL68: =IFERROR(VLOOKUP(O68,'Status Map'!A:B,2,FALSE),"Position Status Not Mapped") -> N | AM68: =IF(AL68="N",TEXT(M68,"yyyymmdd"),"") -> 20260610 | AN68: =IF(M68>AN63,"Fix and Include Record","Exclude record termination over 45 days ago") -> Fix and Include Record | AO68: =B68&C68&D68 -> JonHartman | AP68: =LEFT(G68,FIND(",",G68)-1) -> #VALUE! | AQ68: =IFERROR(VLOOKUP(AP68,D:P,13,FALSE),"No Reports to Name") -> No Reports to Name | AR68: =AQ68=MID(H68,4,6) -> FALSE
A69: KSW | B69: Cherie | D69: Hassey | G69: Wallace, Derron | H69: V0U211998 | I69: chassey@onebarnes.com | J69: c.hassey@att.net | K69: Rep, Customer Service II | L69: 46125 | O69: Active | P69: 213144 | Q69: Biweekly | R69: Full Time | S69: 025 | T69: 025-NGP Hyson Products | U69: Inside Sales | V69: 000850 | W69: Hyson Products | Z69: USA | AA69: S10 | AB69: FMG-S10 | AC69: =IF(ISBLANK(H69),VLOOKUP(P69,'US Supervisor Map'!A:D,4,FALSE),MID(H69,4,6)) -> 211998 | AD69: =IFERROR(VLOOKUP(T69,'Org Map'!A:E,4),"BU Description Not Mapped") -> 0096 | AE69: =IFERROR(VLOOKUP(V69,'Org Map'!C:E,3),"Home Department Code Not Mapped") -> 850 | AF69: =IFERROR(VLOOKUP(AA69,'Salary Map'!A:D,3,FALSE),"Salary Code Not Mapped") -> Default | AG69: =IFERROR(VLOOKUP(AA69,'Salary Map'!A:D,4,FALSE),"Salary Code Not Mapped") -> General | AH69: =IFERROR(VLOOKUP(Z69,'Country Map'!A:B,2,FALSE),"Legal Country Not Mapped") -> US | AI69: =IFERROR(VLOOKUP(X69,'Language Map'!A:C,3,FALSE),IFERROR(VLOOKUP(T69,'Org Map'!A:F,6,FALSE),"ADP and BU Language Code Not Mapped"))&AH69 -> en_US | AJ69: =IFERROR(VLOOKUP(T69,'Org Map'!A:G,7),"BU Currency Not Mapped") -> USD | AK69: =IF(ISBLANK(E69),"",TRIM(E69&" "&F69)) | AL69: =IFERROR(VLOOKUP(O69,'Status Map'!A:B,2,FALSE),"Position Status Not Mapped") -> Y | AM69: =IF(AL69="N",TEXT(M69,"yyyymmdd"),"") | AO69: =B69&C69&D69 -> CherieHassey | AP69: =LEFT(G69,FIND(",",G69)-1) -> Wallace | AQ69: =IFERROR(VLOOKUP(AP69,D:P,13,FALSE),"No Reports to Name") -> 211998 | AR69: =AQ69=MID(H69,4,6) -> TRUE
A70: V0U | B70: Cherie | D70: Hassey | I70: chassey@onebarnes.com | J70: c.hassey@att.net | K70: Rep, Customer Service II | L70: 46125 | M70: 46176 | O70: Terminated | P70: 213144 | Q70: Biweekly | R70: Full Time | S70: 025 | T70: 025-NGP Hyson Products | U70: Inside Sales | V70: 000850 | W70: Hyson Products | Z70: USA | AA70: S10 | AB70: FMG-S10 | AC70: =IF(ISBLANK(H70),VLOOKUP(P70,'US Supervisor Map'!A:D,4,FALSE),MID(H70,4,6)) | AD70: =IFERROR(VLOOKUP(T70,'Org Map'!A:E,4),"BU Description Not Mapped") -> 0096 | AE70: =IFERROR(VLOOKUP(V70,'Org Map'!C:E,3),"Home Department Code Not Mapped") -> 850 | AF70: =IFERROR(VLOOKUP(AA70,'Salary Map'!A:D,3,FALSE),"Salary Code Not Mapped") -> Default | AG70: =IFERROR(VLOOKUP(AA70,'Salary Map'!A:D,4,FALSE),"Salary Code Not Mapped") -> General | AH70: =IFERROR(VLOOKUP(Z70,'Country Map'!A:B,2,FALSE),"Legal Country Not Mapped") -> US | AI70: =IFERROR(VLOOKUP(X70,'Language Map'!A:C,3,FALSE),IFERROR(VLOOKUP(T70,'Org Map'!A:F,6,FALSE),"ADP and BU Language Code Not Mapped"))&AH70 -> en_US | AJ70: =IFERROR(VLOOKUP(T70,'Org Map'!A:G,7),"BU Currency Not Mapped") -> USD | AK70: =IF(ISBLANK(E70),"",TRIM(E70&" "&F70)) | AL70: =IFERROR(VLOOKUP(O70,'Status Map'!A:B,2,FALSE),"Position Status Not Mapped") -> N | AM70: =IF(AL70="N",TEXT(M70,"yyyymmdd"),"") -> 20260603 | AN70: =IF(M70>AN65,"Fix and Include Record","Exclude record termination over 45 days ago") -> Fix and Include Record | AO70: =B70&C70&D70 -> CherieHassey | AP70: =LEFT(G70,FIND(",",G70)-1) -> #VALUE! | AQ70: =IFERROR(VLOOKUP(AP70,D:P,13,FALSE),"No Reports to Name") -> No Reports to Name | AR70: =AQ70=MID(H70,4,6) -> FALSE
A71: KSX | B71: Karla | D71: Hershberger | G71: Burchell, Mathew | H71: KSY211756 | I71: khershberger@onebarnes.com | J71: karhershy14@gmail.com | K71: Assistant, Warehouse II | L71: 44893 | O71: Active | P71: 209424 | Q71: Biweekly | R71: Full Time | S71: 088 | T71: 088-AS Raymond | U71: Assembly | V71: 005100 | W71: AS Raymond | Z71: USA | AA71: S05 | AB71: FMG-S05 | AC71: =IF(ISBLANK(H71),VLOOKUP(P71,'US Supervisor Map'!A:D,4,FALSE),MID(H71,4,6)) -> 211756 | AD71: =IFERROR(VLOOKUP(T71,'Org Map'!A:E,4),"BU Description Not Mapped") -> 0088 | AE71: =IFERROR(VLOOKUP(V71,'Org Map'!C:E,3),"Home Department Code Not Mapped") -> 5100 | AF71: =IFERROR(VLOOKUP(AA71,'Salary Map'!A:D,3,FALSE),"Salary Code Not Mapped") -> Default | AG71: =IFERROR(VLOOKUP(AA71,'Salary Map'!A:D,4,FALSE),"Salary Code Not Mapped") -> General | AH71: =IFERROR(VLOOKUP(Z71,'Country Map'!A:B,2,FALSE),"Legal Country Not Mapped") -> US | AI71: =IFERROR(VLOOKUP(X71,'Language Map'!A:C,3,FALSE),IFERROR(VLOOKUP(T71,'Org Map'!A:F,6,FALSE),"ADP and BU Language Code Not Mapped"))&AH71 -> en_US | AJ71: =IFERROR(VLOOKUP(T71,'Org Map'!A:G,7),"BU Currency Not Mapped") -> USD | AK71: =IF(ISBLANK(E71),"",TRIM(E71&" "&F71)) | AL71: =IFERROR(VLOOKUP(O71,'Status Map'!A:B,2,FALSE),"Position Status Not Mapped") -> Y | AM71: =IF(AL71="N",TEXT(M71,"yyyymmdd"),"") | AO71: =B71&C71&D71 -> KarlaHershberger | AP71: =LEFT(G71,FIND(",",G71)-1) -> Burchell | AQ71: =IFERROR(VLOOKUP(AP71,D:P,13,FALSE),"No Reports to Name") -> 211756 | AR71: =AQ71=MID(H71,4,6) -> TRUE
A72: KSX | B72: Brandon | D72: Hibbitts | H72: KSY900848 | I72: bhibbitts@onebarnes.com | J72: hibbitts.brandon@gmail.com | K72: Intern, IT Indirect | L72: 45502 | M72: 46203 | O72: Terminated | P72: 211181 | Q72: Biweekly | R72: Part Time | S72: 088 | T72: 088-AS Raymond | U72: Business Applications | V72: 009150 | W72: AS Raymond | Z72: USA | AA72: H05 | AB72: FMG-H05 | AC72: =IF(ISBLANK(H72),VLOOKUP(P72,'US Supervisor Map'!A:D,4,FALSE),MID(H72,4,6)) -> 900848 | AD72: =IFERROR(VLOOKUP(T72,'Org Map'!A:E,4),"BU Description Not Mapped") -> 0088 | AE72: =IFERROR(VLOOKUP(V72,'Org Map'!C:E,3),"Home Department Code Not Mapped") -> 9150 | AF72: =IFERROR(VLOOKUP(AA72,'Salary Map'!A:D,3,FALSE),"Salary Code Not Mapped") -> Default | AG72: =IFERROR(VLOOKUP(AA72,'Salary Map'!A:D,4,FALSE),"Salary Code Not Mapped") -> General | AH72: =IFERROR(VLOOKUP(Z72,'Country Map'!A:B,2,FALSE),"Legal Country Not Mapped") -> US | AI72: =IFERROR(VLOOKUP(X72,'Language Map'!A:C,3,FALSE),IFERROR(VLOOKUP(T72,'Org Map'!A:F,6,FALSE),"ADP and BU Language Code Not Mapped"))&AH72 -> en_US | AJ72: =IFERROR(VLOOKUP(T72,'Org Map'!A:G,7),"BU Currency Not Mapped") -> USD | AK72: =IF(ISBLANK(E72),"",TRIM(E72&" "&F72)) | AL72: =IFERROR(VLOOKUP(O72,'Status Map'!A:B,2,FALSE),"Position Status Not Mapped") -> N | AM72: =IF(AL72="N",TEXT(M72,"yyyymmdd"),"") -> 20260630 | AN72: =IF(M72>AN67,"Fix and Include Record","Exclude record termination over 45 days ago") -> Fix and Include Record | AO72: =B72&C72&D72 -> BrandonHibbitts | AP72: =LEFT(G72,FIND(",",G72)-1) -> #VALUE! | AQ72: =IFERROR(VLOOKUP(AP72,D:P,13,FALSE),"No Reports to Name") -> No Reports to Name | AR72: =AQ72=MID(H72,4,6) -> FALSE
A73: KSY | B73: Brandon | D73: Hibbitts | G73: Erdogan, Mehmet | H73: 000207199N | I73: bhibbitts@onebarnes.com | J73: hibbitts.brandon@gmail.com | K73: Analyst, Help Desk II | L73: 45502 | O73: Active | P73: 211181 | Q73: Monthly | R73: Full Time | S73: 088 | T73: 088-AS Raymond | U73: Business Applications | V73: 009150 | W73: AS Raymond | Z73: USA | AA73: S12 | AB73: FMG-S12 | AC73: =IF(ISBLANK(H73),VLOOKUP(P73,'US Supervisor Map'!A:D,4,FALSE),MID(H73,4,6)) -> 207199 | AD73: =IFERROR(VLOOKUP(T73,'Org Map'!A:E,4),"BU Description Not Mapped") -> 0088 | AE73: =IFERROR(VLOOKUP(V73,'Org Map'!C:E,3),"Home Department Code Not Mapped") -> 9150 | AF73: =IFERROR(VLOOKUP(AA73,'Salary Map'!A:D,3,FALSE),"Salary Code Not Mapped") -> Default | AG73: =IFERROR(VLOOKUP(AA73,'Salary Map'!A:D,4,FALSE),"Salary Code Not Mapped") -> General | AH73: =IFERROR(VLOOKUP(Z73,'Country Map'!A:B,2,FALSE),"Legal Country Not Mapped") -> US | AI73: =IFERROR(VLOOKUP(X73,'Language Map'!A:C,3,FALSE),IFERROR(VLOOKUP(T73,'Org Map'!A:F,6,FALSE),"ADP and BU Language Code Not Mapped"))&AH73 -> en_US | AJ73: =IFERROR(VLOOKUP(T73,'Org Map'!A:G,7),"BU Currency Not Mapped") -> USD | AK73: =IF(ISBLANK(E73),"",TRIM(E73&" "&F73)) | AL73: =IFERROR(VLOOKUP(O73,'Status Map'!A:B,2,FALSE),"Position Status Not Mapped") -> Y | AM73: =IF(AL73="N",TEXT(M73,"yyyymmdd"),"") | AO73: =B73&C73&D73 -> BrandonHibbitts | AP73: =LEFT(G73,FIND(",",G73)-1) -> Erdogan | AQ73: =IFERROR(VLOOKUP(AP73,D:P,13,FALSE),"No Reports to Name") -> No Reports to Name | AR73: =AQ73=MID(H73,4,6) -> FALSE
A74: KSW | B74: Bobby | D74: Hicks | G74: Wallace, Derron | H74: V0U211998 | I74: bhicks@onebarnes.com | J74: bhicks1@me.com | K74: Lead, Unit Team | L74: 45481 | O74: Active | P74: 211145 | Q74: Biweekly | R74: Full Time | S74: 025 | T74: 025-NGP Hyson Products | U74: Assembly Hyson | V74: 000200 | W74: Hyson Products | Z74: USA | AA74: H08 | AB74: FMG-H08 | AC74: =IF(ISBLANK(H74),VLOOKUP(P74,'US Supervisor Map'!A:D,4,FALSE),MID(H74,4,6)) -> 211998 | AD74: =IFERROR(VLOOKUP(T74,'Org Map'!A:E,4),"BU Description Not Mapped") -> 0096 | AE74: =IFERROR(VLOOKUP(V74,'Org Map'!C:E,3),"Home Department Code Not Mapped") -> 200 | AF74: =IFERROR(VLOOKUP(AA74,'Salary Map'!A:D,3,FALSE),"Salary Code Not Mapped") -> Default | AG74: =IFERROR(VLOOKUP(AA74,'Salary Map'!A:D,4,FALSE),"Salary Code Not Mapped") -> General | AH74: =IFERROR(VLOOKUP(Z74,'Country Map'!A:B,2,FALSE),"Legal Country Not Mapped") -> US | AI74: =IFERROR(VLOOKUP(X74,'Language Map'!A:C,3,FALSE),IFERROR(VLOOKUP(T74,'Org Map'!A:F,6,FALSE),"ADP and BU Language Code Not Mapped"))&AH74 -> en_US | AJ74: =IFERROR(VLOOKUP(T74,'Org Map'!A:G,7),"BU Currency Not Mapped") -> USD | AK74: =IF(ISBLANK(E74),"",TRIM(E74&" "&F74)) | AL74: =IFERROR(VLOOKUP(O74,'Status Map'!A:B,2,FALSE),"Position Status Not Mapped") -> Y | AM74: =IF(AL74="N",TEXT(M74,"yyyymmdd"),"") | AO74: =B74&C74&D74 -> BobbyHicks | AP74: =LEFT(G74,FIND(",",G74)-1) -> Wallace | AQ74: =IFERROR(VLOOKUP(AP74,D:P,13,FALSE),"No Reports to Name") -> 211998 | AR74: =AQ74=MID(H74,4,6) -> TRUE
A75: KSW | B75: Darin | D75: Hitti | G75: Gang, Terry | H75: V0U006780 | I75: DHitti@onebarnes.com | K75: Mechanic, Maintenance A | L75: 31049 | O75: Active | P75: 006792 | Q75: Biweekly | R75: Full Time | S75: 025 | T75: 025-NGP Hyson Products | U75: Maintenance-Hyson | V75: 000450 | W75: Hyson Products | Z75: USA | AA75: H08 | AB75: FMG-H08 | AC75: =IF(ISBLANK(H75),VLOOKUP(P75,'US Supervisor Map'!A:D,4,FALSE),MID(H75,4,6)) -> 006780 | AD75: =IFERROR(VLOOKUP(T75,'Org Map'!A:E,4),"BU Description Not Mapped") -> 0096 | AE75: =IFERROR(VLOOKUP(V75,'Org Map'!C:E,3),"Home Department Code Not Mapped") -> 450 | AF75: =IFERROR(VLOOKUP(AA75,'Salary Map'!A:D,3,FALSE),"Salary Code Not Mapped") -> Default | AG75: =IFERROR(VLOOKUP(AA75,'Salary Map'!A:D,4,FALSE),"Salary Code Not Mapped") -> General | AH75: =IFERROR(VLOOKUP(Z75,'Country Map'!A:B,2,FALSE),"Legal Country Not Mapped") -> US | AI75: =IFERROR(VLOOKUP(X75,'Language Map'!A:C,3,FALSE),IFERROR(VLOOKUP(T75,'Org Map'!A:F,6,FALSE),"ADP and BU Language Code Not Mapped"))&AH75 -> en_US | AJ75: =IFERROR(VLOOKUP(T75,'Org Map'!A:G,7),"BU Currency Not Mapped") -> USD | AK75: =IF(ISBLANK(E75),"",TRIM(E75&" "&F75)) | AL75: =IFERROR(VLOOKUP(O75,'Status Map'!A:B,2,FALSE),"Position Status Not Mapped") -> Y | AM75: =IF(AL75="N",TEXT(M75,"yyyymmdd"),"") | AO75: =B75&C75&D75 -> DarinHitti | AP75: =LEFT(G75,FIND(",",G75)-1) -> Gang | AQ75: =IFERROR(VLOOKUP(AP75,D:P,13,FALSE),"No Reports to Name") -> 006780 | AR75: =AQ75=MID(H75,4,6) -> TRUE
A76: KSW | B76: Mason | D76: Hitti | H76: V0U211062 | J76: hittimason4@gmail.com | K76: Machinist, CNC | L76: 46190 | M76: 46233 | O76: Terminated | Q76: Biweekly | R76: Temporary | S76: 025 | T76: 025-NGP Hyson Products | U76: CNC Lathe Hyson | V76: 000100 | W76: Hyson Products | Z76: USA | AA76: H04 | AB76: FMG-H04 | AC76: =IF(ISBLANK(H76),VLOOKUP(P76,'US Supervisor Map'!A:D,4,FALSE),MID(H76,4,6)) -> 211062 | AD76: =IFERROR(VLOOKUP(T76,'Org Map'!A:E,4),"BU Description Not Mapped") -> 0096 | AE76: =IFERROR(VLOOKUP(V76,'Org Map'!C:E,3),"Home Department Code Not Mapped") -> 100 | AF76: =IFERROR(VLOOKUP(AA76,'Salary Map'!A:D,3,FALSE),"Salary Code Not Mapped") -> Default | AG76: =IFERROR(VLOOKUP(AA76,'Salary Map'!A:D,4,FALSE),"Salary Code Not Mapped") -> General | AH76: =IFERROR(VLOOKUP(Z76,'Country Map'!A:B,2,FALSE),"Legal Country Not Mapped") -> US | AI76: =IFERROR(VLOOKUP(X76,'Language Map'!A:C,3,FALSE),IFERROR(VLOOKUP(T76,'Org Map'!A:F,6,FALSE),"ADP and BU Language Code Not Mapped"))&AH76 -> en_US | AJ76: =IFERROR(VLOOKUP(T76,'Org Map'!A:G,7),"BU Currency Not Mapped") -> USD | AK76: =IF(ISBLANK(E76),"",TRIM(E76&" "&F76)) | AL76: =IFERROR(VLOOKUP(O76,'Status Map'!A:B,2,FALSE),"Position Status Not Mapped") -> N | AM76: =IF(AL76="N",TEXT(M76,"yyyymmdd"),"") -> 20260730 | AN76: =IF(M76>AN71,"Fix and Include Record","Exclude record termination over 45 days ago") -> Fix and Include Record | AO76: =B76&C76&D76 -> MasonHitti | AP76: =LEFT(G76,FIND(",",G76)-1) -> #VALUE! | AQ76: =IFERROR(VLOOKUP(AP76,D:P,13,FALSE),"No Reports to Name") -> No Reports to Name | AR76: =AQ76=MID(H76,4,6) -> FALSE
A77: KSY | B77: Carrie | C77: M | D77: Hoffman | G77: Oleksa, Laura | H77: V0U209181 | I77: choffman@onebarnes.com | J77: Carriehoffman89@gmail.com | K77: HR Coordinator | L77: 43101 | O77: Active | P77: 902349 | Q77: Monthly | R77: Full Time | S77: 088 | T77: 088-AS Raymond | U77: HR General | V77: 009200 | W77: AS Raymond | Z77: USA | AA77: S11 | AB77: FMG-S11 | AC77: =IF(ISBLANK(H77),VLOOKUP(P77,'US Supervisor Map'!A:D,4,FALSE),MID(H77,4,6)) -> 209181 | AD77: =IFERROR(VLOOKUP(T77,'Org Map'!A:E,4),"BU Description Not Mapped") -> 0088 | AE77: =IFERROR(VLOOKUP(V77,'Org Map'!C:E,3),"Home Department Code Not Mapped") -> 9200 | AF77: =IFERROR(VLOOKUP(AA77,'Salary Map'!A:D,3,FALSE),"Salary Code Not Mapped") -> Default | AG77: =IFERROR(VLOOKUP(AA77,'Salary Map'!A:D,4,FALSE),"Salary Code Not Mapped") -> General | AH77: =IFERROR(VLOOKUP(Z77,'Country Map'!A:B,2,FALSE),"Legal Country Not Mapped") -> US | AI77: =IFERROR(VLOOKUP(X77,'Language Map'!A:C,3,FALSE),IFERROR(VLOOKUP(T77,'Org Map'!A:F,6,FALSE),"ADP and BU Language Code Not Mapped"))&AH77 -> en_US | AJ77: =IFERROR(VLOOKUP(T77,'Org Map'!A:G,7),"BU Currency Not Mapped") -> USD | AK77: =IF(ISBLANK(E77),"",TRIM(E77&" "&F77)) | AL77: =IFERROR(VLOOKUP(O77,'Status Map'!A:B,2,FALSE),"Position Status Not Mapped") -> Y | AM77: =IF(AL77="N",TEXT(M77,"yyyymmdd"),"") | AO77: =B77&C77&D77 -> CarrieMHoffman | AP77: =LEFT(G77,FIND(",",G77)-1) -> Oleksa | AQ77: =IFERROR(VLOOKUP(AP77,D:P,13,FALSE),"No Reports to Name") -> 209181 | AR77: =AQ77=MID(H77,4,6) -> TRUE
A78: KSX | B78: LaMarr | D78: Hogue | G78: Rogers, Wayne | H78: KSY207487 | J78: lamarr.hogue@gmail.com | K78: Assistant, Warehouse II | L78: 46062 | O78: Active | P78: 212966 | Q78: Biweekly | R78: Full Time | S78: 088 | T78: 088-AS Raymond | U78: FG Warehouse | V78: 005200 | W78: AS Raymond | Z78: USA | AA78: S05 | AB78: FMG-S05 | AC78: =IF(ISBLANK(H78),VLOOKUP(P78,'US Supervisor Map'!A:D,4,FALSE),MID(H78,4,6)) -> 207487 | AD78: =IFERROR(VLOOKUP(T78,'Org Map'!A:E,4),"BU Description Not Mapped") -> 0088 | AE78: =IFERROR(VLOOKUP(V78,'Org Map'!C:E,3),"Home Department Code Not Mapped") -> 5200 | AF78: =IFERROR(VLOOKUP(AA78,'Salary Map'!A:D,3,FALSE),"Salary Code Not Mapped") -> Default | AG78: =IFERROR(VLOOKUP(AA78,'Salary Map'!A:D,4,FALSE),"Salary Code Not Mapped") -> General | AH78: =IFERROR(VLOOKUP(Z78,'Country Map'!A:B,2,FALSE),"Legal Country Not Mapped") -> US | AI78: =IFERROR(VLOOKUP(X78,'Language Map'!A:C,3,FALSE),IFERROR(VLOOKUP(T78,'Org Map'!A:F,6,FALSE),"ADP and BU Language Code Not Mapped"))&AH78 -> en_US | AJ78: =IFERROR(VLOOKUP(T78,'Org Map'!A:G,7),"BU Currency Not Mapped") -> USD | AK78: =IF(ISBLANK(E78),"",TRIM(E78&" "&F78)) | AL78: =IFERROR(VLOOKUP(O78,'Status Map'!A:B,2,FALSE),"Position Status Not Mapped") -> Y | AM78: =IF(AL78="N",TEXT(M78,"yyyymmdd"),"") | AO78: =B78&C78&D78 -> LaMarrHogue | AP78: =LEFT(G78,FIND(",",G78)-1) -> Rogers | AQ78: =IFERROR(VLOOKUP(AP78,D:P,13,FALSE),"No Reports to Name") -> 207487 | AR78: =AQ78=MID(H78,4,6) -> TRUE
A79: KSX | B79: Richard | C79: W | D79: Hutt | G79: LaPlante, Derek | H79: KSY211736 | I79: rhutt@onebarnes.com | J79: richard.hutt95@gmail.com | K79: Coord, Logistics I | L79: 45768 | O79: Active | P79: 211932 | Q79: Biweekly | R79: Full Time | S79: 088 | T79: 088-AS Raymond | U79: FG Warehouse | V79: 005200 | W79: AS Raymond | Z79: USA | AA79: S06 | AB79: FMG-S06 | AC79: =IF(ISBLANK(H79),VLOOKUP(P79,'US Supervisor Map'!A:D,4,FALSE),MID(H79,4,6)) -> 211736 | AD79: =IFERROR(VLOOKUP(T79,'Org Map'!A:E,4),"BU Description Not Mapped") -> 0088 | AE79: =IFERROR(VLOOKUP(V79,'Org Map'!C:E,3),"Home Department Code Not Mapped") -> 5200 | AF79: =IFERROR(VLOOKUP(AA79,'Salary Map'!A:D,3,FALSE),"Salary Code Not Mapped") -> Default | AG79: =IFERROR(VLOOKUP(AA79,'Salary Map'!A:D,4,FALSE),"Salary Code Not Mapped") -> General | AH79: =IFERROR(VLOOKUP(Z79,'Country Map'!A:B,2,FALSE),"Legal Country Not Mapped") -> US | AI79: =IFERROR(VLOOKUP(X79,'Language Map'!A:C,3,FALSE),IFERROR(VLOOKUP(T79,'Org Map'!A:F,6,FALSE),"ADP and BU Language Code Not Mapped"))&AH79 -> en_US | AJ79: =IFERROR(VLOOKUP(T79,'Org Map'!A:G,7),"BU Currency Not Mapped") -> USD | AK79: =IF(ISBLANK(E79),"",TRIM(E79&" "&F79)) | AL79: =IFERROR(VLOOKUP(O79,'Status Map'!A:B,2,FALSE),"Position Status Not Mapped") -> Y | AM79: =IF(AL79="N",TEXT(M79,"yyyymmdd"),"") | AO79: =B79&C79&D79 -> RichardWHutt | AP79: =LEFT(G79,FIND(",",G79)-1) -> LaPlante | AQ79: =IFERROR(VLOOKUP(AP79,D:P,13,FALSE),"No Reports to Name") -> 211736 | AR79: =AQ79=MID(H79,4,6) -> TRUE
A80: KSW | B80: Frank | D80: Izzo | G80: Valetta, David | H80: V0U211601 | I80: FIzzo@onebarnes.com | K80: Mgr, Finance II | L80: 44410 | O80: Active | P80: 206442 | Q80: Biweekly | R80: Part Time Long Term EE | S80: 025 | T80: 025-NGP Hyson Products | U80: Project Management | V80: 000801 | W80: Hyson Products | Z80: USA | AA80: S16 | AB80: FMG-S16 | AC80: =IF(ISBLANK(H80),VLOOKUP(P80,'US Supervisor Map'!A:D,4,FALSE),MID(H80,4,6)) -> 211601 | AD80: =IFERROR(VLOOKUP(T80,'Org Map'!A:E,4),"BU Description Not Mapped") -> 0096 | AE80: =IFERROR(VLOOKUP(V80,'Org Map'!C:E,3),"Home Department Code Not Mapped") -> 801 | AF80: =IFERROR(VLOOKUP(AA80,'Salary Map'!A:D,3,FALSE),"Salary Code Not Mapped") -> Default | AG80: =IFERROR(VLOOKUP(AA80,'Salary Map'!A:D,4,FALSE),"Salary Code Not Mapped") -> General | AH80: =IFERROR(VLOOKUP(Z80,'Country Map'!A:B,2,FALSE),"Legal Country Not Mapped") -> US | AI80: =IFERROR(VLOOKUP(X80,'Language Map'!A:C,3,FALSE),IFERROR(VLOOKUP(T80,'Org Map'!A:F,6,FALSE),"ADP and BU Language Code Not Mapped"))&AH80 -> en_US | AJ80: =IFERROR(VLOOKUP(T80,'Org Map'!A:G,7),"BU Currency Not Mapped") -> USD | AK80: =IF(ISBLANK(E80),"",TRIM(E80&" "&F80)) | AL80: =IFERROR(VLOOKUP(O80,'Status Map'!A:B,2,FALSE),"Position Status Not Mapped") -> Y | AM80: =IF(AL80="N",TEXT(M80,"yyyymmdd"),"") | AO80: =B80&C80&D80 -> FrankIzzo | AP80: =LEFT(G80,FIND(",",G80)-1) -> Valetta | AQ80: =IFERROR(VLOOKUP(AP80,D:P,13,FALSE),"No Reports to Name") -> 211601 | AR80: =AQ80=MID(H80,4,6) -> TRUE
A81: V0U | B81: Frank | D81: Izzo | H81: V0U211601 | I81: FIzzo@onebarnes.com | K81: Mgr, Finance II | L81: 44410 | M81: 46204 | O81: Terminated | P81: 206442 | Q81: Monthly | R81: Full Time | S81: 025 | T81: 025-NGP Hyson Products | U81: Project Management | V81: 000801 | W81: Hyson Products | Z81: USA | AA81: S16 | AB81: FMG-S16 | AC81: =IF(ISBLANK(H81),VLOOKUP(P81,'US Supervisor Map'!A:D,4,FALSE),MID(H81,4,6)) -> 211601 | AD81: =IFERROR(VLOOKUP(T81,'Org Map'!A:E,4),"BU Description Not Mapped") -> 0096 | AE81: =IFERROR(VLOOKUP(V81,'Org Map'!C:E,3),"Home Department Code Not Mapped") -> 801 | AF81: =IFERROR(VLOOKUP(AA81,'Salary Map'!A:D,3,FALSE),"Salary Code Not Mapped") -> Default | AG81: =IFERROR(VLOOKUP(AA81,'Salary Map'!A:D,4,FALSE),"Salary Code Not Mapped") -> General | AH81: =IFERROR(VLOOKUP(Z81,'Country Map'!A:B,2,FALSE),"Legal Country Not Mapped") -> US | AI81: =IFERROR(VLOOKUP(X81,'Language Map'!A:C,3,FALSE),IFERROR(VLOOKUP(T81,'Org Map'!A:F,6,FALSE),"ADP and BU Language Code Not Mapped"))&AH81 -> en_US | AJ81: =IFERROR(VLOOKUP(T81,'Org Map'!A:G,7),"BU Currency Not Mapped") -> USD | AK81: =IF(ISBLANK(E81),"",TRIM(E81&" "&F81)) | AL81: =IFERROR(VLOOKUP(O81,'Status Map'!A:B,2,FALSE),"Position Status Not Mapped") -> N | AM81: =IF(AL81="N",TEXT(M81,"yyyymmdd"),"") -> 20260701 | AN81: =IF(M81>AN76,"Fix and Include Record","Exclude record termination over 45 days ago") -> Exclude record termination over 45 days ago | AO81: =B81&C81&D81 -> FrankIzzo | AP81: =LEFT(G81,FIND(",",G81)-1) -> #VALUE! | AQ81: =IFERROR(VLOOKUP(AP81,D:P,13,FALSE),"No Reports to Name") -> No Reports to Name | AR81: =AQ81=MID(H81,4,6) -> FALSE
A82: KSY | B82: Christopher | C82: G | D82: Jablonsky | I82: cjablonsky@onebarnes.com | K82: Mgr, Sales | L82: 45915 | M82: 46122 | O82: Terminated | P82: 212479 | Q82: Monthly | R82: Full Time | S82: 088 | T82: 088-AS Raymond | U82: Outside Sales | V82: 008200 | W82: Work from home - Ohio - New | Z82: USA | AA82: S16 | AB82: FMG-S16 | AC82: =IF(ISBLANK(H82),VLOOKUP(P82,'US Supervisor Map'!A:D,4,FALSE),MID(H82,4,6)) | AD82: =IFERROR(VLOOKUP(T82,'Org Map'!A:E,4),"BU Description Not Mapped") -> 0088 | AE82: =IFERROR(VLOOKUP(V82,'Org Map'!C:E,3),"Home Department Code Not Mapped") -> 8200 | AF82: =IFERROR(VLOOKUP(AA82,'Salary Map'!A:D,3,FALSE),"Salary Code Not Mapped") -> Default | AG82: =IFERROR(VLOOKUP(AA82,'Salary Map'!A:D,4,FALSE),"Salary Code Not Mapped") -> General | AH82: =IFERROR(VLOOKUP(Z82,'Country Map'!A:B,2,FALSE),"Legal Country Not Mapped") -> US | AI82: =IFERROR(VLOOKUP(X82,'Language Map'!A:C,3,FALSE),IFERROR(VLOOKUP(T82,'Org Map'!A:F,6,FALSE),"ADP and BU Language Code Not Mapped"))&AH82 -> en_US | AJ82: =IFERROR(VLOOKUP(T82,'Org Map'!A:G,7),"BU Currency Not Mapped") -> USD | AK82: =IF(ISBLANK(E82),"",TRIM(E82&" "&F82)) | AL82: =IFERROR(VLOOKUP(O82,'Status Map'!A:B,2,FALSE),"Position Status Not Mapped") -> N | AM82: =IF(AL82="N",TEXT(M82,"yyyymmdd"),"") -> 20260410 | AN82: =IF(M82>AN77,"Fix and Include Record","Exclude record termination over 45 days ago") -> Fix and Include Record | AO82: =B82&C82&D82 -> ChristopherGJablonsky | AP82: =LEFT(G82,FIND(",",G82)-1) -> #VALUE! | AQ82: =IFERROR(VLOOKUP(AP82,D:P,13,FALSE),"No Reports to Name") -> No Reports to Name | AR82: =AQ82=MID(H82,4,6) -> FALSE
A83: KSW | B83: Jordan | D83: James | G83: Steen, Michael | H83: V0U211062 | J83: jrdnjms18@gmail.com | K83: Assembler C | L83: 45771 | O83: Active | P83: 211943 | Q83: Biweekly | R83: Full Time | S83: 025 | T83: 025-NGP Hyson Products | U83: Assembly Hyson | V83: 000200 | W83: Hyson Products | Z83: USA | AA83: H05 | AB83: FMG-H05 | AC83: =IF(ISBLANK(H83),VLOOKUP(P83,'US Supervisor Map'!A:D,4,FALSE),MID(H83,4,6)) -> 211062 | AD83: =IFERROR(VLOOKUP(T83,'Org Map'!A:E,4),"BU Description Not Mapped") -> 0096 | AE83: =IFERROR(VLOOKUP(V83,'Org Map'!C:E,3),"Home Department Code Not Mapped") -> 200 | AF83: =IFERROR(VLOOKUP(AA83,'Salary Map'!A:D,3,FALSE),"Salary Code Not Mapped") -> Default | AG83: =IFERROR(VLOOKUP(AA83,'Salary Map'!A:D,4,FALSE),"Salary Code Not Mapped") -> General | AH83: =IFERROR(VLOOKUP(Z83,'Country Map'!A:B,2,FALSE),"Legal Country Not Mapped") -> US | AI83: =IFERROR(VLOOKUP(X83,'Language Map'!A:C,3,FALSE),IFERROR(VLOOKUP(T83,'Org Map'!A:F,6,FALSE),"ADP and BU Language Code Not Mapped"))&AH83 -> en_US | AJ83: =IFERROR(VLOOKUP(T83,'Org Map'!A:G,7),"BU Currency Not Mapped") -> USD | AK83: =IF(ISBLANK(E83),"",TRIM(E83&" "&F83)) | AL83: =IFERROR(VLOOKUP(O83,'Status Map'!A:B,2,FALSE),"Position Status Not Mapped") -> Y | AM83: =IF(AL83="N",TEXT(M83,"yyyymmdd"),"") | AO83: =B83&C83&D83 -> JordanJames | AP83: =LEFT(G83,FIND(",",G83)-1) -> Steen | AQ83: =IFERROR(VLOOKUP(AP83,D:P,13,FALSE),"No Reports to Name") -> 211062 | AR83: =AQ83=MID(H83,4,6) -> TRUE
A84: KSX | B84: Keith | C84: L | D84: James | G84: Rogers, Wayne | H84: KSY207487 | I84: kjames@onebarnes.com | J84: myzonkj87@gmail.com | K84: Assistant, Warehouse II | L84: 42828 | O84: Active | P84: 902026 | Q84: Biweekly | R84: Full Time | S84: 088 | T84: 088-AS Raymond | U84: FG Warehouse | V84: 005200 | W84: AS Raymond | Z84: USA | AA84: S05 | AB84: FMG-S05 | AC84: =IF(ISBLANK(H84),VLOOKUP(P84,'US Supervisor Map'!A:D,4,FALSE),MID(H84,4,6)) -> 207487 | AD84: =IFERROR(VLOOKUP(T84,'Org Map'!A:E,4),"BU Description Not Mapped") -> 0088 | AE84: =IFERROR(VLOOKUP(V84,'Org Map'!C:E,3),"Home Department Code Not Mapped") -> 5200 | AF84: =IFERROR(VLOOKUP(AA84,'Salary Map'!A:D,3,FALSE),"Salary Code Not Mapped") -> Default | AG84: =IFERROR(VLOOKUP(AA84,'Salary Map'!A:D,4,FALSE),"Salary Code Not Mapped") -> General | AH84: =IFERROR(VLOOKUP(Z84,'Country Map'!A:B,2,FALSE),"Legal Country Not Mapped") -> US | AI84: =IFERROR(VLOOKUP(X84,'Language Map'!A:C,3,FALSE),IFERROR(VLOOKUP(T84,'Org Map'!A:F,6,FALSE),"ADP and BU Language Code Not Mapped"))&AH84 -> en_US | AJ84: =IFERROR(VLOOKUP(T84,'Org Map'!A:G,7),"BU Currency Not Mapped") -> USD | AK84: =IF(ISBLANK(E84),"",TRIM(E84&" "&F84)) | AL84: =IFERROR(VLOOKUP(O84,'Status Map'!A:B,2,FALSE),"Position Status Not Mapped") -> Y | AM84: =IF(AL84="N",TEXT(M84,"yyyymmdd"),"") | AO84: =B84&C84&D84 -> KeithLJames | AP84: =LEFT(G84,FIND(",",G84)-1) -> Rogers | AQ84: =IFERROR(VLOOKUP(AP84,D:P,13,FALSE),"No Reports to Name") -> 207487 | AR84: =AQ84=MID(H84,4,6) -> TRUE
A85: KSY | B85: Michael | D85: Jones | G85: Rodriguez, Siobhan | H85: V0U207588 | I85: mjones@onebarnes.com | J85: MIKEJONES6085@GMAIL.COM | K85: Mgr, Sales | L85: 45895 | O85: Active | P85: 212418 | Q85: Monthly | R85: Full Time | S85: 088 | T85: 088-AS Raymond | U85: Outside Sales | V85: 008200 | W85: Works from home - Ohio | Z85: USA | AA85: S16 | AB85: FMG-S16 | AC85: =IF(ISBLANK(H85),VLOOKUP(P85,'US Supervisor Map'!A:D,4,FALSE),MID(H85,4,6)) -> 207588 | AD85: =IFERROR(VLOOKUP(T85,'Org Map'!A:E,4),"BU Description Not Mapped") -> 0088 | AE85: =IFERROR(VLOOKUP(V85,'Org Map'!C:E,3),"Home Department Code Not Mapped") -> 8200 | AF85: =IFERROR(VLOOKUP(AA85,'Salary Map'!A:D,3,FALSE),"Salary Code Not Mapped") -> Default | AG85: =IFERROR(VLOOKUP(AA85,'Salary Map'!A:D,4,FALSE),"Salary Code Not Mapped") -> General | AH85: =IFERROR(VLOOKUP(Z85,'Country Map'!A:B,2,FALSE),"Legal Country Not Mapped") -> US | AI85: =IFERROR(VLOOKUP(X85,'Language Map'!A:C,3,FALSE),IFERROR(VLOOKUP(T85,'Org Map'!A:F,6,FALSE),"ADP and BU Language Code Not Mapped"))&AH85 -> en_US | AJ85: =IFERROR(VLOOKUP(T85,'Org Map'!A:G,7),"BU Currency Not Mapped") -> USD | AK85: =IF(ISBLANK(E85),"",TRIM(E85&" "&F85)) | AL85: =IFERROR(VLOOKUP(O85,'Status Map'!A:B,2,FALSE),"Position Status Not Mapped") -> Y | AM85: =IF(AL85="N",TEXT(M85,"yyyymmdd"),"") | AO85: =B85&C85&D85 -> MichaelJones | AP85: =LEFT(G85,FIND(",",G85)-1) -> Rodriguez | AQ85: =IFERROR(VLOOKUP(AP85,D:P,13,FALSE),"No Reports to Name") -> 212338 | AR85: =AQ85=MID(H85,4,6) -> FALSE
A86: KSX | B86: Shelleion | D86: Jones | G86: Williams, Rachel | H86: KSY202533 | I86: sjones@onebarnes.con | J86: shelleionj@gmail.com | K86: Rep, Customer Service III | L86: 46049 | O86: Active | Q86: Biweekly | R86: Temporary | S86: 088 | T86: 088-AS Raymond | U86: Inside Sales | V86: 008100 | W86: AS Raymond | Z86: USA | AA86: S11 | AB86: FMG-S11 | AC86: =IF(ISBLANK(H86),VLOOKUP(P86,'US Supervisor Map'!A:D,4,FALSE),MID(H86,4,6)) -> 202533 | AD86: =IFERROR(VLOOKUP(T86,'Org Map'!A:E,4),"BU Description Not Mapped") -> 0088 | AE86: =IFERROR(VLOOKUP(V86,'Org Map'!C:E,3),"Home Department Code Not Mapped") -> 8100 | AF86: =IFERROR(VLOOKUP(AA86,'Salary Map'!A:D,3,FALSE),"Salary Code Not Mapped") -> Default | AG86: =IFERROR(VLOOKUP(AA86,'Salary Map'!A:D,4,FALSE),"Salary Code Not Mapped") -> General | AH86: =IFERROR(VLOOKUP(Z86,'Country Map'!A:B,2,FALSE),"Legal Country Not Mapped") -> US | AI86: =IFERROR(VLOOKUP(X86,'Language Map'!A:C,3,FALSE),IFERROR(VLOOKUP(T86,'Org Map'!A:F,6,FALSE),"ADP and BU Language Code Not Mapped"))&AH86 -> en_US | AJ86: =IFERROR(VLOOKUP(T86,'Org Map'!A:G,7),"BU Currency Not Mapped") -> USD | AK86: =IF(ISBLANK(E86),"",TRIM(E86&" "&F86)) | AL86: =IFERROR(VLOOKUP(O86,'Status Map'!A:B,2,FALSE),"Position Status Not Mapped") -> Y | AM86: =IF(AL86="N",TEXT(M86,"yyyymmdd"),"") | AO86: =B86&C86&D86 -> ShelleionJones | AP86: =LEFT(G86,FIND(",",G86)-1) -> Williams | AQ86: =IFERROR(VLOOKUP(AP86,D:P,13,FALSE),"No Reports to Name") -> 202533 | AR86: =AQ86=MID(H86,4,6) -> TRUE
A87: KSX | B87: Brandon | D87: Kelly | G87: Alexander, Thomas | H87: KSY210892 | J87: bkelly8@rockets.utoledo.edu | K87: Intern, Operations Direct | L87: 46155 | M87: 46248 | O87: Terminated | P87: 213235 | Q87: Biweekly | R87: Intern | S87: 088 | T87: 088-AS Raymond | U87: Admin-Quality | V87: 009500 | W87: AS Raymond | Z87: USA | AA87: H05 | AB87: FMG-H05 | AC87: =IF(ISBLANK(H87),VLOOKUP(P87,'US Supervisor Map'!A:D,4,FALSE),MID(H87,4,6)) -> 210892 | AD87: =IFERROR(VLOOKUP(T87,'Org Map'!A:E,4),"BU Description Not Mapped") -> 0088 | AE87: =IFERROR(VLOOKUP(V87,'Org Map'!C:E,3),"Home Department Code Not Mapped") -> 9500 | AF87: =IFERROR(VLOOKUP(AA87,'Salary Map'!A:D,3,FALSE),"Salary Code Not Mapped") -> Default | AG87: =IFERROR(VLOOKUP(AA87,'Salary Map'!A:D,4,FALSE),"Salary Code Not Mapped") -> General | AH87: =IFERROR(VLOOKUP(Z87,'Country Map'!A:B,2,FALSE),"Legal Country Not Mapped") -> US | AI87: =IFERROR(VLOOKUP(X87,'Language Map'!A:C,3,FALSE),IFERROR(VLOOKUP(T87,'Org Map'!A:F,6,FALSE),"ADP and BU Language Code Not Mapped"))&AH87 -> en_US | AJ87: =IFERROR(VLOOKUP(T87,'Org Map'!A:G,7),"BU Currency Not Mapped") -> USD | AK87: =IF(ISBLANK(E87),"",TRIM(E87&" "&F87)) | AL87: =IFERROR(VLOOKUP(O87,'Status Map'!A:B,2,FALSE),"Position Status Not Mapped") -> N | AM87: =IF(AL87="N",TEXT(M87,"yyyymmdd"),"") -> 20260814 | AN87: =IF(M87>AN82,"Fix and Include Record","Exclude record termination over 45 days ago") -> Exclude record termination over 45 days ago | AO87: =B87&C87&D87 -> BrandonKelly | AP87: =LEFT(G87,FIND(",",G87)-1) -> Alexander | AQ87: =IFERROR(VLOOKUP(AP87,D:P,13,FALSE),"No Reports to Name") -> 210892 | AR87: =AQ87=MID(H87,4,6) -> TRUE
A88: KSW | B88: Mason | C88: R | D88: Kelly | G88: Steen, Michael | H88: V0U211062 | J88: kuhlma03335@gmail.com | K88: Machinist, CNC | L88: 44480 | O88: Active | P88: 206680 | Q88: Biweekly | R88: Full Time | S88: 025 | T88: 025-NGP Hyson Products | U88: CNC Lathe Hyson | V88: 000100 | W88: Hyson Products | Z88: USA | AA88: H04 | AB88: FMG-H04 | AC88: =IF(ISBLANK(H88),VLOOKUP(P88,'US Supervisor Map'!A:D,4,FALSE),MID(H88,4,6)) -> 211062 | AD88: =IFERROR(VLOOKUP(T88,'Org Map'!A:E,4),"BU Description Not Mapped") -> 0096 | AE88: =IFERROR(VLOOKUP(V88,'Org Map'!C:E,3),"Home Department Code Not Mapped") -> 100 | AF88: =IFERROR(VLOOKUP(AA88,'Salary Map'!A:D,3,FALSE),"Salary Code Not Mapped") -> Default | AG88: =IFERROR(VLOOKUP(AA88,'Salary Map'!A:D,4,FALSE),"Salary Code Not Mapped") -> General | AH88: =IFERROR(VLOOKUP(Z88,'Country Map'!A:B,2,FALSE),"Legal Country Not Mapped") -> US | AI88: =IFERROR(VLOOKUP(X88,'Language Map'!A:C,3,FALSE),IFERROR(VLOOKUP(T88,'Org Map'!A:F,6,FALSE),"ADP and BU Language Code Not Mapped"))&AH88 -> en_US | AJ88: =IFERROR(VLOOKUP(T88,'Org Map'!A:G,7),"BU Currency Not Mapped") -> USD | AK88: =IF(ISBLANK(E88),"",TRIM(E88&" "&F88)) | AL88: =IFERROR(VLOOKUP(O88,'Status Map'!A:B,2,FALSE),"Position Status Not Mapped") -> Y | AM88: =IF(AL88="N",TEXT(M88,"yyyymmdd"),"") | AO88: =B88&C88&D88 -> MasonRKelly | AP88: =LEFT(G88,FIND(",",G88)-1) -> Steen | AQ88: =IFERROR(VLOOKUP(AP88,D:P,13,FALSE),"No Reports to Name") -> 211062 | AR88: =AQ88=MID(H88,4,6) -> TRUE
A89: KSY | B89: Greg | D89: Kemenah | G89: Bair, Teresa | H89: KSY207709 | I89: gkemenah@onebarnes.com | J89: kemenah@live.com | K89: Mgr, General I | L89: 45712 | O89: Active | P89: 211766 | Q89: Monthly | R89: Full Time | S89: 088 | T89: 088-AS Raymond | U89: Admin-Engineering | V89: 009450 | W89: AS Raymond | Z89: USA | AA89: S19 | AB89: FMG-S19 | AC89: =IF(ISBLANK(H89),VLOOKUP(P89,'US Supervisor Map'!A:D,4,FALSE),MID(H89,4,6)) -> 207709 | AD89: =IFERROR(VLOOKUP(T89,'Org Map'!A:E,4),"BU Description Not Mapped") -> 0088 | AE89: =IFERROR(VLOOKUP(V89,'Org Map'!C:E,3),"Home Department Code Not Mapped") -> 9450 | AF89: =IFERROR(VLOOKUP(AA89,'Salary Map'!A:D,3,FALSE),"Salary Code Not Mapped") -> Default | AG89: =IFERROR(VLOOKUP(AA89,'Salary Map'!A:D,4,FALSE),"Salary Code Not Mapped") -> General | AH89: =IFERROR(VLOOKUP(Z89,'Country Map'!A:B,2,FALSE),"Legal Country Not Mapped") -> US | AI89: =IFERROR(VLOOKUP(X89,'Language Map'!A:C,3,FALSE),IFERROR(VLOOKUP(T89,'Org Map'!A:F,6,FALSE),"ADP and BU Language Code Not Mapped"))&AH89 -> en_US | AJ89: =IFERROR(VLOOKUP(T89,'Org Map'!A:G,7),"BU Currency Not Mapped") -> USD | AK89: =IF(ISBLANK(E89),"",TRIM(E89&" "&F89)) | AL89: =IFERROR(VLOOKUP(O89,'Status Map'!A:B,2,FALSE),"Position Status Not Mapped") -> Y | AM89: =IF(AL89="N",TEXT(M89,"yyyymmdd"),"") | AO89: =B89&C89&D89 -> GregKemenah | AP89: =LEFT(G89,FIND(",",G89)-1) -> Bair | AQ89: =IFERROR(VLOOKUP(AP89,D:P,13,FALSE),"No Reports to Name") -> 207709 | AR89: =AQ89=MID(H89,4,6) -> TRUE
A90: KSX | B90: Jacob | C90: A | D90: Kemenah | G90: Warner, Dwight | H90: V0U008750 | J90: jkemenah@outlook.com | K90: Intern, Finance Indirect | L90: 46153 | M90: 46248 | O90: Terminated | P90: 213229 | Q90: Biweekly | R90: Intern | S90: 088 | T90: 088-AS Raymond | U90: Finance General | V90: 009100 | W90: AS Raymond | Z90: USA | AA90: H05 | AB90: FMG-H05 | AC90: =IF(ISBLANK(H90),VLOOKUP(P90,'US Supervisor Map'!A:D,4,FALSE),MID(H90,4,6)) -> 008750 | AD90: =IFERROR(VLOOKUP(T90,'Org Map'!A:E,4),"BU Description Not Mapped") -> 0088 | AE90: =IFERROR(VLOOKUP(V90,'Org Map'!C:E,3),"Home Department Code Not Mapped") -> 9100 | AF90: =IFERROR(VLOOKUP(AA90,'Salary Map'!A:D,3,FALSE),"Salary Code Not Mapped") -> Default | AG90: =IFERROR(VLOOKUP(AA90,'Salary Map'!A:D,4,FALSE),"Salary Code Not Mapped") -> General | AH90: =IFERROR(VLOOKUP(Z90,'Country Map'!A:B,2,FALSE),"Legal Country Not Mapped") -> US | AI90: =IFERROR(VLOOKUP(X90,'Language Map'!A:C,3,FALSE),IFERROR(VLOOKUP(T90,'Org Map'!A:F,6,FALSE),"ADP and BU Language Code Not Mapped"))&AH90 -> en_US | AJ90: =IFERROR(VLOOKUP(T90,'Org Map'!A:G,7),"BU Currency Not Mapped") -> USD | AK90: =IF(ISBLANK(E90),"",TRIM(E90&" "&F90)) | AL90: =IFERROR(VLOOKUP(O90,'Status Map'!A:B,2,FALSE),"Position Status Not Mapped") -> N | AM90: =IF(AL90="N",TEXT(M90,"yyyymmdd"),"") -> 20260814 | AN90: =IF(M90>AN85,"Fix and Include Record","Exclude record termination over 45 days ago") -> Fix and Include Record | AO90: =B90&C90&D90 -> JacobAKemenah | AP90: =LEFT(G90,FIND(",",G90)-1) -> Warner | AQ90: =IFERROR(VLOOKUP(AP90,D:P,13,FALSE),"No Reports to Name") -> 008750 | AR90: =AQ90=MID(H90,4,6) -> TRUE
A91: KSY | B91: Sai Anusha | D91: Kodali | G91: Kemenah, Greg | H91: KSY211766 | I91: skodalii@onebarnes.com | J91: ksaianusha.2@gmail.com | K91: Spec, Marketing I | L91: 45461 | O91: Leave | P91: 211085 | Q91: Monthly | R91: Full Time | S91: 088 | T91: 088-AS Raymond | U91: Marketing | V91: 008300 | W91: AS Raymond | Z91: USA | AA91: S12 | AB91: FMG-S12 | AC91: =IF(ISBLANK(H91),VLOOKUP(P91,'US Supervisor Map'!A:D,4,FALSE),MID(H91,4,6)) -> 211766 | AD91: =IFERROR(VLOOKUP(T91,'Org Map'!A:E,4),"BU Description Not Mapped") -> 0088 | AE91: =IFERROR(VLOOKUP(V91,'Org Map'!C:E,3),"Home Department Code Not Mapped") -> 8300 | AF91: =IFERROR(VLOOKUP(AA91,'Salary Map'!A:D,3,FALSE),"Salary Code Not Mapped") -> Default | AG91: =IFERROR(VLOOKUP(AA91,'Salary Map'!A:D,4,FALSE),"Salary Code Not Mapped") -> General | AH91: =IFERROR(VLOOKUP(Z91,'Country Map'!A:B,2,FALSE),"Legal Country Not Mapped") -> US | AI91: =IFERROR(VLOOKUP(X91,'Language Map'!A:C,3,FALSE),IFERROR(VLOOKUP(T91,'Org Map'!A:F,6,FALSE),"ADP and BU Language Code Not Mapped"))&AH91 -> en_US | AJ91: =IFERROR(VLOOKUP(T91,'Org Map'!A:G,7),"BU Currency Not Mapped") -> USD | AK91: =IF(ISBLANK(E91),"",TRIM(E91&" "&F91)) | AL91: =IFERROR(VLOOKUP(O91,'Status Map'!A:B,2,FALSE),"Position Status Not Mapped") -> Y | AM91: =IF(AL91="N",TEXT(M91,"yyyymmdd"),"") | AO91: =B91&C91&D91 -> Sai AnushaKodali | AP91: =LEFT(G91,FIND(",",G91)-1) -> Kemenah | AQ91: =IFERROR(VLOOKUP(AP91,D:P,13,FALSE),"No Reports to Name") -> 211766 | AR91: =AQ91=MID(H91,4,6) -> TRUE
A92: KSW | B92: Christopher | C92: J | D92: Kostohryz | G92: Steen, Michael | H92: V0U211062 | J92: cjkgoat@cox.net | K92: Machinist B | L92: 32405 | O92: Active | P92: 006805 | Q92: Biweekly | R92: Full Time | S92: 025 | T92: 025-NGP Hyson Products | U92: CNC Lathe Hyson | V92: 000100 | W92: Hyson Products | Z92: USA | AA92: H07 | AB92: FMG-H07 | AC92: =IF(ISBLANK(H92),VLOOKUP(P92,'US Supervisor Map'!A:D,4,FALSE),MID(H92,4,6)) -> 211062 | AD92: =IFERROR(VLOOKUP(T92,'Org Map'!A:E,4),"BU Description Not Mapped") -> 0096 | AE92: =IFERROR(VLOOKUP(V92,'Org Map'!C:E,3),"Home Department Code Not Mapped") -> 100 | AF92: =IFERROR(VLOOKUP(AA92,'Salary Map'!A:D,3,FALSE),"Salary Code Not Mapped") -> Default | AG92: =IFERROR(VLOOKUP(AA92,'Salary Map'!A:D,4,FALSE),"Salary Code Not Mapped") -> General | AH92: =IFERROR(VLOOKUP(Z92,'Country Map'!A:B,2,FALSE),"Legal Country Not Mapped") -> US | AI92: =IFERROR(VLOOKUP(X92,'Language Map'!A:C,3,FALSE),IFERROR(VLOOKUP(T92,'Org Map'!A:F,6,FALSE),"ADP and BU Language Code Not Mapped"))&AH92 -> en_US | AJ92: =IFERROR(VLOOKUP(T92,'Org Map'!A:G,7),"BU Currency Not Mapped") -> USD | AK92: =IF(ISBLANK(E92),"",TRIM(E92&" "&F92)) | AL92: =IFERROR(VLOOKUP(O92,'Status Map'!A:B,2,FALSE),"Position Status Not Mapped") -> Y | AM92: =IF(AL92="N",TEXT(M92,"yyyymmdd"),"") | AO92: =B92&C92&D92 -> ChristopherJKostohryz | AP92: =LEFT(G92,FIND(",",G92)-1) -> Steen | AQ92: =IFERROR(VLOOKUP(AP92,D:P,13,FALSE),"No Reports to Name") -> 211062 | AR92: =AQ92=MID(H92,4,6) -> TRUE
A93: KSX | B93: Wendy | D93: Kozicki | G93: Williams, Rachel | H93: KSY202533 | I93: wkozicki@onebarnes.com | K93: Rep, Customer Service I | L93: 46174 | O93: Active | P93: 213298 | Q93: Biweekly | R93: Full Time | S93: 088 | T93: 088-AS Raymond | U93: Inside Sales | V93: 008100 | W93: AS Raymond | Z93: USA | AA93: S08 | AB93: FMG-S08 | AC93: =IF(ISBLANK(H93),VLOOKUP(P93,'US Supervisor Map'!A:D,4,FALSE),MID(H93,4,6)) -> 202533 | AD93: =IFERROR(VLOOKUP(T93,'Org Map'!A:E,4),"BU Description Not Mapped") -> 0088 | AE93: =IFERROR(VLOOKUP(V93,'Org Map'!C:E,3),"Home Department Code Not Mapped") -> 8100 | AF93: =IFERROR(VLOOKUP(AA93,'Salary Map'!A:D,3,FALSE),"Salary Code Not Mapped") -> Default | AG93: =IFERROR(VLOOKUP(AA93,'Salary Map'!A:D,4,FALSE),"Salary Code Not Mapped") -> General | AH93: =IFERROR(VLOOKUP(Z93,'Country Map'!A:B,2,FALSE),"Legal Country Not Mapped") -> US | AI93: =IFERROR(VLOOKUP(X93,'Language Map'!A:C,3,FALSE),IFERROR(VLOOKUP(T93,'Org Map'!A:F,6,FALSE),"ADP and BU Language Code Not Mapped"))&AH93 -> en_US | AJ93: =IFERROR(VLOOKUP(T93,'Org Map'!A:G,7),"BU Currency Not Mapped") -> USD | AK93: =IF(ISBLANK(E93),"",TRIM(E93&" "&F93)) | AL93: =IFERROR(VLOOKUP(O93,'Status Map'!A:B,2,FALSE),"Position Status Not Mapped") -> Y | AM93: =IF(AL93="N",TEXT(M93,"yyyymmdd"),"") | AO93: =B93&C93&D93 -> WendyKozicki | AP93: =LEFT(G93,FIND(",",G93)-1) -> Williams | AQ93: =IFERROR(VLOOKUP(AP93,D:P,13,FALSE),"No Reports to Name") -> 202533 | AR93: =AQ93=MID(H93,4,6) -> TRUE
A94: KSX | B94: Mitchell | D94: Kuhlman | G94: LaPlante, Derek | H94: KSY211736 | J94: mkuhlman61@gmail.com | K94: Assistant, Warehouse II | L94: 45831 | O94: Active | P94: 212177 | Q94: Biweekly | R94: Full Time | S94: 088 | T94: 088-AS Raymond | U94: FG Warehouse | V94: 005200 | W94: AS Raymond | Z94: USA | AA94: S05 | AB94: FMG-S05 | AC94: =IF(ISBLANK(H94),VLOOKUP(P94,'US Supervisor Map'!A:D,4,FALSE),MID(H94,4,6)) -> 211736 | AD94: =IFERROR(VLOOKUP(T94,'Org Map'!A:E,4),"BU Description Not Mapped") -> 0088 | AE94: =IFERROR(VLOOKUP(V94,'Org Map'!C:E,3),"Home Department Code Not Mapped") -> 5200 | AF94: =IFERROR(VLOOKUP(AA94,'Salary Map'!A:D,3,FALSE),"Salary Code Not Mapped") -> Default | AG94: =IFERROR(VLOOKUP(AA94,'Salary Map'!A:D,4,FALSE),"Salary Code Not Mapped") -> General | AH94: =IFERROR(VLOOKUP(Z94,'Country Map'!A:B,2,FALSE),"Legal Country Not Mapped") -> US | AI94: =IFERROR(VLOOKUP(X94,'Language Map'!A:C,3,FALSE),IFERROR(VLOOKUP(T94,'Org Map'!A:F,6,FALSE),"ADP and BU Language Code Not Mapped"))&AH94 -> en_US | AJ94: =IFERROR(VLOOKUP(T94,'Org Map'!A:G,7),"BU Currency Not Mapped") -> USD | AK94: =IF(ISBLANK(E94),"",TRIM(E94&" "&F94)) | AL94: =IFERROR(VLOOKUP(O94,'Status Map'!A:B,2,FALSE),"Position Status Not Mapped") -> Y | AM94: =IF(AL94="N",TEXT(M94,"yyyymmdd"),"") | AO94: =B94&C94&D94 -> MitchellKuhlman | AP94: =LEFT(G94,FIND(",",G94)-1) -> LaPlante | AQ94: =IFERROR(VLOOKUP(AP94,D:P,13,FALSE),"No Reports to Name") -> 211736 | AR94: =AQ94=MID(H94,4,6) -> TRUE
A95: KSY | B95: Derek | D95: LaPlante | G95: Bailey, Jason | H95: KSY211464 | I95: dlaplante@onebarnes.com | K95: Supv, Warehouse I | L95: 45705 | O95: Active | P95: 211736 | Q95: Monthly | R95: Full Time | S95: 088 | T95: 088-AS Raymond | U95: FG Warehouse | V95: 005200 | W95: AS Raymond | Z95: USA | AA95: S11 | AB95: FMG-S11 | AC95: =IF(ISBLANK(H95),VLOOKUP(P95,'US Supervisor Map'!A:D,4,FALSE),MID(H95,4,6)) -> 211464 | AD95: =IFERROR(VLOOKUP(T95,'Org Map'!A:E,4),"BU Description Not Mapped") -> 0088 | AE95: =IFERROR(VLOOKUP(V95,'Org Map'!C:E,3),"Home Department Code Not Mapped") -> 5200 | AF95: =IFERROR(VLOOKUP(AA95,'Salary Map'!A:D,3,FALSE),"Salary Code Not Mapped") -> Default | AG95: =IFERROR(VLOOKUP(AA95,'Salary Map'!A:D,4,FALSE),"Salary Code Not Mapped") -> General | AH95: =IFERROR(VLOOKUP(Z95,'Country Map'!A:B,2,FALSE),"Legal Country Not Mapped") -> US | AI95: =IFERROR(VLOOKUP(X95,'Language Map'!A:C,3,FALSE),IFERROR(VLOOKUP(T95,'Org Map'!A:F,6,FALSE),"ADP and BU Language Code Not Mapped"))&AH95 -> en_US | AJ95: =IFERROR(VLOOKUP(T95,'Org Map'!A:G,7),"BU Currency Not Mapped") -> USD | AK95: =IF(ISBLANK(E95),"",TRIM(E95&" "&F95)) | AL95: =IFERROR(VLOOKUP(O95,'Status Map'!A:B,2,FALSE),"Position Status Not Mapped") -> Y | AM95: =IF(AL95="N",TEXT(M95,"yyyymmdd"),"") | AO95: =B95&C95&D95 -> DerekLaPlante | AP95: =LEFT(G95,FIND(",",G95)-1) -> Bailey | AQ95: =IFERROR(VLOOKUP(AP95,D:P,13,FALSE),"No Reports to Name") -> 902688 | AR95: =AQ95=MID(H95,4,6) -> FALSE
A96: KSX | B96: Moulay Abdellah | D96: Lamini | G96: Burchell, Mathew | H96: KSY211756 | J96: moulayabdellahlamini@gmail.com | K96: Assistant, Warehouse II | L96: 45229 | O96: Active | P96: 210371 | Q96: Biweekly | R96: Full Time | S96: 088 | T96: 088-AS Raymond | U96: Assembly | V96: 005100 | W96: AS Raymond | Z96: USA | AA96: S05 | AB96: FMG-S05 | AC96: =IF(ISBLANK(H96),VLOOKUP(P96,'US Supervisor Map'!A:D,4,FALSE),MID(H96,4,6)) -> 211756 | AD96: =IFERROR(VLOOKUP(T96,'Org Map'!A:E,4),"BU Description Not Mapped") -> 0088 | AE96: =IFERROR(VLOOKUP(V96,'Org Map'!C:E,3),"Home Department Code Not Mapped") -> 5100 | AF96: =IFERROR(VLOOKUP(AA96,'Salary Map'!A:D,3,FALSE),"Salary Code Not Mapped") -> Default | AG96: =IFERROR(VLOOKUP(AA96,'Salary Map'!A:D,4,FALSE),"Salary Code Not Mapped") -> General | AH96: =IFERROR(VLOOKUP(Z96,'Country Map'!A:B,2,FALSE),"Legal Country Not Mapped") -> US | AI96: =IFERROR(VLOOKUP(X96,'Language Map'!A:C,3,FALSE),IFERROR(VLOOKUP(T96,'Org Map'!A:F,6,FALSE),"ADP and BU Language Code Not Mapped"))&AH96 -> en_US | AJ96: =IFERROR(VLOOKUP(T96,'Org Map'!A:G,7),"BU Currency Not Mapped") -> USD | AK96: =IF(ISBLANK(E96),"",TRIM(E96&" "&F96)) | AL96: =IFERROR(VLOOKUP(O96,'Status Map'!A:B,2,FALSE),"Position Status Not Mapped") -> Y | AM96: =IF(AL96="N",TEXT(M96,"yyyymmdd"),"") | AO96: =B96&C96&D96 -> Moulay AbdellahLamini | AP96: =LEFT(G96,FIND(",",G96)-1) -> Burchell | AQ96: =IFERROR(VLOOKUP(AP96,D:P,13,FALSE),"No Reports to Name") -> 211756 | AR96: =AQ96=MID(H96,4,6) -> TRUE
