Workbook

Sheet 320 One Time
A1: All fields must be represented. Fields with dark red text are system-required. Other fields may be required by your company's configuration.
A2: 1 | B2: 2 | C2: 3 | D2: 4 | E2: 5 | F2: 6 | G2: 7 | H2: 8 | I2: 9
A3: Trx Type (320) | B3: Current Employee ID | C3: New Employee ID | D3: New Login ID | E3: Future Use 1 | F3: Future Use 2 | G3: Future Use 3 | H3: Future Use 4 | I3: Future Use 5
A4: 3 | B4: 48 | C4: 48 | D4: 64 | E4: Future Use | F4: Future Use | G4: Future Use | H4: Future Use | I4: Future Use
A5: 320 | B5: =ADP!P5 -> 211837 | D5: ='305 ADP Employee (All)'!F5 -> tabitua1@onebarnes.com.new.uat
A6: 320 | B6: =ADP!P6 -> 213331 | D6: ='305 ADP Employee (All)'!F6 -> gadams@onebarnes.com.new.uat
A7: 320 | B7: =ADP!P7 -> 213226 | D7: ='305 ADP Employee (All)'!F7 -> kagler@onebarnes.com.new.uat
A8: 320 | B8: =ADP!P8 -> 210892 | D8: ='305 ADP Employee (All)'!F8 -> talexander@onebarnes.com.new.uat
A9: 320 | B9: =ADP!P9 -> 206848 | D9: ='305 ADP Employee (All)'!F9 -> TAllen2@onebarnes.com.new.uat
A10: 320 | B10: =ADP!P10 -> 201688 | D10: ='305 ADP Employee (All)'!F10 -> KAshley@onebarnes.com.new.uat
A11: 320 | B11: =ADP!P11 -> 902688 | D11: ='305 ADP Employee (All)'!F11 -> jbailey@onebarnes.com.new.uat
A12: 320 | B12: =ADP!P12 -> 207709 | D12: ='305 ADP Employee (All)'!F12 -> TBair@onebarnes.com.new.uat
A13: 320 | B13: =ADP!P13 -> 209579 | D13: ='305 ADP Employee (All)'!F13 -> kbarry@onebarnes.com.new.uat
A14: 320 | B14: =ADP!P14 -> 213037 | D14: ='305 ADP Employee (All)'!F14 -> nbate@onebarnes.com.new.uat
A15: 320 | B15: =ADP!P15 -> 213333 | D15: ='305 ADP Employee (All)'!F15 -> mbeasley@onebarnes.com.new.uat
A16: 320 | B16: =ADP!P16 -> 212626 | D16: ='305 ADP Employee (All)'!F16 -> ebeatrice@onebarnes.com.new.uat
... A169: 320 | B169: =ADP!P169 -> 0 | D169: ='305 ADP Employee (All)'!F169 -> .new.uat
A170: 320 | B170: =ADP!#REF! -> #REF! | D170: ='305 ADP Employee (All)'!F170 -> #REF!
A171: 320 | B171: =ADP!#REF! -> #REF! | D171: ='305 ADP Employee (All)'!F171 -> #REF!
A172: 320 | B172: =ADP!#REF! -> #REF! | D172: ='305 ADP Employee (All)'!F172 -> #REF!
A173: 320 | B173: =ADP!#REF! -> #REF! | D173: ='305 ADP Employee (All)'!F173 -> #REF!
A174: 320 | B174: =ADP!#REF! -> #REF! | D174: ='305 ADP Employee (All)'!F174 -> #REF!
A175: 320 | B175: =ADP!#REF! -> #REF! | D175: ='305 ADP Employee (All)'!F175 -> #REF!
A176: 320 | B176: =ADP!#REF! -> #REF! | D176: ='305 ADP Employee (All)'!F176 -> #REF!
A177: 320 | B177: =ADP!#REF! -> #REF! | D177: ='305 ADP Employee (All)'!F177 -> #REF!
A178: 320 | B178: =ADP!#REF! -> #REF! | D178: ='305 ADP Employee (All)'!F178 -> #REF!
A179: 320 | B179: =ADP!#REF! -> #REF! | D179: ='305 ADP Employee (All)'!F179 -> #REF!
A180: 320 | B180: =ADP!#REF! -> #REF! | D180: ='305 ADP Employee (All)'!F180 -> #REF!
A181: 320 | B181: =ADP!#REF! -> #REF! | D181: ='305 ADP Employee (All)'!F181 -> #REF!
... A203: 320 | B203: =ADP!#REF! -> #REF! | D203: ='305 ADP Employee (All)'!F203 -> #REF!

Sheet Multiple Payrolls
A1: Details for Count of Payroll Company Code
A3: Payroll Company Code | B3: Legal First Name | C3: Middle Initial | D3: Legal Last Name | E3: Preferred or Chosen First Name | F3: Preferred or Chosen Last Name | G3: Reports To Legal Name | H3: Supervisor ID | I3: Work Contact: Work Email | J3: Personal Contact: Personal Email | K3: Job Title Description | L3: Hire Date | M3: Termination Date | N3: Rehire Date | O3: Position Status | P3: File Number | Q3: Pay Frequency | R3: Employee Type | S3: Business Unit Code | T3: Business Unit Description | U3: Home Department Description | V3: Home Department Code | W3: Location Description | X3: Language Description | Y3: Language Code | Z3: Legal / Preferred Address: Country Code | AA3: Pay Grade Code | AB3: Pay Grade Description | AC3: SupervisorID Formatted | AD3: Org Unit 1 | AE3: Org Unit 2 | AF3: Concur Profile | AG3: Travel Profile | AH3: Legal Country | AI3: Local Code | AJ3: Reumbursement Currency | AK3: Perferred Name | AL3: Status | AM3: Term Date | AN3: 7/20/26 | AO3: Name | AP3: SupervisorLastName | AQ3: Lookup Supervisor ID | AR3: SupervisorName=Supervisor ID
A4: KSX | B4: Abdellatef | C4: M | D4: Mahmoud | G4: Burchell, Mathew | H4: KSY211756 | J4: oomer77@yahoo.com | K4: Assistant, Warehouse II | L4: 45208 | O4: Active | P4: 210316 | Q4: Biweekly | R4: Full Time | S4: 088 | T4: 088-AS Raymond | U4: Assembly | V4: 005100 | W4: AS Raymond | Z4: USA | AA4: S05 | AB4: FMG-S05 | AC4: 211756 | AD4: 0088 | AE4: 5100 | AF4: Default | AG4: General | AH4: US | AI4: en_US | AJ4: USD | AL4: Y | AO4: AbdellatefMMahmoud | AP4: Burchell | AQ4: 211756 | AR4: TRUE
A5: KSY | B5: Alex | D5: Palicki | G5: Creager, Andrew | H5: KSY212699 | I5: apalicki@onebarnes.com | J5: alexpalicki4@gmail.com | K5: Buyer III | L5: 45831 | O5: Active | P5: 212119 | Q5: Monthly | R5: Full Time | S5: 088 | T5: 088-AS Raymond | U5: Admin-Material Management | V5: 009400 | W5: AS Raymond | Z5: USA | AA5: S13 | AB5: FMG-S13 | AC5: 212699 | AD5: 0088 | AE5: 9400 | AF5: Default | AG5: General | AH5: US | AI5: en_US | AJ5: USD | AL5: Y | AO5: AlexPalicki | AP5: Creager | AQ5: 212699 | AR5: TRUE
A6: KSX | B6: Amir | D6: Dillard | G6: Burchell, Mathew | H6: KSY211756 | I6: adillard1@onebarnes.com | J6: amirdillard4@gmail.com | K6: Assistant, Warehouse II | L6: 45754 | O6: Active | P6: 211895 | Q6: Biweekly | R6: Full Time | S6: 088 | T6: 088-AS Raymond | U6: Assembly | V6: 005100 | W6: AS Raymond | Z6: USA | AA6: S05 | AB6: FMG-S05 | AC6: 211756 | AD6: 0088 | AE6: 5100 | AF6: Default | AG6: General | AH6: US | AI6: en_US | AJ6: USD | AL6: Y | AO6: AmirDillard | AP6: Burchell | AQ6: 211756 | AR6: TRUE
A7: V0U | B7: Amy | C7: C | D7: McGuire | G7: Warner, Dwight | H7: V0U008750 | I7: AMcGuire@onebarnes.com | J7: RedAmyMcG@gmail.com | K7: Accountant III | L7: 35338 | O7: Active | P7: 007861 | Q7: Monthly | R7: Full Time | S7: 025 | T7: 025-NGP Hyson Products | U7: Finance | V7: 000910 | W7: Hyson Products | Z7: USA | AA7: S13 | AB7: FMG-S13 | AC7: 008750 | AD7: 0096 | AE7: 910 | AF7: Default | AG7: General | AH7: US | AI7: en_US | AJ7: USD | AL7: Y | AO7: AmyCMcGuire | AP7: Warner | AQ7: 008750 | AR7: TRUE
A8: KSY | B8: Andrew | C8: J | D8: Creager | G8: Bailey, Jason | H8: KSY211766 | I8: acreager@onebarnes.com | K8: Mgr, Supply Chain III | L8: 45957 | O8: Active | P8: 212699 | Q8: Monthly | R8: Full Time | S8: 088 | T8: 088-AS Raymond | U8: Admin-Material Management | V8: 009400 | W8: AS Raymond | Z8: USA | AA8: S17 | AB8: FMG-S17 | AC8: 211766 | AD8: 0088 | AE8: 9400 | AF8: Default | AG8: General | AH8: US | AI8: en_US | AJ8: USD | AL8: Y | AO8: AndrewJCreager | AP8: Bailey | AQ8: 902688 | AR8: FALSE
A9: KSX | B9: Angela | D9: Myers | G9: Burchell, Mathew | H9: KSY211756 | J9: amm823@bex.net | K9: Assistant, Warehouse II | L9: 45881 | O9: Active | P9: 212349 | Q9: Biweekly | R9: Full Time | S9: 088 | T9: 088-AS Raymond | U9: Assembly | V9: 005100 | W9: AS Raymond | Z9: USA | AA9: S05 | AB9: FMG-S05 | AC9: 211756 | AD9: 0088 | AE9: 5100 | AF9: Default | AG9: General | AH9: US | AI9: en_US | AJ9: USD | AL9: Y | AO9: AngelaMyers | AP9: Burchell | AQ9: 211756 | AR9: TRUE
A10: V0U | B10: Anne | C10: M | D10: Garber | G10: Bate, Natalie | I10: agarber@onebarnes.com | J10: anne.michael00@gmail.com | K10: Mgr, Program | L10: 46265 | O10: Active | P10: 902627 | Q10: Monthly | R10: Full Time | S10: 025 | T10: 025-NGP Hyson Products | U10: Administration | V10: 000917 | W10: Hyson Products | Z10: USA | AA10: S17 | AB10: FMG-S17 | AD10: 0096 | AE10: 0007 | AF10: Default | AG10: General | AH10: US | AI10: en_US | AJ10: USD | AL10: Y | AO10: AnneMGarber | AP10: Bate | AQ10: 213037 | AR10: FALSE
A11: KSW | B11: Anthony | D11: Desillas | J11: desillasa@yahoo.com | K11: Lathe Operator | L11: 45859 | M11: 46046 | O11: Terminated | P11: 212244 | Q11: Biweekly | R11: Full Time | S11: 025 | T11: 025-NGP Hyson Products | U11: CNC Lathe Hyson | V11: 000100 | W11: Hyson Products | Z11: USA | AA11: H07 | AB11: FMG-H07 | AD11: 0096 | AE11: 100 | AF11: Default | AG11: General | AH11: US | AI11: en_US | AJ11: USD | AL11: N | AM11: 20260124 | AN11: Exclude record termination over 45 days ago | AO11: AnthonyDesillas | AP11: #VALUE! | AQ11: No Reports to Name | AR11: FALSE
A12: KSW | B12: Anthony | C12: J | D12: Frimel | G12: Steen, Michael | H12: V0U211062 | I12: afrimel@onebarnes.com | J12: tfrimel@att.net | K12: Tech, Manufacturing A | L12: 37410 | O12: Active | P12: 004352 | Q12: Biweekly | R12: Full Time | S12: 025 | T12: 025-NGP Hyson Products | U12: CNC Lathe Hyson | V12: 000100 | W12: Hyson Products | Z12: USA | AA12: H08 | AB12: FMG-H08 | AC12: 211062 | AD12: 0096 | AE12: 100 | AF12: Default | AG12: General | AH12: US | AI12: en_US | AJ12: USD | AL12: Y | AO12: AnthonyJFrimel | AP12: Steen | AQ12: 211062 | AR12: TRUE
A13: V0U | B13: Anthony | C13: J | D13: Moavero | G13: Brower, James | I13: amoavero1@onebarnes.com | K13: Intern, Engineering Indir | L13: 45810 | M13: 46176 | O13: Terminated | P13: 212052 | Q13: Monthly | R13: Intern | S13: 025 | T13: 025-NGP Hyson Products | U13: Sustaining Engineering | V13: 000900 | W13: Hyson Products | Z13: USA | AA13: H05 | AB13: FMG-H05 | AD13: 0096 | AE13: 900 | AF13: Default | AG13: General | AH13: US | AI13: en_US | AJ13: USD | AL13: N | AM13: 20260603 | AN13: Fix and Include Record | AO13: AnthonyJMoavero | AP13: Brower | AQ13: 006769 | AR13: FALSE
A14: KSX | B14: Anthony | C14: J | D14: Moavero | I14: amoavero1@onebarnes.com | L14: 45810 | M14: 45878 | O14: Terminated | P14: 212052 | Q14: Biweekly | R14: Full Time | W14: AS Raymond | Z14: USA | AD14: BU Description Not Mapped | AE14: Home Department Code Not Mapped | AF14: Salary Code Not Mapped | AG14: Salary Code Not Mapped | AH14: US | AI14: ADP and BU Language Code Not MappedUS | AJ14: BU Currency Not Mapped | AL14: N | AM14: 20250809 | AN14: Exclude record termination over 45 days ago | AO14: AnthonyJMoavero | AP14: #VALUE! | AQ14: No Reports to Name | AR14: FALSE
A15: KSW | B15: Anthony | C15: J | D15: Moavero | G15: Brower, James | H15: V0U006769 | I15: amoavero1@onebarnes.com | K15: Intern, Engineering Indir | L15: 45810 | M15: 46248 | O15: Terminated | P15: 212052 | Q15: Biweekly | R15: Intern | S15: 025 | T15: 025-NGP Hyson Products | U15: Sustaining Engineering | V15: 000900 | W15: Hyson Products | Z15: USA | AA15: H05 | AB15: FMG-H05 | AC15: 006769 | AD15: 0096 | AE15: 900 | AF15: Default | AG15: General | AH15: US | AI15: en_US | AJ15: USD | AL15: N | AM15: 20260814 | AN15: Exclude record termination over 45 days ago | AO15: AnthonyJMoavero | AP15: Brower | AQ15: 006769 | AR15: TRUE
A16: V0U | B16: Anthony | C16: J | D16: Moavero | G16: Brower, James | I16: amoavero1@onebarnes.com | K16: Intern, Engineering Indir | L16: 45810 | M16: 46176 | O16: Terminated | P16: 212052 | Q16: Biweekly | R16: Intern | S16: 025 | T16: 025-NGP Hyson Products | U16: Sustaining Engineering | V16: 000900 | W16: Hyson Products | Z16: USA | AA16: H05 | AB16: FMG-H05 | AD16: 0096 | AE16: 900 | AF16: Default | AG16: General | AH16: US | AI16: en_US | AJ16: USD | AL16: N | AM16: 20260603 | AN16: Fix and Include Record | AO16: AnthonyJMoavero | AP16: Brower | AQ16: 006769 | AR16: FALSE
A17: KSX | B17: Asia | D17: Sexton | G17: Burchell, Mathew | H17: KSY211756 | J17: asexton@yahoo.com | K17: Assistant, Warehouse II | L17: 46190 | M17: 46251 | O17: Terminated | Q17: Biweekly | R17: Temporary | S17: 088 | T17: 088-AS Raymond | U17: Assembly | V17: 005100 | W17: AS Raymond | Z17: USA | AA17: S05 | AB17: FMG-S05 | AC17: 211756 | AD17: 0088 | AE17: 5100 | AF17: Default | AG17: General | AH17: US | AI17: en_US | AJ17: USD | AL17: N | AM17: 20260817 | AN17: Fix and Include Record | AO17: AsiaSexton | AP17: Burchell | AQ17: 211756 | AR17: TRUE
A18: KSX | B18: Aydrian | C18: M | D18: Ahrens | G18: Burchell, Mathew | H18: KSY211756 | J18: aydrian0323@yahoo.com | K18: Assistant, Warehouse II | L18: 45754 | O18: Active | P18: 211901 | Q18: Biweekly | R18: Full Time | S18: 088 | T18: 088-AS Raymond | U18: Assembly | V18: 005100 | W18: AS Raymond | Z18: USA | AA18: S05 | AB18: FMG-S05 | AC18: 211756 | AD18: 0088 | AE18: 5100 | AF18: Default | AG18: General | AH18: US | AI18: en_US | AJ18: USD | AL18: Y | AO18: AydrianMAhrens | AP18: Burchell | AQ18: 211756 | AR18: TRUE
A19: KSX | B19: Barbara | C19: C | D19: Wilkinson | G19: Burchell, Mathew | H19: KSY211756 | J19: wilkinsonb518@gmail.com | K19: Assistant, Warehouse II | L19: 44942 | O19: Active | P19: 209539 | Q19: Biweekly | R19: Full Time | S19: 088 | T19: 088-AS Raymond | U19: Assembly | V19: 005100 | W19: AS Raymond | Z19: USA | AA19: S05 | AB19: FMG-S05 | AC19: 211756 | AD19: 0088 | AE19: 5100 | AF19: Default | AG19: General | AH19: US | AI19: en_US | AJ19: USD | AL19: Y | AO19: BarbaraCWilkinson | AP19: Burchell | AQ19: 211756 | AR19: TRUE
A20: KSX | B20: Benjamin | C20: D | D20: Uncapher | G20: Rafferty, Jonathan | H20: KSY211131 | I20: buncapher@onebarnes.com | K20: Rep, Customer Service III | L20: 45867 | O20: Active | P20: 212254 | Q20: Biweekly | R20: Full Time | S20: 088 | T20: 088-AS Raymond | U20: Inside Sales | V20: 008100 | W20: AS Raymond | Z20: USA | AA20: S11 | AB20: FMG-S11 | AC20: 211131 | AD20: 0088 | AE20: 8100 | AF20: Default | AG20: General | AH20: US | AI20: en_US | AJ20: USD | AL20: Y | AO20: BenjaminDUncapher | AP20: Rafferty | AQ20: 211131 | AR20: TRUE
A21: KSY | B21: Benjamin | C21: D | D21: Uncapher | I21: buncapher@onebarnes.com | K21: Rep, Customer Service III | L21: 45867 | M21: 46175 | O21: Terminated | P21: 212254 | Q21: Monthly | R21: Full Time | S21: 088 | T21: 088-AS Raymond | U21: Inside Sales | V21: 008100 | W21: AS Raymond | Z21: USA | AA21: S11 | AB21: FMG-S11 | AD21: 0088 | AE21: 8100 | AF21: Default | AG21: General | AH21: US | AI21: en_US | AJ21: USD | AL21: N | AM21: 20260602 | AN21: Fix and Include Record | AO21: BenjaminDUncapher | AP21: #VALUE! | AQ21: No Reports to Name | AR21: FALSE
A22: KSY | B22: Benjamin | D22: Sullivan | G22: Creager, Andrew | H22: KSY212699 | I22: bsullivan@onebarnes.com | K22: Planner, Production II | L22: 45131 | O22: Active | P22: 210103 | Q22: Monthly | R22: Full Time | S22: 088 | T22: 088-AS Raymond | U22: Admin-Material Management | V22: 009400 | W22: AS Raymond | Z22: USA | AA22: S12 | AB22: FMG-S12 | AC22: 212699 | AD22: 0088 | AE22: 9400 | AF22: Default | AG22: General | AH22: US | AI22: en_US | AJ22: USD | AL22: Y | AO22: BenjaminSullivan | AP22: Creager | AQ22: 212699 | AR22: TRUE
A23: KSW | B23: Bobby | D23: Hicks | G23: Wallace, Derron | H23: V0U211998 | I23: bhicks@onebarnes.com | J23: bhicks1@me.com | K23: Lead, Unit Team | L23: 45481 | O23: Active | P23: 211145 | Q23: Biweekly | R23: Full Time | S23: 025 | T23: 025-NGP Hyson Products | U23: Assembly Hyson | V23: 000200 | W23: Hyson Products | Z23: USA | AA23: H08 | AB23: FMG-H08 | AC23: 211998 | AD23: 0096 | AE23: 200 | AF23: Default | AG23: General | AH23: US | AI23: en_US | AJ23: USD | AL23: Y | AO23: BobbyHicks | AP23: Wallace | AQ23: 211998 | AR23: TRUE
A24: KSY | B24: Bonnetta | C24: D | D24: Warren | G24: Oleksa, Laura | H24: V0U209181 | I24: bwarren@onebarnes.com | K24: Mgr, HR I | L24: 45958 | O24: Active | P24: 212705 | Q24: Monthly | R24: Full Time | S24: 088 | T24: 088-AS Raymond | U24: HR CU | V24: 009210 | W24: Works from home - Ohio | Z24: USA | AA24: S15 | AB24: FMG-S15 | AC24: 209181 | AD24: 0088 | AE24: 9210 | AF24: Default | AG24: General | AH24: US | AI24: en_US | AJ24: USD | AL24: Y | AO24: BonnettaDWarren | AP24: Oleksa | AQ24: 209181 | AR24: TRUE
A25: KSY | B25: Bradley | D25: Masters | E25: Brad | F25: Masters | G25: Rodriguez, Siobhan | H25: V0U207588 | I25: bmasters@onebarnes.com | J25: brad.a.masters@gmail.com | K25: Mgr, Sales | L25: 46223 | O25: Active | P25: 902437 | Q25: Monthly | R25: Full Time | S25: 088 | T25: 088-AS Raymond | U25: Outside Sales | V25: 008200 | W25: Works from home - Ohio | Z25: USA | AA25: S16 | AB25: FMG-S16 | AC25: 207588 | AD25: 0088 | AE25: 8200 | AF25: Default | AG25: General | AH25: US | AI25: en_US | AJ25: USD | AK25: Brad Masters | AL25: Y | AO25: BradleyMasters | AP25: Rodriguez | AQ25: 212338 | AR25: FALSE
A26: KSX | B26: Brandon | D26: Hibbitts | H26: KSY900848 | I26: bhibbitts@onebarnes.com | J26: hibbitts.brandon@gmail.com | K26: Intern, IT Indirect | L26: 45502 | M26: 46203 | O26: Terminated | P26: 211181 | Q26: Biweekly | R26: Part Time | S26: 088 | T26: 088-AS Raymond | U26: Business Applications | V26: 009150 | W26: AS Raymond | Z26: USA | AA26: H05 | AB26: FMG-H05 | AC26: 900848 | AD26: 0088 | AE26: 9150 | AF26: Default | AG26: General | AH26: US | AI26: en_US | AJ26: USD | AL26: N | AM26: 20260630 | AN26: Fix and Include Record | AO26: BrandonHibbitts | AP26: #VALUE! | AQ26: No Reports to Name | AR26: FALSE
A27: KSY | B27: Brandon | D27: Hibbitts | G27: Erdogan, Mehmet | H27: 000207199N | I27: bhibbitts@onebarnes.com | J27: hibbitts.brandon@gmail.com | K27: Analyst, Help Desk II | L27: 45502 | O27: Active | P27: 211181 | Q27: Monthly | R27: Full Time | S27: 088 | T27: 088-AS Raymond | U27: Business Applications | V27: 009150 | W27: AS Raymond | Z27: USA | AA27: S12 | AB27: FMG-S12 | AC27: 207199 | AD27: 0088 | AE27: 9150 | AF27: Default | AG27: General | AH27: US | AI27: en_US | AJ27: USD | AL27: Y | AO27: BrandonHibbitts | AP27: Erdogan | AQ27: No Reports to Name | AR27: FALSE
A28: KSX | B28: Brandon | D28: Kelly | G28: Alexander, Thomas | H28: KSY210892 | J28: bkelly8@rockets.utoledo.edu | K28: Intern, Operations Direct | L28: 46155 | M28: 46248 | O28: Terminated | P28: 213235 | Q28: Biweekly | R28: Intern | S28: 088 | T28: 088-AS Raymond | U28: Admin-Quality | V28: 009500 | W28: AS Raymond | Z28: USA | AA28: H05 | AB28: FMG-H05 | AC28: 210892 | AD28: 0088 | AE28: 9500 | AF28: Default | AG28: General | AH28: US | AI28: en_US | AJ28: USD | AL28: N | AM28: 20260814 | AN28: Exclude record termination over 45 days ago | AO28: BrandonKelly | AP28: Alexander | AQ28: 210892 | AR28: TRUE
A29: KSX | B29: Brenda | D29: Bixler | G29: LaPlante, Derek | H29: KSY211736 | I29: bbixler@onebarnes.com | J29: beebix911@gmail.com | K29: Expeditor, Warehouse | L29: 45502 | O29: Active | P29: 211174 | Q29: Biweekly | R29: Full Time | S29: 088 | T29: 088-AS Raymond | U29: FG Warehouse | V29: 005200 | W29: AS Raymond | Z29: USA | AA29: S06 | AB29: FMG-S06 | AC29: 211736 | AD29: 0088 | AE29: 5200 | AF29: Default | AG29: General | AH29: US | AI29: en_US | AJ29: USD | AL29: Y | AO29: BrendaBixler | AP29: LaPlante | AQ29: 211736 | AR29: TRUE
A30: KSX | B30: Brenda | C30: J | D30: Daniel | H30: KSY202533 | J30: brendajdaniel@gmail.com | K30: Rep, Customer Service I | L30: 46160 | M30: 46181 | O30: Terminated | P30: 213236 | Q30: Biweekly | R30: Full Time | S30: 088 | T30: 088-AS Raymond | U30: Inside Sales | V30: 008100 | W30: AS Raymond | Z30: USA | AA30: S08 | AB30: FMG-S08 | AC30: 202533 | AD30: 0088 | AE30: 8100 | AF30: Default | AG30: General | AH30: US | AI30: en_US | AJ30: USD | AL30: N | AM30: 20260608 | AN30: Fix and Include Record | AO30: BrendaJDaniel | AP30: #VALUE! | AQ30: No Reports to Name | AR30: FALSE
A31: KSW | B31: Brennen | C31: G | D31: Valley | G31: Steen, Michael | H31: V0U211062 | I31: bvalley@onebarnes.com | K31: Machinist, CNC | L31: 44361 | O31: Active | P31: 206287 | Q31: Biweekly | R31: Part Time | S31: 025 | T31: 025-NGP Hyson Products | U31: CNC Lathe Hyson | V31: 000100 | W31: Hyson Products | Z31: USA | AA31: H04 | AB31: FMG-H04 | AC31: 211062 | AD31: 0096 | AE31: 100 | AF31: Default | AG31: General | AH31: US | AI31: en_US | AJ31: USD | AL31: Y | AO31: BrennenGValley | AP31: Steen | AQ31: 211062 | AR31: TRUE
A32: KSY | B32: Brittany | C32: M | D32: Velner | I32: bvelner@onebarnes.com | K32: Lead, Cust Serv | L32: 45951 | M32: 46136 | O32: Terminated | P32: 212687 | Q32: Monthly | R32: Full Time | S32: 088 | T32: 088-AS Raymond | U32: Inside Sales | V32: 008100 | W32: AS Raymond | Z32: USA | AA32: S12 | AB32: FMG-S12 | AD32: 0088 | AE32: 8100 | AF32: Default | AG32: General | AH32: US | AI32: en_US | AJ32: USD | AL32: N | AM32: 20260424 | AN32: Fix and Include Record | AO32: BrittanyMVelner | AP32: #VALUE! | AQ32: No Reports to Name | AR32: FALSE
A33: KSX | B33: Candi | C33: M | D33: Morales | G33: Alexander, Thomas | H33: KSY210892 | I33: cburris@onebarnes.com | J33: cmorales6132015@gmail.com | K33: Admin, Document Control | L33: 35947 | O33: Active | P33: 007630 | Q33: Biweekly | R33: Full Time | S33: 088 | T33: 088-AS Raymond | U33: Admin-Quality | V33: 009500 | W33: AS Raymond | Z33: USA | AA33: S10 | AB33: FMG-S10 | AC33: 210892 | AD33: 0088 | AE33: 9500 | AF33: Default | AG33: General | AH33: US | AI33: en_US | AJ33: USD | AL33: Y | AO33: CandiMMorales | AP33: Alexander | AQ33: 210892 | AR33: TRUE
A34: KSY | B34: Carla | C34: J | D34: Cunningham | I34: ccunningham@onebarnes.com | J34: springgirl3@sbcglobal.net | L34: 46022 | M34: 46022 | O34: Terminated | P34: 007633 | Q34: Monthly | R34: Full Time | W34: AS Raymond | Z34: USA | AD34: BU Description Not Mapped | AE34: Home Department Code Not Mapped | AF34: Salary Code Not Mapped | AG34: Salary Code Not Mapped | AH34: US | AI34: ADP and BU Language Code Not MappedUS | AJ34: BU Currency Not Mapped | AL34: N | AM34: 20251231 | AN34: Fix and Include Record | AO34: CarlaJCunningham | AP34: #VALUE! | AQ34: No Reports to Name | AR34: FALSE
B35: Carla | C35: J | D35: Cunningham | I35: ccunningham@onebarnes.com | J35: springgirl3@sbcglobal.net | L35: 46022 | M35: 46023 | O35: Terminated | Q35: Weekly | Z35: USA | AD35: BU Description Not Mapped | AE35: Home Department Code Not Mapped | AF35: Salary Code Not Mapped | AG35: Salary Code Not Mapped | AH35: US | AI35: ADP and BU Language Code Not MappedUS | AJ35: BU Currency Not Mapped | AL35: N | AM35: 20260101 | AN35: Exclude record termination over 45 days ago | AO35: CarlaJCunningham | AP35: #VALUE! | AQ35: No Reports to Name | AR35: FALSE
A36: KSY | B36: Carol | D36: Phillips | G36: Rodriguez, Siobhan | H36: V0U207588 | I36: cphillips1@onebarnes.com | J36: cphillips1226@icloud.com | K36: Mgr, Sales | L36: 45909 | O36: Active | P36: 212478 | Q36: Monthly | R36: Full Time | S36: 088 | T36: 088-AS Raymond | U36: Outside Sales | V36: 008200 | W36: Works from home - Ohio | Z36: USA | AA36: S16 | AB36: FMG-S16 | AC36: 207588 | AD36: 0088 | AE36: 8200 | AF36: Default | AG36: General | AH36: US | AI36: en_US | AJ36: USD | AL36: Y | AO36: CarolPhillips | AP36: Rodriguez | AQ36: 212338 | AR36: FALSE
A37: KSY | B37: Carrie | C37: M | D37: Hoffman | G37: Oleksa, Laura | H37: V0U209181 | I37: choffman@onebarnes.com | J37: Carriehoffman89@gmail.com | K37: HR Coordinator | L37: 43101 | O37: Active | P37: 902349 | Q37: Monthly | R37: Full Time | S37: 088 | T37: 088-AS Raymond | U37: HR General | V37: 009200 | W37: AS Raymond | Z37: USA | AA37: S11 | AB37: FMG-S11 | AC37: 209181 | AD37: 0088 | AE37: 9200 | AF37: Default | AG37: General | AH37: US | AI37: en_US | AJ37: USD | AL37: Y | AO37: CarrieMHoffman | AP37: Oleksa | AQ37: 209181 | AR37: TRUE
A38: KSX | B38: Cassandra | C38: G | D38: Richards | G38: LaPlante, Derek | H38: KSY211736 | I38: crichards@onebarnes.com | J38: cassandrarichards13@gmail.com | K38: Assistant, Warehouse II | L38: 45334 | M38: 46262 | O38: Terminated | P38: 210727 | Q38: Biweekly | R38: Full Time | S38: 088 | T38: 088-AS Raymond | U38: FG Warehouse | V38: 005200 | W38: AS Raymond | Z38: USA | AA38: S05 | AB38: FMG-S05 | AC38: 211736 | AD38: 0088 | AE38: 5200 | AF38: Default | AG38: General | AH38: US | AI38: en_US | AJ38: USD | AL38: N | AM38: 20260828 | AN38: Fix and Include Record | AO38: CassandraGRichards | AP38: LaPlante | AQ38: 211736 | AR38: TRUE
A39: V0U | B39: Chad | D39: Phillips | G39: Wilkins, William | H39: V0U901934 | I39: cphillips@onebarnes.com | J39: phillipsx2@verizon.net | K39: Mgr, Sales | L39: 45243 | M39: 46248 | O39: Terminated | P39: 210402 | Q39: Monthly | R39: Full Time | S39: 025 | T39: 025-NGP Hyson Products | U39: Outside Sales | V39: 000820 | W39: Hyson Products | Z39: USA | AA39: S15 | AB39: FMG-S15 | AC39: 901934 | AD39: 0096 | AE39: 820 | AF39: Default | AG39: General | AH39: US | AI39: en_US | AJ39: USD | AL39: N | AM39: 20260814 | AN39: Fix and Include Record | AO39: ChadPhillips | AP39: Wilkins | AQ39: 901934 | AR39: TRUE
A40: KSW | B40: Charles | D40: McDavid | H40: V0U211062 | J40: chuckmcdavid1999@icloud.com | K40: Lathe Operator | L40: 46202 | O40: Active | P40: 213332 | Q40: Biweekly | R40: Full Time | S40: 025 | T40: 025-NGP Hyson Products | U40: CNC Lathe Hyson | V40: 000100 | W40: Hyson Products | Z40: USA | AA40: H07 | AB40: FMG-H07 | AC40: 211062 | AD40: 0096 | AE40: 100 | AF40: Default | AG40: General | AH40: US | AI40: en_US | AJ40: USD | AL40: Y | AO40: CharlesMcDavid | AP40: #VALUE! | AQ40: No Reports to Name | AR40: FALSE
A41: KSW | B41: Cherie | D41: Hassey | G41: Wallace, Derron | H41: V0U211998 | I41: chassey@onebarnes.com | J41: c.hassey@att.net | K41: Rep, Customer Service II | L41: 46125 | O41: Active | P41: 213144 | Q41: Biweekly | R41: Full Time | S41: 025 | T41: 025-NGP Hyson Products | U41: Inside Sales | V41: 000850 | W41: Hyson Products | Z41: USA | AA41: S10 | AB41: FMG-S10 | AC41: 211998 | AD41: 0096 | AE41: 850 | AF41: Default | AG41: General | AH41: US | AI41: en_US | AJ41: USD | AL41: Y | AO41: CherieHassey | AP41: Wallace | AQ41: 211998 | AR41: TRUE
A42: V0U | B42: Cherie | D42: Hassey | I42: chassey@onebarnes.com | J42: c.hassey@att.net | K42: Rep, Customer Service II | L42: 46125 | M42: 46176 | O42: Terminated | P42: 213144 | Q42: Biweekly | R42: Full Time | S42: 025 | T42: 025-NGP Hyson Products | U42: Inside Sales | V42: 000850 | W42: Hyson Products | Z42: USA | AA42: S10 | AB42: FMG-S10 | AD42: 0096 | AE42: 850 | AF42: Default | AG42: General | AH42: US | AI42: en_US | AJ42: USD | AL42: N | AM42: 20260603 | AN42: Fix and Include Record | AO42: CherieHassey | AP42: #VALUE! | AQ42: No Reports to Name | AR42: FALSE
A43: V0U | B43: Chris | C43: F | D43: Martin | G43: Leftrict, Wayne | H43: V0U210910 | I43: cmartin@onebarnes.com | J43: 3martmojo@gmail.com | K43: Coord, Quality & Environ | L43: 44270 | O43: Active | P43: 202609 | Q43: Monthly | R43: Full Time | S43: 025 | T43: 025-NGP Hyson Products | U43: Quality | V43: 000500 | W43: Hyson Products | Z43: USA | AA43: S15 | AB43: FMG-S15 | AC43: 210910 | AD43: 0096 | AE43: 500 | AF43: Default | AG43: General | AH43: US | AI43: en_US | AJ43: USD | AL43: Y | AO43: ChrisFMartin | AP43: Leftrict | AQ43: 210910 | AR43: TRUE
A44: KSX | B44: Christopher | C44: D | D44: Sanderson | G44: Rogers, Wayne | H44: KSY207487 | J44: sandecd@gmail.com | K44: Assistant, Warehouse II | L44: 46104 | O44: Active | P44: 213091 | Q44: Biweekly | R44: Full Time | S44: 088 | T44: 088-AS Raymond | U44: FG Warehouse | V44: 005200 | W44: AS Raymond | Z44: USA | AA44: S05 | AB44: FMG-S05 | AC44: 207487 | AD44: 0088 | AE44: 5200 | AF44: Default | AG44: General | AH44: US | AI44: en_US | AJ44: USD | AL44: Y | AO44: ChristopherDSanderson | AP44: Rogers | AQ44: 207487 | AR44: TRUE
A45: KSY | B45: Christopher | C45: G | D45: Jablonsky | I45: cjablonsky@onebarnes.com | K45: Mgr, Sales | L45: 45915 | M45: 46122 | O45: Terminated | P45: 212479 | Q45: Monthly | R45: Full Time | S45: 088 | T45: 088-AS Raymond | U45: Outside Sales | V45: 008200 | W45: Work from home - Ohio - New | Z45: USA | AA45: S16 | AB45: FMG-S16 | AD45: 0088 | AE45: 8200 | AF45: Default | AG45: General | AH45: US | AI45: en_US | AJ45: USD | AL45: N | AM45: 20260410 | AN45: Fix and Include Record | AO45: ChristopherGJablonsky | AP45: #VALUE! | AQ45: No Reports to Name | AR45: FALSE
A46: KSW | B46: Christopher | C46: J | D46: Kostohryz | G46: Steen, Michael | H46: V0U211062 | J46: cjkgoat@cox.net | K46: Machinist B | L46: 32405 | O46: Active | P46: 006805 | Q46: Biweekly | R46: Full Time | S46: 025 | T46: 025-NGP Hyson Products | U46: CNC Lathe Hyson | V46: 000100 | W46: Hyson Products | Z46: USA | AA46: H07 | AB46: FMG-H07 | AC46: 211062 | AD46: 0096 | AE46: 100 | AF46: Default | AG46: General | AH46: US | AI46: en_US | AJ46: USD | AL46: Y | AO46: ChristopherJKostohryz | AP46: Steen | AQ46: 211062 | AR46: TRUE
A47: KSX | B47: Conner | C47: J | D47: Frankforther | G47: Burchell, Mathew | H47: KSY211756 | I47: cfrankforther@onebarnes.com | J47: frankfortherconner@gmail.com | K47: Assistant, Warehouse II | L47: 45838 | O47: Active | P47: 212151 | Q47: Biweekly | R47: Full Time | S47: 088 | T47: 088-AS Raymond | U47: Assembly | V47: 005100 | W47: AS Raymond | Z47: USA | AA47: S05 | AB47: FMG-S05 | AC47: 211756 | AD47: 0088 | AE47: 5100 | AF47: Default | AG47: General | AH47: US | AI47: en_US | AJ47: USD | AL47: Y | AO47: ConnerJFrankforther | AP47: Burchell | AQ47: 211756 | AR47: TRUE
A48: KSX | B48: Craig | D48: Mata | G48: LaPlante, Derek | H48: KSY211736 | I48: cmata@onebarnes.com | J48: CRAIGMATA51@YAHOO.COM | K48: Assistant, Warehouse II | L48: 43388 | O48: Active | P48: 201343 | Q48: Biweekly | R48: Full Time | S48: 088 | T48: 088-AS Raymond | U48: FG Warehouse | V48: 005200 | W48: AS Raymond | Z48: USA | AA48: S05 | AB48: FMG-S05 | AC48: 211736 | AD48: 0088 | AE48: 5200 | AF48: Default | AG48: General | AH48: US | AI48: en_US | AJ48: USD | AL48: Y | AO48: CraigMata | AP48: LaPlante | AQ48: 211736 | AR48: TRUE
A49: KSX | B49: Craig | D49: Wagner | G49: Burchell, Mathew | H49: KSY211756 | I49: cwagner@onebarnes.com | J49: mich_n_trum84@yahoo.com | K49: Assistant, Warehouse | L49: 44348 | O49: Active | P49: 206272 | Q49: Biweekly | R49: Full Time | S49: 088 | T49: 088-AS Raymond | U49: Assembly | V49: 005100 | W49: AS Raymond | Z49: USA | AA49: S08 | AB49: FMG-S08 | AC49: 211756 | AD49: 0088 | AE49: 5100 | AF49: Default | AG49: General | AH49: US | AI49: en_US | AJ49: USD | AL49: Y | AO49: CraigWagner | AP49: Burchell | AQ49: 211756 | AR49: TRUE
A50: KSX | B50: Cristel | D50: Grandowicz | G50: Burchell, Mathew | H50: KSY211756 | I50: cgrandowicz@onebarnes.com | J50: grandowicz.cristel@gmail.com | K50: Assistant, Warehouse II | L50: 45789 | O50: Active | P50: 211991 | Q50: Biweekly | R50: Full Time | S50: 088 | T50: 088-AS Raymond | U50: Assembly | V50: 005100 | W50: AS Raymond | Z50: USA | AA50: S05 | AB50: FMG-S05 | AC50: 211756 | AD50: 0088 | AE50: 5100 | AF50: Default | AG50: General | AH50: US | AI50: en_US | AJ50: USD | AL50: Y | AO50: CristelGrandowicz | AP50: Burchell | AQ50: 211756 | AR50: TRUE
A51: KSX | B51: Crystal | D51: Dedes | G51: LaPlante, Derek | H51: KSY211736 | I51: cdedes@onebarnes.com | J51: criss4200@yahoo.com | K51: Assistant, Warehouse II | L51: 44620 | O51: Active | P51: 207391 | Q51: Biweekly | R51: Full Time | S51: 088 | T51: 088-AS Raymond | U51: FG Warehouse | V51: 005200 | W51: AS Raymond | Z51: USA | AA51: S05 | AB51: FMG-S05 | AC51: 211736 | AD51: 0088 | AE51: 5200 | AF51: Default | AG51: General | AH51: US | AI51: en_US | AJ51: USD | AL51: Y | AO51: CrystalDedes | AP51: LaPlante | AQ51: 211736 | AR51: TRUE
A52: KSY | B52: Daniel | C52: P | D52: Tuller | H52: V0U008750 | I52: dtuller@onebarnes.com | J52: dptuller@gmail.com | K52: Controller, Division II | L52: 45208 | M52: 46227 | O52: Terminated | P52: 210339 | Q52: Monthly | R52: Full Time | S52: 088 | T52: 088-AS Raymond | U52: Finance General | V52: 009100 | W52: AS Raymond | Z52: USA | AA52: S17 | AB52: FMG-S17 | AC52: 008750 | AD52: 0088 | AE52: 9100 | AF52: Default | AG52: General | AH52: US | AI52: en_US | AJ52: USD | AL52: N | AM52: 20260724 | AN52: Fix and Include Record | AO52: DanielPTuller | AP52: #VALUE! | AQ52: No Reports to Name | AR52: FALSE
A53: KSW | B53: Daniel | D53: White | G53: Wallace, Derron | H53: V0U211998 | I53: dwhite@onebarnes.com | J53: tntwhite33@aol.com | K53: Rep, Customer Service II | L53: 45769 | O53: Active | P53: 211939 | Q53: Biweekly | R53: Full Time | S53: 025 | T53: 025-NGP Hyson Products | U53: Inside Sales | V53: 000850 | W53: Hyson Products | Z53: USA | AA53: S10 | AB53: FMG-S10 | AC53: 211998 | AD53: 0096 | AE53: 850 | AF53: Default | AG53: General | AH53: US | AI53: en_US | AJ53: USD | AL53: Y | AO53: DanielWhite | AP53: Wallace | AQ53: 211998 | AR53: TRUE
A54: V0U | B54: Daniel | D54: White | I54: dwhite@onebarnes.com | J54: tntwhite33@aol.com | K54: Rep, Customer Service II | L54: 45769 | M54: 46175 | O54: Terminated | P54: 211939 | Q54: Biweekly | R54: Full Time | S54: 025 | T54: 025-NGP Hyson Products | U54: Inside Sales | V54: 000850 | W54: Hyson Products | Z54: USA | AA54: S10 | AB54: FMG-S10 | AD54: 0096 | AE54: 850 | AF54: Default | AG54: General | AH54: US | AI54: en_US | AJ54: USD | AL54: N | AM54: 20260602 | AN54: Fix and Include Record | AO54: DanielWhite | AP54: #VALUE! | AQ54: No Reports to Name | AR54: FALSE
A55: V0U | B55: Daniel | D55: White | I55: dwhite@onebarnes.com | J55: tntwhite33@aol.com | K55: Rep, Customer Service II | L55: 45769 | M55: 46175 | O55: Terminated | P55: 211939 | Q55: Monthly | R55: Full Time | S55: 025 | T55: 025-NGP Hyson Products | U55: Inside Sales | V55: 000850 | W55: Hyson Products | Z55: USA | AA55: S10 | AB55: FMG-S10 | AD55: 0096 | AE55: 850 | AF55: Default | AG55: General | AH55: US | AI55: en_US | AJ55: USD | AL55: N | AM55: 20260602 | AN55: Exclude record termination over 45 days ago | AO55: DanielWhite | AP55: #VALUE! | AQ55: No Reports to Name | AR55: FALSE
A56: KSW | B56: Darin | D56: Hitti | G56: Gang, Terry | H56: V0U006780 | I56: DHitti@onebarnes.com | K56: Mechanic, Maintenance A | L56: 31049 | O56: Active | P56: 006792 | Q56: Biweekly | R56: Full Time | S56: 025 | T56: 025-NGP Hyson Products | U56: Maintenance-Hyson | V56: 000450 | W56: Hyson Products | Z56: USA | AA56: H08 | AB56: FMG-H08 | AC56: 006780 | AD56: 0096 | AE56: 450 | AF56: Default | AG56: General | AH56: US | AI56: en_US | AJ56: USD | AL56: Y | AO56: DarinHitti | AP56: Gang | AQ56: 006780 | AR56: TRUE
A57: KSW | B57: David | C57: A | D57: Dixon | G57: Steen, Michael | H57: V0U211062 | J57: chevelle2212@aol.com | K57: Machinist A | L57: 35604 | O57: Active | P57: 004330 | Q57: Biweekly | R57: Full Time | S57: 025 | T57: 025-NGP Hyson Products | U57: CNC Lathe Hyson | V57: 000100 | W57: Hyson Products | Z57: USA | AA57: H08 | AB57: FMG-H08 | AC57: 211062 | AD57: 0096 | AE57: 100 | AF57: Default | AG57: General | AH57: US | AI57: en_US | AJ57: USD | AL57: Y | AO57: DavidADixon | AP57: Steen | AQ57: 211062 | AR57: TRUE
A58: KSX | B58: David | C58: J | D58: Page | G58: Bate, Natalie | H58: V0U213037 | I58: dpage@onebarnes.com | J58: davidjpage@sbcglobal.net | K58: Mgr, Project II | L58: 45964 | O58: Active | P58: 212725 | Q58: Biweekly | R58: Part Time | S58: 088 | T58: 088-AS Raymond | U58: Admin-Engineering | V58: 009450 | W58: AS Raymond | Z58: USA | AA58: S16 | AB58: FMG-S16 | AC58: 213037 | AD58: 0088 | AE58: 9450 | AF58: Default | AG58: General | AH58: US | AI58: en_US | AJ58: USD | AL58: Y | AO58: DavidJPage | AP58: Bate | AQ58: 213037 | AR58: TRUE
A59: V0U | B59: David | D59: Valetta | G59: Bair, Teresa | H59: KSY207709 | I59: dvaletta@onebarnes.com | J59: dval8200@yahoo.com | K59: Dir, Pricing | L59: 45642 | O59: Active | P59: 211601 | Q59: Monthly | R59: Full Time | S59: 025 | T59: 025-NGP Hyson Products | U59: Outside Sales | V59: 000820 | W59: Works from home - Ohio | Z59: USA | AA59: S19 | AB59: FMG-S19 | AC59: 207709 | AD59: 0096 | AE59: 820 | AF59: Default | AG59: General | AH59: US | AI59: en_US | AJ59: USD | AL59: Y | AO59: DavidValetta | AP59: Bair | AQ59: 207709 | AR59: TRUE
A60: KSY | B60: David | D60: Wilson | G60: Alexander, Thomas | H60: KSY210892 | I60: dwilson@onebarnes.com | K60: Tech, Quality III | L60: 44767 | O60: Active | P60: 207809 | Q60: Monthly | R60: Full Time | S60: 088 | T60: 088-AS Raymond | U60: Admin-Quality | V60: 009500 | W60: AS Raymond | Z60: USA | AA60: S12 | AB60: FMG-S12 | AC60: 210892 | AD60: 0088 | AE60: 9500 | AF60: Default | AG60: General | AH60: US | AI60: en_US | AJ60: USD | AL60: Y | AO60: DavidWilson | AP60: Alexander | AQ60: 210892 | AR60: TRUE
A61: KSX | B61: DayShawn | D61: Rome | H61: KSY207487 | J61: dayshawnrome16@yahoo.com | K61: Assistant, Warehouse II | L61: 46190 | M61: 46205 | O61: Terminated | Q61: Biweekly | R61: Temporary | S61: 088 | T61: 088-AS Raymond | U61: FG Warehouse | V61: 005200 | W61: AS Raymond | Z61: USA | AA61: S05 | AB61: FMG-S05 | AC61: 207487 | AD61: 0088 | AE61: 5200 | AF61: Default | AG61: General | AH61: US | AI61: en_US | AJ61: USD | AL61: N | AM61: 20260702 | AN61: Exclude record termination over 45 days ago | AO61: DayShawnRome | AP61: #VALUE! | AQ61: No Reports to Name | AR61: FALSE
A62: V0U | B62: Demetrius | C62: A | D62: Daniels | I62: ddaniels@kaller.com | J62: mrtruth75@gmail.com | K62: Rep, Customer Service II | L62: 37424 | M62: 46175 | O62: Terminated | P62: 006774 | Q62: Biweekly | R62: Full Time | S62: 025 | T62: 025-NGP Hyson Products | U62: Inside Sales | V62: 000850 | W62: Hyson Products | Z62: USA | AA62: S10 | AB62: FMG-S10 | AD62: 0096 | AE62: 850 | AF62: Default | AG62: General | AH62: US | AI62: en_US | AJ62: USD | AL62: N | AM62: 20260602 | AN62: Exclude record termination over 45 days ago | AO62: DemetriusADaniels | AP62: #VALUE! | AQ62: No Reports to Name | AR62: FALSE
A63: V0U | B63: Demetrius | C63: A | D63: Daniels | I63: ddaniels@kaller.com | J63: mrtruth75@gmail.com | K63: Rep, Customer Service II | L63: 37424 | M63: 46175 | O63: Terminated | P63: 006774 | Q63: Monthly | R63: Full Time | S63: 025 | T63: 025-NGP Hyson Products | U63: Inside Sales | V63: 000850 | W63: Hyson Products | Z63: USA | AA63: S10 | AB63: FMG-S10 | AD63: 0096 | AE63: 850 | AF63: Default | AG63: General | AH63: US | AI63: en_US | AJ63: USD | AL63: N | AM63: 20260602 | AN63: Fix and Include Record | AO63: DemetriusADaniels | AP63: #VALUE! | AQ63: No Reports to Name | AR63: FALSE
A64: KSW | B64: Demetrius | C64: A | D64: Daniels | G64: Wallace, Derron | H64: V0U211998 | I64: ddaniels@kaller.com | J64: mrtruth75@gmail.com | K64: Rep, Customer Service II | L64: 37424 | O64: Active | P64: 006774 | Q64: Biweekly | R64: Full Time | S64: 025 | T64: 025-NGP Hyson Products | U64: Inside Sales | V64: 000850 | W64: Hyson Products | Z64: USA | AA64: S10 | AB64: FMG-S10 | AC64: 211998 | AD64: 0096 | AE64: 850 | AF64: Default | AG64: General | AH64: US | AI64: en_US | AJ64: USD | AL64: Y | AO64: DemetriusADaniels | AP64: Wallace | AQ64: 211998 | AR64: TRUE
A65: KSY | B65: Derek | D65: LaPlante | G65: Bailey, Jason | H65: KSY211464 | I65: dlaplante@onebarnes.com | K65: Supv, Warehouse I | L65: 45705 | O65: Active | P65: 211736 | Q65: Monthly | R65: Full Time | S65: 088 | T65: 088-AS Raymond | U65: FG Warehouse | V65: 005200 | W65: AS Raymond | Z65: USA | AA65: S11 | AB65: FMG-S11 | AC65: 211464 | AD65: 0088 | AE65: 5200 | AF65: Default | AG65: General | AH65: US | AI65: en_US | AJ65: USD | AL65: Y | AO65: DerekLaPlante | AP65: Bailey | AQ65: 902688 | AR65: FALSE
A66: V0U | B66: Derron | D66: Wallace | G66: Bate, Natalie | H66: V0U213037 | I66: dwallace@onebarnes.com | J66: derronw@gmail.com | K66: Mgr, Cust Srvc, Assembly | L66: 45789 | O66: Active | P66: 211998 | Q66: Monthly | R66: Full Time | S66: 025 | T66: 025-NGP Hyson Products | U66: Inside Sales | V66: 000850 | W66: Hyson Products | Z66: USA | AA66: S15 | AB66: FMG-S15 | AC66: 213037 | AD66: 0096 | AE66: 850 | AF66: Default | AG66: General | AH66: US | AI66: en_US | AJ66: USD | AL66: Y | AO66: DerronWallace | AP66: Bate | AQ66: 213037 | AR66: TRUE
A67: KSX | B67: Dillon | C67: M | D67: Frankforther | G67: LaPlante, Derek | H67: KSY211736 | I67: dfrankforther@onebarnes.com | J67: frankfortherdillon@gmail.com | K67: Assistant, Warehouse II | L67: 45719 | O67: Active | P67: 211779 | Q67: Biweekly | R67: Full Time | S67: 088 | T67: 088-AS Raymond | U67: FG Warehouse | V67: 005200 | W67: AS Raymond | Z67: USA | AA67: S05 | AB67: FMG-S05 | AC67: 211736 | AD67: 0088 | AE67: 5200 | AF67: Default | AG67: General | AH67: US | AI67: en_US | AJ67: USD | AL67: Y | AO67: DillonMFrankforther | AP67: LaPlante | AQ67: 211736 | AR67: TRUE
A68: V0U | B68: Donald | C68: C | D68: Felts | G68: Wilkins, William | H68: V0U901934 | I68: cfelts@onebarnes.com | J68: dcfelts@comcast.net | K68: Mgr, Sales | L68: 43885 | O68: Active | P68: 201958 | Q68: Monthly | R68: Full Time | S68: 025 | T68: 025-NGP Hyson Products | U68: Outside Sales | V68: 000820 | W68: Hyson Products | Z68: USA | AA68: S15 | AB68: FMG-S15 | AC68: 901934 | AD68: 0096 | AE68: 820 | AF68: Default | AG68: General | AH68: US | AI68: en_US | AJ68: USD | AL68: Y | AO68: DonaldCFelts | AP68: Wilkins | AQ68: 901934 | AR68: TRUE
A69: KSW | B69: Duane | C69: A | D69: Turner | G69: Steen, Michael | H69: V0U211062 | J69: ugkone10@yahoo.com | K69: Machinist B | L69: 44312 | O69: Active | P69: 206110 | Q69: Biweekly | R69: Full Time | S69: 025 | T69: 025-NGP Hyson Products | U69: CNC Lathe Hyson | V69: 000100 | W69: Hyson Products | Z69: USA | AA69: H07 | AB69: FMG-H07 | AC69: 211062 | AD69: 0096 | AE69: 100 | AF69: Default | AG69: General | AH69: US | AI69: en_US | AJ69: USD | AL69: Y | AO69: DuaneATurner | AP69: Steen | AQ69: 211062 | AR69: TRUE
A70: V0U | B70: Dwight | C70: A | D70: Warner | G70: Bair, Teresa | H70: KSY207709 | I70: DWarner@onebarnes.com | K70: Dir, Finance I | L70: 38691 | O70: Active | P70: 008750 | Q70: Monthly | R70: Full Time | S70: 025 | T70: 025-NGP Hyson Products | U70: Finance | V70: 000910 | W70: Hyson Products | Z70: USA | AA70: S18 | AB70: FMG-S18 | AC70: 207709 | AD70: 0096 | AE70: 910 | AF70: Default | AG70: General | AH70: US | AI70: en_US | AJ70: USD | AL70: Y | AO70: DwightAWarner | AP70: Bair | AQ70: 207709 | AR70: TRUE
A71: KSX | B71: Ella Renae | C71: E | D71: Beatrice | G71: LaPlante, Derek | H71: KSY211736 | I71: ebeatrice@onebarnes.com | J71: thatellachick@gmail.com | K71: Assistant, Warehouse II | L71: 45929 | O71: Active | P71: 212626 | Q71: Biweekly | R71: Full Time | S71: 088 | T71: 088-AS Raymond | U71: FG Warehouse | V71: 005200 | W71: AS Raymond | Z71: USA | AA71: S05 | AB71: FMG-S05 | AC71: 211736 | AD71: 0088 | AE71: 5200 | AF71: Default | AG71: General | AH71: US | AI71: en_US | AJ71: USD | AL71: Y | AO71: Ella RenaeEBeatrice | AP71: LaPlante | AQ71: 211736 | AR71: TRUE
A72: KSY | B72: Emma | D72: Halpin | G72: Kemenah, Greg | H72: KSY211766 | I72: ehalpin@onebarnes.com | J72: sampson.emma17@gmail.com | K72: Mgr, Product III | L72: 45566 | O72: Active | P72: 211489 | Q72: Monthly | R72: Full Time | S72: 088 | T72: 088-AS Raymond | U72: Marketing | V72: 008300 | W72: AS Raymond | Z72: USA | AA72: S16 | AB72: FMG-S16 | AC72: 211766 | AD72: 0088 | AE72: 8300 | AF72: Default | AG72: General | AH72: US | AI72: en_US | AJ72: USD | AL72: Y | AO72: EmmaHalpin | AP72: Kemenah | AQ72: 211766 | AR72: TRUE
A73: KSX | B73: Evelyn | D73: Gonzalez | I73: EGonzalez@onebarnes.com | K73: Assistant, Warehouse II | L73: 44942 | M73: 46148 | O73: Terminated | P73: 209540 | Q73: Biweekly | R73: Full Time | S73: 088 | T73: 088-AS Raymond | U73: Supply Chain | V73: 000004 | W73: AS Raymond | Z73: USA | AA73: S05 | AB73: FMG-S05 | AD73: 0088 | AE73: Home Department Code Not Mapped | AF73: Default | AG73: General | AH73: US | AI73: en_US | AJ73: USD | AL73: N | AM73: 20260506 | AN73: Fix and Include Record | AO73: EvelynGonzalez | AP73: #VALUE! | AQ73: No Reports to Name | AR73: FALSE
A74: KSW | B74: Frank | D74: Izzo | G74: Valetta, David | H74: V0U211601 | I74: FIzzo@onebarnes.com | K74: Mgr, Finance II | L74: 44410 | O74: Active | P74: 206442 | Q74: Biweekly | R74: Part Time Long Term EE | S74: 025 | T74: 025-NGP Hyson Products | U74: Project Management | V74: 000801 | W74: Hyson Products | Z74: USA | AA74: S16 | AB74: FMG-S16 | AC74: 211601 | AD74: 0096 | AE74: 801 | AF74: Default | AG74: General | AH74: US | AI74: en_US | AJ74: USD | AL74: Y | AO74: FrankIzzo | AP74: Valetta | AQ74: 211601 | AR74: TRUE
A75: V0U | B75: Frank | D75: Izzo | H75: V0U211601 | I75: FIzzo@onebarnes.com | K75: Mgr, Finance II | L75: 44410 | M75: 46204 | O75: Terminated | P75: 206442 | Q75: Monthly | R75: Full Time | S75: 025 | T75: 025-NGP Hyson Products | U75: Project Management | V75: 000801 | W75: Hyson Products | Z75: USA | AA75: S16 | AB75: FMG-S16 | AC75: 211601 | AD75: 0096 | AE75: 801 | AF75: Default | AG75: General | AH75: US | AI75: en_US | AJ75: USD | AL75: N | AM75: 20260701 | AN75: Exclude record termination over 45 days ago | AO75: FrankIzzo | AP75: #VALUE! | AQ75: No Reports to Name | AR75: FALSE
A76: KSY | B76: Greg | D76: Kemenah | G76: Bair, Teresa | H76: KSY207709 | I76: gkemenah@onebarnes.com | J76: kemenah@live.com | K76: Mgr, General I | L76: 45712 | O76: Active | P76: 211766 | Q76: Monthly | R76: Full Time | S76: 088 | T76: 088-AS Raymond | U76: Admin-Engineering | V76: 009450 | W76: AS Raymond | Z76: USA | AA76: S19 | AB76: FMG-S19 | AC76: 207709 | AD76: 0088 | AE76: 9450 | AF76: Default | AG76: General | AH76: US | AI76: en_US | AJ76: USD | AL76: Y | AO76: GregKemenah | AP76: Bair | AQ76: 207709 | AR76: TRUE
A77: KSY | B77: Gregory | C77: S | D77: Adams | G77: Rodriguez, Siobhan | H77: V0U207588 | I77: gadams@onebarnes.com | J77: gdsad.adams@cox.net | K77: Mgr, Sales | L77: 46188 | O77: Active | P77: 213331 | Q77: Monthly | R77: Full Time | S77: 088 | T77: 088-AS Raymond | U77: Outside Sales | V77: 008200 | W77: Work from home - Connecticut | Z77: USA | AA77: S16 | AB77: FMG-S16 | AC77: 207588 | AD77: 0088 | AE77: 8200 | AF77: Default | AG77: General | AH77: US | AI77: en_US | AJ77: USD | AL77: Y | AO77: GregorySAdams | AP77: Rodriguez | AQ77: 212338 | AR77: FALSE
A78: KSY | B78: Gwendolyn | C78: L | D78: Rome | G78: Warner, Dwight | H78: V0U008750 | I78: grome@onebarnes.com | J78: gwenlr2013@gmail.com | K78: Analyst, Shared Services | L78: 36535 | N78: 46119 | O78: Active | P78: 007647 | Q78: Monthly | R78: Full Time | S78: 088 | T78: 088-AS Raymond | U78: Finance General | V78: 009100 | W78: AS Raymond | Z78: USA | AA78: S11 | AB78: FMG-S11 | AC78: 008750 | AD78: 0088 | AE78: 9100 | AF78: Default | AG78: General | AH78: US | AI78: en_US | AJ78: USD | AL78: Y | AO78: GwendolynLRome | AP78: Warner | AQ78: 008750 | AR78: TRUE
A79: KSX | B79: Heather | C79: A | D79: Schmidt | G79: LaPlante, Derek | H79: KSY211736 | I79: hschmidt2@onebarnes.com | K79: Assistant, Warehouse | L79: 45138 | O79: Active | P79: 210127 | Q79: Biweekly | R79: Full Time | S79: 088 | T79: 088-AS Raymond | U79: FG Warehouse | V79: 005200 | W79: AS Raymond | Z79: USA | AA79: S08 | AB79: FMG-S08 | AC79: 211736 | AD79: 0088 | AE79: 5200 | AF79: Default | AG79: General | AH79: US | AI79: en_US | AJ79: USD | AL79: Y | AO79: HeatherASchmidt | AP79: LaPlante | AQ79: 211736 | AR79: TRUE
A80: KSW | B80: Isaak | C80: R | D80: Taiclet | G80: Leftrict, Wayne | H80: V0U210910 | I80: itaiclet@onebarnes.com | K80: Intern, Engineering Indir | L80: 46153 | M80: 46255 | O80: Terminated | P80: 213227 | Q80: Biweekly | R80: Intern | S80: 025 | T80: 025-NGP Hyson Products | U80: Quality | V80: 000500 | W80: Hyson Products | Z80: USA | AA80: H05 | AB80: FMG-H05 | AC80: 210910 | AD80: 0096 | AE80: 500 | AF80: Default | AG80: General | AH80: US | AI80: en_US | AJ80: USD | AL80: N | AM80: 20260821 | AN80: Exclude record termination over 45 days ago | AO80: IsaakRTaiclet | AP80: Leftrict | AQ80: 210910 | AR80: TRUE
A81: V0U | B81: Isaak | C81: R | D81: Taiclet | I81: itaiclet@onebarnes.com | K81: Intern, Engineering Indir | L81: 46153 | M81: 46176 | O81: Terminated | P81: 213227 | Q81: Biweekly | R81: Intern | S81: 025 | T81: 025-NGP Hyson Products | U81: Quality | V81: 000500 | W81: Hyson Products | Z81: USA | AA81: H05 | AB81: FMG-H05 | AD81: 0096 | AE81: 500 | AF81: Default | AG81: General | AH81: US | AI81: en_US | AJ81: USD | AL81: N | AM81: 20260603 | AN81: Fix and Include Record | AO81: IsaakRTaiclet | AP81: #VALUE! | AQ81: No Reports to Name | AR81: FALSE
A82: V0U | B82: Isaak | C82: R | D82: Taiclet | I82: itaiclet@onebarnes.com | K82: Intern, Engineering Indir | L82: 46153 | M82: 46176 | O82: Terminated | P82: 213227 | Q82: Monthly | R82: Intern | S82: 025 | T82: 025-NGP Hyson Products | U82: Quality | V82: 000500 | W82: Hyson Products | Z82: USA | AA82: H05 | AB82: FMG-H05 | AD82: 0096 | AE82: 500 | AF82: Default | AG82: General | AH82: US | AI82: en_US | AJ82: USD | AL82: N | AM82: 20260603 | AN82: Fix and Include Record | AO82: IsaakRTaiclet | AP82: #VALUE! | AQ82: No Reports to Name | AR82: FALSE
A83: KSX | B83: Ivy | C83: J | D83: Grant | G83: Warner, Dwight | H83: V0U008750 | I83: igrant1@onebarnes.com | J83: igrant1453@yahoo.com | K83: Spec, Accounts Rec III | L83: 46181 | O83: Active | P83: 209642 | Q83: Biweekly | R83: Full Time | S83: 088 | T83: 088-AS Raymond | U83: Finance General | V83: 009100 | W83: Work from home - Virginia | Z83: USA | AA83: S10 | AB83: FMG-S10 | AC83: 008750 | AD83: 0088 | AE83: 9100 | AF83: Default | AG83: General | AH83: US | AI83: en_US | AJ83: USD | AL83: Y | AO83: IvyJGrant | AP83: Warner | AQ83: 008750 | AR83: TRUE
A84: KSX | B84: Jack | C84: O | D84: Bradford | G84: Halpin, Emma | H84: KSY211489 | J84: jb7222222@gmail.com | K84: Intern, Project Mgr Indir | L84: 46153 | M84: 46241 | O84: Terminated | P84: 213234 | Q84: Biweekly | R84: Intern | S84: 088 | T84: 088-AS Raymond | U84: Marketing | V84: 008300 | W84: AS Raymond | Z84: USA | AA84: H05 | AB84: FMG-H05 | AC84: 211489 | AD84: 0088 | AE84: 8300 | AF84: Default | AG84: General | AH84: US | AI84: en_US | AJ84: USD | AL84: N | AM84: 20260807 | AN84: Fix and Include Record | AO84: JackOBradford | AP84: Halpin | AQ84: 211489 | AR84: TRUE
A85: KSX | B85: Jacob | C85: A | D85: Kemenah | G85: Warner, Dwight | H85: V0U008750 | J85: jkemenah@outlook.com | K85: Intern, Finance Indirect | L85: 46153 | M85: 46248 | O85: Terminated | P85: 213229 | Q85: Biweekly | R85: Intern | S85: 088 | T85: 088-AS Raymond | U85: Finance General | V85: 009100 | W85: AS Raymond | Z85: USA | AA85: H05 | AB85: FMG-H05 | AC85: 008750 | AD85: 0088 | AE85: 9100 | AF85: Default | AG85: General | AH85: US | AI85: en_US | AJ85: USD | AL85: N | AM85: 20260814 | AN85: Fix and Include Record | AO85: JacobAKemenah | AP85: Warner | AQ85: 008750 | AR85: TRUE
A86: KSX | B86: Jacqueline | C86: M | D86: Reed | G86: LaPlante, Derek | H86: KSY211736 | I86: jfoggyrobinson@onebarnes.com | J86: shower781@yahoo.com | K86: Assistant, Warehouse II | L86: 45117 | O86: Active | P86: 210035 | Q86: Biweekly | R86: Full Time | S86: 088 | T86: 088-AS Raymond | U86: FG Warehouse | V86: 005200 | W86: AS Raymond | Z86: USA | AA86: S05 | AB86: FMG-S05 | AC86: 211736 | AD86: 0088 | AE86: 5200 | AF86: Default | AG86: General | AH86: US | AI86: en_US | AJ86: USD | AL86: Y | AO86: JacquelineMReed | AP86: LaPlante | AQ86: 211736 | AR86: TRUE
A87: KSW | B87: James | D87: Biss | G87: Steen, Michael | H87: V0U211062 | J87: jlbjr7784@gmail.com | K87: Assembler B | L87: 45232 | O87: Active | P87: 210375 | Q87: Biweekly | R87: Full Time | S87: 025 | T87: 025-NGP Hyson Products | U87: Assembly Hyson | V87: 000200 | W87: Hyson Products | Z87: USA | AA87: H05 | AB87: FMG-H05 | AC87: 211062 | AD87: 0096 | AE87: 200 | AF87: Default | AG87: General | AH87: US | AI87: en_US | AJ87: USD | AL87: Y | AO87: JamesBiss | AP87: Steen | AQ87: 211062 | AR87: TRUE
A88: V0U | B88: James | D88: Brower | G88: Bate, Natalie | H88: V0U213037 | I88: JBrower@onebarnes.com | J88: browerj@cox.net | K88: Engineer, Application III | L88: 34736 | O88: Active | P88: 006769 | Q88: Monthly | R88: Full Time | S88: 025 | T88: 025-NGP Hyson Products | U88: Engineering | V88: 000718 | W88: Hyson Products | Z88: USA | AA88: S15 | AB88: FMG-S15 | AC88: 213037 | AD88: 0096 | AE88: 718 | AF88: Default | AG88: General | AH88: US | AI88: en_US | AJ88: USD | AL88: Y | AO88: JamesBrower | AP88: Bate | AQ88: 213037 | AR88: TRUE
A89: KSW | B89: James | D89: McConnell | G89: Steen, Michael | H89: V0U211062 | J89: nonyiot2.0@yahoo.com | K89: Machinist B | L89: 31130 | O89: Active | P89: 006811 | Q89: Biweekly | R89: Full Time | S89: 025 | T89: 025-NGP Hyson Products | U89: Edgework- Hyson | V89: 000350 | W89: Hyson Products | Z89: USA | AA89: H07 | AB89: FMG-H07 | AC89: 211062 | AD89: 0096 | AE89: 350 | AF89: Default | AG89: General | AH89: US | AI89: en_US | AJ89: USD | AL89: Y | AO89: JamesMcConnell | AP89: Steen | AQ89: 211062 | AR89: TRUE
A90: KSY | B90: James | D90: Stefancin | G90: Valetta, David | H90: V0U211601 | I90: jstefancin@onebarnes.com | J90: jimstefancin@gmail.com | K90: Mgr, Supply Chain III | L90: 45840 | M90: 46235 | O90: Terminated | P90: 212191 | Q90: Monthly | R90: Full Time | S90: 088 | T90: 088-AS Raymond | U90: Admin-Material Management | V90: 009400 | W90: Work from home - Ohio - New | Z90: USA | AA90: S17 | AB90: FMG-S17 | AC90: 211601 | AD90: 0088 | AE90: 9400 | AF90: Default | AG90: General | AH90: US | AI90: en_US | AJ90: USD | AL90: N | AM90: 20260801 | AN90: Exclude record termination over 45 days ago | AO90: JamesStefancin | AP90: Valetta | AQ90: 211601 | AR90: TRUE
A91: V0U | B91: James | D91: Stefancin | G91: Bate, Natalie | H91: V0U213037 | I91: jstefancin@onebarnes.com | J91: jimstefancin@gmail.com | K91: Mgr, Supply Chain III | L91: 45840 | O91: Active | P91: 212191 | Q91: Monthly | R91: Full Time | S91: 025 | T91: 025-NGP Hyson Products | U91: Administration | V91: 000917 | W91: Works from home - Ohio | Z91: USA | AA91: S17 | AB91: FMG-S17 | AC91: 213037 | AD91: 0096 | AE91: 0007 | AF91: Default | AG91: General | AH91: US | AI91: en_US | AJ91: USD | AL91: Y | AO91: JamesStefancin | AP91: Bate | AQ91: 213037 | AR91: TRUE
A92: KSY | B92: Jason | C92: J | D92: Bailey | G92: Kemenah, Greg | I92: jbailey@onebarnes.com | J92: jjbailey08@gmail.com | K92: Senior Mgr, Operations | L92: 46258 | O92: Active | P92: 902688 | Q92: Monthly | R92: Full Time | S92: 088 | T92: 088-AS Raymond | U92: Operations 5200 5200 | V92: 000007 | W92: AS Raymond | Z92: USA | AA92: S18 | AB92: FMG-S18 | AD92: 0088 | AE92: Home Department Code Not Mapped | AF92: Default | AG92: General | AH92: US | AI92: en_US | AJ92: USD | AL92: Y | AO92: JasonJBailey | AP92: Kemenah | AQ92: 211766 | AR92: FALSE
A93: KSY | B93: Jason | D93: Majewski | G93: Creager, Andrew | H93: KSY212699 | I93: JMajewski@onebarnes.com | J93: jmajewski06@yahoo.com | K93: Mgr, Materials | L93: 34869 | O93: Active | P93: 006809 | Q93: Monthly | R93: Full Time | S93: 088 | T93: 088-AS Raymond | U93: Admin-Material Management | V93: 009400 | W93: AS Raymond | Z93: USA | AA93: S17 | AB93: FMG-S17 | AC93: 212699 | AD93: 0088 | AE93: 9400 | AF93: Default | AG93: General | AH93: US | AI93: en_US | AJ93: USD | AL93: Y | AO93: JasonMajewski | AP93: Creager | AQ93: 212699 | AR93: TRUE
A94: V0U | B94: Jason | D94: Majewski | G94: Bate, Natalie | H94: V0U213037 | I94: JMajewski@onebarnes.com | J94: jmajewski06@yahoo.com | K94: Mgr, Purchasing III | L94: 34869 | M94: 46235 | O94: Terminated | P94: 006809 | Q94: Monthly | R94: Full Time | S94: 025 | T94: 025-NGP Hyson Products | U94: Warehouse | V94: 000555 | W94: Hyson Products | Z94: USA | AA94: S17 | AB94: FMG-S17 | AC94: 213037 | AD94: 0096 | AE94: 555 | AF94: Default | AG94: General | AH94: US | AI94: en_US | AJ94: USD | AL94: N | AM94: 20260801 | AN94: Exclude record termination over 45 days ago | AO94: JasonMajewski | AP94: Bate | AQ94: 213037 | AR94: TRUE
A95: KSY | B95: Jeff | D95: Raese | G95: Rodriguez, Siobhan | H95: V0U207588 | I95: jraese@onebarnes.com | J95: jraese@hotmail.com | K95: Mgr, Sales I | L95: 45113 | O95: Active | P95: 210018 | Q95: Monthly | R95: Full Time | S95: 088 | T95: 088-AS Raymond | U95: Outside Sales | V95: 008200 | W95: Works from home - Ohio | Z95: USA | AA95: S16 | AB95: FMG-S16 | AC95: 207588 | AD95: 0088 | AE95: 8200 | AF95: Default | AG95: General | AH95: US | AI95: en_US | AJ95: USD | AL95: Y | AO95: JeffRaese | AP95: Rodriguez | AQ95: 212338 | AR95: FALSE
A96: KSY | B96: Jeffrey | C96: L | D96: Finch | G96: Erdogan, Mehmet | I96: Jfinch@onebarnes.com | J96: jefffinch@bex.net | K96: Mgr, IT I | L96: 41422 | O96: Active | P96: 900848 | Q96: Monthly | R96: Full Time | S96: 088 | T96: 088-AS Raymond | U96: Business Applications | V96: 009150 | W96: AS Raymond | Z96: USA | AA96: S15 | AB96: FMG-S15 | AD96: 0088 | AE96: 9150 | AF96: Default | AG96: General | AH96: US | AI96: en_US | AJ96: USD | AL96: Y | AO96: JeffreyLFinch | AP96: Erdogan | AQ96: No Reports to Name | AR96: FALSE
A97: KSW | B97: Jermey | D97: McKinney | H97: V0U211998 | J97: jeremyy92600@gmail.com | K97: Assembler C | L97: 46190 | M97: 46234 | O97: Terminated | Q97: Biweekly | R97: Temporary | S97: 025 | T97: 025-NGP Hyson Products | U97: Assembly Hyson | V97: 000200 | W97: Hyson Products | Z97: USA | AA97: H05 | AB97: FMG-H05 | AC97: 211998 | AD97: 0096 | AE97: 200 | AF97: Default | AG97: General | AH97: US | AI97: en_US | AJ97: USD | AL97: N | AM97: 20260731 | AN97: Fix and Include Record | AO97: JermeyMcKinney | AP97: #VALUE! | AQ97: No Reports to Name | AR97: FALSE
B98: Jill | D98: Rockow | J98: JMROCKOW@YAHOO.COM | L98: 46053 | M98: 46054 | O98: Terminated | Q98: Weekly | Z98: USA | AD98: BU Description Not Mapped | AE98: Home Department Code Not Mapped | AF98: Salary Code Not Mapped | AG98: Salary Code Not Mapped | AH98: US | AI98: ADP and BU Language Code Not MappedUS | AJ98: BU Currency Not Mapped | AL98: N | AM98: 20260201 | AN98: Exclude record termination over 45 days ago | AO98: JillRockow | AP98: #VALUE! | AQ98: No Reports to Name | AR98: FALSE
A99: KSX | B99: Joann | D99: Whaley | G99: Valetta, David | H99: V0U211601 | J99: subjetta@icloud.com | K99: Admin, Sales Support II | L99: 44776 | O99: Active | P99: 207850 | Q99: Biweekly | R99: Full Time | S99: 088 | T99: 088-AS Raymond | U99: Outside Sales | V99: 008200 | W99: AS Raymond | Z99: USA | AA99: S10 | AB99: FMG-S10 | AC99: 211601 | AD99: 0088 | AE99: 8200 | AF99: Default | AG99: General | AH99: US | AI99: en_US | AJ99: USD | AL99: Y | AO99: JoannWhaley | AP99: Valetta | AQ99: 211601 | AR99: TRUE
A100: KSY | B100: Joel | C100: E | D100: McCoy | G100: Kemenah, Greg | H100: KSY211766 | I100: jmccoy@onebarnes.com | J100: joelmccoy@hotmail.com | K100: Engineer, Product III | L100: 41771 | O100: Active | P100: 901213 | Q100: Monthly | R100: Full Time | S100: 088 | T100: 088-AS Raymond | U100: Admin-Engineering | V100: 009450 | W100: AS Raymond | Z100: USA | AA100: S15 | AB100: FMG-S15 | AC100: 211766 | AD100: 0088 | AE100: 9450 | AF100: Default | AG100: General | AH100: US | AI100: en_US | AJ100: USD | AL100: Y | AO100: JoelEMcCoy | AP100: Kemenah | AQ100: 211766 | AR100: TRUE
A101: KSX | B101: John | D101: Bentz | G101: LaPlante, Derek | H101: KSY211736 | I101: jbentz@onebarnes.com | J101: xjbm13@yahoo.com | K101: Assistant, Warehouse II | L101: 45937 | O101: Active | P101: 212639 | Q101: Biweekly | R101: Full Time | S101: 088 | T101: 088-AS Raymond | U101: FG Warehouse | V101: 005200 | W101: AS Raymond | Z101: USA | AA101: S05 | AB101: FMG-S05 | AC101: 211736 | AD101: 0088 | AE101: 5200 | AF101: Default | AG101: General | AH101: US | AI101: en_US | AJ101: USD | AL101: Y | AO101: JohnBentz | AP101: LaPlante | AQ101: 211736 | AR101: TRUE
...

Sheet Status Map
A1: Position Status | B1: Concur Status
A2: Active | B2: Y
A3: Terminated | B3: N
A4: Retired | B4: N
A5: Leave | B5: Y
A6: Leave of absence | B6: N

Sheet Country Map
A1: Legal / Preferred Address: Country Code | B1: ADP Country | C1: Country | D1: Currency Code | E1: Currency
A2: USA | B2: US | C2: United States | D2: USD | E2: US Dollar
A3: CHN | B3: CN | C3: China | D3: CNY | E3: Chinese Yuan (Renminbi)
A4: DEU | B4: DE | C4: Germany | D4: EUR | E4: Euro
A5: ESP | B5: ES | C5: Spail | D5: EUR | E5: Euro
A6: FRA | B6: FR | C6: France | D6: EUR | E6: Euro
A7: GBR | B7: GB | C7: United Kingdom | D7: GBP | E7: Pound Sterling
A8: IND | B8: IN | C8: India | D8: INR | E8: Indian Rupee
A9: KOR | B9: KR | C9: South Korea | D9: KRW | E9: South Korean Won
A10: MEX | B10: MX | C10: Mexico | D10: MXN | E10: Mexican Peso
A11: SWE | B11: SE | C11: Sweden | D11: SEK | E11: Swedish Krona
A12: SGP | B12: SG | C12: Singapore | D12: SGD | E12: Singapore Dollar
A13: JPN | B13: JP | C13: Japan | D13: JPY | E13: Japanese Yen

Sheet Org Map
A1: Business Unit Description | B1: Home Department Description | C1: Home Department Code | D1: Concur Org 1 (and others) | E1: Concur / ERP Code Org 2 | F1: Default Org Language | G1: Reimbursement Currency
A2: 025-NGP Hyson Products | B2: CNC Lathe Hyson | C2: 000100 | D2: 0096 | E2: 100 | F2: en_ | G2: USD
A3: 025-NGP Hyson Products | B3: Assembly Hyson | C3: 000200 | D3: 0096 | E3: 200 | F3: en_ | G3: USD
A4: 025-NGP Hyson Products | B4: Edgework- Hyson | C4: 000350 | D4: 0096 | E4: 350 | F4: en_ | G4: USD
A5: 025-NGP Hyson Products | B5: Indirect General -Hyson | C5: 000400 | D5: 0096 | E5: 400 | F5: en_ | G5: USD
A6: 025-NGP Hyson Products | B6: Maintenance-Hyson | C6: 000450 | D6: 0096 | E6: 450 | F6: en_ | G6: USD
A7: 025-NGP Hyson Products | B7: Quality | C7: 000500 | D7: 0096 | E7: 500 | F7: en_ | G7: USD
A8: 025-NGP Hyson Products | B8: Factory Super-Hyson | C8: 000515 | D8: 0096 | E8: 515 | F8: en_ | G8: USD
A9: 025-NGP Hyson Products | B9: Warehouse | C9: 000555 | D9: 0096 | E9: 555 | F9: en_ | G9: USD
A10: 025-NGP Hyson Products | B10: R&D | C10: 000713 | D10: 0096 | E10: 713 | F10: en_ | G10: USD
A11: 025-NGP Hyson Products | B11: Engineering | C11: 000718 | D11: 0096 | E11: 718 | F11: en_ | G11: USD
A12: 025-NGP Hyson Products | B12: Project Management | C12: 000801 | D12: 0096 | E12: 801 | F12: en_ | G12: USD
A13: 025-NGP Hyson Products | B13: Outside Sales | C13: 000820 | D13: 0096 | E13: 820 | F13: en_ | G13: USD
... A19: 088-AS Raymond | B19: Admin-Quality | C19: 009500 | D19: 0088 | E19: 9500 | F19: en_ | G19: USD
A20: 088-AS Raymond | B20: Customer Service | C20: 000002 | D20: 0088 | E20: 0002 | F20: en_ | G20: USD | H20: Move to inside sales
A21: 088-AS Raymond | B21: Supply Chain | C21: 000004 | D21: 0088 | E21: 0004 | F21: en_ | G21: USD | H21: Move to material management
A22: 088-AS Raymond | B22: Operations 5200 5200 | C22: 000007 | D22: 0088 | E22: 0007 | F22: en_ | G22: USD | H22: Move to FG Warehouse
A23: 088-AS Raymond | B23: Assembly | C23: 005100 | D23: 0088 | E23: 5100 | F23: en_ | G23: USD
A24: 088-AS Raymond | B24: FG Warehouse | C24: 005200 | D24: 0088 | E24: 5200 | F24: en_ | G24: USD
A25: 088-AS Raymond | B25: WH Material Management | C25: 005300 | D25: 0088 | E25: 5300 | F25: en_ | G25: USD
A26: 088-AS Raymond | B26: Inside Sales | C26: 008100 | D26: 0088 | E26: 8100 | F26: en_ | G26: USD
A27: 088-AS Raymond | B27: Outside Sales | C27: 008200 | D27: 0088 | E27: 8200 | F27: en_ | G27: USD
A28: 088-AS Raymond | B28: Marketing | C28: 008300 | D28: 0088 | E28: 8300 | F28: en_ | G28: USD
A29: 088-AS Raymond | B29: Finance General | C29: 009100 | D29: 0088 | E29: 9100 | F29: en_ | G29: USD
A30: 088-AS Raymond | B30: Business Applications | C30: 009150 | D30: 0088 | E30: 9150 | F30: en_ | G30: USD
A31: 088-AS Raymond | B31: HR General | C31: 009200 | D31: 0088 | E31: 9200 | F31: en_ | G31: USD
A32: 088-AS Raymond | B32: HR CU | C32: 009210 | D32: 0088 | E32: 9210 | F32: en_ | G32: USD
A33: 088-AS Raymond | B33: Bus Execs CU | C33: 009310 | D33: 0088 | E33: 9310 | F33: en_ | G33: USD
A34: 088-AS Raymond | B34: Admin-Material Management | C34: 009400 | D34: 0088 | E34: 9400 | F34: en_ | G34: USD
... A36: 088-AS Raymond | B36: Admin-Quality | C36: 009500 | D36: 0088 | E36: 9500 | F36: en_ | G36: USD

Sheet Language Map
A1: Language | B1: Language Code | C1: ADP Language
A2: English | B2: 4 | C2: en_ | M2: =RIGHT(O2,2) -> AU | N2: English (Australia) | O2: en_AU | R2: =LEFT(N2,FIND(" ",N2)-1) -> English | S2: =LEFT(O2,3) -> en_
A3: Tamil | B3: 24 | C3: en_ | M3: =RIGHT(O3,2) -> CA | N3: English (Canada) | O3: en_CA | R3: =LEFT(N3,FIND(" ",N3)-1) -> English | S3: =LEFT(O3,3) -> en_
A4: English | C4: en_ | M4: =RIGHT(O4,2) -> IE | N4: English (Ireland) | O4: en_IE | R4: =LEFT(N4,FIND(" ",N4)-1) -> English | S4: =LEFT(O4,3) -> en_
A5: Bulgarian | C5: bg_ | M5: =RIGHT(O5,2) -> IN | N5: English (India) | O5: en_IN | R5: =LEFT(N5,FIND(" ",N5)-1) -> English | S5: =LEFT(O5,3) -> en_
A6: Chinese | C6: zh_ | M6: =RIGHT(O6,2) -> NZ | N6: English (New Zealand) | O6: en_NZ | R6: =LEFT(N6,FIND(" ",N6)-1) -> English | S6: =LEFT(O6,3) -> en_
A7: Croatian | C7: hr_ | M7: =RIGHT(O7,2) -> US | N7: English (United States) | O7: en_US | R7: =LEFT(N7,FIND(" ",N7)-1) -> English | S7: =LEFT(O7,3) -> en_
A8: Czech | C8: cs_ | M8: =RIGHT(O8,2) -> ZA | N8: English (South Africa) | O8: en_ZA | R8: =LEFT(N8,FIND(" ",N8)-1) -> English | S8: =LEFT(O8,3) -> en_
A9: Danish | C9: da_ | M9: =RIGHT(O9,2) -> BG | N9: Bulgarian (Bulgaria) | O9: bg_BG | R9: =LEFT(N9,FIND(" ",N9)-1) -> Bulgarian | S9: =LEFT(O9,3) -> bg_
A10: Dutch | C10: nl_ | M10: =RIGHT(O10,2) -> CN | N10: Chinese (China) | O10: zh_CN | R10: =LEFT(N10,FIND(" ",N10)-1) -> Chinese | S10: =LEFT(O10,3) -> zh_
A11: Finnish | C11: fi_ | M11: =RIGHT(O11,2) -> HK | N11: Chinese (Hong Kong, China) | O11: zh_HK | R11: =LEFT(N11,FIND(" ",N11)-1) -> Chinese | S11: =LEFT(O11,3) -> zh_
A12: French | C12: fr_ | M12: =RIGHT(O12,2) -> TW | N12: Chinese (Taiwan, China) | O12: zh_TW | R12: =LEFT(N12,FIND(" ",N12)-1) -> Chinese | S12: =LEFT(O12,3) -> zh_
A13: German | C13: de_ | M13: =RIGHT(O13,2) -> HR | N13: Croatian (Croatia) | O13: hr_HR | R13: =LEFT(N13,FIND(" ",N13)-1) -> Croatian | S13: =LEFT(O13,3) -> hr_
A14: Greek | C14: el_ | M14: =RIGHT(O14,2) -> CZ | N14: Czech (Czech Republic) | O14: cs_CZ | R14: =LEFT(N14,FIND(" ",N14)-1) -> Czech | S14: =LEFT(O14,3) -> cs_
A15: Hungarian | C15: hu_ | M15: =RIGHT(O15,2) -> DK | N15: Danish (Denmark) | O15: da_DK | R15: =LEFT(N15,FIND(" ",N15)-1) -> Danish | S15: =LEFT(O15,3) -> da_
... A33: Vietnamese | C33: vi_ | M33: =RIGHT(O33,2) -> DE | N33: German (Germany) | O33: de_DE | R33: =LEFT(N33,FIND(" ",N33)-1) -> German | S33: =LEFT(O33,3) -> de_
M34: =RIGHT(O34,2) -> LU | N34: German (Luxembourg) | O34: de_LU | R34: =LEFT(N34,FIND(" ",N34)-1) -> German | S34: =LEFT(O34,3) -> de_
M35: =RIGHT(O35,2) -> CH | N35: German (Switzerland) | O35: de_CH | R35: =LEFT(N35,FIND(" ",N35)-1) -> German | S35: =LEFT(O35,3) -> de_
M36: =RIGHT(O36,2) -> GR | N36: Greek (Greece) | O36: el_GR | R36: =LEFT(N36,FIND(" ",N36)-1) -> Greek | S36: =LEFT(O36,3) -> el_
M37: =RIGHT(O37,2) -> HU | N37: Hungarian (Hungary) | O37: hu_HU | R37: =LEFT(N37,FIND(" ",N37)-1) -> Hungarian | S37: =LEFT(O37,3) -> hu_
M38: =RIGHT(O38,2) -> ID | N38: Indonesian (Indonesia) | O38: id_ID | R38: =LEFT(N38,FIND(" ",N38)-1) -> Indonesian | S38: =LEFT(O38,3) -> id_
M39: =RIGHT(O39,2) -> IT | N39: Italian (Italy) | O39: it_IT | R39: =LEFT(N39,FIND(" ",N39)-1) -> Italian | S39: =LEFT(O39,3) -> it_
M40: =RIGHT(O40,2) -> CH | N40: Italian (Switzerland) | O40: it_CH | R40: =LEFT(N40,FIND(" ",N40)-1) -> Italian | S40: =LEFT(O40,3) -> it_
M41: =RIGHT(O41,2) -> JP | N41: Japanese (Japan) | O41: ja_JP | R41: =LEFT(N41,FIND(" ",N41)-1) -> Japanese | S41: =LEFT(O41,3) -> ja_
M42: =RIGHT(O42,2) -> KP | N42: Korean (North Korea) | O42: ko_KP | R42: =LEFT(N42,FIND(" ",N42)-1) -> Korean | S42: =LEFT(O42,3) -> ko_
M43: =RIGHT(O43,2) -> KR | N43: Korean (South Korea) | O43: ko_KR | R43: =LEFT(N43,FIND(" ",N43)-1) -> Korean | S43: =LEFT(O43,3) -> ko_
M44: =RIGHT(O44,2) -> MY | N44: Malay (Malaysia) | O44: ms_MY | R44: =LEFT(N44,FIND(" ",N44)-1) -> Malay | S44: =LEFT(O44,3) -> ms_
M45: =RIGHT(O45,2) -> NO | N45: Norwegian (Norway) | O45: no_NO | R45: =LEFT(N45,FIND(" ",N45)-1) -> Norwegian | S45: =LEFT(O45,3) -> no_
... M75: =RIGHT(O75,2) -> VN | N75: Vietnamese (Vietnam) | O75: vi_VN | R75: =LEFT(N75,FIND(" ",N75)-1) -> Vietnamese | S75: =LEFT(O75,3) -> vi_

Sheet Salary Map
A1: Pay Grade Code | B1: Pay Grade Description | C1: Expense Map | D1: Travel Map | E1: Invoice Approval
A2: S24 | B2: FMG-S24 | C2: Officers | D2: VIP
A3: S23 | B3: FMG-S23 | C3: Grade 20 | D3: Senior Leadership
A4: S22 | B4: FMG-S22 | C4: Grade 20 | D4: Senior Leadership | E4: 1e+09 | G4: Per conversation/decision Tunde, Dwight, Amy Sept 9, 2026
A5: S21 | B5: FMG-S21 | C5: Grade 20 | D5: Senior Leadership | E5: 1000000 | G5: Per conversation/decision Tunde, Dwight, Amy Sept 9, 2026
A6: S20 | B6: FMG-S20 | C6: Grade 20 | D6: Senior Leadership | E6: 100000
A7: S19 | B7: FMG-S19 | C7: Default | D7: General | E7: 100000
A8: S18 | B8: FMG-S18 | C8: Default | D8: General | E8: 25000
A9: S17 | B9: FMG-S17 | C9: Default | D9: General | E9: 25000
A10: S16 | B10: FMG-S16 | C10: Default | D10: General | E10: 25000
A11: S15 | B11: FMG-S15 | C11: Default | D11: General | E11: 0
A12: S14 | B12: FMG-S14 | C12: Default | D12: General | E12: 0
A13: S13 | B13: FMG-S13 | C13: Default | D13: General | E13: 0
A14: S12 | B14: FMG-S12 | C14: Default | D14: General | E14: 0
A15: S11 | B15: FMG-S11 | C15: Default | D15: General | E15: 0
A16: S10 | B16: FMG-S10 | C16: Default | D16: General | E16: 0
A17: S09 | B17: FMG-S09 | C17: Default | D17: General | E17: 0
... A37: H0000 | B37: FMG-H0000 | C37: Default | D37: General | E37: 0

Sheet Role Assignment Map
A1: Role | B1: Category | C1: Assign Role Automatically
A2: Card Program Administrator | B2: Admin | C2: N
A3: Cognos Business Author | B3: Admin | C3: N
A4: Employee Administrator | B4: Admin | C4: N
A5: Invoice Configuration Administrator (Restricted) | B5: Admin | C5: N
A6: Invoice Proxy Logon | B6: Admin | C6: N
A7: Reimbursement Manager | B7: Admin | C7: N
A8: Role Administrator | B8: Admin | C8: N
A9: Expense User | B9: Expense | C9: Y
A10: Expense Processor | B10: Expense | C10: Y
A11: Expense Processor (Audit) | B11: Expense | C11: Y
A12: Expense Proxy Logon | B12: Expense | C12: Y
... A22: Purchase Request Processor (Audit) | B22: Payables | C22: N

Sheet Invoice Exception Map
A1: Invoice Exception Employee Id | B1: Invoice Exception Employee Name | C1: Invoice Access Value
A2: 007861 | B2: Amy McGuire | C2: Y
A3: 203011 | B3: Babatunde Adewalure | C3: Y
A4: 902437 | B4: Bradley Masters | C4: N
A5: 007630 | B5: Candi Morals | C5: Y
A6: 212478 | B6: Carol Phillips | C6: N
A7: 213331 | B7: Gregory Adams | C7: N
A8: 203036 | B8: Jean-Philippe Duvillard | C8: Y
A9: 210018 | B9: Jeff Raese | C9: N | H9: 901934 | J9: Y | K9: S17 reports to him
A10: 212146 | B10: Joyce Spilza | C10: Y
A11: 209579 | B11: Kirsten Barry | C11: N
A12: 902013 | B12: Kugagini Thineshkumar | C12: Y
A13: 207199 | B13: Mehmet Erdogan | C13: Y
A14: 213333 | B14: Michael Beasley | C14: N | H14: 901934 | I14: William Wilkins | J14: N
A15: 212418 | B15: Michael Jones | C15: N
A16: 901943 | B16: Richard Taiclet | C16: Y
A17: 213174 | B17: Robert Schortz | C17: Y
A18: 201688 | B18: Kim Ashley | C18: Y
A19: 210102 | B19: Nathan Bird | C19: N
A20: 212705 | B20: Bonnetta Warren | C20: Y
A21: 213174 | B21: Robert Schortz | C21: Y

Sheet UKG Company Map
A1: Site Location | B1: Site Location Code | C1: Concur Org Unit | D1: Concur Company Code Description | E1: Expense Group Code | F1: Ledger Code | G1: Custom 5 Code | K1: Division | L1: Description | R1: Expense Group ID | S1: Description
A2: ASI Raymond China | B2: 0083 | C2: 0083 | D2: Raymond China | E2: 0083 | F2: 0083 | G2: 0083 | K2: 0041 | L2: (0041) Singapore MRO | R2: ISG | S2: (00) ISG
A3: NGP China | B3: 0079 | C3: 0079 | D3: NP China | E3: 0079 | F3: 0079 | G3: 0079 | K3: 0096 | L3: (0096) NGP Brecksville | R3: 0035 | S3: (0035) Raymond UK
A4: Barnes Acquisition Group | B4: 0400 | C4: 0400 | E4: 0400 | F4: 0400 | G4: 0400 | K4: 0146 | L4: (0146) Singapore OEM Division | R4: 0041 | S4: (0041) Singapore MRO
A5: ASI Raymond France | B5: 127 | C5: 0055 | D5: Raymond France | E5: 0055 | F5: 0055 | G5: 0055 | K5: 0147 | L5: (0147) Malaysia OEM | R5: 0055 | S5: (0055) Raymond France
A6: ASI Raymond UK | B6: 0035 | C6: 0035 | D6: Raymond - UK | E6: 0035 | F6: 0035 | G6: 0035 | K6: 0148 | L6: (0148) East Granby (MB) | R6: 0057 | S6: (0057) Raymond Singapore
A7: NGP IGS UK | B7: 0218 | C7: 0218 | D7: Industrial Gas Springs Ltd (UK) | E7: 0218 | F7: 0218 | G7: 0218 | K7: 0149 | L7: (0149) Warren (MB) | R7: 0075 | S7: (0075) NGP Mexico
A8: NGP United Kingdom | B8: 0219 | C8: 0114 | D8: Industrial Gas Springs Ltd (UK) | E8: 0114 | F8: 0114 | G8: 0114 | K8: 0150 | L8: (0150) Rzeszow | R8: 0077 | S8: (0077) Stromsholmen
A9: NGP India | B9: 176 | C9: 26 | D9: NP India | E9: 26 | F9: 26 | G9: 0026 | K9: 0151 | L9: (0151) Technologies | R9: 0079 | S9: (0079) NP China
A10: MAI Maenner Japan | B10: 406 | C10: 0406 | D10: Männer Japan | E10: 0406 | F10: 0406 | G10: 0406 | K10: 0155 | L10: (0155) Taoyuan (MB) | R10: 0083 | S10: (0083) Raymond China
A11: SMS Japan | B11: 0463 | C11: 0463 | D11: SMS Japan | E11: 0463 | F11: 0463 | G11: 0463 | K11: 0177 | L11: (0177) East Hartford | R11: 0084 | S11: (0084) Raymond Mexico
A12: NGP Korea | B12: 179 | C12: 34 | D12: NP Korea | E12: 34 | F12: 34 | G12: 0034 | K12: 0443 | L12: (0443) SMS BV (Holland) | R12: 0094 | S12: (0094) Raymond Spain
A13: Raymond Distribution – MX | B13: 0084 | C13: 0084 | D13: Raymond Mexico | E13: 0084 | F13: 0084 | G13: 0084 | K13: 06 | L13: (06) Aerospace Headquarters | R13: 0096 | S13: (0096) NGP Brecksville
A14: MX Nitrogen Division | B14: 0075 | C14: 0075 | D14: NGP Mexico | E14: 0075 | F14: 0075 | G14: 0075 | K14: 30 | L14: AS Asia | R14: 0097 | S14: (0097) Raymond Germany
A15: NGP Sweden | B15: 0077 | C15: 0077 | D15: Stromsholmen | E15: 0077 | F15: 0077 | G15: 0077 | K15: 0048 | L15: AS Brazil | R15: 0114 | S15: (0114) NGP UK
A16: NGP Sweden | B16: 177 | C16: 0077 | D16: Stromsholmen | E16: 0077 | F16: 0077 | G16: 0077 | K16: 36 | L16: AS Mexico | R16: 0143 | S16: (0143) Newton Abbot
A17: ASI Raymond Singapore | B17: 0057 | C17: 0057 | D17: Raymond Singapore | E17: 0057 | F17: 0057 | G17: 0057 | K17: 0173 | L17: AS Thailand | R17: 0146 | S17: (0146) Singapore OEM Division
K18: 33 | L18: AS Trading Brazil | R18: 0148 | S18: (0148) East Granby (MB)
A19: List Management (Invoice): | F19: Requires Concur | K19: 0418 | L19: Automation HQ | R19: 0150 | S19: (0150) Rzeszow
A20: List Management (Expense): | C20: *Division - Department | E20: *Expense Group ID | G20: *UKG Site Locations (Employee) | K20: 169 | L20: Barnes Aerospace - UK | R20: 0151 | S20: (0151) Technologies
K21: Barnes Group - Do Not Use | L21: Barnes Group - Do Not Use | R21: 0153 | S21: (0153) Motherwell
A22: KBD: | K22: 00 | L22: Barnes Group Corporate Office | R22: 0155 | S22: (0155) Taoyuan (MB Taiwan)
K23: 0400 | L23: BG Germany Acq GmbH | R23: 0169 | S23: (0169) European Sales Force
K24: 0470 | L24: BMS Korea | R24: 0170 | S24: (0170) Holdings (MB)
K25: 0175 | L25: Burnley (MB) | R25: 0173 | S25: (0173) AS Thailand
K26: 0169 | L26: European Sales Force | R26: 0175 | S26: (0175) Burnley
K27: 0502 | L27: FOBOHA China | R27: 0177 | S27: (0177) East Hartford
K28: 0501 | L28: FOBOHA Germany | R28: 0218 | S28: (0218) Industrial Gas Springs Ltd (UK)
K29: 0426 | L29: Gammaflux Germany | R29: 0400 | S29: (0400) BG Germany Acq GmbH
K30: GhostCard | L30: Ghost Card | R30: 0401 | S30: (0401) Manner Germany
K31: 0602 | L31: Gimatic S. r. l. | R31: 0404 | S31: (0404) Manner US
K32: GuestTravel | L32: Guest Traveler | R32: 0406 | S32: (0406) Männer Japan
K33: 0196 | L33: Heinz Hänggi | R33: 0420 | S33: (0420) Priamus Switzerland
K34: 0170 | L34: Holdings (MB) | R34: 0421 | S34: (0421) Priamus Germany
... K123: 225 | L123: zSynventive Thailand | R123: 602 | S123: z602
R124: 0612 | S124: zGimatic Balkan d.o.o. Beograd – Savski Venac
R125: 0407 | S125: zMänner Hong Kong

Sheet KN EP Brute Force
A1: Company Code | B1: Name | C1: Department Added
A2: 0035 | B2: Raymond UK | C2: 140102 | H2: 212047 | I2: 901934 | J2: Will Wilking
H3: 210703 | J3: Sebastian Lobner | K3: Made Leave of Absense
A4: 0035 | B4: Raymond UK | C4: 910 | H4: Svetlana | J4: Dwight
A7: 0077 | B7: Stroms | C7: 720000 | D7: Robert S. Bad data in UKG?
A8: 0084 | B8: Raymond Mexico | C8: 800
A9: 26 | B9: NGP India | C9: 0900 | D9: But 900 existed
A10: 0406 | B10: Japan | C10: 0000 | D10: Concur had 3 zeros
H12: Emails changed for ssncharacters
H16: Robert (CFO) Department
H22: Hedborg, Josefine <jhedborg@onebarnes.com>
H24: Not in UKG

Sheet ADP
A1: Employment Profile - Effective Date | B1: Effective as of 08/31/2026 | H1: Non US Temp Employee | I1: Missing work email address | R1: Filter to employee types | T1: Map and Filter | V1: Map based on ERP length | X1: Will be filled in | Y1: Will be filled in | AC1: Fix Supervisor ID | AD1: Assign an Org correctly | AE1: Fix to valid GL Company codes | AF1: Assign Salary Code | AG1: Assign Salary Code | AO1: 88 & 25/92 with $more than 0 | AR1: Where false validate the actual supervisor id is correct
A2: Employment Profile - Time & Attendance - Effective Date | B2: All records independent of date | H2: Missing Supervisor | AO2: Exception List
A3: Employment Profile - Pay Rates - Effective Date | B3: All records independent of date | H3: Top of food chain
A4: Payroll Company Code | B4: Legal First Name | C4: Middle Initial | D4: Legal Last Name | E4: Preferred or Chosen First Name | F4: Preferred or Chosen Last Name | G4: Reports To Legal Name | H4: Supervisor ID | I4: Work Contact: Work Email | J4: Personal Contact: Personal Email | K4: Job Title Description | L4: Hire Date | M4: Termination Date | N4: Rehire Date | O4: Position Status | P4: File Number | Q4: Pay Frequency | R4: Employee Type | S4: Business Unit Code | T4: Business Unit Description | U4: Home Department Description | V4: Home Department Code | W4: Location Description | X4: Language Description | Y4: Language Code | Z4: Legal / Preferred Address: Country Code | AA4: Pay Grade Code | AB4: Pay Grade Description | AC4: Supervisor Id | AD4: Org Unit 1 | AE4: Org Unit 2 | AF4: Concur Profile | AG4: Travel Profile | AH4: Invoice | AI4: Legal Country | AJ4: Local Code | AK4: Reumbursement Currency | AL4: Perferred Name | AM4: Status | AN4: TermDate | AO4: InvoiceAccess
A5: KSX | B5: Tammie | D5: Abitua | G5: Burchell, Mathew | H5: KSY211756 | I5: tabitua1@onebarnes.com | J5: abituatammie@gmail.com | K5: Assistant, Warehouse II | L5: 45733 | O5: Active | P5: 211837 | Q5: Biweekly | R5: Full Time | S5: 088 | T5: 088-AS Raymond | U5: Assembly | V5: 005100 | W5: AS Raymond | Z5: USA | AA5: S05 | AB5: FMG-S05 | AC5: =MID(H5,4,6) -> 211756 | AD5: =IFERROR(VLOOKUP(T5,'Org Map'!A:E,4),"BU Description Not Mapped") -> 0088 | AE5: =IFERROR(VLOOKUP(V5,'Org Map'!C:E,3,FALSE),"Home Department Code Not Mapped") -> 5100 | AF5: =IFERROR(VLOOKUP(AA5,'Salary Map'!A:D,3,FALSE),"Salary Code Not Mapped") -> Default | AG5: =IFERROR(VLOOKUP(AA5,'Salary Map'!A:D,4,FALSE),"Salary Code Not Mapped") -> General | AH5: =IFERROR(VLOOKUP(AA5,'Salary Map'!A:E,5,FALSE),"Invoice Approval Not Mapped") -> 0 | AI5: =IFERROR(VLOOKUP(Z5,'Country Map'!A:B,2,FALSE),"Legal Country Not Mapped") -> US | AJ5: =IFERROR(VLOOKUP(X5,'Language Map'!A:C,3,FALSE),IFERROR(VLOOKUP(T5,'Org Map'!A:F,6,FALSE),"ADP and BU Language Code Not Mapped"))&AI5 -> en_US | AK5: =IFERROR(VLOOKUP(T5,'Org Map'!A:G,7),"BU Currency Not Mapped") -> USD | AL5: =IF(ISBLANK(E5),"",TRIM(E5&" "&F5)) | AM5: =IFERROR(VLOOKUP(O5,'Status Map'!A:B,2,FALSE),"Position Status Not Mapped") -> Y | AN5: =IF(AM5="N",TEXT(M5,"yyyymmdd"),"") | AO5: =IFERROR(VLOOKUP(P5,'Invoice Exception Map'!A:C,3,FALSE),IF(AH5>0,"Y","N")) -> N
A6: KSY | B6: Gregory | C6: S | D6: Adams | G6: Rodriguez, Siobhan | H6: V0U207588 | I6: gadams@onebarnes.com | J6: gdsad.adams@cox.net | K6: Mgr, Sales | L6: 46188 | O6: Active | P6: 213331 | Q6: Monthly | R6: Full Time | S6: 088 | T6: 088-AS Raymond | U6: Outside Sales | V6: 008200 | W6: Work from home - Connecticut | Z6: USA | AA6: S16 | AB6: FMG-S16 | AC6: =IF(ISBLANK(H6),VLOOKUP(P6,'Invoice Exception Map'!A:D,4,FALSE),MID(H6,4,6)) -> 207588 | AD6: =IFERROR(VLOOKUP(T6,'Org Map'!A:E,4),"BU Description Not Mapped") -> 0088 | AE6: =IFERROR(VLOOKUP(V6,'Org Map'!C:E,3,FALSE),"Home Department Code Not Mapped") -> 8200 | AF6: =IFERROR(VLOOKUP(AA6,'Salary Map'!A:D,3,FALSE),"Salary Code Not Mapped") -> Default | AG6: =IFERROR(VLOOKUP(AA6,'Salary Map'!A:D,4,FALSE),"Salary Code Not Mapped") -> General | AH6: =IFERROR(VLOOKUP(AA6,'Salary Map'!A:E,5,FALSE),"Invoice Approval Not Mapped") -> 25000 | AI6: =IFERROR(VLOOKUP(Z6,'Country Map'!A:B,2,FALSE),"Legal Country Not Mapped") -> US | AJ6: =IFERROR(VLOOKUP(X6,'Language Map'!A:C,3,FALSE),IFERROR(VLOOKUP(T6,'Org Map'!A:F,6,FALSE),"ADP and BU Language Code Not Mapped"))&AI6 -> en_US | AK6: =IFERROR(VLOOKUP(T6,'Org Map'!A:G,7),"BU Currency Not Mapped") -> USD | AL6: =IF(ISBLANK(E6),"",TRIM(E6&" "&F6)) | AM6: =IFERROR(VLOOKUP(O6,'Status Map'!A:B,2,FALSE),"Position Status Not Mapped") -> Y | AN6: =IF(AM6="N",TEXT(M6,"yyyymmdd"),"") | AO6: =IFERROR(VLOOKUP(P6,'Invoice Exception Map'!A:C,3,FALSE),IF(AH6>0,"Y","N")) -> N
A7: KSY | B7: Krystle | D7: Agler | G7: Kemenah, Greg | H7: KSY211766 | I7: kagler@onebarnes.com | J7: krystle.agler@gmail.com | K7: Mgr, Marketing II | L7: 46160 | O7: Active | P7: 213226 | Q7: Monthly | R7: Full Time | S7: 088 | T7: 088-AS Raymond | U7: Marketing | V7: 008300 | W7: AS Raymond | Z7: USA | AA7: S16 | AB7: FMG-S16 | AC7: =IF(ISBLANK(H7),VLOOKUP(P7,'Invoice Exception Map'!A:D,4,FALSE),MID(H7,4,6)) -> 211766 | AD7: =IFERROR(VLOOKUP(T7,'Org Map'!A:E,4),"BU Description Not Mapped") -> 0088 | AE7: =IFERROR(VLOOKUP(V7,'Org Map'!C:E,3,FALSE),"Home Department Code Not Mapped") -> 8300 | AF7: =IFERROR(VLOOKUP(AA7,'Salary Map'!A:D,3,FALSE),"Salary Code Not Mapped") -> Default | AG7: =IFERROR(VLOOKUP(AA7,'Salary Map'!A:D,4,FALSE),"Salary Code Not Mapped") -> General | AH7: =IFERROR(VLOOKUP(AA7,'Salary Map'!A:E,5,FALSE),"Invoice Approval Not Mapped") -> 25000 | AI7: =IFERROR(VLOOKUP(Z7,'Country Map'!A:B,2,FALSE),"Legal Country Not Mapped") -> US | AJ7: =IFERROR(VLOOKUP(X7,'Language Map'!A:C,3,FALSE),IFERROR(VLOOKUP(T7,'Org Map'!A:F,6,FALSE),"ADP and BU Language Code Not Mapped"))&AI7 -> en_US | AK7: =IFERROR(VLOOKUP(T7,'Org Map'!A:G,7),"BU Currency Not Mapped") -> USD | AL7: =IF(ISBLANK(E7),"",TRIM(E7&" "&F7)) | AM7: =IFERROR(VLOOKUP(O7,'Status Map'!A:B,2,FALSE),"Position Status Not Mapped") -> Y | AN7: =IF(AM7="N",TEXT(M7,"yyyymmdd"),"") | AO7: =IFERROR(VLOOKUP(P7,'Invoice Exception Map'!A:C,3,FALSE),IF(AH7>0,"Y","N")) -> Y
A8: KSY | B8: Thomas | C8: E | D8: Alexander | G8: Kemenah, Greg | H8: KSY211766 | I8: talexander@onebarnes.com | J8: tom5683alexander@gmail.com | K8: Mgr, Quality II | L8: 45392 | O8: Active | P8: 210892 | Q8: Monthly | R8: Full Time | S8: 088 | T8: 088-AS Raymond | U8: Admin-Quality | V8: 009500 | W8: AS Raymond | Z8: USA | AA8: S16 | AB8: FMG-S16 | AC8: =IF(ISBLANK(H8),VLOOKUP(P8,'Invoice Exception Map'!A:D,4,FALSE),MID(H8,4,6)) -> 211766 | AD8: =IFERROR(VLOOKUP(T8,'Org Map'!A:E,4),"BU Description Not Mapped") -> 0088 | AE8: =IFERROR(VLOOKUP(V8,'Org Map'!C:E,3,FALSE),"Home Department Code Not Mapped") -> 9500 | AF8: =IFERROR(VLOOKUP(AA8,'Salary Map'!A:D,3,FALSE),"Salary Code Not Mapped") -> Default | AG8: =IFERROR(VLOOKUP(AA8,'Salary Map'!A:D,4,FALSE),"Salary Code Not Mapped") -> General | AH8: =IFERROR(VLOOKUP(AA8,'Salary Map'!A:E,5,FALSE),"Invoice Approval Not Mapped") -> 25000 | AI8: =IFERROR(VLOOKUP(Z8,'Country Map'!A:B,2,FALSE),"Legal Country Not Mapped") -> US | AJ8: =IFERROR(VLOOKUP(X8,'Language Map'!A:C,3,FALSE),IFERROR(VLOOKUP(T8,'Org Map'!A:F,6,FALSE),"ADP and BU Language Code Not Mapped"))&AI8 -> en_US | AK8: =IFERROR(VLOOKUP(T8,'Org Map'!A:G,7),"BU Currency Not Mapped") -> USD | AL8: =IF(ISBLANK(E8),"",TRIM(E8&" "&F8)) | AM8: =IFERROR(VLOOKUP(O8,'Status Map'!A:B,2,FALSE),"Position Status Not Mapped") -> Y | AN8: =IF(AM8="N",TEXT(M8,"yyyymmdd"),"") | AO8: =IFERROR(VLOOKUP(P8,'Invoice Exception Map'!A:C,3,FALSE),IF(AH8>0,"Y","N")) -> Y
A9: KSX | B9: Tina | C9: M | D9: Allen | G9: LaPlante, Derek | H9: KSY211736 | I9: TAllen2@onebarnes.com | J9: tinaallen908@gmail.com | K9: Assistant, Warehouse II | L9: 44550 | O9: Active | P9: 206848 | Q9: Biweekly | R9: Full Time | S9: 088 | T9: 088-AS Raymond | U9: FG Warehouse | V9: 005200 | W9: AS Raymond | Z9: USA | AA9: S05 | AB9: FMG-S05 | AC9: =IF(ISBLANK(H9),VLOOKUP(P9,'Invoice Exception Map'!A:D,4,FALSE),MID(H9,4,6)) -> 211736 | AD9: =IFERROR(VLOOKUP(T9,'Org Map'!A:E,4),"BU Description Not Mapped") -> 0088 | AE9: =IFERROR(VLOOKUP(V9,'Org Map'!C:E,3,FALSE),"Home Department Code Not Mapped") -> 5200 | AF9: =IFERROR(VLOOKUP(AA9,'Salary Map'!A:D,3,FALSE),"Salary Code Not Mapped") -> Default | AG9: =IFERROR(VLOOKUP(AA9,'Salary Map'!A:D,4,FALSE),"Salary Code Not Mapped") -> General | AH9: =IFERROR(VLOOKUP(AA9,'Salary Map'!A:E,5,FALSE),"Invoice Approval Not Mapped") -> 0 | AI9: =IFERROR(VLOOKUP(Z9,'Country Map'!A:B,2,FALSE),"Legal Country Not Mapped") -> US | AJ9: =IFERROR(VLOOKUP(X9,'Language Map'!A:C,3,FALSE),IFERROR(VLOOKUP(T9,'Org Map'!A:F,6,FALSE),"ADP and BU Language Code Not Mapped"))&AI9 -> en_US | AK9: =IFERROR(VLOOKUP(T9,'Org Map'!A:G,7),"BU Currency Not Mapped") -> USD | AL9: =IF(ISBLANK(E9),"",TRIM(E9&" "&F9)) | AM9: =IFERROR(VLOOKUP(O9,'Status Map'!A:B,2,FALSE),"Position Status Not Mapped") -> Y | AN9: =IF(AM9="N",TEXT(M9,"yyyymmdd"),"") | AO9: =IFERROR(VLOOKUP(P9,'Invoice Exception Map'!A:C,3,FALSE),IF(AH9>0,"Y","N")) -> N
A10: KSY | B10: Kimberly | D10: Ashley | G10: Warner, Dwight | H10: V0U008750 | I10: KAshley@onebarnes.com | K10: Accountant III | L10: 43710 | O10: Active | P10: 201688 | Q10: Monthly | R10: Full Time | S10: 088 | T10: 088-AS Raymond | U10: Finance General | V10: 009100 | W10: Work from home - Connecticut | Z10: USA | AA10: S13 | AB10: FMG-S13 | AC10: =IF(ISBLANK(H10),VLOOKUP(P10,'Invoice Exception Map'!A:D,4,FALSE),MID(H10,4,6)) -> 008750 | AD10: =IFERROR(VLOOKUP(T10,'Org Map'!A:E,4),"BU Description Not Mapped") -> 0088 | AE10: =IFERROR(VLOOKUP(V10,'Org Map'!C:E,3,FALSE),"Home Department Code Not Mapped") -> 9100 | AF10: =IFERROR(VLOOKUP(AA10,'Salary Map'!A:D,3,FALSE),"Salary Code Not Mapped") -> Default | AG10: =IFERROR(VLOOKUP(AA10,'Salary Map'!A:D,4,FALSE),"Salary Code Not Mapped") -> General | AH10: =IFERROR(VLOOKUP(AA10,'Salary Map'!A:E,5,FALSE),"Invoice Approval Not Mapped") -> 0 | AI10: =IFERROR(VLOOKUP(Z10,'Country Map'!A:B,2,FALSE),"Legal Country Not Mapped") -> US | AJ10: =IFERROR(VLOOKUP(X10,'Language Map'!A:C,3,FALSE),IFERROR(VLOOKUP(T10,'Org Map'!A:F,6,FALSE),"ADP and BU Language Code Not Mapped"))&AI10 -> en_US | AK10: =IFERROR(VLOOKUP(T10,'Org Map'!A:G,7),"BU Currency Not Mapped") -> USD | AL10: =IF(ISBLANK(E10),"",TRIM(E10&" "&F10)) | AM10: =IFERROR(VLOOKUP(O10,'Status Map'!A:B,2,FALSE),"Position Status Not Mapped") -> Y | AN10: =IF(AM10="N",TEXT(M10,"yyyymmdd"),"") | AO10: =IFERROR(VLOOKUP(P10,'Invoice Exception Map'!A:C,3,FALSE),IF(AH10>0,"Y","N")) -> Y
A11: KSY | B11: Jason | C11: J | D11: Bailey | G11: Kemenah, Greg | H11: KSY211766 | I11: jbailey@onebarnes.com | J11: jjbailey08@gmail.com | K11: Senior Mgr, Operations | L11: 46258 | O11: Active | P11: 902688 | Q11: Monthly | R11: Full Time | S11: 088 | T11: 088-AS Raymond | U11: FG Warehouse | V11: 005200 | W11: AS Raymond | Z11: USA | AA11: S18 | AB11: FMG-S18 | AC11: =IF(ISBLANK(H11),VLOOKUP(P11,'Invoice Exception Map'!A:D,4,FALSE),MID(H11,4,6)) -> 211766 | AD11: =IFERROR(VLOOKUP(T11,'Org Map'!A:E,4),"BU Description Not Mapped") -> 0088 | AE11: =IFERROR(VLOOKUP(V11,'Org Map'!C:E,3,FALSE),"Home Department Code Not Mapped") -> 5200 | AF11: =IFERROR(VLOOKUP(AA11,'Salary Map'!A:D,3,FALSE),"Salary Code Not Mapped") -> Default | AG11: =IFERROR(VLOOKUP(AA11,'Salary Map'!A:D,4,FALSE),"Salary Code Not Mapped") -> General | AH11: =IFERROR(VLOOKUP(AA11,'Salary Map'!A:E,5,FALSE),"Invoice Approval Not Mapped") -> 25000 | AI11: =IFERROR(VLOOKUP(Z11,'Country Map'!A:B,2,FALSE),"Legal Country Not Mapped") -> US | AJ11: =IFERROR(VLOOKUP(X11,'Language Map'!A:C,3,FALSE),IFERROR(VLOOKUP(T11,'Org Map'!A:F,6,FALSE),"ADP and BU Language Code Not Mapped"))&AI11 -> en_US | AK11: =IFERROR(VLOOKUP(T11,'Org Map'!A:G,7),"BU Currency Not Mapped") -> USD | AL11: =IF(ISBLANK(E11),"",TRIM(E11&" "&F11)) | AM11: =IFERROR(VLOOKUP(O11,'Status Map'!A:B,2,FALSE),"Position Status Not Mapped") -> Y | AN11: =IF(AM11="N",TEXT(M11,"yyyymmdd"),"") | AO11: =IFERROR(VLOOKUP(P11,'Invoice Exception Map'!A:C,3,FALSE),IF(AH11>0,"Y","N")) -> Y
A12: KSY | B12: Teresa | D12: Bair | I12: TBair@onebarnes.com | K12: President, SBU II | L12: 44732 | O12: Active | P12: 207709 | Q12: Monthly | R12: Full Time | S12: 088 | T12: 088-AS Raymond | U12: Bus Execs CU | V12: 009310 | W12: AS Raymond | Z12: USA | AA12: S22 | AB12: FMG-S22 | AC12: =IF(ISBLANK(H12),VLOOKUP(P12,'Invoice Exception Map'!A:D,4,FALSE),MID(H12,4,6)) | AD12: =IFERROR(VLOOKUP(T12,'Org Map'!A:E,4),"BU Description Not Mapped") -> 0088 | AE12: =IFERROR(VLOOKUP(V12,'Org Map'!C:E,3,FALSE),"Home Department Code Not Mapped") -> 9310 | AF12: =IFERROR(VLOOKUP(AA12,'Salary Map'!A:D,3,FALSE),"Salary Code Not Mapped") -> Grade 20 | AG12: =IFERROR(VLOOKUP(AA12,'Salary Map'!A:D,4,FALSE),"Salary Code Not Mapped") -> Senior Leadership | AH12: =IFERROR(VLOOKUP(AA12,'Salary Map'!A:E,5,FALSE),"Invoice Approval Not Mapped") -> 1e+09 | AI12: =IFERROR(VLOOKUP(Z12,'Country Map'!A:B,2,FALSE),"Legal Country Not Mapped") -> US | AJ12: =IFERROR(VLOOKUP(X12,'Language Map'!A:C,3,FALSE),IFERROR(VLOOKUP(T12,'Org Map'!A:F,6,FALSE),"ADP and BU Language Code Not Mapped"))&AI12 -> en_US | AK12: =IFERROR(VLOOKUP(T12,'Org Map'!A:G,7),"BU Currency Not Mapped") -> USD | AL12: =IF(ISBLANK(E12),"",TRIM(E12&" "&F12)) | AM12: =IFERROR(VLOOKUP(O12,'Status Map'!A:B,2,FALSE),"Position Status Not Mapped") -> Y | AN12: =IF(AM12="N",TEXT(M12,"yyyymmdd"),"") | AO12: =IFERROR(VLOOKUP(P12,'Invoice Exception Map'!A:C,3,FALSE),IF(AH12>0,"Y","N")) -> Y
A13: V0U | B13: Kirsten | C13: V | D13: Barry | G13: Rodriguez, Siobhan | H13: V0U207588 | I13: kbarry@onebarnes.com | K13: Mgr, Project I | L13: 44949 | O13: Active | P13: 209579 | Q13: Monthly | R13: Full Time | S13: 025 | T13: 025-NGP Hyson Products | U13: Outside Sales | V13: 000820 | W13: Hyson Products | Z13: USA | AA13: S15 | AB13: FMG-S15 | AC13: =IF(ISBLANK(H13),VLOOKUP(P13,'Invoice Exception Map'!A:D,4,FALSE),MID(H13,4,6)) -> 207588 | AD13: =IFERROR(VLOOKUP(T13,'Org Map'!A:E,4),"BU Description Not Mapped") -> 0096 | AE13: =IFERROR(VLOOKUP(V13,'Org Map'!C:E,3,FALSE),"Home Department Code Not Mapped") -> 820 | AF13: =IFERROR(VLOOKUP(AA13,'Salary Map'!A:D,3,FALSE),"Salary Code Not Mapped") -> Default | AG13: =IFERROR(VLOOKUP(AA13,'Salary Map'!A:D,4,FALSE),"Salary Code Not Mapped") -> General | AH13: =IFERROR(VLOOKUP(AA13,'Salary Map'!A:E,5,FALSE),"Invoice Approval Not Mapped") -> 0 | AI13: =IFERROR(VLOOKUP(Z13,'Country Map'!A:B,2,FALSE),"Legal Country Not Mapped") -> US | AJ13: =IFERROR(VLOOKUP(X13,'Language Map'!A:C,3,FALSE),IFERROR(VLOOKUP(T13,'Org Map'!A:F,6,FALSE),"ADP and BU Language Code Not Mapped"))&AI13 -> en_US | AK13: =IFERROR(VLOOKUP(T13,'Org Map'!A:G,7),"BU Currency Not Mapped") -> USD | AL13: =IF(ISBLANK(E13),"",TRIM(E13&" "&F13)) | AM13: =IFERROR(VLOOKUP(O13,'Status Map'!A:B,2,FALSE),"Position Status Not Mapped") -> Y | AN13: =IF(AM13="N",TEXT(M13,"yyyymmdd"),"") | AO13: =IFERROR(VLOOKUP(P13,'Invoice Exception Map'!A:C,3,FALSE),IF(AH13>0,"Y","N")) -> N
A14: V0U | B14: Natalie | D14: Bate | G14: Bair, Teresa | H14: KSY207709 | I14: nbate@onebarnes.com | J14: natalie.m.bate@gmail.com | K14: Mgr, Division II | L14: 46083 | O14: Active | P14: 213037 | Q14: Monthly | R14: Full Time | S14: 025 | T14: 025-NGP Hyson Products | U14: Administration | V14: 000917 | W14: Hyson Products | Z14: USA | AA14: S19 | AB14: FMG-S19 | AC14: =IF(ISBLANK(H14),VLOOKUP(P14,'Invoice Exception Map'!A:D,4,FALSE),MID(H14,4,6)) -> 207709 | AD14: =IFERROR(VLOOKUP(T14,'Org Map'!A:E,4),"BU Description Not Mapped") -> 0096 | AE14: =IFERROR(VLOOKUP(V14,'Org Map'!C:E,3,FALSE),"Home Department Code Not Mapped") -> 917 | AF14: =IFERROR(VLOOKUP(AA14,'Salary Map'!A:D,3,FALSE),"Salary Code Not Mapped") -> Default | AG14: =IFERROR(VLOOKUP(AA14,'Salary Map'!A:D,4,FALSE),"Salary Code Not Mapped") -> General | AH14: =IFERROR(VLOOKUP(AA14,'Salary Map'!A:E,5,FALSE),"Invoice Approval Not Mapped") -> 100000 | AI14: =IFERROR(VLOOKUP(Z14,'Country Map'!A:B,2,FALSE),"Legal Country Not Mapped") -> US | AJ14: =IFERROR(VLOOKUP(X14,'Language Map'!A:C,3,FALSE),IFERROR(VLOOKUP(T14,'Org Map'!A:F,6,FALSE),"ADP and BU Language Code Not Mapped"))&AI14 -> en_US | AK14: =IFERROR(VLOOKUP(T14,'Org Map'!A:G,7),"BU Currency Not Mapped") -> USD | AL14: =IF(ISBLANK(E14),"",TRIM(E14&" "&F14)) | AM14: =IFERROR(VLOOKUP(O14,'Status Map'!A:B,2,FALSE),"Position Status Not Mapped") -> Y | AN14: =IF(AM14="N",TEXT(M14,"yyyymmdd"),"") | AO14: =IFERROR(VLOOKUP(P14,'Invoice Exception Map'!A:C,3,FALSE),IF(AH14>0,"Y","N")) -> Y
A15: KSY | B15: Michael | C15: J | D15: Beasley | G15: Rodriguez, Siobhan | H15: V0U207588 | I15: mbeasley@onebarnes.com | J15: gqnbeasley@comcast.net | K15: Mgr, Sales | L15: 46202 | O15: Active | P15: 213333 | Q15: Monthly | R15: Full Time | S15: 088 | T15: 088-AS Raymond | U15: Outside Sales | V15: 008200 | W15: Work from home - Washington | Z15: USA | AA15: S16 | AB15: FMG-S16 | AC15: =IF(ISBLANK(H15),VLOOKUP(P15,'Invoice Exception Map'!A:D,4,FALSE),MID(H15,4,6)) -> 207588 | AD15: =IFERROR(VLOOKUP(T15,'Org Map'!A:E,4),"BU Description Not Mapped") -> 0088 | AE15: =IFERROR(VLOOKUP(V15,'Org Map'!C:E,3,FALSE),"Home Department Code Not Mapped") -> 8200 | AF15: =IFERROR(VLOOKUP(AA15,'Salary Map'!A:D,3,FALSE),"Salary Code Not Mapped") -> Default | AG15: =IFERROR(VLOOKUP(AA15,'Salary Map'!A:D,4,FALSE),"Salary Code Not Mapped") -> General | AH15: =IFERROR(VLOOKUP(AA15,'Salary Map'!A:E,5,FALSE),"Invoice Approval Not Mapped") -> 25000 | AI15: =IFERROR(VLOOKUP(Z15,'Country Map'!A:B,2,FALSE),"Legal Country Not Mapped") -> US | AJ15: =IFERROR(VLOOKUP(X15,'Language Map'!A:C,3,FALSE),IFERROR(VLOOKUP(T15,'Org Map'!A:F,6,FALSE),"ADP and BU Language Code Not Mapped"))&AI15 -> en_US | AK15: =IFERROR(VLOOKUP(T15,'Org Map'!A:G,7),"BU Currency Not Mapped") -> USD | AL15: =IF(ISBLANK(E15),"",TRIM(E15&" "&F15)) | AM15: =IFERROR(VLOOKUP(O15,'Status Map'!A:B,2,FALSE),"Position Status Not Mapped") -> Y | AN15: =IF(AM15="N",TEXT(M15,"yyyymmdd"),"") | AO15: =IFERROR(VLOOKUP(P15,'Invoice Exception Map'!A:C,3,FALSE),IF(AH15>0,"Y","N")) -> N
A16: KSX | B16: Ella Renae | C16: E | D16: Beatrice | G16: LaPlante, Derek | H16: KSY211736 | I16: ebeatrice@onebarnes.com | J16: thatellachick@gmail.com | K16: Assistant, Warehouse II | L16: 45929 | O16: Active | P16: 212626 | Q16: Biweekly | R16: Full Time | S16: 088 | T16: 088-AS Raymond | U16: FG Warehouse | V16: 005200 | W16: AS Raymond | Z16: USA | AA16: S05 | AB16: FMG-S05 | AC16: =IF(ISBLANK(H16),VLOOKUP(P16,'Invoice Exception Map'!A:D,4,FALSE),MID(H16,4,6)) -> 211736 | AD16: =IFERROR(VLOOKUP(T16,'Org Map'!A:E,4),"BU Description Not Mapped") -> 0088 | AE16: =IFERROR(VLOOKUP(V16,'Org Map'!C:E,3,FALSE),"Home Department Code Not Mapped") -> 5200 | AF16: =IFERROR(VLOOKUP(AA16,'Salary Map'!A:D,3,FALSE),"Salary Code Not Mapped") -> Default | AG16: =IFERROR(VLOOKUP(AA16,'Salary Map'!A:D,4,FALSE),"Salary Code Not Mapped") -> General | AH16: =IFERROR(VLOOKUP(AA16,'Salary Map'!A:E,5,FALSE),"Invoice Approval Not Mapped") -> 0 | AI16: =IFERROR(VLOOKUP(Z16,'Country Map'!A:B,2,FALSE),"Legal Country Not Mapped") -> US | AJ16: =IFERROR(VLOOKUP(X16,'Language Map'!A:C,3,FALSE),IFERROR(VLOOKUP(T16,'Org Map'!A:F,6,FALSE),"ADP and BU Language Code Not Mapped"))&AI16 -> en_US | AK16: =IFERROR(VLOOKUP(T16,'Org Map'!A:G,7),"BU Currency Not Mapped") -> USD | AL16: =IF(ISBLANK(E16),"",TRIM(E16&" "&F16)) | AM16: =IFERROR(VLOOKUP(O16,'Status Map'!A:B,2,FALSE),"Position Status Not Mapped") -> Y | AN16: =IF(AM16="N",TEXT(M16,"yyyymmdd"),"") | AO16: =IFERROR(VLOOKUP(P16,'Invoice Exception Map'!A:C,3,FALSE),IF(AH16>0,"Y","N")) -> N
A17: KSX | B17: John | D17: Bentz | G17: LaPlante, Derek | H17: KSY211736 | I17: jbentz@onebarnes.com | J17: xjbm13@yahoo.com | K17: Assistant, Warehouse II | L17: 45937 | O17: Active | P17: 212639 | Q17: Biweekly | R17: Full Time | S17: 088 | T17: 088-AS Raymond | U17: FG Warehouse | V17: 005200 | W17: AS Raymond | Z17: USA | AA17: S05 | AB17: FMG-S05 | AC17: =IF(ISBLANK(H17),VLOOKUP(P17,'Invoice Exception Map'!A:D,4,FALSE),MID(H17,4,6)) -> 211736 | AD17: =IFERROR(VLOOKUP(T17,'Org Map'!A:E,4),"BU Description Not Mapped") -> 0088 | AE17: =IFERROR(VLOOKUP(V17,'Org Map'!C:E,3,FALSE),"Home Department Code Not Mapped") -> 5200 | AF17: =IFERROR(VLOOKUP(AA17,'Salary Map'!A:D,3,FALSE),"Salary Code Not Mapped") -> Default | AG17: =IFERROR(VLOOKUP(AA17,'Salary Map'!A:D,4,FALSE),"Salary Code Not Mapped") -> General | AH17: =IFERROR(VLOOKUP(AA17,'Salary Map'!A:E,5,FALSE),"Invoice Approval Not Mapped") -> 0 | AI17: =IFERROR(VLOOKUP(Z17,'Country Map'!A:B,2,FALSE),"Legal Country Not Mapped") -> US | AJ17: =IFERROR(VLOOKUP(X17,'Language Map'!A:C,3,FALSE),IFERROR(VLOOKUP(T17,'Org Map'!A:F,6,FALSE),"ADP and BU Language Code Not Mapped"))&AI17 -> en_US | AK17: =IFERROR(VLOOKUP(T17,'Org Map'!A:G,7),"BU Currency Not Mapped") -> USD | AL17: =IF(ISBLANK(E17),"",TRIM(E17&" "&F17)) | AM17: =IFERROR(VLOOKUP(O17,'Status Map'!A:B,2,FALSE),"Position Status Not Mapped") -> Y | AN17: =IF(AM17="N",TEXT(M17,"yyyymmdd"),"") | AO17: =IFERROR(VLOOKUP(P17,'Invoice Exception Map'!A:C,3,FALSE),IF(AH17>0,"Y","N")) -> N
A18: KSY | B18: Michael | D18: Biniecki | G18: Bailey, Jason | H18: KSY902688 | I18: mbiniecki@onebarnes.com | J18: mbineck@frontier.com | K18: Supv, CI | L18: 45565 | O18: Active | P18: 211464 | Q18: Monthly | R18: Full Time | S18: 088 | T18: 088-AS Raymond | U18: FG Warehouse | V18: 005200 | W18: AS Raymond | Z18: USA | AA18: S16 | AB18: FMG-S16 | AC18: =IF(ISBLANK(H18),VLOOKUP(P18,'Invoice Exception Map'!A:D,4,FALSE),MID(H18,4,6)) -> 902688 | AD18: =IFERROR(VLOOKUP(T18,'Org Map'!A:E,4),"BU Description Not Mapped") -> 0088 | AE18: =IFERROR(VLOOKUP(V18,'Org Map'!C:E,3,FALSE),"Home Department Code Not Mapped") -> 5200 | AF18: =IFERROR(VLOOKUP(AA18,'Salary Map'!A:D,3,FALSE),"Salary Code Not Mapped") -> Default | AG18: =IFERROR(VLOOKUP(AA18,'Salary Map'!A:D,4,FALSE),"Salary Code Not Mapped") -> General | AH18: =IFERROR(VLOOKUP(AA18,'Salary Map'!A:E,5,FALSE),"Invoice Approval Not Mapped") -> 25000 | AI18: =IFERROR(VLOOKUP(Z18,'Country Map'!A:B,2,FALSE),"Legal Country Not Mapped") -> US | AJ18: =IFERROR(VLOOKUP(X18,'Language Map'!A:C,3,FALSE),IFERROR(VLOOKUP(T18,'Org Map'!A:F,6,FALSE),"ADP and BU Language Code Not Mapped"))&AI18 -> en_US | AK18: =IFERROR(VLOOKUP(T18,'Org Map'!A:G,7),"BU Currency Not Mapped") -> USD | AL18: =IF(ISBLANK(E18),"",TRIM(E18&" "&F18)) | AM18: =IFERROR(VLOOKUP(O18,'Status Map'!A:B,2,FALSE),"Position Status Not Mapped") -> Y | AN18: =IF(AM18="N",TEXT(M18,"yyyymmdd"),"") | AO18: =IFERROR(VLOOKUP(P18,'Invoice Exception Map'!A:C,3,FALSE),IF(AH18>0,"Y","N")) -> Y
A19: V0U | B19: Nathan | D19: Bird | G19: Wilkins, William | H19: V0U901934 | I19: nbird@onebarnes.com | J19: bird.nathan@icloud.com | K19: Mgr, Sales | L19: 45131 | O19: Active | P19: 210102 | Q19: Monthly | R19: Full Time | S19: 025 | T19: 025-NGP Hyson Products | U19: Outside Sales | V19: 000820 | W19: Work from home - Arizona | Z19: USA | AA19: S15 | AB19: FMG-S15 | AC19: =IF(ISBLANK(H19),VLOOKUP(P19,'Invoice Exception Map'!A:D,4,FALSE),MID(H19,4,6)) -> 901934 | AD19: =IFERROR(VLOOKUP(T19,'Org Map'!A:E,4),"BU Description Not Mapped") -> 0096 | AE19: =IFERROR(VLOOKUP(V19,'Org Map'!C:E,3,FALSE),"Home Department Code Not Mapped") -> 820 | AF19: =IFERROR(VLOOKUP(AA19,'Salary Map'!A:D,3,FALSE),"Salary Code Not Mapped") -> Default | AG19: =IFERROR(VLOOKUP(AA19,'Salary Map'!A:D,4,FALSE),"Salary Code Not Mapped") -> General | AH19: =IFERROR(VLOOKUP(AA19,'Salary Map'!A:E,5,FALSE),"Invoice Approval Not Mapped") -> 0 | AI19: =IFERROR(VLOOKUP(Z19,'Country Map'!A:B,2,FALSE),"Legal Country Not Mapped") -> US | AJ19: =IFERROR(VLOOKUP(X19,'Language Map'!A:C,3,FALSE),IFERROR(VLOOKUP(T19,'Org Map'!A:F,6,FALSE),"ADP and BU Language Code Not Mapped"))&AI19 -> en_US | AK19: =IFERROR(VLOOKUP(T19,'Org Map'!A:G,7),"BU Currency Not Mapped") -> USD | AL19: =IF(ISBLANK(E19),"",TRIM(E19&" "&F19)) | AM19: =IFERROR(VLOOKUP(O19,'Status Map'!A:B,2,FALSE),"Position Status Not Mapped") -> Y | AN19: =IF(AM19="N",TEXT(M19,"yyyymmdd"),"") | AO19: =IFERROR(VLOOKUP(P19,'Invoice Exception Map'!A:C,3,FALSE),IF(AH19>0,"Y","N")) -> N
A20: KSX | B20: Brenda | D20: Bixler | G20: LaPlante, Derek | H20: KSY211736 | I20: bbixler@onebarnes.com | J20: beebix911@gmail.com | K20: Expeditor, Warehouse | L20: 45502 | O20: Active | P20: 211174 | Q20: Biweekly | R20: Full Time | S20: 088 | T20: 088-AS Raymond | U20: FG Warehouse | V20: 005200 | W20: AS Raymond | Z20: USA | AA20: S06 | AB20: FMG-S06 | AC20: =IF(ISBLANK(H20),VLOOKUP(P20,'Invoice Exception Map'!A:D,4,FALSE),MID(H20,4,6)) -> 211736 | AD20: =IFERROR(VLOOKUP(T20,'Org Map'!A:E,4),"BU Description Not Mapped") -> 0088 | AE20: =IFERROR(VLOOKUP(V20,'Org Map'!C:E,3,FALSE),"Home Department Code Not Mapped") -> 5200 | AF20: =IFERROR(VLOOKUP(AA20,'Salary Map'!A:D,3,FALSE),"Salary Code Not Mapped") -> Default | AG20: =IFERROR(VLOOKUP(AA20,'Salary Map'!A:D,4,FALSE),"Salary Code Not Mapped") -> General | AH20: =IFERROR(VLOOKUP(AA20,'Salary Map'!A:E,5,FALSE),"Invoice Approval Not Mapped") -> 0 | AI20: =IFERROR(VLOOKUP(Z20,'Country Map'!A:B,2,FALSE),"Legal Country Not Mapped") -> US | AJ20: =IFERROR(VLOOKUP(X20,'Language Map'!A:C,3,FALSE),IFERROR(VLOOKUP(T20,'Org Map'!A:F,6,FALSE),"ADP and BU Language Code Not Mapped"))&AI20 -> en_US | AK20: =IFERROR(VLOOKUP(T20,'Org Map'!A:G,7),"BU Currency Not Mapped") -> USD | AL20: =IF(ISBLANK(E20),"",TRIM(E20&" "&F20)) | AM20: =IFERROR(VLOOKUP(O20,'Status Map'!A:B,2,FALSE),"Position Status Not Mapped") -> Y | AN20: =IF(AM20="N",TEXT(M20,"yyyymmdd"),"") | AO20: =IFERROR(VLOOKUP(P20,'Invoice Exception Map'!A:C,3,FALSE),IF(AH20>0,"Y","N")) -> N
A21: V0U | B21: James | D21: Brower | G21: Bate, Natalie | H21: V0U213037 | I21: JBrower@onebarnes.com | J21: browerj@cox.net | K21: Engineer, Application III | L21: 34736 | O21: Active | P21: 006769 | Q21: Monthly | R21: Full Time | S21: 025 | T21: 025-NGP Hyson Products | U21: Engineering | V21: 000718 | W21: Hyson Products | Z21: USA | AA21: S15 | AB21: FMG-S15 | AC21: =IF(ISBLANK(H21),VLOOKUP(P21,'Invoice Exception Map'!A:D,4,FALSE),MID(H21,4,6)) -> 213037 | AD21: =IFERROR(VLOOKUP(T21,'Org Map'!A:E,4),"BU Description Not Mapped") -> 0096 | AE21: =IFERROR(VLOOKUP(V21,'Org Map'!C:E,3,FALSE),"Home Department Code Not Mapped") -> 718 | AF21: =IFERROR(VLOOKUP(AA21,'Salary Map'!A:D,3,FALSE),"Salary Code Not Mapped") -> Default | AG21: =IFERROR(VLOOKUP(AA21,'Salary Map'!A:D,4,FALSE),"Salary Code Not Mapped") -> General | AH21: =IFERROR(VLOOKUP(AA21,'Salary Map'!A:E,5,FALSE),"Invoice Approval Not Mapped") -> 0 | AI21: =IFERROR(VLOOKUP(Z21,'Country Map'!A:B,2,FALSE),"Legal Country Not Mapped") -> US | AJ21: =IFERROR(VLOOKUP(X21,'Language Map'!A:C,3,FALSE),IFERROR(VLOOKUP(T21,'Org Map'!A:F,6,FALSE),"ADP and BU Language Code Not Mapped"))&AI21 -> en_US | AK21: =IFERROR(VLOOKUP(T21,'Org Map'!A:G,7),"BU Currency Not Mapped") -> USD | AL21: =IF(ISBLANK(E21),"",TRIM(E21&" "&F21)) | AM21: =IFERROR(VLOOKUP(O21,'Status Map'!A:B,2,FALSE),"Position Status Not Mapped") -> Y | AN21: =IF(AM21="N",TEXT(M21,"yyyymmdd"),"") | AO21: =IFERROR(VLOOKUP(P21,'Invoice Exception Map'!A:C,3,FALSE),IF(AH21>0,"Y","N")) -> N
A22: KSY | B22: Trevor | D22: Bunch | G22: Valetta, David | H22: V0U211601 | I22: Tbunch@onebarnes.com | K22: Analyst, Pricing | L22: 45033 | O22: Active | P22: 209735 | Q22: Monthly | R22: Full Time | S22: 088 | T22: 088-AS Raymond | U22: Marketing | V22: 008300 | W22: AS Raymond | Z22: USA | AA22: S13 | AB22: FMG-S13 | AC22: =IF(ISBLANK(H22),VLOOKUP(P22,'Invoice Exception Map'!A:D,4,FALSE),MID(H22,4,6)) -> 211601 | AD22: =IFERROR(VLOOKUP(T22,'Org Map'!A:E,4),"BU Description Not Mapped") -> 0088 | AE22: =IFERROR(VLOOKUP(V22,'Org Map'!C:E,3,FALSE),"Home Department Code Not Mapped") -> 8300 | AF22: =IFERROR(VLOOKUP(AA22,'Salary Map'!A:D,3,FALSE),"Salary Code Not Mapped") -> Default | AG22: =IFERROR(VLOOKUP(AA22,'Salary Map'!A:D,4,FALSE),"Salary Code Not Mapped") -> General | AH22: =IFERROR(VLOOKUP(AA22,'Salary Map'!A:E,5,FALSE),"Invoice Approval Not Mapped") -> 0 | AI22: =IFERROR(VLOOKUP(Z22,'Country Map'!A:B,2,FALSE),"Legal Country Not Mapped") -> US | AJ22: =IFERROR(VLOOKUP(X22,'Language Map'!A:C,3,FALSE),IFERROR(VLOOKUP(T22,'Org Map'!A:F,6,FALSE),"ADP and BU Language Code Not Mapped"))&AI22 -> en_US | AK22: =IFERROR(VLOOKUP(T22,'Org Map'!A:G,7),"BU Currency Not Mapped") -> USD | AL22: =IF(ISBLANK(E22),"",TRIM(E22&" "&F22)) | AM22: =IFERROR(VLOOKUP(O22,'Status Map'!A:B,2,FALSE),"Position Status Not Mapped") -> Y | AN22: =IF(AM22="N",TEXT(M22,"yyyymmdd"),"") | AO22: =IFERROR(VLOOKUP(P22,'Invoice Exception Map'!A:C,3,FALSE),IF(AH22>0,"Y","N")) -> N
A23: KSY | B23: Mathew | C23: A | D23: Burchell | G23: Bailey, Jason | H23: KSY902688 | I23: mburchell@onebarnes.com | J23: mathew121709@outlook.com | K23: Supv, Warehouse I | L23: 45719 | O23: Active | P23: 211756 | Q23: Monthly | R23: Full Time | S23: 088 | T23: 088-AS Raymond | U23: Assembly | V23: 005100 | W23: AS Raymond | Z23: USA | AA23: S11 | AB23: FMG-S11 | AC23: =IF(ISBLANK(H23),VLOOKUP(P23,'Invoice Exception Map'!A:D,4,FALSE),MID(H23,4,6)) -> 902688 | AD23: =IFERROR(VLOOKUP(T23,'Org Map'!A:E,4),"BU Description Not Mapped") -> 0088 | AE23: =IFERROR(VLOOKUP(V23,'Org Map'!C:E,3,FALSE),"Home Department Code Not Mapped") -> 5100 | AF23: =IFERROR(VLOOKUP(AA23,'Salary Map'!A:D,3,FALSE),"Salary Code Not Mapped") -> Default | AG23: =IFERROR(VLOOKUP(AA23,'Salary Map'!A:D,4,FALSE),"Salary Code Not Mapped") -> General | AH23: =IFERROR(VLOOKUP(AA23,'Salary Map'!A:E,5,FALSE),"Invoice Approval Not Mapped") -> 0 | AI23: =IFERROR(VLOOKUP(Z23,'Country Map'!A:B,2,FALSE),"Legal Country Not Mapped") -> US | AJ23: =IFERROR(VLOOKUP(X23,'Language Map'!A:C,3,FALSE),IFERROR(VLOOKUP(T23,'Org Map'!A:F,6,FALSE),"ADP and BU Language Code Not Mapped"))&AI23 -> en_US | AK23: =IFERROR(VLOOKUP(T23,'Org Map'!A:G,7),"BU Currency Not Mapped") -> USD | AL23: =IF(ISBLANK(E23),"",TRIM(E23&" "&F23)) | AM23: =IFERROR(VLOOKUP(O23,'Status Map'!A:B,2,FALSE),"Position Status Not Mapped") -> Y | AN23: =IF(AM23="N",TEXT(M23,"yyyymmdd"),"") | AO23: =IFERROR(VLOOKUP(P23,'Invoice Exception Map'!A:C,3,FALSE),IF(AH23>0,"Y","N")) -> N
A24: KSW | B24: Kenneth | C24: D | D24: Butler | G24: Steen, Michael | H24: V0U211062 | I24: kbutler@onebarnes.com | J24: kennethbutler6459@yahoo.com | K24: Coord, Material B | L24: 44529 | O24: Active | P24: 206741 | Q24: Biweekly | R24: Full Time | S24: 025 | T24: 025-NGP Hyson Products | U24: Indirect General -Hyson | V24: 000400 | W24: Hyson Products | Z24: USA | AA24: H05 | AB24: FMG-H05 | AC24: =IF(ISBLANK(H24),VLOOKUP(P24,'Invoice Exception Map'!A:D,4,FALSE),MID(H24,4,6)) -> 211062 | AD24: =IFERROR(VLOOKUP(T24,'Org Map'!A:E,4),"BU Description Not Mapped") -> 0096 | AE24: =IFERROR(VLOOKUP(V24,'Org Map'!C:E,3,FALSE),"Home Department Code Not Mapped") -> 400 | AF24: =IFERROR(VLOOKUP(AA24,'Salary Map'!A:D,3,FALSE),"Salary Code Not Mapped") -> Default | AG24: =IFERROR(VLOOKUP(AA24,'Salary Map'!A:D,4,FALSE),"Salary Code Not Mapped") -> General | AH24: =IFERROR(VLOOKUP(AA24,'Salary Map'!A:E,5,FALSE),"Invoice Approval Not Mapped") -> 0 | AI24: =IFERROR(VLOOKUP(Z24,'Country Map'!A:B,2,FALSE),"Legal Country Not Mapped") -> US | AJ24: =IFERROR(VLOOKUP(X24,'Language Map'!A:C,3,FALSE),IFERROR(VLOOKUP(T24,'Org Map'!A:F,6,FALSE),"ADP and BU Language Code Not Mapped"))&AI24 -> en_US | AK24: =IFERROR(VLOOKUP(T24,'Org Map'!A:G,7),"BU Currency Not Mapped") -> USD | AL24: =IF(ISBLANK(E24),"",TRIM(E24&" "&F24)) | AM24: =IFERROR(VLOOKUP(O24,'Status Map'!A:B,2,FALSE),"Position Status Not Mapped") -> Y | AN24: =IF(AM24="N",TEXT(M24,"yyyymmdd"),"") | AO24: =IFERROR(VLOOKUP(P24,'Invoice Exception Map'!A:C,3,FALSE),IF(AH24>0,"Y","N")) -> N
A25: V0U | B25: Timothy | C25: D | D25: Carmichael | G25: Valetta, David | H25: V0U211601 | I25: TCarmichael@onebarnes.com | J25: tritectim@yahoo.com | K25: Analyst, Pricing | L25: 41386 | O25: Active | P25: 900826 | Q25: Monthly | R25: Full Time | S25: 025 | T25: 025-NGP Hyson Products | U25: Inside Sales | V25: 000850 | W25: Hyson Products | Z25: USA | AA25: S13 | AB25: FMG-S13 | AC25: =IF(ISBLANK(H25),VLOOKUP(P25,'Invoice Exception Map'!A:D,4,FALSE),MID(H25,4,6)) -> 211601 | AD25: =IFERROR(VLOOKUP(T25,'Org Map'!A:E,4),"BU Description Not Mapped") -> 0096 | AE25: =IFERROR(VLOOKUP(V25,'Org Map'!C:E,3,FALSE),"Home Department Code Not Mapped") -> 850 | AF25: =IFERROR(VLOOKUP(AA25,'Salary Map'!A:D,3,FALSE),"Salary Code Not Mapped") -> Default | AG25: =IFERROR(VLOOKUP(AA25,'Salary Map'!A:D,4,FALSE),"Salary Code Not Mapped") -> General | AH25: =IFERROR(VLOOKUP(AA25,'Salary Map'!A:E,5,FALSE),"Invoice Approval Not Mapped") -> 0 | AI25: =IFERROR(VLOOKUP(Z25,'Country Map'!A:B,2,FALSE),"Legal Country Not Mapped") -> US | AJ25: =IFERROR(VLOOKUP(X25,'Language Map'!A:C,3,FALSE),IFERROR(VLOOKUP(T25,'Org Map'!A:F,6,FALSE),"ADP and BU Language Code Not Mapped"))&AI25 -> en_US | AK25: =IFERROR(VLOOKUP(T25,'Org Map'!A:G,7),"BU Currency Not Mapped") -> USD | AL25: =IF(ISBLANK(E25),"",TRIM(E25&" "&F25)) | AM25: =IFERROR(VLOOKUP(O25,'Status Map'!A:B,2,FALSE),"Position Status Not Mapped") -> Y | AN25: =IF(AM25="N",TEXT(M25,"yyyymmdd"),"") | AO25: =IFERROR(VLOOKUP(P25,'Invoice Exception Map'!A:C,3,FALSE),IF(AH25>0,"Y","N")) -> N
A26: V0U | B26: Jonathan | D26: Carter | G26: Bate, Natalie | H26: V0U213037 | I26: jcarter@onebarnes.com | J26: Jonathancarter201157@gmail.com | K26: Engineer, Production II | L26: 45971 | O26: Active | P26: 212737 | Q26: Monthly | R26: Full Time | S26: 025 | T26: 025-NGP Hyson Products | U26: Engineering | V26: 000718 | W26: Hyson Products | Z26: USA | AA26: S14 | AB26: FMG-S14 | AC26: =IF(ISBLANK(H26),VLOOKUP(P26,'Invoice Exception Map'!A:D,4,FALSE),MID(H26,4,6)) -> 213037 | AD26: =IFERROR(VLOOKUP(T26,'Org Map'!A:E,4),"BU Description Not Mapped") -> 0096 | AE26: =IFERROR(VLOOKUP(V26,'Org Map'!C:E,3,FALSE),"Home Department Code Not Mapped") -> 718 | AF26: =IFERROR(VLOOKUP(AA26,'Salary Map'!A:D,3,FALSE),"Salary Code Not Mapped") -> Default | AG26: =IFERROR(VLOOKUP(AA26,'Salary Map'!A:D,4,FALSE),"Salary Code Not Mapped") -> General | AH26: =IFERROR(VLOOKUP(AA26,'Salary Map'!A:E,5,FALSE),"Invoice Approval Not Mapped") -> 0 | AI26: =IFERROR(VLOOKUP(Z26,'Country Map'!A:B,2,FALSE),"Legal Country Not Mapped") -> US | AJ26: =IFERROR(VLOOKUP(X26,'Language Map'!A:C,3,FALSE),IFERROR(VLOOKUP(T26,'Org Map'!A:F,6,FALSE),"ADP and BU Language Code Not Mapped"))&AI26 -> en_US | AK26: =IFERROR(VLOOKUP(T26,'Org Map'!A:G,7),"BU Currency Not Mapped") -> USD | AL26: =IF(ISBLANK(E26),"",TRIM(E26&" "&F26)) | AM26: =IFERROR(VLOOKUP(O26,'Status Map'!A:B,2,FALSE),"Position Status Not Mapped") -> Y | AN26: =IF(AM26="N",TEXT(M26,"yyyymmdd"),"") | AO26: =IFERROR(VLOOKUP(P26,'Invoice Exception Map'!A:C,3,FALSE),IF(AH26>0,"Y","N")) -> N
A27: KSY | B27: Tyler | D27: Cler | G27: Kemenah, Greg | H27: KSY211766 | I27: tcler@onebarnes.com | J27: tyler.cler@gmail.com | K27: Engineer, Production II | L27: 43192 | O27: Active | P27: 902435 | Q27: Monthly | R27: Full Time | S27: 088 | T27: 088-AS Raymond | U27: Admin-Engineering | V27: 009450 | W27: AS Raymond | X27: English | Y27: 4 | Z27: USA | AA27: S14 | AB27: FMG-S14 | AC27: =IF(ISBLANK(H27),VLOOKUP(P27,'Invoice Exception Map'!A:D,4,FALSE),MID(H27,4,6)) -> 211766 | AD27: =IFERROR(VLOOKUP(T27,'Org Map'!A:E,4),"BU Description Not Mapped") -> 0088 | AE27: =IFERROR(VLOOKUP(V27,'Org Map'!C:E,3,FALSE),"Home Department Code Not Mapped") -> 9450 | AF27: =IFERROR(VLOOKUP(AA27,'Salary Map'!A:D,3,FALSE),"Salary Code Not Mapped") -> Default | AG27: =IFERROR(VLOOKUP(AA27,'Salary Map'!A:D,4,FALSE),"Salary Code Not Mapped") -> General | AH27: =IFERROR(VLOOKUP(AA27,'Salary Map'!A:E,5,FALSE),"Invoice Approval Not Mapped") -> 0 | AI27: =IFERROR(VLOOKUP(Z27,'Country Map'!A:B,2,FALSE),"Legal Country Not Mapped") -> US | AJ27: =IFERROR(VLOOKUP(X27,'Language Map'!A:C,3,FALSE),IFERROR(VLOOKUP(T27,'Org Map'!A:F,6,FALSE),"ADP and BU Language Code Not Mapped"))&AI27 -> en_US | AK27: =IFERROR(VLOOKUP(T27,'Org Map'!A:G,7),"BU Currency Not Mapped") -> USD | AL27: =IF(ISBLANK(E27),"",TRIM(E27&" "&F27)) | AM27: =IFERROR(VLOOKUP(O27,'Status Map'!A:B,2,FALSE),"Position Status Not Mapped") -> Y | AN27: =IF(AM27="N",TEXT(M27,"yyyymmdd"),"") | AO27: =IFERROR(VLOOKUP(P27,'Invoice Exception Map'!A:C,3,FALSE),IF(AH27>0,"Y","N")) -> N
A28: KSW | B28: Timothy | C28: E | D28: Clifton | G28: Leftrict, Wayne | H28: V0U210910 | I28: tclifton1@onebarnes.com | J28: clifford43431t@yahoo.com | K28: Tech, Quality I | L28: 46160 | O28: Active | P28: 213265 | Q28: Biweekly | R28: Full Time | S28: 025 | T28: 025-NGP Hyson Products | U28: Quality | V28: 000500 | W28: Hyson Products | Z28: USA | AA28: S10 | AB28: FMG-S10 | AC28: =IF(ISBLANK(H28),VLOOKUP(P28,'Invoice Exception Map'!A:D,4,FALSE),MID(H28,4,6)) -> 210910 | AD28: =IFERROR(VLOOKUP(T28,'Org Map'!A:E,4),"BU Description Not Mapped") -> 0096 | AE28: =IFERROR(VLOOKUP(V28,'Org Map'!C:E,3,FALSE),"Home Department Code Not Mapped") -> 500 | AF28: =IFERROR(VLOOKUP(AA28,'Salary Map'!A:D,3,FALSE),"Salary Code Not Mapped") -> Default | AG28: =IFERROR(VLOOKUP(AA28,'Salary Map'!A:D,4,FALSE),"Salary Code Not Mapped") -> General | AH28: =IFERROR(VLOOKUP(AA28,'Salary Map'!A:E,5,FALSE),"Invoice Approval Not Mapped") -> 0 | AI28: =IFERROR(VLOOKUP(Z28,'Country Map'!A:B,2,FALSE),"Legal Country Not Mapped") -> US | AJ28: =IFERROR(VLOOKUP(X28,'Language Map'!A:C,3,FALSE),IFERROR(VLOOKUP(T28,'Org Map'!A:F,6,FALSE),"ADP and BU Language Code Not Mapped"))&AI28 -> en_US | AK28: =IFERROR(VLOOKUP(T28,'Org Map'!A:G,7),"BU Currency Not Mapped") -> USD | AL28: =IF(ISBLANK(E28),"",TRIM(E28&" "&F28)) | AM28: =IFERROR(VLOOKUP(O28,'Status Map'!A:B,2,FALSE),"Position Status Not Mapped") -> Y | AN28: =IF(AM28="N",TEXT(M28,"yyyymmdd"),"") | AO28: =IFERROR(VLOOKUP(P28,'Invoice Exception Map'!A:C,3,FALSE),IF(AH28>0,"Y","N")) -> N
A29: KSY | B29: Andrew | C29: J | D29: Creager | G29: Bailey, Jason | H29: KSY902688 | I29: acreager@onebarnes.com | K29: Mgr, Supply Chain III | L29: 45957 | O29: Active | P29: 212699 | Q29: Monthly | R29: Full Time | S29: 088 | T29: 088-AS Raymond | U29: Admin-Material Management | V29: 009400 | W29: AS Raymond | Z29: USA | AA29: S17 | AB29: FMG-S17 | AC29: =IF(ISBLANK(H29),VLOOKUP(P29,'Invoice Exception Map'!A:D,4,FALSE),MID(H29,4,6)) -> 902688 | AD29: =IFERROR(VLOOKUP(T29,'Org Map'!A:E,4),"BU Description Not Mapped") -> 0088 | AE29: =IFERROR(VLOOKUP(V29,'Org Map'!C:E,3,FALSE),"Home Department Code Not Mapped") -> 9400 | AF29: =IFERROR(VLOOKUP(AA29,'Salary Map'!A:D,3,FALSE),"Salary Code Not Mapped") -> Default | AG29: =IFERROR(VLOOKUP(AA29,'Salary Map'!A:D,4,FALSE),"Salary Code Not Mapped") -> General | AH29: =IFERROR(VLOOKUP(AA29,'Salary Map'!A:E,5,FALSE),"Invoice Approval Not Mapped") -> 25000 | AI29: =IFERROR(VLOOKUP(Z29,'Country Map'!A:B,2,FALSE),"Legal Country Not Mapped") -> US | AJ29: =IFERROR(VLOOKUP(X29,'Language Map'!A:C,3,FALSE),IFERROR(VLOOKUP(T29,'Org Map'!A:F,6,FALSE),"ADP and BU Language Code Not Mapped"))&AI29 -> en_US | AK29: =IFERROR(VLOOKUP(T29,'Org Map'!A:G,7),"BU Currency Not Mapped") -> USD | AL29: =IF(ISBLANK(E29),"",TRIM(E29&" "&F29)) | AM29: =IFERROR(VLOOKUP(O29,'Status Map'!A:B,2,FALSE),"Position Status Not Mapped") -> Y | AN29: =IF(AM29="N",TEXT(M29,"yyyymmdd"),"") | AO29: =IFERROR(VLOOKUP(P29,'Invoice Exception Map'!A:C,3,FALSE),IF(AH29>0,"Y","N")) -> Y
A30: KSW | B30: Demetrius | C30: A | D30: Daniels | G30: Wallace, Derron | H30: V0U211998 | I30: ddaniels@kaller.com | J30: mrtruth75@gmail.com | K30: Rep, Customer Service II | L30: 37424 | O30: Active | P30: 006774 | Q30: Biweekly | R30: Full Time | S30: 025 | T30: 025-NGP Hyson Products | U30: Inside Sales | V30: 000850 | W30: Hyson Products | Z30: USA | AA30: S10 | AB30: FMG-S10 | AC30: =IF(ISBLANK(H30),VLOOKUP(P30,'Invoice Exception Map'!A:D,4,FALSE),MID(H30,4,6)) -> 211998 | AD30: =IFERROR(VLOOKUP(T30,'Org Map'!A:E,4),"BU Description Not Mapped") -> 0096 | AE30: =IFERROR(VLOOKUP(V30,'Org Map'!C:E,3,FALSE),"Home Department Code Not Mapped") -> 850 | AF30: =IFERROR(VLOOKUP(AA30,'Salary Map'!A:D,3,FALSE),"Salary Code Not Mapped") -> Default | AG30: =IFERROR(VLOOKUP(AA30,'Salary Map'!A:D,4,FALSE),"Salary Code Not Mapped") -> General | AH30: =IFERROR(VLOOKUP(AA30,'Salary Map'!A:E,5,FALSE),"Invoice Approval Not Mapped") -> 0 | AI30: =IFERROR(VLOOKUP(Z30,'Country Map'!A:B,2,FALSE),"Legal Country Not Mapped") -> US | AJ30: =IFERROR(VLOOKUP(X30,'Language Map'!A:C,3,FALSE),IFERROR(VLOOKUP(T30,'Org Map'!A:F,6,FALSE),"ADP and BU Language Code Not Mapped"))&AI30 -> en_US | AK30: =IFERROR(VLOOKUP(T30,'Org Map'!A:G,7),"BU Currency Not Mapped") -> USD | AL30: =IF(ISBLANK(E30),"",TRIM(E30&" "&F30)) | AM30: =IFERROR(VLOOKUP(O30,'Status Map'!A:B,2,FALSE),"Position Status Not Mapped") -> Y | AN30: =IF(AM30="N",TEXT(M30,"yyyymmdd"),"") | AO30: =IFERROR(VLOOKUP(P30,'Invoice Exception Map'!A:C,3,FALSE),IF(AH30>0,"Y","N")) -> N
A31: KSX | B31: Crystal | D31: Dedes | G31: LaPlante, Derek | H31: KSY211736 | I31: cdedes@onebarnes.com | J31: criss4200@yahoo.com | K31: Assistant, Warehouse II | L31: 44620 | O31: Active | P31: 207391 | Q31: Biweekly | R31: Full Time | S31: 088 | T31: 088-AS Raymond | U31: FG Warehouse | V31: 005200 | W31: AS Raymond | Z31: USA | AA31: S05 | AB31: FMG-S05 | AC31: =IF(ISBLANK(H31),VLOOKUP(P31,'Invoice Exception Map'!A:D,4,FALSE),MID(H31,4,6)) -> 211736 | AD31: =IFERROR(VLOOKUP(T31,'Org Map'!A:E,4),"BU Description Not Mapped") -> 0088 | AE31: =IFERROR(VLOOKUP(V31,'Org Map'!C:E,3,FALSE),"Home Department Code Not Mapped") -> 5200 | AF31: =IFERROR(VLOOKUP(AA31,'Salary Map'!A:D,3,FALSE),"Salary Code Not Mapped") -> Default | AG31: =IFERROR(VLOOKUP(AA31,'Salary Map'!A:D,4,FALSE),"Salary Code Not Mapped") -> General | AH31: =IFERROR(VLOOKUP(AA31,'Salary Map'!A:E,5,FALSE),"Invoice Approval Not Mapped") -> 0 | AI31: =IFERROR(VLOOKUP(Z31,'Country Map'!A:B,2,FALSE),"Legal Country Not Mapped") -> US | AJ31: =IFERROR(VLOOKUP(X31,'Language Map'!A:C,3,FALSE),IFERROR(VLOOKUP(T31,'Org Map'!A:F,6,FALSE),"ADP and BU Language Code Not Mapped"))&AI31 -> en_US | AK31: =IFERROR(VLOOKUP(T31,'Org Map'!A:G,7),"BU Currency Not Mapped") -> USD | AL31: =IF(ISBLANK(E31),"",TRIM(E31&" "&F31)) | AM31: =IFERROR(VLOOKUP(O31,'Status Map'!A:B,2,FALSE),"Position Status Not Mapped") -> Y | AN31: =IF(AM31="N",TEXT(M31,"yyyymmdd"),"") | AO31: =IFERROR(VLOOKUP(P31,'Invoice Exception Map'!A:C,3,FALSE),IF(AH31>0,"Y","N")) -> N
A32: KSX | B32: Amir | D32: Dillard | G32: Burchell, Mathew | H32: KSY211756 | I32: adillard1@onebarnes.com | J32: amirdillard4@gmail.com | K32: Assistant, Warehouse II | L32: 45754 | O32: Active | P32: 211895 | Q32: Biweekly | R32: Full Time | S32: 088 | T32: 088-AS Raymond | U32: Assembly | V32: 005100 | W32: AS Raymond | Z32: USA | AA32: S05 | AB32: FMG-S05 | AC32: =IF(ISBLANK(H32),VLOOKUP(P32,'Invoice Exception Map'!A:D,4,FALSE),MID(H32,4,6)) -> 211756 | AD32: =IFERROR(VLOOKUP(T32,'Org Map'!A:E,4),"BU Description Not Mapped") -> 0088 | AE32: =IFERROR(VLOOKUP(V32,'Org Map'!C:E,3,FALSE),"Home Department Code Not Mapped") -> 5100 | AF32: =IFERROR(VLOOKUP(AA32,'Salary Map'!A:D,3,FALSE),"Salary Code Not Mapped") -> Default | AG32: =IFERROR(VLOOKUP(AA32,'Salary Map'!A:D,4,FALSE),"Salary Code Not Mapped") -> General | AH32: =IFERROR(VLOOKUP(AA32,'Salary Map'!A:E,5,FALSE),"Invoice Approval Not Mapped") -> 0 | AI32: =IFERROR(VLOOKUP(Z32,'Country Map'!A:B,2,FALSE),"Legal Country Not Mapped") -> US | AJ32: =IFERROR(VLOOKUP(X32,'Language Map'!A:C,3,FALSE),IFERROR(VLOOKUP(T32,'Org Map'!A:F,6,FALSE),"ADP and BU Language Code Not Mapped"))&AI32 -> en_US | AK32: =IFERROR(VLOOKUP(T32,'Org Map'!A:G,7),"BU Currency Not Mapped") -> USD | AL32: =IF(ISBLANK(E32),"",TRIM(E32&" "&F32)) | AM32: =IFERROR(VLOOKUP(O32,'Status Map'!A:B,2,FALSE),"Position Status Not Mapped") -> Y | AN32: =IF(AM32="N",TEXT(M32,"yyyymmdd"),"") | AO32: =IFERROR(VLOOKUP(P32,'Invoice Exception Map'!A:C,3,FALSE),IF(AH32>0,"Y","N")) -> N
A33: V0U | B33: Donald | C33: C | D33: Felts | G33: Wilkins, William | H33: V0U901934 | I33: cfelts@onebarnes.com | J33: dcfelts@comcast.net | K33: Mgr, Sales | L33: 43885 | O33: Active | P33: 201958 | Q33: Monthly | R33: Full Time | S33: 025 | T33: 025-NGP Hyson Products | U33: Outside Sales | V33: 000820 | W33: Hyson Products | Z33: USA | AA33: S15 | AB33: FMG-S15 | AC33: =IF(ISBLANK(H33),VLOOKUP(P33,'Invoice Exception Map'!A:D,4,FALSE),MID(H33,4,6)) -> 901934 | AD33: =IFERROR(VLOOKUP(T33,'Org Map'!A:E,4),"BU Description Not Mapped") -> 0096 | AE33: =IFERROR(VLOOKUP(V33,'Org Map'!C:E,3,FALSE),"Home Department Code Not Mapped") -> 820 | AF33: =IFERROR(VLOOKUP(AA33,'Salary Map'!A:D,3,FALSE),"Salary Code Not Mapped") -> Default | AG33: =IFERROR(VLOOKUP(AA33,'Salary Map'!A:D,4,FALSE),"Salary Code Not Mapped") -> General | AH33: =IFERROR(VLOOKUP(AA33,'Salary Map'!A:E,5,FALSE),"Invoice Approval Not Mapped") -> 0 | AI33: =IFERROR(VLOOKUP(Z33,'Country Map'!A:B,2,FALSE),"Legal Country Not Mapped") -> US | AJ33: =IFERROR(VLOOKUP(X33,'Language Map'!A:C,3,FALSE),IFERROR(VLOOKUP(T33,'Org Map'!A:F,6,FALSE),"ADP and BU Language Code Not Mapped"))&AI33 -> en_US | AK33: =IFERROR(VLOOKUP(T33,'Org Map'!A:G,7),"BU Currency Not Mapped") -> USD | AL33: =IF(ISBLANK(E33),"",TRIM(E33&" "&F33)) | AM33: =IFERROR(VLOOKUP(O33,'Status Map'!A:B,2,FALSE),"Position Status Not Mapped") -> Y | AN33: =IF(AM33="N",TEXT(M33,"yyyymmdd"),"") | AO33: =IFERROR(VLOOKUP(P33,'Invoice Exception Map'!A:C,3,FALSE),IF(AH33>0,"Y","N")) -> N
A34: KSY | B34: Jeffrey | C34: L | D34: Finch | G34: Erdogan, Mehmet | H34: 000207199N | I34: Jfinch@onebarnes.com | J34: jefffinch@bex.net | K34: Mgr, IT I | L34: 41422 | O34: Active | P34: 900848 | Q34: Monthly | R34: Full Time | S34: 088 | T34: 088-AS Raymond | U34: Business Applications | V34: 009150 | W34: AS Raymond | Z34: USA | AA34: S15 | AB34: FMG-S15 | AC34: =IF(ISBLANK(H34),VLOOKUP(P34,'Invoice Exception Map'!A:D,4,FALSE),MID(H34,4,6)) -> 207199 | AD34: =IFERROR(VLOOKUP(T34,'Org Map'!A:E,4),"BU Description Not Mapped") -> 0088 | AE34: =IFERROR(VLOOKUP(V34,'Org Map'!C:E,3,FALSE),"Home Department Code Not Mapped") -> 9150 | AF34: =IFERROR(VLOOKUP(AA34,'Salary Map'!A:D,3,FALSE),"Salary Code Not Mapped") -> Default | AG34: =IFERROR(VLOOKUP(AA34,'Salary Map'!A:D,4,FALSE),"Salary Code Not Mapped") -> General | AH34: =IFERROR(VLOOKUP(AA34,'Salary Map'!A:E,5,FALSE),"Invoice Approval Not Mapped") -> 0 | AI34: =IFERROR(VLOOKUP(Z34,'Country Map'!A:B,2,FALSE),"Legal Country Not Mapped") -> US | AJ34: =IFERROR(VLOOKUP(X34,'Language Map'!A:C,3,FALSE),IFERROR(VLOOKUP(T34,'Org Map'!A:F,6,FALSE),"ADP and BU Language Code Not Mapped"))&AI34 -> en_US | AK34: =IFERROR(VLOOKUP(T34,'Org Map'!A:G,7),"BU Currency Not Mapped") -> USD | AL34: =IF(ISBLANK(E34),"",TRIM(E34&" "&F34)) | AM34: =IFERROR(VLOOKUP(O34,'Status Map'!A:B,2,FALSE),"Position Status Not Mapped") -> Y | AN34: =IF(AM34="N",TEXT(M34,"yyyymmdd"),"") | AO34: =IFERROR(VLOOKUP(P34,'Invoice Exception Map'!A:C,3,FALSE),IF(AH34>0,"Y","N")) -> N
A35: V0U | B35: John | D35: Foisel | G35: Wilkins, William | H35: V0U901934 | I35: jfoisel@onebarnes.com | J35: Jfoisel1@att.net | K35: Mgr, Sales II | L35: 37599 | O35: Active | P35: 007863 | Q35: Monthly | R35: Full Time | S35: 025 | T35: 025-NGP Hyson Products | U35: Outside Sales | V35: 000820 | W35: Hyson Products | Z35: USA | AA35: S17 | AB35: FMG-S17 | AC35: =IF(ISBLANK(H35),VLOOKUP(P35,'Invoice Exception Map'!A:D,4,FALSE),MID(H35,4,6)) -> 901934 | AD35: =IFERROR(VLOOKUP(T35,'Org Map'!A:E,4),"BU Description Not Mapped") -> 0096 | AE35: =IFERROR(VLOOKUP(V35,'Org Map'!C:E,3,FALSE),"Home Department Code Not Mapped") -> 820 | AF35: =IFERROR(VLOOKUP(AA35,'Salary Map'!A:D,3,FALSE),"Salary Code Not Mapped") -> Default | AG35: =IFERROR(VLOOKUP(AA35,'Salary Map'!A:D,4,FALSE),"Salary Code Not Mapped") -> General | AH35: =IFERROR(VLOOKUP(AA35,'Salary Map'!A:E,5,FALSE),"Invoice Approval Not Mapped") -> 25000 | AI35: =IFERROR(VLOOKUP(Z35,'Country Map'!A:B,2,FALSE),"Legal Country Not Mapped") -> US | AJ35: =IFERROR(VLOOKUP(X35,'Language Map'!A:C,3,FALSE),IFERROR(VLOOKUP(T35,'Org Map'!A:F,6,FALSE),"ADP and BU Language Code Not Mapped"))&AI35 -> en_US | AK35: =IFERROR(VLOOKUP(T35,'Org Map'!A:G,7),"BU Currency Not Mapped") -> USD | AL35: =IF(ISBLANK(E35),"",TRIM(E35&" "&F35)) | AM35: =IFERROR(VLOOKUP(O35,'Status Map'!A:B,2,FALSE),"Position Status Not Mapped") -> Y | AN35: =IF(AM35="N",TEXT(M35,"yyyymmdd"),"") | AO35: =IFERROR(VLOOKUP(P35,'Invoice Exception Map'!A:C,3,FALSE),IF(AH35>0,"Y","N")) -> Y
A36: KSX | B36: Conner | C36: J | D36: Frankforther | G36: Burchell, Mathew | H36: KSY211756 | I36: cfrankforther@onebarnes.com | J36: frankfortherconner@gmail.com | K36: Assistant, Warehouse II | L36: 45838 | O36: Active | P36: 212151 | Q36: Biweekly | R36: Full Time | S36: 088 | T36: 088-AS Raymond | U36: Assembly | V36: 005100 | W36: AS Raymond | Z36: USA | AA36: S05 | AB36: FMG-S05 | AC36: =IF(ISBLANK(H36),VLOOKUP(P36,'Invoice Exception Map'!A:D,4,FALSE),MID(H36,4,6)) -> 211756 | AD36: =IFERROR(VLOOKUP(T36,'Org Map'!A:E,4),"BU Description Not Mapped") -> 0088 | AE36: =IFERROR(VLOOKUP(V36,'Org Map'!C:E,3,FALSE),"Home Department Code Not Mapped") -> 5100 | AF36: =IFERROR(VLOOKUP(AA36,'Salary Map'!A:D,3,FALSE),"Salary Code Not Mapped") -> Default | AG36: =IFERROR(VLOOKUP(AA36,'Salary Map'!A:D,4,FALSE),"Salary Code Not Mapped") -> General | AH36: =IFERROR(VLOOKUP(AA36,'Salary Map'!A:E,5,FALSE),"Invoice Approval Not Mapped") -> 0 | AI36: =IFERROR(VLOOKUP(Z36,'Country Map'!A:B,2,FALSE),"Legal Country Not Mapped") -> US | AJ36: =IFERROR(VLOOKUP(X36,'Language Map'!A:C,3,FALSE),IFERROR(VLOOKUP(T36,'Org Map'!A:F,6,FALSE),"ADP and BU Language Code Not Mapped"))&AI36 -> en_US | AK36: =IFERROR(VLOOKUP(T36,'Org Map'!A:G,7),"BU Currency Not Mapped") -> USD | AL36: =IF(ISBLANK(E36),"",TRIM(E36&" "&F36)) | AM36: =IFERROR(VLOOKUP(O36,'Status Map'!A:B,2,FALSE),"Position Status Not Mapped") -> Y | AN36: =IF(AM36="N",TEXT(M36,"yyyymmdd"),"") | AO36: =IFERROR(VLOOKUP(P36,'Invoice Exception Map'!A:C,3,FALSE),IF(AH36>0,"Y","N")) -> N
A37: KSX | B37: Dillon | C37: M | D37: Frankforther | G37: LaPlante, Derek | H37: KSY211736 | I37: dfrankforther@onebarnes.com | J37: frankfortherdillon@gmail.com | K37: Assistant, Warehouse II | L37: 45719 | O37: Active | P37: 211779 | Q37: Biweekly | R37: Full Time | S37: 088 | T37: 088-AS Raymond | U37: FG Warehouse | V37: 005200 | W37: AS Raymond | Z37: USA | AA37: S05 | AB37: FMG-S05 | AC37: =IF(ISBLANK(H37),VLOOKUP(P37,'Invoice Exception Map'!A:D,4,FALSE),MID(H37,4,6)) -> 211736 | AD37: =IFERROR(VLOOKUP(T37,'Org Map'!A:E,4),"BU Description Not Mapped") -> 0088 | AE37: =IFERROR(VLOOKUP(V37,'Org Map'!C:E,3,FALSE),"Home Department Code Not Mapped") -> 5200 | AF37: =IFERROR(VLOOKUP(AA37,'Salary Map'!A:D,3,FALSE),"Salary Code Not Mapped") -> Default | AG37: =IFERROR(VLOOKUP(AA37,'Salary Map'!A:D,4,FALSE),"Salary Code Not Mapped") -> General | AH37: =IFERROR(VLOOKUP(AA37,'Salary Map'!A:E,5,FALSE),"Invoice Approval Not Mapped") -> 0 | AI37: =IFERROR(VLOOKUP(Z37,'Country Map'!A:B,2,FALSE),"Legal Country Not Mapped") -> US | AJ37: =IFERROR(VLOOKUP(X37,'Language Map'!A:C,3,FALSE),IFERROR(VLOOKUP(T37,'Org Map'!A:F,6,FALSE),"ADP and BU Language Code Not Mapped"))&AI37 -> en_US | AK37: =IFERROR(VLOOKUP(T37,'Org Map'!A:G,7),"BU Currency Not Mapped") -> USD | AL37: =IF(ISBLANK(E37),"",TRIM(E37&" "&F37)) | AM37: =IFERROR(VLOOKUP(O37,'Status Map'!A:B,2,FALSE),"Position Status Not Mapped") -> Y | AN37: =IF(AM37="N",TEXT(M37,"yyyymmdd"),"") | AO37: =IFERROR(VLOOKUP(P37,'Invoice Exception Map'!A:C,3,FALSE),IF(AH37>0,"Y","N")) -> N
A38: KSW | B38: Anthony | C38: J | D38: Frimel | G38: Steen, Michael | H38: V0U211062 | I38: afrimel@onebarnes.com | J38: tfrimel@att.net | K38: Tech, Manufacturing A | L38: 37410 | O38: Active | P38: 004352 | Q38: Biweekly | R38: Full Time | S38: 025 | T38: 025-NGP Hyson Products | U38: CNC Lathe Hyson | V38: 000100 | W38: Hyson Products | Z38: USA | AA38: H08 | AB38: FMG-H08 | AC38: =IF(ISBLANK(H38),VLOOKUP(P38,'Invoice Exception Map'!A:D,4,FALSE),MID(H38,4,6)) -> 211062 | AD38: =IFERROR(VLOOKUP(T38,'Org Map'!A:E,4),"BU Description Not Mapped") -> 0096 | AE38: =IFERROR(VLOOKUP(V38,'Org Map'!C:E,3,FALSE),"Home Department Code Not Mapped") -> 100 | AF38: =IFERROR(VLOOKUP(AA38,'Salary Map'!A:D,3,FALSE),"Salary Code Not Mapped") -> Default | AG38: =IFERROR(VLOOKUP(AA38,'Salary Map'!A:D,4,FALSE),"Salary Code Not Mapped") -> General | AH38: =IFERROR(VLOOKUP(AA38,'Salary Map'!A:E,5,FALSE),"Invoice Approval Not Mapped") -> 0 | AI38: =IFERROR(VLOOKUP(Z38,'Country Map'!A:B,2,FALSE),"Legal Country Not Mapped") -> US | AJ38: =IFERROR(VLOOKUP(X38,'Language Map'!A:C,3,FALSE),IFERROR(VLOOKUP(T38,'Org Map'!A:F,6,FALSE),"ADP and BU Language Code Not Mapped"))&AI38 -> en_US | AK38: =IFERROR(VLOOKUP(T38,'Org Map'!A:G,7),"BU Currency Not Mapped") -> USD | AL38: =IF(ISBLANK(E38),"",TRIM(E38&" "&F38)) | AM38: =IFERROR(VLOOKUP(O38,'Status Map'!A:B,2,FALSE),"Position Status Not Mapped") -> Y | AN38: =IF(AM38="N",TEXT(M38,"yyyymmdd"),"") | AO38: =IFERROR(VLOOKUP(P38,'Invoice Exception Map'!A:C,3,FALSE),IF(AH38>0,"Y","N")) -> N
A39: V0U | B39: Terry | C39: L | D39: Gang | G39: Bate, Natalie | H39: V0U213037 | I39: TGang@onebarnes.com | J39: Terrygang1987@gmail.com | K39: Mgr, Engineering II | L39: 37704 | O39: Active | P39: 006780 | Q39: Monthly | R39: Full Time | S39: 025 | T39: 025-NGP Hyson Products | U39: Warehouse | V39: 000555 | W39: Hyson Products | Z39: USA | AA39: S17 | AB39: FMG-S17 | AC39: =IF(ISBLANK(H39),VLOOKUP(P39,'Invoice Exception Map'!A:D,4,FALSE),MID(H39,4,6)) -> 213037 | AD39: =IFERROR(VLOOKUP(T39,'Org Map'!A:E,4),"BU Description Not Mapped") -> 0096 | AE39: =IFERROR(VLOOKUP(V39,'Org Map'!C:E,3,FALSE),"Home Department Code Not Mapped") -> 555 | AF39: =IFERROR(VLOOKUP(AA39,'Salary Map'!A:D,3,FALSE),"Salary Code Not Mapped") -> Default | AG39: =IFERROR(VLOOKUP(AA39,'Salary Map'!A:D,4,FALSE),"Salary Code Not Mapped") -> General | AH39: =IFERROR(VLOOKUP(AA39,'Salary Map'!A:E,5,FALSE),"Invoice Approval Not Mapped") -> 25000 | AI39: =IFERROR(VLOOKUP(Z39,'Country Map'!A:B,2,FALSE),"Legal Country Not Mapped") -> US | AJ39: =IFERROR(VLOOKUP(X39,'Language Map'!A:C,3,FALSE),IFERROR(VLOOKUP(T39,'Org Map'!A:F,6,FALSE),"ADP and BU Language Code Not Mapped"))&AI39 -> en_US | AK39: =IFERROR(VLOOKUP(T39,'Org Map'!A:G,7),"BU Currency Not Mapped") -> USD | AL39: =IF(ISBLANK(E39),"",TRIM(E39&" "&F39)) | AM39: =IFERROR(VLOOKUP(O39,'Status Map'!A:B,2,FALSE),"Position Status Not Mapped") -> Y | AN39: =IF(AM39="N",TEXT(M39,"yyyymmdd"),"") | AO39: =IFERROR(VLOOKUP(P39,'Invoice Exception Map'!A:C,3,FALSE),IF(AH39>0,"Y","N")) -> Y
A40: V0U | B40: Anne | C40: M | D40: Garber | G40: Bate, Natalie | H40: V0U213037 | I40: agarber@onebarnes.com | J40: anne.michael00@gmail.com | K40: Mgr, Program | L40: 46265 | O40: Active | P40: 902627 | Q40: Monthly | R40: Full Time | S40: 025 | T40: 025-NGP Hyson Products | U40: Administration | V40: 000917 | W40: Hyson Products | Z40: USA | AA40: S17 | AB40: FMG-S17 | AC40: =IF(ISBLANK(H40),VLOOKUP(P40,'Invoice Exception Map'!A:D,4,FALSE),MID(H40,4,6)) -> 213037 | AD40: =IFERROR(VLOOKUP(T40,'Org Map'!A:E,4),"BU Description Not Mapped") -> 0096 | AE40: =IFERROR(VLOOKUP(V40,'Org Map'!C:E,3,FALSE),"Home Department Code Not Mapped") -> 917 | AF40: =IFERROR(VLOOKUP(AA40,'Salary Map'!A:D,3,FALSE),"Salary Code Not Mapped") -> Default | AG40: =IFERROR(VLOOKUP(AA40,'Salary Map'!A:D,4,FALSE),"Salary Code Not Mapped") -> General | AH40: =IFERROR(VLOOKUP(AA40,'Salary Map'!A:E,5,FALSE),"Invoice Approval Not Mapped") -> 25000 | AI40: =IFERROR(VLOOKUP(Z40,'Country Map'!A:B,2,FALSE),"Legal Country Not Mapped") -> US | AJ40: =IFERROR(VLOOKUP(X40,'Language Map'!A:C,3,FALSE),IFERROR(VLOOKUP(T40,'Org Map'!A:F,6,FALSE),"ADP and BU Language Code Not Mapped"))&AI40 -> en_US | AK40: =IFERROR(VLOOKUP(T40,'Org Map'!A:G,7),"BU Currency Not Mapped") -> USD | AL40: =IF(ISBLANK(E40),"",TRIM(E40&" "&F40)) | AM40: =IFERROR(VLOOKUP(O40,'Status Map'!A:B,2,FALSE),"Position Status Not Mapped") -> Y | AN40: =IF(AM40="N",TEXT(M40,"yyyymmdd"),"") | AO40: =IFERROR(VLOOKUP(P40,'Invoice Exception Map'!A:C,3,FALSE),IF(AH40>0,"Y","N")) -> Y
A41: KSX | B41: Cristel | D41: Grandowicz | G41: Burchell, Mathew | H41: KSY211756 | I41: cgrandowicz@onebarnes.com | J41: grandowicz.cristel@gmail.com | K41: Assistant, Warehouse II | L41: 45789 | O41: Active | P41: 211991 | Q41: Biweekly | R41: Full Time | S41: 088 | T41: 088-AS Raymond | U41: Assembly | V41: 005100 | W41: AS Raymond | Z41: USA | AA41: S05 | AB41: FMG-S05 | AC41: =IF(ISBLANK(H41),VLOOKUP(P41,'Invoice Exception Map'!A:D,4,FALSE),MID(H41,4,6)) -> 211756 | AD41: =IFERROR(VLOOKUP(T41,'Org Map'!A:E,4),"BU Description Not Mapped") -> 0088 | AE41: =IFERROR(VLOOKUP(V41,'Org Map'!C:E,3,FALSE),"Home Department Code Not Mapped") -> 5100 | AF41: =IFERROR(VLOOKUP(AA41,'Salary Map'!A:D,3,FALSE),"Salary Code Not Mapped") -> Default | AG41: =IFERROR(VLOOKUP(AA41,'Salary Map'!A:D,4,FALSE),"Salary Code Not Mapped") -> General | AH41: =IFERROR(VLOOKUP(AA41,'Salary Map'!A:E,5,FALSE),"Invoice Approval Not Mapped") -> 0 | AI41: =IFERROR(VLOOKUP(Z41,'Country Map'!A:B,2,FALSE),"Legal Country Not Mapped") -> US | AJ41: =IFERROR(VLOOKUP(X41,'Language Map'!A:C,3,FALSE),IFERROR(VLOOKUP(T41,'Org Map'!A:F,6,FALSE),"ADP and BU Language Code Not Mapped"))&AI41 -> en_US | AK41: =IFERROR(VLOOKUP(T41,'Org Map'!A:G,7),"BU Currency Not Mapped") -> USD | AL41: =IF(ISBLANK(E41),"",TRIM(E41&" "&F41)) | AM41: =IFERROR(VLOOKUP(O41,'Status Map'!A:B,2,FALSE),"Position Status Not Mapped") -> Y | AN41: =IF(AM41="N",TEXT(M41,"yyyymmdd"),"") | AO41: =IFERROR(VLOOKUP(P41,'Invoice Exception Map'!A:C,3,FALSE),IF(AH41>0,"Y","N")) -> N
A42: KSX | B42: Ivy | C42: J | D42: Grant | G42: Warner, Dwight | H42: V0U008750 | I42: igrant1@onebarnes.com | J42: igrant1453@yahoo.com | K42: Spec, Accounts Rec III | L42: 46181 | O42: Active | P42: 209642 | Q42: Biweekly | R42: Full Time | S42: 088 | T42: 088-AS Raymond | U42: Finance General | V42: 009100 | W42: Work from home - Virginia | Z42: USA | AA42: S10 | AB42: FMG-S10 | AC42: =IF(ISBLANK(H42),VLOOKUP(P42,'Invoice Exception Map'!A:D,4,FALSE),MID(H42,4,6)) -> 008750 | AD42: =IFERROR(VLOOKUP(T42,'Org Map'!A:E,4),"BU Description Not Mapped") -> 0088 | AE42: =IFERROR(VLOOKUP(V42,'Org Map'!C:E,3,FALSE),"Home Department Code Not Mapped") -> 9100 | AF42: =IFERROR(VLOOKUP(AA42,'Salary Map'!A:D,3,FALSE),"Salary Code Not Mapped") -> Default | AG42: =IFERROR(VLOOKUP(AA42,'Salary Map'!A:D,4,FALSE),"Salary Code Not Mapped") -> General | AH42: =IFERROR(VLOOKUP(AA42,'Salary Map'!A:E,5,FALSE),"Invoice Approval Not Mapped") -> 0 | AI42: =IFERROR(VLOOKUP(Z42,'Country Map'!A:B,2,FALSE),"Legal Country Not Mapped") -> US | AJ42: =IFERROR(VLOOKUP(X42,'Language Map'!A:C,3,FALSE),IFERROR(VLOOKUP(T42,'Org Map'!A:F,6,FALSE),"ADP and BU Language Code Not Mapped"))&AI42 -> en_US | AK42: =IFERROR(VLOOKUP(T42,'Org Map'!A:G,7),"BU Currency Not Mapped") -> USD | AL42: =IF(ISBLANK(E42),"",TRIM(E42&" "&F42)) | AM42: =IFERROR(VLOOKUP(O42,'Status Map'!A:B,2,FALSE),"Position Status Not Mapped") -> Y | AN42: =IF(AM42="N",TEXT(M42,"yyyymmdd"),"") | AO42: =IFERROR(VLOOKUP(P42,'Invoice Exception Map'!A:C,3,FALSE),IF(AH42>0,"Y","N")) -> N
A43: KSX | B43: Tirani | C43: J | D43: Hague | G43: Rafferty, Jonathan | H43: KSY211131 | I43: thague@onebarnes.com | J43: tirani.hague@gmail.com | K43: Rep, Customer Service III | L43: 46153 | O43: Active | P43: 213224 | Q43: Biweekly | R43: Full Time | S43: 088 | T43: 088-AS Raymond | U43: Inside Sales | V43: 008100 | W43: AS Raymond | Z43: USA | AA43: S11 | AB43: FMG-S11 | AC43: =IF(ISBLANK(H43),VLOOKUP(P43,'Invoice Exception Map'!A:D,4,FALSE),MID(H43,4,6)) -> 211131 | AD43: =IFERROR(VLOOKUP(T43,'Org Map'!A:E,4),"BU Description Not Mapped") -> 0088 | AE43: =IFERROR(VLOOKUP(V43,'Org Map'!C:E,3,FALSE),"Home Department Code Not Mapped") -> 8100 | AF43: =IFERROR(VLOOKUP(AA43,'Salary Map'!A:D,3,FALSE),"Salary Code Not Mapped") -> Default | AG43: =IFERROR(VLOOKUP(AA43,'Salary Map'!A:D,4,FALSE),"Salary Code Not Mapped") -> General | AH43: =IFERROR(VLOOKUP(AA43,'Salary Map'!A:E,5,FALSE),"Invoice Approval Not Mapped") -> 0 | AI43: =IFERROR(VLOOKUP(Z43,'Country Map'!A:B,2,FALSE),"Legal Country Not Mapped") -> US | AJ43: =IFERROR(VLOOKUP(X43,'Language Map'!A:C,3,FALSE),IFERROR(VLOOKUP(T43,'Org Map'!A:F,6,FALSE),"ADP and BU Language Code Not Mapped"))&AI43 -> en_US | AK43: =IFERROR(VLOOKUP(T43,'Org Map'!A:G,7),"BU Currency Not Mapped") -> USD | AL43: =IF(ISBLANK(E43),"",TRIM(E43&" "&F43)) | AM43: =IFERROR(VLOOKUP(O43,'Status Map'!A:B,2,FALSE),"Position Status Not Mapped") -> Y | AN43: =IF(AM43="N",TEXT(M43,"yyyymmdd"),"") | AO43: =IFERROR(VLOOKUP(P43,'Invoice Exception Map'!A:C,3,FALSE),IF(AH43>0,"Y","N")) -> N
A44: KSX | B44: Kimberly | D44: Hall | G44: Alexander, Thomas | H44: KSY210892 | I44: KHall@onebarnes.com | K44: Tech, Quality I | L44: 44333 | O44: Active | P44: 206228 | Q44: Biweekly | R44: Full Time | S44: 088 | T44: 088-AS Raymond | U44: Admin-Quality | V44: 009500 | W44: AS Raymond | Z44: USA | AA44: S10 | AB44: FMG-S10 | AC44: =IF(ISBLANK(H44),VLOOKUP(P44,'Invoice Exception Map'!A:D,4,FALSE),MID(H44,4,6)) -> 210892 | AD44: =IFERROR(VLOOKUP(T44,'Org Map'!A:E,4),"BU Description Not Mapped") -> 0088 | AE44: =IFERROR(VLOOKUP(V44,'Org Map'!C:E,3,FALSE),"Home Department Code Not Mapped") -> 9500 | AF44: =IFERROR(VLOOKUP(AA44,'Salary Map'!A:D,3,FALSE),"Salary Code Not Mapped") -> Default | AG44: =IFERROR(VLOOKUP(AA44,'Salary Map'!A:D,4,FALSE),"Salary Code Not Mapped") -> General | AH44: =IFERROR(VLOOKUP(AA44,'Salary Map'!A:E,5,FALSE),"Invoice Approval Not Mapped") -> 0 | AI44: =IFERROR(VLOOKUP(Z44,'Country Map'!A:B,2,FALSE),"Legal Country Not Mapped") -> US | AJ44: =IFERROR(VLOOKUP(X44,'Language Map'!A:C,3,FALSE),IFERROR(VLOOKUP(T44,'Org Map'!A:F,6,FALSE),"ADP and BU Language Code Not Mapped"))&AI44 -> en_US | AK44: =IFERROR(VLOOKUP(T44,'Org Map'!A:G,7),"BU Currency Not Mapped") -> USD | AL44: =IF(ISBLANK(E44),"",TRIM(E44&" "&F44)) | AM44: =IFERROR(VLOOKUP(O44,'Status Map'!A:B,2,FALSE),"Position Status Not Mapped") -> Y | AN44: =IF(AM44="N",TEXT(M44,"yyyymmdd"),"") | AO44: =IFERROR(VLOOKUP(P44,'Invoice Exception Map'!A:C,3,FALSE),IF(AH44>0,"Y","N")) -> N
A45: KSY | B45: Emma | D45: Halpin | G45: Kemenah, Greg | H45: KSY211766 | I45: ehalpin@onebarnes.com | J45: sampson.emma17@gmail.com | K45: Mgr, Product III | L45: 45566 | O45: Active | P45: 211489 | Q45: Monthly | R45: Full Time | S45: 088 | T45: 088-AS Raymond | U45: Marketing | V45: 008300 | W45: AS Raymond | Z45: USA | AA45: S16 | AB45: FMG-S16 | AC45: =IF(ISBLANK(H45),VLOOKUP(P45,'Invoice Exception Map'!A:D,4,FALSE),MID(H45,4,6)) -> 211766 | AD45: =IFERROR(VLOOKUP(T45,'Org Map'!A:E,4),"BU Description Not Mapped") -> 0088 | AE45: =IFERROR(VLOOKUP(V45,'Org Map'!C:E,3,FALSE),"Home Department Code Not Mapped") -> 8300 | AF45: =IFERROR(VLOOKUP(AA45,'Salary Map'!A:D,3,FALSE),"Salary Code Not Mapped") -> Default | AG45: =IFERROR(VLOOKUP(AA45,'Salary Map'!A:D,4,FALSE),"Salary Code Not Mapped") -> General | AH45: =IFERROR(VLOOKUP(AA45,'Salary Map'!A:E,5,FALSE),"Invoice Approval Not Mapped") -> 25000 | AI45: =IFERROR(VLOOKUP(Z45,'Country Map'!A:B,2,FALSE),"Legal Country Not Mapped") -> US | AJ45: =IFERROR(VLOOKUP(X45,'Language Map'!A:C,3,FALSE),IFERROR(VLOOKUP(T45,'Org Map'!A:F,6,FALSE),"ADP and BU Language Code Not Mapped"))&AI45 -> en_US | AK45: =IFERROR(VLOOKUP(T45,'Org Map'!A:G,7),"BU Currency Not Mapped") -> USD | AL45: =IF(ISBLANK(E45),"",TRIM(E45&" "&F45)) | AM45: =IFERROR(VLOOKUP(O45,'Status Map'!A:B,2,FALSE),"Position Status Not Mapped") -> Y | AN45: =IF(AM45="N",TEXT(M45,"yyyymmdd"),"") | AO45: =IFERROR(VLOOKUP(P45,'Invoice Exception Map'!A:C,3,FALSE),IF(AH45>0,"Y","N")) -> Y
A46: KSW | B46: Michael | C46: J | D46: Hamar | G46: Wallace, Derron | H46: V0U211998 | I46: mhamar@onebarnes.com | K46: Shipping/Receiving ClerkB | L46: 42072 | O46: Active | P46: 901454 | Q46: Biweekly | R46: Full Time | S46: 025 | T46: 025-NGP Hyson Products | U46: Assembly Hyson | V46: 000200 | W46: Hyson Products | Z46: USA | AA46: H06 | AB46: FMG-H06 | AC46: =IF(ISBLANK(H46),VLOOKUP(P46,'Invoice Exception Map'!A:D,4,FALSE),MID(H46,4,6)) -> 211998 | AD46: =IFERROR(VLOOKUP(T46,'Org Map'!A:E,4),"BU Description Not Mapped") -> 0096 | AE46: =IFERROR(VLOOKUP(V46,'Org Map'!C:E,3,FALSE),"Home Department Code Not Mapped") -> 200 | AF46: =IFERROR(VLOOKUP(AA46,'Salary Map'!A:D,3,FALSE),"Salary Code Not Mapped") -> Default | AG46: =IFERROR(VLOOKUP(AA46,'Salary Map'!A:D,4,FALSE),"Salary Code Not Mapped") -> General | AH46: =IFERROR(VLOOKUP(AA46,'Salary Map'!A:E,5,FALSE),"Invoice Approval Not Mapped") -> 0 | AI46: =IFERROR(VLOOKUP(Z46,'Country Map'!A:B,2,FALSE),"Legal Country Not Mapped") -> US | AJ46: =IFERROR(VLOOKUP(X46,'Language Map'!A:C,3,FALSE),IFERROR(VLOOKUP(T46,'Org Map'!A:F,6,FALSE),"ADP and BU Language Code Not Mapped"))&AI46 -> en_US | AK46: =IFERROR(VLOOKUP(T46,'Org Map'!A:G,7),"BU Currency Not Mapped") -> USD | AL46: =IF(ISBLANK(E46),"",TRIM(E46&" "&F46)) | AM46: =IFERROR(VLOOKUP(O46,'Status Map'!A:B,2,FALSE),"Position Status Not Mapped") -> Y | AN46: =IF(AM46="N",TEXT(M46,"yyyymmdd"),"") | AO46: =IFERROR(VLOOKUP(P46,'Invoice Exception Map'!A:C,3,FALSE),IF(AH46>0,"Y","N")) -> N
A47: KSX | B47: Patsy | D47: Hamby | G47: Burchell, Mathew | H47: KSY211756 | I47: PHamby@onebarnes.com | J47: phamby456@gmail.com | K47: Assistant, Warehouse II | L47: 44893 | O47: Active | P47: 209425 | Q47: Biweekly | R47: Full Time | S47: 088 | T47: 088-AS Raymond | U47: Assembly | V47: 005100 | W47: AS Raymond | Z47: USA | AA47: S05 | AB47: FMG-S05 | AC47: =IF(ISBLANK(H47),VLOOKUP(P47,'Invoice Exception Map'!A:D,4,FALSE),MID(H47,4,6)) -> 211756 | AD47: =IFERROR(VLOOKUP(T47,'Org Map'!A:E,4),"BU Description Not Mapped") -> 0088 | AE47: =IFERROR(VLOOKUP(V47,'Org Map'!C:E,3,FALSE),"Home Department Code Not Mapped") -> 5100 | AF47: =IFERROR(VLOOKUP(AA47,'Salary Map'!A:D,3,FALSE),"Salary Code Not Mapped") -> Default | AG47: =IFERROR(VLOOKUP(AA47,'Salary Map'!A:D,4,FALSE),"Salary Code Not Mapped") -> General | AH47: =IFERROR(VLOOKUP(AA47,'Salary Map'!A:E,5,FALSE),"Invoice Approval Not Mapped") -> 0 | AI47: =IFERROR(VLOOKUP(Z47,'Country Map'!A:B,2,FALSE),"Legal Country Not Mapped") -> US | AJ47: =IFERROR(VLOOKUP(X47,'Language Map'!A:C,3,FALSE),IFERROR(VLOOKUP(T47,'Org Map'!A:F,6,FALSE),"ADP and BU Language Code Not Mapped"))&AI47 -> en_US | AK47: =IFERROR(VLOOKUP(T47,'Org Map'!A:G,7),"BU Currency Not Mapped") -> USD | AL47: =IF(ISBLANK(E47),"",TRIM(E47&" "&F47)) | AM47: =IFERROR(VLOOKUP(O47,'Status Map'!A:B,2,FALSE),"Position Status Not Mapped") -> Y | AN47: =IF(AM47="N",TEXT(M47,"yyyymmdd"),"") | AO47: =IFERROR(VLOOKUP(P47,'Invoice Exception Map'!A:C,3,FALSE),IF(AH47>0,"Y","N")) -> N
A48: KSW | B48: Cherie | D48: Hassey | G48: Wallace, Derron | H48: V0U211998 | I48: chassey@onebarnes.com | J48: c.hassey@att.net | K48: Rep, Customer Service II | L48: 46125 | O48: Active | P48: 213144 | Q48: Biweekly | R48: Full Time | S48: 025 | T48: 025-NGP Hyson Products | U48: Inside Sales | V48: 000850 | W48: Hyson Products | Z48: USA | AA48: S10 | AB48: FMG-S10 | AC48: =IF(ISBLANK(H48),VLOOKUP(P48,'Invoice Exception Map'!A:D,4,FALSE),MID(H48,4,6)) -> 211998 | AD48: =IFERROR(VLOOKUP(T48,'Org Map'!A:E,4),"BU Description Not Mapped") -> 0096 | AE48: =IFERROR(VLOOKUP(V48,'Org Map'!C:E,3,FALSE),"Home Department Code Not Mapped") -> 850 | AF48: =IFERROR(VLOOKUP(AA48,'Salary Map'!A:D,3,FALSE),"Salary Code Not Mapped") -> Default | AG48: =IFERROR(VLOOKUP(AA48,'Salary Map'!A:D,4,FALSE),"Salary Code Not Mapped") -> General | AH48: =IFERROR(VLOOKUP(AA48,'Salary Map'!A:E,5,FALSE),"Invoice Approval Not Mapped") -> 0 | AI48: =IFERROR(VLOOKUP(Z48,'Country Map'!A:B,2,FALSE),"Legal Country Not Mapped") -> US | AJ48: =IFERROR(VLOOKUP(X48,'Language Map'!A:C,3,FALSE),IFERROR(VLOOKUP(T48,'Org Map'!A:F,6,FALSE),"ADP and BU Language Code Not Mapped"))&AI48 -> en_US | AK48: =IFERROR(VLOOKUP(T48,'Org Map'!A:G,7),"BU Currency Not Mapped") -> USD | AL48: =IF(ISBLANK(E48),"",TRIM(E48&" "&F48)) | AM48: =IFERROR(VLOOKUP(O48,'Status Map'!A:B,2,FALSE),"Position Status Not Mapped") -> Y | AN48: =IF(AM48="N",TEXT(M48,"yyyymmdd"),"") | AO48: =IFERROR(VLOOKUP(P48,'Invoice Exception Map'!A:C,3,FALSE),IF(AH48>0,"Y","N")) -> N
A49: KSX | B49: Karla | D49: Hershberger | G49: Burchell, Mathew | H49: KSY211756 | I49: khershberger@onebarnes.com | J49: karhershy14@gmail.com | K49: Assistant, Warehouse II | L49: 44893 | O49: Active | P49: 209424 | Q49: Biweekly | R49: Full Time | S49: 088 | T49: 088-AS Raymond | U49: Assembly | V49: 005100 | W49: AS Raymond | Z49: USA | AA49: S05 | AB49: FMG-S05 | AC49: =IF(ISBLANK(H49),VLOOKUP(P49,'Invoice Exception Map'!A:D,4,FALSE),MID(H49,4,6)) -> 211756 | AD49: =IFERROR(VLOOKUP(T49,'Org Map'!A:E,4),"BU Description Not Mapped") -> 0088 | AE49: =IFERROR(VLOOKUP(V49,'Org Map'!C:E,3,FALSE),"Home Department Code Not Mapped") -> 5100 | AF49: =IFERROR(VLOOKUP(AA49,'Salary Map'!A:D,3,FALSE),"Salary Code Not Mapped") -> Default | AG49: =IFERROR(VLOOKUP(AA49,'Salary Map'!A:D,4,FALSE),"Salary Code Not Mapped") -> General | AH49: =IFERROR(VLOOKUP(AA49,'Salary Map'!A:E,5,FALSE),"Invoice Approval Not Mapped") -> 0 | AI49: =IFERROR(VLOOKUP(Z49,'Country Map'!A:B,2,FALSE),"Legal Country Not Mapped") -> US | AJ49: =IFERROR(VLOOKUP(X49,'Language Map'!A:C,3,FALSE),IFERROR(VLOOKUP(T49,'Org Map'!A:F,6,FALSE),"ADP and BU Language Code Not Mapped"))&AI49 -> en_US | AK49: =IFERROR(VLOOKUP(T49,'Org Map'!A:G,7),"BU Currency Not Mapped") -> USD | AL49: =IF(ISBLANK(E49),"",TRIM(E49&" "&F49)) | AM49: =IFERROR(VLOOKUP(O49,'Status Map'!A:B,2,FALSE),"Position Status Not Mapped") -> Y | AN49: =IF(AM49="N",TEXT(M49,"yyyymmdd"),"") | AO49: =IFERROR(VLOOKUP(P49,'Invoice Exception Map'!A:C,3,FALSE),IF(AH49>0,"Y","N")) -> N
A50: KSY | B50: Brandon | D50: Hibbitts | G50: Erdogan, Mehmet | H50: 000207199N | I50: bhibbitts@onebarnes.com | J50: hibbitts.brandon@gmail.com | K50: Analyst, Help Desk II | L50: 45502 | O50: Active | P50: 211181 | Q50: Monthly | R50: Full Time | S50: 088 | T50: 088-AS Raymond | U50: Business Applications | V50: 009150 | W50: AS Raymond | Z50: USA | AA50: S12 | AB50: FMG-S12 | AC50: =IF(ISBLANK(H50),VLOOKUP(P50,'Invoice Exception Map'!A:D,4,FALSE),MID(H50,4,6)) -> 207199 | AD50: =IFERROR(VLOOKUP(T50,'Org Map'!A:E,4),"BU Description Not Mapped") -> 0088 | AE50: =IFERROR(VLOOKUP(V50,'Org Map'!C:E,3,FALSE),"Home Department Code Not Mapped") -> 9150 | AF50: =IFERROR(VLOOKUP(AA50,'Salary Map'!A:D,3,FALSE),"Salary Code Not Mapped") -> Default | AG50: =IFERROR(VLOOKUP(AA50,'Salary Map'!A:D,4,FALSE),"Salary Code Not Mapped") -> General | AH50: =IFERROR(VLOOKUP(AA50,'Salary Map'!A:E,5,FALSE),"Invoice Approval Not Mapped") -> 0 | AI50: =IFERROR(VLOOKUP(Z50,'Country Map'!A:B,2,FALSE),"Legal Country Not Mapped") -> US | AJ50: =IFERROR(VLOOKUP(X50,'Language Map'!A:C,3,FALSE),IFERROR(VLOOKUP(T50,'Org Map'!A:F,6,FALSE),"ADP and BU Language Code Not Mapped"))&AI50 -> en_US | AK50: =IFERROR(VLOOKUP(T50,'Org Map'!A:G,7),"BU Currency Not Mapped") -> USD | AL50: =IF(ISBLANK(E50),"",TRIM(E50&" "&F50)) | AM50: =IFERROR(VLOOKUP(O50,'Status Map'!A:B,2,FALSE),"Position Status Not Mapped") -> Y | AN50: =IF(AM50="N",TEXT(M50,"yyyymmdd"),"") | AO50: =IFERROR(VLOOKUP(P50,'Invoice Exception Map'!A:C,3,FALSE),IF(AH50>0,"Y","N")) -> N
A51: KSW | B51: Bobby | D51: Hicks | G51: Wallace, Derron | H51: V0U211998 | I51: bhicks@onebarnes.com | J51: bhicks1@me.com | K51: Lead, Unit Team | L51: 45481 | O51: Active | P51: 211145 | Q51: Biweekly | R51: Full Time | S51: 025 | T51: 025-NGP Hyson Products | U51: Assembly Hyson | V51: 000200 | W51: Hyson Products | Z51: USA | AA51: H08 | AB51: FMG-H08 | AC51: =IF(ISBLANK(H51),VLOOKUP(P51,'Invoice Exception Map'!A:D,4,FALSE),MID(H51,4,6)) -> 211998 | AD51: =IFERROR(VLOOKUP(T51,'Org Map'!A:E,4),"BU Description Not Mapped") -> 0096 | AE51: =IFERROR(VLOOKUP(V51,'Org Map'!C:E,3,FALSE),"Home Department Code Not Mapped") -> 200 | AF51: =IFERROR(VLOOKUP(AA51,'Salary Map'!A:D,3,FALSE),"Salary Code Not Mapped") -> Default | AG51: =IFERROR(VLOOKUP(AA51,'Salary Map'!A:D,4,FALSE),"Salary Code Not Mapped") -> General | AH51: =IFERROR(VLOOKUP(AA51,'Salary Map'!A:E,5,FALSE),"Invoice Approval Not Mapped") -> 0 | AI51: =IFERROR(VLOOKUP(Z51,'Country Map'!A:B,2,FALSE),"Legal Country Not Mapped") -> US | AJ51: =IFERROR(VLOOKUP(X51,'Language Map'!A:C,3,FALSE),IFERROR(VLOOKUP(T51,'Org Map'!A:F,6,FALSE),"ADP and BU Language Code Not Mapped"))&AI51 -> en_US | AK51: =IFERROR(VLOOKUP(T51,'Org Map'!A:G,7),"BU Currency Not Mapped") -> USD | AL51: =IF(ISBLANK(E51),"",TRIM(E51&" "&F51)) | AM51: =IFERROR(VLOOKUP(O51,'Status Map'!A:B,2,FALSE),"Position Status Not Mapped") -> Y | AN51: =IF(AM51="N",TEXT(M51,"yyyymmdd"),"") | AO51: =IFERROR(VLOOKUP(P51,'Invoice Exception Map'!A:C,3,FALSE),IF(AH51>0,"Y","N")) -> N
A52: KSW | B52: Darin | D52: Hitti | G52: Gang, Terry | H52: V0U006780 | I52: DHitti@onebarnes.com | K52: Mechanic, Maintenance A | L52: 31049 | O52: Active | P52: 006792 | Q52: Biweekly | R52: Full Time | S52: 025 | T52: 025-NGP Hyson Products | U52: Maintenance-Hyson | V52: 000450 | W52: Hyson Products | Z52: USA | AA52: H08 | AB52: FMG-H08 | AC52: =IF(ISBLANK(H52),VLOOKUP(P52,'Invoice Exception Map'!A:D,4,FALSE),MID(H52,4,6)) -> 006780 | AD52: =IFERROR(VLOOKUP(T52,'Org Map'!A:E,4),"BU Description Not Mapped") -> 0096 | AE52: =IFERROR(VLOOKUP(V52,'Org Map'!C:E,3,FALSE),"Home Department Code Not Mapped") -> 450 | AF52: =IFERROR(VLOOKUP(AA52,'Salary Map'!A:D,3,FALSE),"Salary Code Not Mapped") -> Default | AG52: =IFERROR(VLOOKUP(AA52,'Salary Map'!A:D,4,FALSE),"Salary Code Not Mapped") -> General | AH52: =IFERROR(VLOOKUP(AA52,'Salary Map'!A:E,5,FALSE),"Invoice Approval Not Mapped") -> 0 | AI52: =IFERROR(VLOOKUP(Z52,'Country Map'!A:B,2,FALSE),"Legal Country Not Mapped") -> US | AJ52: =IFERROR(VLOOKUP(X52,'Language Map'!A:C,3,FALSE),IFERROR(VLOOKUP(T52,'Org Map'!A:F,6,FALSE),"ADP and BU Language Code Not Mapped"))&AI52 -> en_US | AK52: =IFERROR(VLOOKUP(T52,'Org Map'!A:G,7),"BU Currency Not Mapped") -> USD | AL52: =IF(ISBLANK(E52),"",TRIM(E52&" "&F52)) | AM52: =IFERROR(VLOOKUP(O52,'Status Map'!A:B,2,FALSE),"Position Status Not Mapped") -> Y | AN52: =IF(AM52="N",TEXT(M52,"yyyymmdd"),"") | AO52: =IFERROR(VLOOKUP(P52,'Invoice Exception Map'!A:C,3,FALSE),IF(AH52>0,"Y","N")) -> N
A53: KSY | B53: Carrie | C53: M | D53: Hoffman | G53: Oleksa, Laura | H53: V0U209181 | I53: choffman@onebarnes.com | J53: Carriehoffman89@gmail.com | K53: HR Coordinator | L53: 43101 | O53: Active | P53: 902349 | Q53: Monthly | R53: Full Time | S53: 088 | T53: 088-AS Raymond | U53: HR General | V53: 009200 | W53: AS Raymond | Z53: USA | AA53: S11 | AB53: FMG-S11 | AC53: =IF(ISBLANK(H53),VLOOKUP(P53,'Invoice Exception Map'!A:D,4,FALSE),MID(H53,4,6)) -> 209181 | AD53: =IFERROR(VLOOKUP(T53,'Org Map'!A:E,4),"BU Description Not Mapped") -> 0088 | AE53: =IFERROR(VLOOKUP(V53,'Org Map'!C:E,3,FALSE),"Home Department Code Not Mapped") -> 9200 | AF53: =IFERROR(VLOOKUP(AA53,'Salary Map'!A:D,3,FALSE),"Salary Code Not Mapped") -> Default | AG53: =IFERROR(VLOOKUP(AA53,'Salary Map'!A:D,4,FALSE),"Salary Code Not Mapped") -> General | AH53: =IFERROR(VLOOKUP(AA53,'Salary Map'!A:E,5,FALSE),"Invoice Approval Not Mapped") -> 0 | AI53: =IFERROR(VLOOKUP(Z53,'Country Map'!A:B,2,FALSE),"Legal Country Not Mapped") -> US | AJ53: =IFERROR(VLOOKUP(X53,'Language Map'!A:C,3,FALSE),IFERROR(VLOOKUP(T53,'Org Map'!A:F,6,FALSE),"ADP and BU Language Code Not Mapped"))&AI53 -> en_US | AK53: =IFERROR(VLOOKUP(T53,'Org Map'!A:G,7),"BU Currency Not Mapped") -> USD | AL53: =IF(ISBLANK(E53),"",TRIM(E53&" "&F53)) | AM53: =IFERROR(VLOOKUP(O53,'Status Map'!A:B,2,FALSE),"Position Status Not Mapped") -> Y | AN53: =IF(AM53="N",TEXT(M53,"yyyymmdd"),"") | AO53: =IFERROR(VLOOKUP(P53,'Invoice Exception Map'!A:C,3,FALSE),IF(AH53>0,"Y","N")) -> N
A54: KSX | B54: Richard | C54: W | D54: Hutt | G54: LaPlante, Derek | H54: KSY211736 | I54: rhutt@onebarnes.com | J54: richard.hutt95@gmail.com | K54: Coord, Logistics I | L54: 45768 | O54: Active | P54: 211932 | Q54: Biweekly | R54: Full Time | S54: 088 | T54: 088-AS Raymond | U54: FG Warehouse | V54: 005200 | W54: AS Raymond | Z54: USA | AA54: S06 | AB54: FMG-S06 | AC54: =IF(ISBLANK(H54),VLOOKUP(P54,'Invoice Exception Map'!A:D,4,FALSE),MID(H54,4,6)) -> 211736 | AD54: =IFERROR(VLOOKUP(T54,'Org Map'!A:E,4),"BU Description Not Mapped") -> 0088 | AE54: =IFERROR(VLOOKUP(V54,'Org Map'!C:E,3,FALSE),"Home Department Code Not Mapped") -> 5200 | AF54: =IFERROR(VLOOKUP(AA54,'Salary Map'!A:D,3,FALSE),"Salary Code Not Mapped") -> Default | AG54: =IFERROR(VLOOKUP(AA54,'Salary Map'!A:D,4,FALSE),"Salary Code Not Mapped") -> General | AH54: =IFERROR(VLOOKUP(AA54,'Salary Map'!A:E,5,FALSE),"Invoice Approval Not Mapped") -> 0 | AI54: =IFERROR(VLOOKUP(Z54,'Country Map'!A:B,2,FALSE),"Legal Country Not Mapped") -> US | AJ54: =IFERROR(VLOOKUP(X54,'Language Map'!A:C,3,FALSE),IFERROR(VLOOKUP(T54,'Org Map'!A:F,6,FALSE),"ADP and BU Language Code Not Mapped"))&AI54 -> en_US | AK54: =IFERROR(VLOOKUP(T54,'Org Map'!A:G,7),"BU Currency Not Mapped") -> USD | AL54: =IF(ISBLANK(E54),"",TRIM(E54&" "&F54)) | AM54: =IFERROR(VLOOKUP(O54,'Status Map'!A:B,2,FALSE),"Position Status Not Mapped") -> Y | AN54: =IF(AM54="N",TEXT(M54,"yyyymmdd"),"") | AO54: =IFERROR(VLOOKUP(P54,'Invoice Exception Map'!A:C,3,FALSE),IF(AH54>0,"Y","N")) -> N
A55: KSW | B55: Frank | D55: Izzo | G55: Valetta, David | H55: V0U211601 | I55: FIzzo@onebarnes.com | K55: Mgr, Finance II | L55: 44410 | O55: Active | P55: 206442 | Q55: Biweekly | R55: Part Time Long Term EE | S55: 025 | T55: 025-NGP Hyson Products | U55: Project Management | V55: 000801 | W55: Hyson Products | Z55: USA | AA55: S16 | AB55: FMG-S16 | AC55: =IF(ISBLANK(H55),VLOOKUP(P55,'Invoice Exception Map'!A:D,4,FALSE),MID(H55,4,6)) -> 211601 | AD55: =IFERROR(VLOOKUP(T55,'Org Map'!A:E,4),"BU Description Not Mapped") -> 0096 | AE55: =IFERROR(VLOOKUP(V55,'Org Map'!C:E,3,FALSE),"Home Department Code Not Mapped") -> 801 | AF55: =IFERROR(VLOOKUP(AA55,'Salary Map'!A:D,3,FALSE),"Salary Code Not Mapped") -> Default | AG55: =IFERROR(VLOOKUP(AA55,'Salary Map'!A:D,4,FALSE),"Salary Code Not Mapped") -> General | AH55: =IFERROR(VLOOKUP(AA55,'Salary Map'!A:E,5,FALSE),"Invoice Approval Not Mapped") -> 25000 | AI55: =IFERROR(VLOOKUP(Z55,'Country Map'!A:B,2,FALSE),"Legal Country Not Mapped") -> US | AJ55: =IFERROR(VLOOKUP(X55,'Language Map'!A:C,3,FALSE),IFERROR(VLOOKUP(T55,'Org Map'!A:F,6,FALSE),"ADP and BU Language Code Not Mapped"))&AI55 -> en_US | AK55: =IFERROR(VLOOKUP(T55,'Org Map'!A:G,7),"BU Currency Not Mapped") -> USD | AL55: =IF(ISBLANK(E55),"",TRIM(E55&" "&F55)) | AM55: =IFERROR(VLOOKUP(O55,'Status Map'!A:B,2,FALSE),"Position Status Not Mapped") -> Y | AN55: =IF(AM55="N",TEXT(M55,"yyyymmdd"),"") | AO55: =IFERROR(VLOOKUP(P55,'Invoice Exception Map'!A:C,3,FALSE),IF(AH55>0,"Y","N")) -> Y
A56: KSX | B56: Keith | C56: L | D56: James | G56: Rogers, Wayne | H56: KSY207487 | I56: kjames@onebarnes.com | J56: myzonkj87@gmail.com | K56: Assistant, Warehouse II | L56: 42828 | O56: Active | P56: 902026 | Q56: Biweekly | R56: Full Time | S56: 088 | T56: 088-AS Raymond | U56: FG Warehouse | V56: 005200 | W56: AS Raymond | Z56: USA | AA56: S05 | AB56: FMG-S05 | AC56: =IF(ISBLANK(H56),VLOOKUP(P56,'Invoice Exception Map'!A:D,4,FALSE),MID(H56,4,6)) -> 207487 | AD56: =IFERROR(VLOOKUP(T56,'Org Map'!A:E,4),"BU Description Not Mapped") -> 0088 | AE56: =IFERROR(VLOOKUP(V56,'Org Map'!C:E,3,FALSE),"Home Department Code Not Mapped") -> 5200 | AF56: =IFERROR(VLOOKUP(AA56,'Salary Map'!A:D,3,FALSE),"Salary Code Not Mapped") -> Default | AG56: =IFERROR(VLOOKUP(AA56,'Salary Map'!A:D,4,FALSE),"Salary Code Not Mapped") -> General | AH56: =IFERROR(VLOOKUP(AA56,'Salary Map'!A:E,5,FALSE),"Invoice Approval Not Mapped") -> 0 | AI56: =IFERROR(VLOOKUP(Z56,'Country Map'!A:B,2,FALSE),"Legal Country Not Mapped") -> US | AJ56: =IFERROR(VLOOKUP(X56,'Language Map'!A:C,3,FALSE),IFERROR(VLOOKUP(T56,'Org Map'!A:F,6,FALSE),"ADP and BU Language Code Not Mapped"))&AI56 -> en_US | AK56: =IFERROR(VLOOKUP(T56,'Org Map'!A:G,7),"BU Currency Not Mapped") -> USD | AL56: =IF(ISBLANK(E56),"",TRIM(E56&" "&F56)) | AM56: =IFERROR(VLOOKUP(O56,'Status Map'!A:B,2,FALSE),"Position Status Not Mapped") -> Y | AN56: =IF(AM56="N",TEXT(M56,"yyyymmdd"),"") | AO56: =IFERROR(VLOOKUP(P56,'Invoice Exception Map'!A:C,3,FALSE),IF(AH56>0,"Y","N")) -> N
A57: KSY | B57: Michael | D57: Jones | G57: Rodriguez, Siobhan | H57: V0U207588 | I57: mjones@onebarnes.com | J57: MIKEJONES6085@GMAIL.COM | K57: Mgr, Sales | L57: 45895 | O57: Active | P57: 212418 | Q57: Monthly | R57: Full Time | S57: 088 | T57: 088-AS Raymond | U57: Outside Sales | V57: 008200 | W57: Works from home - Ohio | Z57: USA | AA57: S16 | AB57: FMG-S16 | AC57: =IF(ISBLANK(H57),VLOOKUP(P57,'Invoice Exception Map'!A:D,4,FALSE),MID(H57,4,6)) -> 207588 | AD57: =IFERROR(VLOOKUP(T57,'Org Map'!A:E,4),"BU Description Not Mapped") -> 0088 | AE57: =IFERROR(VLOOKUP(V57,'Org Map'!C:E,3,FALSE),"Home Department Code Not Mapped") -> 8200 | AF57: =IFERROR(VLOOKUP(AA57,'Salary Map'!A:D,3,FALSE),"Salary Code Not Mapped") -> Default | AG57: =IFERROR(VLOOKUP(AA57,'Salary Map'!A:D,4,FALSE),"Salary Code Not Mapped") -> General | AH57: =IFERROR(VLOOKUP(AA57,'Salary Map'!A:E,5,FALSE),"Invoice Approval Not Mapped") -> 25000 | AI57: =IFERROR(VLOOKUP(Z57,'Country Map'!A:B,2,FALSE),"Legal Country Not Mapped") -> US | AJ57: =IFERROR(VLOOKUP(X57,'Language Map'!A:C,3,FALSE),IFERROR(VLOOKUP(T57,'Org Map'!A:F,6,FALSE),"ADP and BU Language Code Not Mapped"))&AI57 -> en_US | AK57: =IFERROR(VLOOKUP(T57,'Org Map'!A:G,7),"BU Currency Not Mapped") -> USD | AL57: =IF(ISBLANK(E57),"",TRIM(E57&" "&F57)) | AM57: =IFERROR(VLOOKUP(O57,'Status Map'!A:B,2,FALSE),"Position Status Not Mapped") -> Y | AN57: =IF(AM57="N",TEXT(M57,"yyyymmdd"),"") | AO57: =IFERROR(VLOOKUP(P57,'Invoice Exception Map'!A:C,3,FALSE),IF(AH57>0,"Y","N")) -> N
A58: KSY | B58: Greg | D58: Kemenah | G58: Bair, Teresa | H58: KSY207709 | I58: gkemenah@onebarnes.com | J58: kemenah@live.com | K58: Mgr, General I | L58: 45712 | O58: Active | P58: 211766 | Q58: Monthly | R58: Full Time | S58: 088 | T58: 088-AS Raymond | U58: Admin-Engineering | V58: 009450 | W58: AS Raymond | Z58: USA | AA58: S19 | AB58: FMG-S19 | AC58: =IF(ISBLANK(H58),VLOOKUP(P58,'Invoice Exception Map'!A:D,4,FALSE),MID(H58,4,6)) -> 207709 | AD58: =IFERROR(VLOOKUP(T58,'Org Map'!A:E,4),"BU Description Not Mapped") -> 0088 | AE58: =IFERROR(VLOOKUP(V58,'Org Map'!C:E,3,FALSE),"Home Department Code Not Mapped") -> 9450 | AF58: =IFERROR(VLOOKUP(AA58,'Salary Map'!A:D,3,FALSE),"Salary Code Not Mapped") -> Default | AG58: =IFERROR(VLOOKUP(AA58,'Salary Map'!A:D,4,FALSE),"Salary Code Not Mapped") -> General | AH58: =IFERROR(VLOOKUP(AA58,'Salary Map'!A:E,5,FALSE),"Invoice Approval Not Mapped") -> 100000 | AI58: =IFERROR(VLOOKUP(Z58,'Country Map'!A:B,2,FALSE),"Legal Country Not Mapped") -> US | AJ58: =IFERROR(VLOOKUP(X58,'Language Map'!A:C,3,FALSE),IFERROR(VLOOKUP(T58,'Org Map'!A:F,6,FALSE),"ADP and BU Language Code Not Mapped"))&AI58 -> en_US | AK58: =IFERROR(VLOOKUP(T58,'Org Map'!A:G,7),"BU Currency Not Mapped") -> USD | AL58: =IF(ISBLANK(E58),"",TRIM(E58&" "&F58)) | AM58: =IFERROR(VLOOKUP(O58,'Status Map'!A:B,2,FALSE),"Position Status Not Mapped") -> Y | AN58: =IF(AM58="N",TEXT(M58,"yyyymmdd"),"") | AO58: =IFERROR(VLOOKUP(P58,'Invoice Exception Map'!A:C,3,FALSE),IF(AH58>0,"Y","N")) -> Y
A59: KSX | B59: Wendy | D59: Kozicki | G59: Williams, Rachel | H59: KSY202533 | I59: wkozicki@onebarnes.com | K59: Rep, Customer Service I | L59: 46174 | O59: Active | P59: 213298 | Q59: Biweekly | R59: Full Time | S59: 088 | T59: 088-AS Raymond | U59: Inside Sales | V59: 008100 | W59: AS Raymond | Z59: USA | AA59: S08 | AB59: FMG-S08 | AC59: =IF(ISBLANK(H59),VLOOKUP(P59,'Invoice Exception Map'!A:D,4,FALSE),MID(H59,4,6)) -> 202533 | AD59: =IFERROR(VLOOKUP(T59,'Org Map'!A:E,4),"BU Description Not Mapped") -> 0088 | AE59: =IFERROR(VLOOKUP(V59,'Org Map'!C:E,3,FALSE),"Home Department Code Not Mapped") -> 8100 | AF59: =IFERROR(VLOOKUP(AA59,'Salary Map'!A:D,3,FALSE),"Salary Code Not Mapped") -> Default | AG59: =IFERROR(VLOOKUP(AA59,'Salary Map'!A:D,4,FALSE),"Salary Code Not Mapped") -> General | AH59: =IFERROR(VLOOKUP(AA59,'Salary Map'!A:E,5,FALSE),"Invoice Approval Not Mapped") -> 0 | AI59: =IFERROR(VLOOKUP(Z59,'Country Map'!A:B,2,FALSE),"Legal Country Not Mapped") -> US | AJ59: =IFERROR(VLOOKUP(X59,'Language Map'!A:C,3,FALSE),IFERROR(VLOOKUP(T59,'Org Map'!A:F,6,FALSE),"ADP and BU Language Code Not Mapped"))&AI59 -> en_US | AK59: =IFERROR(VLOOKUP(T59,'Org Map'!A:G,7),"BU Currency Not Mapped") -> USD | AL59: =IF(ISBLANK(E59),"",TRIM(E59&" "&F59)) | AM59: =IFERROR(VLOOKUP(O59,'Status Map'!A:B,2,FALSE),"Position Status Not Mapped") -> Y | AN59: =IF(AM59="N",TEXT(M59,"yyyymmdd"),"") | AO59: =IFERROR(VLOOKUP(P59,'Invoice Exception Map'!A:C,3,FALSE),IF(AH59>0,"Y","N")) -> N
A60: KSY | B60: Derek | D60: LaPlante | G60: Bailey, Jason | H60: KSY902688 | I60: dlaplante@onebarnes.com | K60: Supv, Warehouse I | L60: 45705 | O60: Active | P60: 211736 | Q60: Monthly | R60: Full Time | S60: 088 | T60: 088-AS Raymond | U60: FG Warehouse | V60: 005200 | W60: AS Raymond | Z60: USA | AA60: S11 | AB60: FMG-S11 | AC60: =IF(ISBLANK(H60),VLOOKUP(P60,'Invoice Exception Map'!A:D,4,FALSE),MID(H60,4,6)) -> 902688 | AD60: =IFERROR(VLOOKUP(T60,'Org Map'!A:E,4),"BU Description Not Mapped") -> 0088 | AE60: =IFERROR(VLOOKUP(V60,'Org Map'!C:E,3,FALSE),"Home Department Code Not Mapped") -> 5200 | AF60: =IFERROR(VLOOKUP(AA60,'Salary Map'!A:D,3,FALSE),"Salary Code Not Mapped") -> Default | AG60: =IFERROR(VLOOKUP(AA60,'Salary Map'!A:D,4,FALSE),"Salary Code Not Mapped") -> General | AH60: =IFERROR(VLOOKUP(AA60,'Salary Map'!A:E,5,FALSE),"Invoice Approval Not Mapped") -> 0 | AI60: =IFERROR(VLOOKUP(Z60,'Country Map'!A:B,2,FALSE),"Legal Country Not Mapped") -> US | AJ60: =IFERROR(VLOOKUP(X60,'Language Map'!A:C,3,FALSE),IFERROR(VLOOKUP(T60,'Org Map'!A:F,6,FALSE),"ADP and BU Language Code Not Mapped"))&AI60 -> en_US | AK60: =IFERROR(VLOOKUP(T60,'Org Map'!A:G,7),"BU Currency Not Mapped") -> USD | AL60: =IF(ISBLANK(E60),"",TRIM(E60&" "&F60)) | AM60: =IFERROR(VLOOKUP(O60,'Status Map'!A:B,2,FALSE),"Position Status Not Mapped") -> Y | AN60: =IF(AM60="N",TEXT(M60,"yyyymmdd"),"") | AO60: =IFERROR(VLOOKUP(P60,'Invoice Exception Map'!A:C,3,FALSE),IF(AH60>0,"Y","N")) -> N
A61: V0U | B61: Wayne | D61: Leftrict | G61: Bate, Natalie | H61: V0U213037 | I61: wleftrict@onebarnes.com | J61: leftrictwayne@gmail.com | K61: Mgr, Quality II | L61: 45397 | O61: Active | P61: 210910 | Q61: Monthly | R61: Full Time | S61: 025 | T61: 025-NGP Hyson Products | U61: Warehouse | V61: 000555 | W61: Hyson Products | Z61: USA | AA61: S16 | AB61: FMG-S16 | AC61: =IF(ISBLANK(H61),VLOOKUP(P61,'Invoice Exception Map'!A:D,4,FALSE),MID(H61,4,6)) -> 213037 | AD61: =IFERROR(VLOOKUP(T61,'Org Map'!A:E,4),"BU Description Not Mapped") -> 0096 | AE61: =IFERROR(VLOOKUP(V61,'Org Map'!C:E,3,FALSE),"Home Department Code Not Mapped") -> 555 | AF61: =IFERROR(VLOOKUP(AA61,'Salary Map'!A:D,3,FALSE),"Salary Code Not Mapped") -> Default | AG61: =IFERROR(VLOOKUP(AA61,'Salary Map'!A:D,4,FALSE),"Salary Code Not Mapped") -> General | AH61: =IFERROR(VLOOKUP(AA61,'Salary Map'!A:E,5,FALSE),"Invoice Approval Not Mapped") -> 25000 | AI61: =IFERROR(VLOOKUP(Z61,'Country Map'!A:B,2,FALSE),"Legal Country Not Mapped") -> US | AJ61: =IFERROR(VLOOKUP(X61,'Language Map'!A:C,3,FALSE),IFERROR(VLOOKUP(T61,'Org Map'!A:F,6,FALSE),"ADP and BU Language Code Not Mapped"))&AI61 -> en_US | AK61: =IFERROR(VLOOKUP(T61,'Org Map'!A:G,7),"BU Currency Not Mapped") -> USD | AL61: =IF(ISBLANK(E61),"",TRIM(E61&" "&F61)) | AM61: =IFERROR(VLOOKUP(O61,'Status Map'!A:B,2,FALSE),"Position Status Not Mapped") -> Y | AN61: =IF(AM61="N",TEXT(M61,"yyyymmdd"),"") | AO61: =IFERROR(VLOOKUP(P61,'Invoice Exception Map'!A:C,3,FALSE),IF(AH61>0,"Y","N")) -> Y
A62: KSY | B62: Tamara | C62: K | D62: Lipp | G62: Oleksa, Laura | H62: V0U209181 | I62: tlipp@onebarnes.com | K62: Generalist, HR III | L62: 46078 | O62: Active | P62: 212990 | Q62: Monthly | R62: Full Time | S62: 088 | T62: 088-AS Raymond | U62: HR General | V62: 009200 | W62: AS Raymond | Z62: USA | AA62: S14 | AB62: FMG-S14 | AC62: =IF(ISBLANK(H62),VLOOKUP(P62,'Invoice Exception Map'!A:D,4,FALSE),MID(H62,4,6)) -> 209181 | AD62: =IFERROR(VLOOKUP(T62,'Org Map'!A:E,4),"BU Description Not Mapped") -> 0088 | AE62: =IFERROR(VLOOKUP(V62,'Org Map'!C:E,3,FALSE),"Home Department Code Not Mapped") -> 9200 | AF62: =IFERROR(VLOOKUP(AA62,'Salary Map'!A:D,3,FALSE),"Salary Code Not Mapped") -> Default | AG62: =IFERROR(VLOOKUP(AA62,'Salary Map'!A:D,4,FALSE),"Salary Code Not Mapped") -> General | AH62: =IFERROR(VLOOKUP(AA62,'Salary Map'!A:E,5,FALSE),"Invoice Approval Not Mapped") -> 0 | AI62: =IFERROR(VLOOKUP(Z62,'Country Map'!A:B,2,FALSE),"Legal Country Not Mapped") -> US | AJ62: =IFERROR(VLOOKUP(X62,'Language Map'!A:C,3,FALSE),IFERROR(VLOOKUP(T62,'Org Map'!A:F,6,FALSE),"ADP and BU Language Code Not Mapped"))&AI62 -> en_US | AK62: =IFERROR(VLOOKUP(T62,'Org Map'!A:G,7),"BU Currency Not Mapped") -> USD | AL62: =IF(ISBLANK(E62),"",TRIM(E62&" "&F62)) | AM62: =IFERROR(VLOOKUP(O62,'Status Map'!A:B,2,FALSE),"Position Status Not Mapped") -> Y | AN62: =IF(AM62="N",TEXT(M62,"yyyymmdd"),"") | AO62: =IFERROR(VLOOKUP(P62,'Invoice Exception Map'!A:C,3,FALSE),IF(AH62>0,"Y","N")) -> N
A63: KSW | B63: Joseph | C63: M | D63: Lorenz | G63: Wallace, Derron | H63: V0U211998 | I63: Jlorenz@onebarnes.com | J63: jlorenz66@yahoo.com | K63: Rep, Customer Service II | L63: 45923 | O63: Active | P63: 212598 | Q63: Biweekly | R63: Full Time | S63: 025 | T63: 025-NGP Hyson Products | U63: Inside Sales | V63: 000850 | W63: Hyson Products | Z63: USA | AA63: S10 | AB63: FMG-S10 | AC63: =IF(ISBLANK(H63),VLOOKUP(P63,'Invoice Exception Map'!A:D,4,FALSE),MID(H63,4,6)) -> 211998 | AD63: =IFERROR(VLOOKUP(T63,'Org Map'!A:E,4),"BU Description Not Mapped") -> 0096 | AE63: =IFERROR(VLOOKUP(V63,'Org Map'!C:E,3,FALSE),"Home Department Code Not Mapped") -> 850 | AF63: =IFERROR(VLOOKUP(AA63,'Salary Map'!A:D,3,FALSE),"Salary Code Not Mapped") -> Default | AG63: =IFERROR(VLOOKUP(AA63,'Salary Map'!A:D,4,FALSE),"Salary Code Not Mapped") -> General | AH63: =IFERROR(VLOOKUP(AA63,'Salary Map'!A:E,5,FALSE),"Invoice Approval Not Mapped") -> 0 | AI63: =IFERROR(VLOOKUP(Z63,'Country Map'!A:B,2,FALSE),"Legal Country Not Mapped") -> US | AJ63: =IFERROR(VLOOKUP(X63,'Language Map'!A:C,3,FALSE),IFERROR(VLOOKUP(T63,'Org Map'!A:F,6,FALSE),"ADP and BU Language Code Not Mapped"))&AI63 -> en_US | AK63: =IFERROR(VLOOKUP(T63,'Org Map'!A:G,7),"BU Currency Not Mapped") -> USD | AL63: =IF(ISBLANK(E63),"",TRIM(E63&" "&F63)) | AM63: =IFERROR(VLOOKUP(O63,'Status Map'!A:B,2,FALSE),"Position Status Not Mapped") -> Y | AN63: =IF(AM63="N",TEXT(M63,"yyyymmdd"),"") | AO63: =IFERROR(VLOOKUP(P63,'Invoice Exception Map'!A:C,3,FALSE),IF(AH63>0,"Y","N")) -> N
A64: KSY | B64: Jason | D64: Majewski | G64: Creager, Andrew | H64: KSY212699 | I64: JMajewski@onebarnes.com | J64: jmajewski06@yahoo.com | K64: Mgr, Materials | L64: 34869 | O64: Active | P64: 006809 | Q64: Monthly | R64: Full Time | S64: 088 | T64: 088-AS Raymond | U64: Admin-Material Management | V64: 009400 | W64: AS Raymond | Z64: USA | AA64: S17 | AB64: FMG-S17 | AC64: =IF(ISBLANK(H64),VLOOKUP(P64,'Invoice Exception Map'!A:D,4,FALSE),MID(H64,4,6)) -> 212699 | AD64: =IFERROR(VLOOKUP(T64,'Org Map'!A:E,4),"BU Description Not Mapped") -> 0088 | AE64: =IFERROR(VLOOKUP(V64,'Org Map'!C:E,3,FALSE),"Home Department Code Not Mapped") -> 9400 | AF64: =IFERROR(VLOOKUP(AA64,'Salary Map'!A:D,3,FALSE),"Salary Code Not Mapped") -> Default | AG64: =IFERROR(VLOOKUP(AA64,'Salary Map'!A:D,4,FALSE),"Salary Code Not Mapped") -> General | AH64: =IFERROR(VLOOKUP(AA64,'Salary Map'!A:E,5,FALSE),"Invoice Approval Not Mapped") -> 25000 | AI64: =IFERROR(VLOOKUP(Z64,'Country Map'!A:B,2,FALSE),"Legal Country Not Mapped") -> US | AJ64: =IFERROR(VLOOKUP(X64,'Language Map'!A:C,3,FALSE),IFERROR(VLOOKUP(T64,'Org Map'!A:F,6,FALSE),"ADP and BU Language Code Not Mapped"))&AI64 -> en_US | AK64: =IFERROR(VLOOKUP(T64,'Org Map'!A:G,7),"BU Currency Not Mapped") -> USD | AL64: =IF(ISBLANK(E64),"",TRIM(E64&" "&F64)) | AM64: =IFERROR(VLOOKUP(O64,'Status Map'!A:B,2,FALSE),"Position Status Not Mapped") -> Y | AN64: =IF(AM64="N",TEXT(M64,"yyyymmdd"),"") | AO64: =IFERROR(VLOOKUP(P64,'Invoice Exception Map'!A:C,3,FALSE),IF(AH64>0,"Y","N")) -> Y
A65: V0U | B65: Chris | C65: F | D65: Martin | G65: Leftrict, Wayne | H65: V0U210910 | I65: cmartin@onebarnes.com | J65: 3martmojo@gmail.com | K65: Coord, Quality & Environ | L65: 44270 | O65: Active | P65: 202609 | Q65: Monthly | R65: Full Time | S65: 025 | T65: 025-NGP Hyson Products | U65: Quality | V65: 000500 | W65: Hyson Products | Z65: USA | AA65: S15 | AB65: FMG-S15 | AC65: =IF(ISBLANK(H65),VLOOKUP(P65,'Invoice Exception Map'!A:D,4,FALSE),MID(H65,4,6)) -> 210910 | AD65: =IFERROR(VLOOKUP(T65,'Org Map'!A:E,4),"BU Description Not Mapped") -> 0096 | AE65: =IFERROR(VLOOKUP(V65,'Org Map'!C:E,3,FALSE),"Home Department Code Not Mapped") -> 500 | AF65: =IFERROR(VLOOKUP(AA65,'Salary Map'!A:D,3,FALSE),"Salary Code Not Mapped") -> Default | AG65: =IFERROR(VLOOKUP(AA65,'Salary Map'!A:D,4,FALSE),"Salary Code Not Mapped") -> General | AH65: =IFERROR(VLOOKUP(AA65,'Salary Map'!A:E,5,FALSE),"Invoice Approval Not Mapped") -> 0 | AI65: =IFERROR(VLOOKUP(Z65,'Country Map'!A:B,2,FALSE),"Legal Country Not Mapped") -> US | AJ65: =IFERROR(VLOOKUP(X65,'Language Map'!A:C,3,FALSE),IFERROR(VLOOKUP(T65,'Org Map'!A:F,6,FALSE),"ADP and BU Language Code Not Mapped"))&AI65 -> en_US | AK65: =IFERROR(VLOOKUP(T65,'Org Map'!A:G,7),"BU Currency Not Mapped") -> USD | AL65: =IF(ISBLANK(E65),"",TRIM(E65&" "&F65)) | AM65: =IFERROR(VLOOKUP(O65,'Status Map'!A:B,2,FALSE),"Position Status Not Mapped") -> Y | AN65: =IF(AM65="N",TEXT(M65,"yyyymmdd"),"") | AO65: =IFERROR(VLOOKUP(P65,'Invoice Exception Map'!A:C,3,FALSE),IF(AH65>0,"Y","N")) -> N
A66: KSX | B66: Martin | D66: Martinez | G66: Burchell, Mathew | H66: KSY211756 | I66: martinezmartin161@gmail.com | J66: porkchops2581@gmail.com | K66: Assistant, Warehouse II | L66: 43283 | O66: Active | P66: 902563 | Q66: Biweekly | R66: Full Time | S66: 088 | T66: 088-AS Raymond | U66: Assembly | V66: 005100 | W66: AS Raymond | Z66: USA | AA66: S05 | AB66: FMG-S05 | AC66: =IF(ISBLANK(H66),VLOOKUP(P66,'Invoice Exception Map'!A:D,4,FALSE),MID(H66,4,6)) -> 211756 | AD66: =IFERROR(VLOOKUP(T66,'Org Map'!A:E,4),"BU Description Not Mapped") -> 0088 | AE66: =IFERROR(VLOOKUP(V66,'Org Map'!C:E,3,FALSE),"Home Department Code Not Mapped") -> 5100 | AF66: =IFERROR(VLOOKUP(AA66,'Salary Map'!A:D,3,FALSE),"Salary Code Not Mapped") -> Default | AG66: =IFERROR(VLOOKUP(AA66,'Salary Map'!A:D,4,FALSE),"Salary Code Not Mapped") -> General | AH66: =IFERROR(VLOOKUP(AA66,'Salary Map'!A:E,5,FALSE),"Invoice Approval Not Mapped") -> 0 | AI66: =IFERROR(VLOOKUP(Z66,'Country Map'!A:B,2,FALSE),"Legal Country Not Mapped") -> US | AJ66: =IFERROR(VLOOKUP(X66,'Language Map'!A:C,3,FALSE),IFERROR(VLOOKUP(T66,'Org Map'!A:F,6,FALSE),"ADP and BU Language Code Not Mapped"))&AI66 -> en_US | AK66: =IFERROR(VLOOKUP(T66,'Org Map'!A:G,7),"BU Currency Not Mapped") -> USD | AL66: =IF(ISBLANK(E66),"",TRIM(E66&" "&F66)) | AM66: =IFERROR(VLOOKUP(O66,'Status Map'!A:B,2,FALSE),"Position Status Not Mapped") -> Y | AN66: =IF(AM66="N",TEXT(M66,"yyyymmdd"),"") | AO66: =IFERROR(VLOOKUP(P66,'Invoice Exception Map'!A:C,3,FALSE),IF(AH66>0,"Y","N")) -> N
A67: KSY | B67: Bradley | D67: Masters | E67: Brad | F67: Masters | G67: Rodriguez, Siobhan | H67: V0U207588 | I67: bmasters@onebarnes.com | J67: brad.a.masters@gmail.com | K67: Mgr, Sales | L67: 46223 | O67: Active | P67: 902437 | Q67: Monthly | R67: Full Time | S67: 088 | T67: 088-AS Raymond | U67: Outside Sales | V67: 008200 | W67: Works from home - Ohio | Z67: USA | AA67: S16 | AB67: FMG-S16 | AC67: =IF(ISBLANK(H67),VLOOKUP(P67,'Invoice Exception Map'!A:D,4,FALSE),MID(H67,4,6)) -> 207588 | AD67: =IFERROR(VLOOKUP(T67,'Org Map'!A:E,4),"BU Description Not Mapped") -> 0088 | AE67: =IFERROR(VLOOKUP(V67,'Org Map'!C:E,3,FALSE),"Home Department Code Not Mapped") -> 8200 | AF67: =IFERROR(VLOOKUP(AA67,'Salary Map'!A:D,3,FALSE),"Salary Code Not Mapped") -> Default | AG67: =IFERROR(VLOOKUP(AA67,'Salary Map'!A:D,4,FALSE),"Salary Code Not Mapped") -> General | AH67: =IFERROR(VLOOKUP(AA67,'Salary Map'!A:E,5,FALSE),"Invoice Approval Not Mapped") -> 25000 | AI67: =IFERROR(VLOOKUP(Z67,'Country Map'!A:B,2,FALSE),"Legal Country Not Mapped") -> US | AJ67: =IFERROR(VLOOKUP(X67,'Language Map'!A:C,3,FALSE),IFERROR(VLOOKUP(T67,'Org Map'!A:F,6,FALSE),"ADP and BU Language Code Not Mapped"))&AI67 -> en_US | AK67: =IFERROR(VLOOKUP(T67,'Org Map'!A:G,7),"BU Currency Not Mapped") -> USD | AL67: =IF(ISBLANK(E67),"",TRIM(E67&" "&F67)) -> Brad Masters | AM67: =IFERROR(VLOOKUP(O67,'Status Map'!A:B,2,FALSE),"Position Status Not Mapped") -> Y | AN67: =IF(AM67="N",TEXT(M67,"yyyymmdd"),"") | AO67: =IFERROR(VLOOKUP(P67,'Invoice Exception Map'!A:C,3,FALSE),IF(AH67>0,"Y","N")) -> N
A68: KSX | B68: Craig | D68: Mata | G68: LaPlante, Derek | H68: KSY211736 | I68: cmata@onebarnes.com | J68: CRAIGMATA51@YAHOO.COM | K68: Assistant, Warehouse II | L68: 43388 | O68: Active | P68: 201343 | Q68: Biweekly | R68: Full Time | S68: 088 | T68: 088-AS Raymond | U68: FG Warehouse | V68: 005200 | W68: AS Raymond | Z68: USA | AA68: S05 | AB68: FMG-S05 | AC68: =IF(ISBLANK(H68),VLOOKUP(P68,'Invoice Exception Map'!A:D,4,FALSE),MID(H68,4,6)) -> 211736 | AD68: =IFERROR(VLOOKUP(T68,'Org Map'!A:E,4),"BU Description Not Mapped") -> 0088 | AE68: =IFERROR(VLOOKUP(V68,'Org Map'!C:E,3,FALSE),"Home Department Code Not Mapped") -> 5200 | AF68: =IFERROR(VLOOKUP(AA68,'Salary Map'!A:D,3,FALSE),"Salary Code Not Mapped") -> Default | AG68: =IFERROR(VLOOKUP(AA68,'Salary Map'!A:D,4,FALSE),"Salary Code Not Mapped") -> General | AH68: =IFERROR(VLOOKUP(AA68,'Salary Map'!A:E,5,FALSE),"Invoice Approval Not Mapped") -> 0 | AI68: =IFERROR(VLOOKUP(Z68,'Country Map'!A:B,2,FALSE),"Legal Country Not Mapped") -> US | AJ68: =IFERROR(VLOOKUP(X68,'Language Map'!A:C,3,FALSE),IFERROR(VLOOKUP(T68,'Org Map'!A:F,6,FALSE),"ADP and BU Language Code Not Mapped"))&AI68 -> en_US | AK68: =IFERROR(VLOOKUP(T68,'Org Map'!A:G,7),"BU Currency Not Mapped") -> USD | AL68: =IF(ISBLANK(E68),"",TRIM(E68&" "&F68)) | AM68: =IFERROR(VLOOKUP(O68,'Status Map'!A:B,2,FALSE),"Position Status Not Mapped") -> Y | AN68: =IF(AM68="N",TEXT(M68,"yyyymmdd"),"") | AO68: =IFERROR(VLOOKUP(P68,'Invoice Exception Map'!A:C,3,FALSE),IF(AH68>0,"Y","N")) -> N
A69: KSX | B69: Scott | C69: T | D69: Mazzei | G69: Burchell, Mathew | H69: KSY211756 | I69: SMazzei@onebarnes.com | J69: smazzei426@gmail.com | K69: Assistant, Warehouse | L69: 38887 | O69: Active | P69: 662995 | Q69: Biweekly | R69: Full Time | S69: 088 | T69: 088-AS Raymond | U69: Assembly | V69: 005100 | W69: AS Raymond | Z69: USA | AA69: S08 | AB69: FMG-S08 | AC69: =IF(ISBLANK(H69),VLOOKUP(P69,'Invoice Exception Map'!A:D,4,FALSE),MID(H69,4,6)) -> 211756 | AD69: =IFERROR(VLOOKUP(T69,'Org Map'!A:E,4),"BU Description Not Mapped") -> 0088 | AE69: =IFERROR(VLOOKUP(V69,'Org Map'!C:E,3,FALSE),"Home Department Code Not Mapped") -> 5100 | AF69: =IFERROR(VLOOKUP(AA69,'Salary Map'!A:D,3,FALSE),"Salary Code Not Mapped") -> Default | AG69: =IFERROR(VLOOKUP(AA69,'Salary Map'!A:D,4,FALSE),"Salary Code Not Mapped") -> General | AH69: =IFERROR(VLOOKUP(AA69,'Salary Map'!A:E,5,FALSE),"Invoice Approval Not Mapped") -> 0 | AI69: =IFERROR(VLOOKUP(Z69,'Country Map'!A:B,2,FALSE),"Legal Country Not Mapped") -> US | AJ69: =IFERROR(VLOOKUP(X69,'Language Map'!A:C,3,FALSE),IFERROR(VLOOKUP(T69,'Org Map'!A:F,6,FALSE),"ADP and BU Language Code Not Mapped"))&AI69 -> en_US | AK69: =IFERROR(VLOOKUP(T69,'Org Map'!A:G,7),"BU Currency Not Mapped") -> USD | AL69: =IF(ISBLANK(E69),"",TRIM(E69&" "&F69)) | AM69: =IFERROR(VLOOKUP(O69,'Status Map'!A:B,2,FALSE),"Position Status Not Mapped") -> Y | AN69: =IF(AM69="N",TEXT(M69,"yyyymmdd"),"") | AO69: =IFERROR(VLOOKUP(P69,'Invoice Exception Map'!A:C,3,FALSE),IF(AH69>0,"Y","N")) -> N
A70: KSY | B70: Joel | C70: E | D70: McCoy | G70: Kemenah, Greg | H70: KSY211766 | I70: jmccoy@onebarnes.com | J70: joelmccoy@hotmail.com | K70: Engineer, Product III | L70: 41771 | O70: Active | P70: 901213 | Q70: Monthly | R70: Full Time | S70: 088 | T70: 088-AS Raymond | U70: Admin-Engineering | V70: 009450 | W70: AS Raymond | Z70: USA | AA70: S15 | AB70: FMG-S15 | AC70: =IF(ISBLANK(H70),VLOOKUP(P70,'Invoice Exception Map'!A:D,4,FALSE),MID(H70,4,6)) -> 211766 | AD70: =IFERROR(VLOOKUP(T70,'Org Map'!A:E,4),"BU Description Not Mapped") -> 0088 | AE70: =IFERROR(VLOOKUP(V70,'Org Map'!C:E,3,FALSE),"Home Department Code Not Mapped") -> 9450 | AF70: =IFERROR(VLOOKUP(AA70,'Salary Map'!A:D,3,FALSE),"Salary Code Not Mapped") -> Default | AG70: =IFERROR(VLOOKUP(AA70,'Salary Map'!A:D,4,FALSE),"Salary Code Not Mapped") -> General | AH70: =IFERROR(VLOOKUP(AA70,'Salary Map'!A:E,5,FALSE),"Invoice Approval Not Mapped") -> 0 | AI70: =IFERROR(VLOOKUP(Z70,'Country Map'!A:B,2,FALSE),"Legal Country Not Mapped") -> US | AJ70: =IFERROR(VLOOKUP(X70,'Language Map'!A:C,3,FALSE),IFERROR(VLOOKUP(T70,'Org Map'!A:F,6,FALSE),"ADP and BU Language Code Not Mapped"))&AI70 -> en_US | AK70: =IFERROR(VLOOKUP(T70,'Org Map'!A:G,7),"BU Currency Not Mapped") -> USD | AL70: =IF(ISBLANK(E70),"",TRIM(E70&" "&F70)) | AM70: =IFERROR(VLOOKUP(O70,'Status Map'!A:B,2,FALSE),"Position Status Not Mapped") -> Y | AN70: =IF(AM70="N",TEXT(M70,"yyyymmdd"),"") | AO70: =IFERROR(VLOOKUP(P70,'Invoice Exception Map'!A:C,3,FALSE),IF(AH70>0,"Y","N")) -> N
A71: V0U | B71: Amy | C71: C | D71: McGuire | G71: Warner, Dwight | H71: V0U008750 | I71: AMcGuire@onebarnes.com | J71: RedAmyMcG@gmail.com | K71: Accountant III | L71: 35338 | O71: Active | P71: 007861 | Q71: Monthly | R71: Full Time | S71: 025 | T71: 025-NGP Hyson Products | U71: Finance | V71: 000910 | W71: Hyson Products | Z71: USA | AA71: S13 | AB71: FMG-S13 | AC71: =IF(ISBLANK(H71),VLOOKUP(P71,'Invoice Exception Map'!A:D,4,FALSE),MID(H71,4,6)) -> 008750 | AD71: =IFERROR(VLOOKUP(T71,'Org Map'!A:E,4),"BU Description Not Mapped") -> 0096 | AE71: =IFERROR(VLOOKUP(V71,'Org Map'!C:E,3,FALSE),"Home Department Code Not Mapped") -> 910 | AF71: =IFERROR(VLOOKUP(AA71,'Salary Map'!A:D,3,FALSE),"Salary Code Not Mapped") -> Default | AG71: =IFERROR(VLOOKUP(AA71,'Salary Map'!A:D,4,FALSE),"Salary Code Not Mapped") -> General | AH71: =IFERROR(VLOOKUP(AA71,'Salary Map'!A:E,5,FALSE),"Invoice Approval Not Mapped") -> 0 | AI71: =IFERROR(VLOOKUP(Z71,'Country Map'!A:B,2,FALSE),"Legal Country Not Mapped") -> US | AJ71: =IFERROR(VLOOKUP(X71,'Language Map'!A:C,3,FALSE),IFERROR(VLOOKUP(T71,'Org Map'!A:F,6,FALSE),"ADP and BU Language Code Not Mapped"))&AI71 -> en_US | AK71: =IFERROR(VLOOKUP(T71,'Org Map'!A:G,7),"BU Currency Not Mapped") -> USD | AL71: =IF(ISBLANK(E71),"",TRIM(E71&" "&F71)) | AM71: =IFERROR(VLOOKUP(O71,'Status Map'!A:B,2,FALSE),"Position Status Not Mapped") -> Y | AN71: =IF(AM71="N",TEXT(M71,"yyyymmdd"),"") | AO71: =IFERROR(VLOOKUP(P71,'Invoice Exception Map'!A:C,3,FALSE),IF(AH71>0,"Y","N")) -> Y
A72: KSX | B72: Michael | D72: Molnar | G72: Rafferty, Jonathan | H72: KSY211131 | I72: Mmolnar@onebarnes.com | J72: michaelmolnar419@gmail.com | K72: Rep, Customer Service III | L72: 45040 | O72: Active | P72: 209746 | Q72: Biweekly | R72: Full Time | S72: 088 | T72: 088-AS Raymond | U72: Inside Sales | V72: 008100 | W72: AS Raymond | Z72: USA | AA72: S11 | AB72: FMG-S11 | AC72: =IF(ISBLANK(H72),VLOOKUP(P72,'Invoice Exception Map'!A:D,4,FALSE),MID(H72,4,6)) -> 211131 | AD72: =IFERROR(VLOOKUP(T72,'Org Map'!A:E,4),"BU Description Not Mapped") -> 0088 | AE72: =IFERROR(VLOOKUP(V72,'Org Map'!C:E,3,FALSE),"Home Department Code Not Mapped") -> 8100 | AF72: =IFERROR(VLOOKUP(AA72,'Salary Map'!A:D,3,FALSE),"Salary Code Not Mapped") -> Default | AG72: =IFERROR(VLOOKUP(AA72,'Salary Map'!A:D,4,FALSE),"Salary Code Not Mapped") -> General | AH72: =IFERROR(VLOOKUP(AA72,'Salary Map'!A:E,5,FALSE),"Invoice Approval Not Mapped") -> 0 | AI72: =IFERROR(VLOOKUP(Z72,'Country Map'!A:B,2,FALSE),"Legal Country Not Mapped") -> US | AJ72: =IFERROR(VLOOKUP(X72,'Language Map'!A:C,3,FALSE),IFERROR(VLOOKUP(T72,'Org Map'!A:F,6,FALSE),"ADP and BU Language Code Not Mapped"))&AI72 -> en_US | AK72: =IFERROR(VLOOKUP(T72,'Org Map'!A:G,7),"BU Currency Not Mapped") -> USD | AL72: =IF(ISBLANK(E72),"",TRIM(E72&" "&F72)) | AM72: =IFERROR(VLOOKUP(O72,'Status Map'!A:B,2,FALSE),"Position Status Not Mapped") -> Y | AN72: =IF(AM72="N",TEXT(M72,"yyyymmdd"),"") | AO72: =IFERROR(VLOOKUP(P72,'Invoice Exception Map'!A:C,3,FALSE),IF(AH72>0,"Y","N")) -> N
A73: KSX | B73: Candi | C73: M | D73: Morales | G73: Alexander, Thomas | H73: KSY210892 | I73: cburris@onebarnes.com | J73: cmorales6132015@gmail.com | K73: Admin, Document Control | L73: 35947 | O73: Active | P73: 007630 | Q73: Biweekly | R73: Full Time | S73: 088 | T73: 088-AS Raymond | U73: Admin-Quality | V73: 009500 | W73: AS Raymond | Z73: USA | AA73: S10 | AB73: FMG-S10 | AC73: =IF(ISBLANK(H73),VLOOKUP(P73,'Invoice Exception Map'!A:D,4,FALSE),MID(H73,4,6)) -> 210892 | AD73: =IFERROR(VLOOKUP(T73,'Org Map'!A:E,4),"BU Description Not Mapped") -> 0088 | AE73: =IFERROR(VLOOKUP(V73,'Org Map'!C:E,3,FALSE),"Home Department Code Not Mapped") -> 9500 | AF73: =IFERROR(VLOOKUP(AA73,'Salary Map'!A:D,3,FALSE),"Salary Code Not Mapped") -> Default | AG73: =IFERROR(VLOOKUP(AA73,'Salary Map'!A:D,4,FALSE),"Salary Code Not Mapped") -> General | AH73: =IFERROR(VLOOKUP(AA73,'Salary Map'!A:E,5,FALSE),"Invoice Approval Not Mapped") -> 0 | AI73: =IFERROR(VLOOKUP(Z73,'Country Map'!A:B,2,FALSE),"Legal Country Not Mapped") -> US | AJ73: =IFERROR(VLOOKUP(X73,'Language Map'!A:C,3,FALSE),IFERROR(VLOOKUP(T73,'Org Map'!A:F,6,FALSE),"ADP and BU Language Code Not Mapped"))&AI73 -> en_US | AK73: =IFERROR(VLOOKUP(T73,'Org Map'!A:G,7),"BU Currency Not Mapped") -> USD | AL73: =IF(ISBLANK(E73),"",TRIM(E73&" "&F73)) | AM73: =IFERROR(VLOOKUP(O73,'Status Map'!A:B,2,FALSE),"Position Status Not Mapped") -> Y | AN73: =IF(AM73="N",TEXT(M73,"yyyymmdd"),"") | AO73: =IFERROR(VLOOKUP(P73,'Invoice Exception Map'!A:C,3,FALSE),IF(AH73>0,"Y","N")) -> Y
A74: KSX | B74: Peter | D74: Morgan | G74: Rafferty, Jonathan | H74: KSY211131 | I74: pmorgan@onebarnes.com | J74: pete.petemorgan@gmail.com | K74: Rep, Customer Service III | L74: 46153 | O74: Active | P74: 213225 | Q74: Biweekly | R74: Full Time | S74: 088 | T74: 088-AS Raymond | U74: Inside Sales | V74: 008100 | W74: AS Raymond | Z74: USA | AA74: S11 | AB74: FMG-S11 | AC74: =IF(ISBLANK(H74),VLOOKUP(P74,'Invoice Exception Map'!A:D,4,FALSE),MID(H74,4,6)) -> 211131 | AD74: =IFERROR(VLOOKUP(T74,'Org Map'!A:E,4),"BU Description Not Mapped") -> 0088 | AE74: =IFERROR(VLOOKUP(V74,'Org Map'!C:E,3,FALSE),"Home Department Code Not Mapped") -> 8100 | AF74: =IFERROR(VLOOKUP(AA74,'Salary Map'!A:D,3,FALSE),"Salary Code Not Mapped") -> Default | AG74: =IFERROR(VLOOKUP(AA74,'Salary Map'!A:D,4,FALSE),"Salary Code Not Mapped") -> General | AH74: =IFERROR(VLOOKUP(AA74,'Salary Map'!A:E,5,FALSE),"Invoice Approval Not Mapped") -> 0 | AI74: =IFERROR(VLOOKUP(Z74,'Country Map'!A:B,2,FALSE),"Legal Country Not Mapped") -> US | AJ74: =IFERROR(VLOOKUP(X74,'Language Map'!A:C,3,FALSE),IFERROR(VLOOKUP(T74,'Org Map'!A:F,6,FALSE),"ADP and BU Language Code Not Mapped"))&AI74 -> en_US | AK74: =IFERROR(VLOOKUP(T74,'Org Map'!A:G,7),"BU Currency Not Mapped") -> USD | AL74: =IF(ISBLANK(E74),"",TRIM(E74&" "&F74)) | AM74: =IFERROR(VLOOKUP(O74,'Status Map'!A:B,2,FALSE),"Position Status Not Mapped") -> Y | AN74: =IF(AM74="N",TEXT(M74,"yyyymmdd"),"") | AO74: =IFERROR(VLOOKUP(P74,'Invoice Exception Map'!A:C,3,FALSE),IF(AH74>0,"Y","N")) -> N
A75: KSY | B75: Rachel | C75: E | D75: Neri | G75: Kemenah, Greg | H75: KSY211766 | I75: rneri@onebarnes.com | J75: neri.rachel14@gmail.com | K75: Supv, CI | L75: 45832 | O75: Active | P75: 212129 | Q75: Monthly | R75: Full Time | S75: 088 | T75: 088-AS Raymond | U75: Inside Sales | V75: 008100 | W75: AS Raymond | Z75: USA | AA75: S15 | AB75: FMG-S15 | AC75: =IF(ISBLANK(H75),VLOOKUP(P75,'Invoice Exception Map'!A:D,4,FALSE),MID(H75,4,6)) -> 211766 | AD75: =IFERROR(VLOOKUP(T75,'Org Map'!A:E,4),"BU Description Not Mapped") -> 0088 | AE75: =IFERROR(VLOOKUP(V75,'Org Map'!C:E,3,FALSE),"Home Department Code Not Mapped") -> 8100 | AF75: =IFERROR(VLOOKUP(AA75,'Salary Map'!A:D,3,FALSE),"Salary Code Not Mapped") -> Default | AG75: =IFERROR(VLOOKUP(AA75,'Salary Map'!A:D,4,FALSE),"Salary Code Not Mapped") -> General | AH75: =IFERROR(VLOOKUP(AA75,'Salary Map'!A:E,5,FALSE),"Invoice Approval Not Mapped") -> 0 | AI75: =IFERROR(VLOOKUP(Z75,'Country Map'!A:B,2,FALSE),"Legal Country Not Mapped") -> US | AJ75: =IFERROR(VLOOKUP(X75,'Language Map'!A:C,3,FALSE),IFERROR(VLOOKUP(T75,'Org Map'!A:F,6,FALSE),"ADP and BU Language Code Not Mapped"))&AI75 -> en_US | AK75: =IFERROR(VLOOKUP(T75,'Org Map'!A:G,7),"BU Currency Not Mapped") -> USD | AL75: =IF(ISBLANK(E75),"",TRIM(E75&" "&F75)) | AM75: =IFERROR(VLOOKUP(O75,'Status Map'!A:B,2,FALSE),"Position Status Not Mapped") -> Y | AN75: =IF(AM75="N",TEXT(M75,"yyyymmdd"),"") | AO75: =IFERROR(VLOOKUP(P75,'Invoice Exception Map'!A:C,3,FALSE),IF(AH75>0,"Y","N")) -> N
A76: V0U | B76: Kevin | C76: D | D76: OConnor | G76: Wilkins, William | H76: V0U901934 | I76: koconnor@onebarnes.com | J76: koconnor2020@gmail.com | K76: Mgr, Account Sls/Serv II | L76: 45953 | O76: Active | P76: 212678 | Q76: Monthly | R76: Full Time | S76: 025 | T76: 025-NGP Hyson Products | U76: Outside Sales | V76: 000820 | W76: Hyson Products | Z76: USA | AA76: S16 | AB76: FMG-S16 | AC76: =IF(ISBLANK(H76),VLOOKUP(P76,'Invoice Exception Map'!A:D,4,FALSE),MID(H76,4,6)) -> 901934 | AD76: =IFERROR(VLOOKUP(T76,'Org Map'!A:E,4),"BU Description Not Mapped") -> 0096 | AE76: =IFERROR(VLOOKUP(V76,'Org Map'!C:E,3,FALSE),"Home Department Code Not Mapped") -> 820 | AF76: =IFERROR(VLOOKUP(AA76,'Salary Map'!A:D,3,FALSE),"Salary Code Not Mapped") -> Default | AG76: =IFERROR(VLOOKUP(AA76,'Salary Map'!A:D,4,FALSE),"Salary Code Not Mapped") -> General | AH76: =IFERROR(VLOOKUP(AA76,'Salary Map'!A:E,5,FALSE),"Invoice Approval Not Mapped") -> 25000 | AI76: =IFERROR(VLOOKUP(Z76,'Country Map'!A:B,2,FALSE),"Legal Country Not Mapped") -> US | AJ76: =IFERROR(VLOOKUP(X76,'Language Map'!A:C,3,FALSE),IFERROR(VLOOKUP(T76,'Org Map'!A:F,6,FALSE),"ADP and BU Language Code Not Mapped"))&AI76 -> en_US | AK76: =IFERROR(VLOOKUP(T76,'Org Map'!A:G,7),"BU Currency Not Mapped") -> USD | AL76: =IF(ISBLANK(E76),"",TRIM(E76&" "&F76)) | AM76: =IFERROR(VLOOKUP(O76,'Status Map'!A:B,2,FALSE),"Position Status Not Mapped") -> Y | AN76: =IF(AM76="N",TEXT(M76,"yyyymmdd"),"") | AO76: =IFERROR(VLOOKUP(P76,'Invoice Exception Map'!A:C,3,FALSE),IF(AH76>0,"Y","N")) -> Y
A77: V0U | B77: Laura | C77: Z | D77: Oleksa | G77: Adewalure, Babatunde | H77: 000203011N | I77: LOleksa@onebarnes.com | J77: lzoleksa13@gmail.com | K77: Mgr, HR III | L77: 44837 | O77: Active | P77: 209181 | Q77: Monthly | R77: Full Time | S77: 025 | T77: 025-NGP Hyson Products | U77: Human Resources 9210 9210 | V77: 000920 | W77: Hyson Products | Z77: USA | AA77: S17 | AB77: FMG-S17 | AC77: =IF(ISBLANK(H77),VLOOKUP(P77,'Invoice Exception Map'!A:D,4,FALSE),MID(H77,4,6)) -> 203011 | AD77: =IFERROR(VLOOKUP(T77,'Org Map'!A:E,4),"BU Description Not Mapped") -> 0096 | AE77: =IFERROR(VLOOKUP(V77,'Org Map'!C:E,3,FALSE),"Home Department Code Not Mapped") -> 920 | AF77: =IFERROR(VLOOKUP(AA77,'Salary Map'!A:D,3,FALSE),"Salary Code Not Mapped") -> Default | AG77: =IFERROR(VLOOKUP(AA77,'Salary Map'!A:D,4,FALSE),"Salary Code Not Mapped") -> General | AH77: =IFERROR(VLOOKUP(AA77,'Salary Map'!A:E,5,FALSE),"Invoice Approval Not Mapped") -> 25000 | AI77: =IFERROR(VLOOKUP(Z77,'Country Map'!A:B,2,FALSE),"Legal Country Not Mapped") -> US | AJ77: =IFERROR(VLOOKUP(X77,'Language Map'!A:C,3,FALSE),IFERROR(VLOOKUP(T77,'Org Map'!A:F,6,FALSE),"ADP and BU Language Code Not Mapped"))&AI77 -> en_US | AK77: =IFERROR(VLOOKUP(T77,'Org Map'!A:G,7),"BU Currency Not Mapped") -> USD | AL77: =IF(ISBLANK(E77),"",TRIM(E77&" "&F77)) | AM77: =IFERROR(VLOOKUP(O77,'Status Map'!A:B,2,FALSE),"Position Status Not Mapped") -> Y | AN77: =IF(AM77="N",TEXT(M77,"yyyymmdd"),"") | AO77: =IFERROR(VLOOKUP(P77,'Invoice Exception Map'!A:C,3,FALSE),IF(AH77>0,"Y","N")) -> Y
A78: KSX | B78: David | C78: J | D78: Page | G78: Bate, Natalie | H78: V0U213037 | I78: dpage@onebarnes.com | J78: davidjpage@sbcglobal.net | K78: Mgr, Project II | L78: 45964 | O78: Active | P78: 212725 | Q78: Biweekly | R78: Part Time | S78: 088 | T78: 088-AS Raymond | U78: Admin-Engineering | V78: 009450 | W78: AS Raymond | Z78: USA | AA78: S16 | AB78: FMG-S16 | AC78: =IF(ISBLANK(H78),VLOOKUP(P78,'Invoice Exception Map'!A:D,4,FALSE),MID(H78,4,6)) -> 213037 | AD78: =IFERROR(VLOOKUP(T78,'Org Map'!A:E,4),"BU Description Not Mapped") -> 0088 | AE78: =IFERROR(VLOOKUP(V78,'Org Map'!C:E,3,FALSE),"Home Department Code Not Mapped") -> 9450 | AF78: =IFERROR(VLOOKUP(AA78,'Salary Map'!A:D,3,FALSE),"Salary Code Not Mapped") -> Default | AG78: =IFERROR(VLOOKUP(AA78,'Salary Map'!A:D,4,FALSE),"Salary Code Not Mapped") -> General | AH78: =IFERROR(VLOOKUP(AA78,'Salary Map'!A:E,5,FALSE),"Invoice Approval Not Mapped") -> 25000 | AI78: =IFERROR(VLOOKUP(Z78,'Country Map'!A:B,2,FALSE),"Legal Country Not Mapped") -> US | AJ78: =IFERROR(VLOOKUP(X78,'Language Map'!A:C,3,FALSE),IFERROR(VLOOKUP(T78,'Org Map'!A:F,6,FALSE),"ADP and BU Language Code Not Mapped"))&AI78 -> en_US | AK78: =IFERROR(VLOOKUP(T78,'Org Map'!A:G,7),"BU Currency Not Mapped") -> USD | AL78: =IF(ISBLANK(E78),"",TRIM(E78&" "&F78)) | AM78: =IFERROR(VLOOKUP(O78,'Status Map'!A:B,2,FALSE),"Position Status Not Mapped") -> Y | AN78: =IF(AM78="N",TEXT(M78,"yyyymmdd"),"") | AO78: =IFERROR(VLOOKUP(P78,'Invoice Exception Map'!A:C,3,FALSE),IF(AH78>0,"Y","N")) -> Y
A79: KSY | B79: Alex | D79: Palicki | G79: Creager, Andrew | H79: KSY212699 | I79: apalicki@onebarnes.com | J79: alexpalicki4@gmail.com | K79: Buyer III | L79: 45831 | O79: Active | P79: 212119 | Q79: Monthly | R79: Full Time | S79: 088 | T79: 088-AS Raymond | U79: Admin-Material Management | V79: 009400 | W79: AS Raymond | Z79: USA | AA79: S13 | AB79: FMG-S13 | AC79: =IF(ISBLANK(H79),VLOOKUP(P79,'Invoice Exception Map'!A:D,4,FALSE),MID(H79,4,6)) -> 212699 | AD79: =IFERROR(VLOOKUP(T79,'Org Map'!A:E,4),"BU Description Not Mapped") -> 0088 | AE79: =IFERROR(VLOOKUP(V79,'Org Map'!C:E,3,FALSE),"Home Department Code Not Mapped") -> 9400 | AF79: =IFERROR(VLOOKUP(AA79,'Salary Map'!A:D,3,FALSE),"Salary Code Not Mapped") -> Default | AG79: =IFERROR(VLOOKUP(AA79,'Salary Map'!A:D,4,FALSE),"Salary Code Not Mapped") -> General | AH79: =IFERROR(VLOOKUP(AA79,'Salary Map'!A:E,5,FALSE),"Invoice Approval Not Mapped") -> 0 | AI79: =IFERROR(VLOOKUP(Z79,'Country Map'!A:B,2,FALSE),"Legal Country Not Mapped") -> US | AJ79: =IFERROR(VLOOKUP(X79,'Language Map'!A:C,3,FALSE),IFERROR(VLOOKUP(T79,'Org Map'!A:F,6,FALSE),"ADP and BU Language Code Not Mapped"))&AI79 -> en_US | AK79: =IFERROR(VLOOKUP(T79,'Org Map'!A:G,7),"BU Currency Not Mapped") -> USD | AL79: =IF(ISBLANK(E79),"",TRIM(E79&" "&F79)) | AM79: =IFERROR(VLOOKUP(O79,'Status Map'!A:B,2,FALSE),"Position Status Not Mapped") -> Y | AN79: =IF(AM79="N",TEXT(M79,"yyyymmdd"),"") | AO79: =IFERROR(VLOOKUP(P79,'Invoice Exception Map'!A:C,3,FALSE),IF(AH79>0,"Y","N")) -> N
A80: KSX | B80: Linette | C80: W | D80: Parks | G80: Rafferty, Jonathan | H80: KSY211131 | I80: Lparks@onebarnes.com | J80: linetteparks914@gmail.com | K80: Rep, Customer Service III | L80: 46237 | O80: Active | P80: 902690 | Q80: Biweekly | R80: Full Time | S80: 088 | T80: 088-AS Raymond | U80: Inside Sales | V80: 008100 | W80: AS Raymond | Z80: USA | AA80: S11 | AB80: FMG-S11 | AC80: =IF(ISBLANK(H80),VLOOKUP(P80,'Invoice Exception Map'!A:D,4,FALSE),MID(H80,4,6)) -> 211131 | AD80: =IFERROR(VLOOKUP(T80,'Org Map'!A:E,4),"BU Description Not Mapped") -> 0088 | AE80: =IFERROR(VLOOKUP(V80,'Org Map'!C:E,3,FALSE),"Home Department Code Not Mapped") -> 8100 | AF80: =IFERROR(VLOOKUP(AA80,'Salary Map'!A:D,3,FALSE),"Salary Code Not Mapped") -> Default | AG80: =IFERROR(VLOOKUP(AA80,'Salary Map'!A:D,4,FALSE),"Salary Code Not Mapped") -> General | AH80: =IFERROR(VLOOKUP(AA80,'Salary Map'!A:E,5,FALSE),"Invoice Approval Not Mapped") -> 0 | AI80: =IFERROR(VLOOKUP(Z80,'Country Map'!A:B,2,FALSE),"Legal Country Not Mapped") -> US | AJ80: =IFERROR(VLOOKUP(X80,'Language Map'!A:C,3,FALSE),IFERROR(VLOOKUP(T80,'Org Map'!A:F,6,FALSE),"ADP and BU Language Code Not Mapped"))&AI80 -> en_US | AK80: =IFERROR(VLOOKUP(T80,'Org Map'!A:G,7),"BU Currency Not Mapped") -> USD | AL80: =IF(ISBLANK(E80),"",TRIM(E80&" "&F80)) | AM80: =IFERROR(VLOOKUP(O80,'Status Map'!A:B,2,FALSE),"Position Status Not Mapped") -> Y | AN80: =IF(AM80="N",TEXT(M80,"yyyymmdd"),"") | AO80: =IFERROR(VLOOKUP(P80,'Invoice Exception Map'!A:C,3,FALSE),IF(AH80>0,"Y","N")) -> N
A81: KSY | B81: Shivam | D81: Patel | G81: Creager, Andrew | H81: KSY212699 | I81: spatel@onebarnes.com | J81: patel.shivam2511@gmail.com | K81: Buyer II | L81: 43836 | O81: Active | P81: 201903 | Q81: Monthly | R81: Full Time | S81: 088 | T81: 088-AS Raymond | U81: Admin-Material Management | V81: 009400 | W81: AS Raymond | Z81: USA | AA81: S12 | AB81: FMG-S12 | AC81: =IF(ISBLANK(H81),VLOOKUP(P81,'Invoice Exception Map'!A:D,4,FALSE),MID(H81,4,6)) -> 212699 | AD81: =IFERROR(VLOOKUP(T81,'Org Map'!A:E,4),"BU Description Not Mapped") -> 0088 | AE81: =IFERROR(VLOOKUP(V81,'Org Map'!C:E,3,FALSE),"Home Department Code Not Mapped") -> 9400 | AF81: =IFERROR(VLOOKUP(AA81,'Salary Map'!A:D,3,FALSE),"Salary Code Not Mapped") -> Default | AG81: =IFERROR(VLOOKUP(AA81,'Salary Map'!A:D,4,FALSE),"Salary Code Not Mapped") -> General | AH81: =IFERROR(VLOOKUP(AA81,'Salary Map'!A:E,5,FALSE),"Invoice Approval Not Mapped") -> 0 | AI81: =IFERROR(VLOOKUP(Z81,'Country Map'!A:B,2,FALSE),"Legal Country Not Mapped") -> US | AJ81: =IFERROR(VLOOKUP(X81,'Language Map'!A:C,3,FALSE),IFERROR(VLOOKUP(T81,'Org Map'!A:F,6,FALSE),"ADP and BU Language Code Not Mapped"))&AI81 -> en_US | AK81: =IFERROR(VLOOKUP(T81,'Org Map'!A:G,7),"BU Currency Not Mapped") -> USD | AL81: =IF(ISBLANK(E81),"",TRIM(E81&" "&F81)) | AM81: =IFERROR(VLOOKUP(O81,'Status Map'!A:B,2,FALSE),"Position Status Not Mapped") -> Y | AN81: =IF(AM81="N",TEXT(M81,"yyyymmdd"),"") | AO81: =IFERROR(VLOOKUP(P81,'Invoice Exception Map'!A:C,3,FALSE),IF(AH81>0,"Y","N")) -> N
A82: KSX | B82: Joshua | C82: S | D82: Paulsen | G82: LaPlante, Derek | H82: KSY211736 | I82: jpaulsen@onebarnes.com | J82: tagjosh36@gmail.com | K82: Assistant, Warehouse II | L82: 41407 | O82: Active | P82: 900851 | Q82: Biweekly | R82: Full Time | S82: 088 | T82: 088-AS Raymond | U82: FG Warehouse | V82: 005200 | W82: AS Raymond | Z82: USA | AA82: S05 | AB82: FMG-S05 | AC82: =IF(ISBLANK(H82),VLOOKUP(P82,'Invoice Exception Map'!A:D,4,FALSE),MID(H82,4,6)) -> 211736 | AD82: =IFERROR(VLOOKUP(T82,'Org Map'!A:E,4),"BU Description Not Mapped") -> 0088 | AE82: =IFERROR(VLOOKUP(V82,'Org Map'!C:E,3,FALSE),"Home Department Code Not Mapped") -> 5200 | AF82: =IFERROR(VLOOKUP(AA82,'Salary Map'!A:D,3,FALSE),"Salary Code Not Mapped") -> Default | AG82: =IFERROR(VLOOKUP(AA82,'Salary Map'!A:D,4,FALSE),"Salary Code Not Mapped") -> General | AH82: =IFERROR(VLOOKUP(AA82,'Salary Map'!A:E,5,FALSE),"Invoice Approval Not Mapped") -> 0 | AI82: =IFERROR(VLOOKUP(Z82,'Country Map'!A:B,2,FALSE),"Legal Country Not Mapped") -> US | AJ82: =IFERROR(VLOOKUP(X82,'Language Map'!A:C,3,FALSE),IFERROR(VLOOKUP(T82,'Org Map'!A:F,6,FALSE),"ADP and BU Language Code Not Mapped"))&AI82 -> en_US | AK82: =IFERROR(VLOOKUP(T82,'Org Map'!A:G,7),"BU Currency Not Mapped") -> USD | AL82: =IF(ISBLANK(E82),"",TRIM(E82&" "&F82)) | AM82: =IFERROR(VLOOKUP(O82,'Status Map'!A:B,2,FALSE),"Position Status Not Mapped") -> Y | AN82: =IF(AM82="N",TEXT(M82,"yyyymmdd"),"") | AO82: =IFERROR(VLOOKUP(P82,'Invoice Exception Map'!A:C,3,FALSE),IF(AH82>0,"Y","N")) -> N
A83: KSY | B83: Carol | D83: Phillips | G83: Rodriguez, Siobhan | H83: V0U207588 | I83: cphillips1@onebarnes.com | J83: cphillips1226@icloud.com | K83: Mgr, Sales | L83: 45909 | O83: Active | P83: 212478 | Q83: Monthly | R83: Full Time | S83: 088 | T83: 088-AS Raymond | U83: Outside Sales | V83: 008200 | W83: Works from home - Ohio | Z83: USA | AA83: S16 | AB83: FMG-S16 | AC83: =IF(ISBLANK(H83),VLOOKUP(P83,'Invoice Exception Map'!A:D,4,FALSE),MID(H83,4,6)) -> 207588 | AD83: =IFERROR(VLOOKUP(T83,'Org Map'!A:E,4),"BU Description Not Mapped") -> 0088 | AE83: =IFERROR(VLOOKUP(V83,'Org Map'!C:E,3,FALSE),"Home Department Code Not Mapped") -> 8200 | AF83: =IFERROR(VLOOKUP(AA83,'Salary Map'!A:D,3,FALSE),"Salary Code Not Mapped") -> Default | AG83: =IFERROR(VLOOKUP(AA83,'Salary Map'!A:D,4,FALSE),"Salary Code Not Mapped") -> General | AH83: =IFERROR(VLOOKUP(AA83,'Salary Map'!A:E,5,FALSE),"Invoice Approval Not Mapped") -> 25000 | AI83: =IFERROR(VLOOKUP(Z83,'Country Map'!A:B,2,FALSE),"Legal Country Not Mapped") -> US | AJ83: =IFERROR(VLOOKUP(X83,'Language Map'!A:C,3,FALSE),IFERROR(VLOOKUP(T83,'Org Map'!A:F,6,FALSE),"ADP and BU Language Code Not Mapped"))&AI83 -> en_US | AK83: =IFERROR(VLOOKUP(T83,'Org Map'!A:G,7),"BU Currency Not Mapped") -> USD | AL83: =IF(ISBLANK(E83),"",TRIM(E83&" "&F83)) | AM83: =IFERROR(VLOOKUP(O83,'Status Map'!A:B,2,FALSE),"Position Status Not Mapped") -> Y | AN83: =IF(AM83="N",TEXT(M83,"yyyymmdd"),"") | AO83: =IFERROR(VLOOKUP(P83,'Invoice Exception Map'!A:C,3,FALSE),IF(AH83>0,"Y","N")) -> N
A84: KSX | B84: William | D84: Phoenix | G84: LaPlante, Derek | H84: KSY211736 | I84: wphoenix1@onebarnes.com | J84: w.phoenix365@gmail.com | K84: Assistant, Warehouse II | L84: 45593 | O84: Active | P84: 211531 | Q84: Biweekly | R84: Full Time | S84: 088 | T84: 088-AS Raymond | U84: FG Warehouse | V84: 005200 | W84: AS Raymond | Z84: USA | AA84: S05 | AB84: FMG-S05 | AC84: =IF(ISBLANK(H84),VLOOKUP(P84,'Invoice Exception Map'!A:D,4,FALSE),MID(H84,4,6)) -> 211736 | AD84: =IFERROR(VLOOKUP(T84,'Org Map'!A:E,4),"BU Description Not Mapped") -> 0088 | AE84: =IFERROR(VLOOKUP(V84,'Org Map'!C:E,3,FALSE),"Home Department Code Not Mapped") -> 5200 | AF84: =IFERROR(VLOOKUP(AA84,'Salary Map'!A:D,3,FALSE),"Salary Code Not Mapped") -> Default | AG84: =IFERROR(VLOOKUP(AA84,'Salary Map'!A:D,4,FALSE),"Salary Code Not Mapped") -> General | AH84: =IFERROR(VLOOKUP(AA84,'Salary Map'!A:E,5,FALSE),"Invoice Approval Not Mapped") -> 0 | AI84: =IFERROR(VLOOKUP(Z84,'Country Map'!A:B,2,FALSE),"Legal Country Not Mapped") -> US | AJ84: =IFERROR(VLOOKUP(X84,'Language Map'!A:C,3,FALSE),IFERROR(VLOOKUP(T84,'Org Map'!A:F,6,FALSE),"ADP and BU Language Code Not Mapped"))&AI84 -> en_US | AK84: =IFERROR(VLOOKUP(T84,'Org Map'!A:G,7),"BU Currency Not Mapped") -> USD | AL84: =IF(ISBLANK(E84),"",TRIM(E84&" "&F84)) | AM84: =IFERROR(VLOOKUP(O84,'Status Map'!A:B,2,FALSE),"Position Status Not Mapped") -> Y | AN84: =IF(AM84="N",TEXT(M84,"yyyymmdd"),"") | AO84: =IFERROR(VLOOKUP(P84,'Invoice Exception Map'!A:C,3,FALSE),IF(AH84>0,"Y","N")) -> N
